{
  "url": "https://in.linkedin.com/in/tjz",
  "raw_text": "0 notifications total\nnew feed updates notifications\nHome\n1\n1 new network update notification\nMy Network\nJobs\nMessaging\nNotifications\nMe\nFor Business\nTry Premium for ‚Çπ0\nTejasvee has a {:badgeType} account\nTejasvee Srikantan\nEngineering | Walmart | xto10x | Flipkart\nWalmart Global Tech India\nBengaluru, Karnataka, India Contact info\n382 connections\nMessage\nFollow\nMore\nActivity\nActivity\n390 followers\n390 followers\nLoaded 3 Comments posts\nTejasvee Srikantan commented on a post ‚Ä¢ 3mo\n3mo\nCongrats Gaurav! üéâ\nCongrats Gaurav! üéâ\nTejasvee Srikantan commented on a post ‚Ä¢ 5mo\n5mo\nCongratulations Surbhi Jain\nCongratulations Surbhi Jain\nTejasvee Srikantan commented on a post ‚Ä¢ 5mo\n5mo\nCongrats Shriganesh!\nCongrats Shriganesh!\nShow all comments\nExperience\nExperience\nSenior Engineering Manager\nSenior Engineering Manager\nWalmart Global Tech India ¬∑ Full-time\nWalmart Global Tech India ¬∑ Full-time\nDec 2023 - Present ¬∑ 1 yr 8 mos\nDec 2023 to Present ¬∑ 1 yr 8 mos\nBengaluru, Karnataka, India ¬∑ On-site\nBengaluru, Karnataka, India ¬∑ On-site\nxto10x\nxto10x\n4 yrs 3 mos\n4 yrs 3 mos\nEngineering Manager\nEngineering Manager\nFull-time\nFull-time\nMar 2020 - Sep 2023 ¬∑ 3 yrs 7 mos\nMar 2020 to Sep 2023 ¬∑ 3 yrs 7 mos\nBengaluru, Karnataka, India\nBengaluru, Karnataka, India\nSoftware Development, Agile Methodologies and +15 skills\nTech Lead\nTech Lead\nJul 2019 - Feb 2020 ¬∑ 8 mos\nJul 2019 to Feb 2020 ¬∑ 8 mos\nSoftware Development, Agile Methodologies and +15 skills\nFlipkart\nFlipkart\nFull-time ¬∑ 5 yrs 3 mos\nFull-time ¬∑ 5 yrs 3 mos\nBengaluru, Karnataka, India ¬∑ On-site\nBengaluru, Karnataka, India ¬∑ On-site\nSoftware Development Engineer (SDE-3)\nSoftware Development Engineer (SDE-3)\nJan 2017 - Jul 2019 ¬∑ 2 yrs 7 mos\nJan 2017 to Jul 2019 ¬∑ 2 yrs 7 mos\nSoftware Development, Agile Methodologies and +12 skills\nSoftware Development Engineer (SDE-2)\nSoftware Development Engineer (SDE-2)\nMay 2014 - Dec 2016 ¬∑ 2 yrs 8 mos\nMay 2014 to Dec 2016 ¬∑ 2 yrs 8 mos\nSoftware Development, Agile Methodologies and +6 skills\nOnMobile Global Limited\nOnMobile Global Limited\nFull-time ¬∑ 4 yrs 1 mo\nFull-time ¬∑ 4 yrs 1 mo\nBengaluru, Karnataka, India ¬∑ On-site\nBengaluru, Karnataka, India ¬∑ On-site\nEngineering Lead\nEngineering Lead\nApr 2012 - Apr 2014 ¬∑ 2 yrs 1 mo\nApr 2012 to Apr 2014 ¬∑ 2 yrs 1 mo\nSoftware Development, Software Development Life Cycle (SDLC) and +9 skills\nSenior Software Engineer\nSenior Software Engineer\nApr 2010 - Mar 2012 ¬∑ 2 yrs\nApr 2010 to Mar 2012 ¬∑ 2 yrs\nSoftware Development, Java and +4 skills\nSoftware Engineer\nSoftware Engineer\nSoftware Engineer\nOnMobile Global Limited (On contract from Cerulean Information Technology) ¬∑ Full-time\nOnMobile Global Limited (On contract from Cerulean Information Technology) ¬∑ Full-time\nFeb 2006 - Apr 2010 ¬∑ 4 yrs 3 mos\nFeb 2006 to Apr 2010 ¬∑ 4 yrs 3 mos\nBengaluru, Karnataka, India ¬∑ On-site\nBengaluru, Karnataka, India ¬∑ On-site\nSoftware Development, Java and +2 skills\nSkills\nSkills\nSoftware Development Life Cycle (SDLC)\nSoftware Development Life Cycle (SDLC)\n4 experiences across xto10x and 3 other companies\n4 experiences across xto10x and 3 other companies\n1 endorsement\n1 endorsement\nProject Management\nProject Management\n4 experiences across xto10x and 3 other companies\n4 experiences across xto10x and 3 other companies\nShow all 17 skills\nInterests\nInterests\nTop Voices\nTop Voices\nCompanies\nCompanies\nGroups\nGroups\nNewsletters\nNewsletters\nMatt Gray\nMatt Gray\nFounder & CEO, Founder OS | Proven systems to grow a profitable audience with organic content.\nFounder & CEO, Founder OS | Proven systems to grow a profitable audience with organic content.\n836,260 followers\n836,260 followers\nFollow\nAlex Brogan\nAlex Brogan\nTrying to see more clearly\nTrying to see more clearly\n231,731 followers\n231,731 followers\nFollow\nShow all Top Voices\nMore profiles for you\nMore profiles for you\nShubhangini Devalatkar\nShubhangini Devalatkar\n¬∑ 3rd+\n3rd+ degree connection\nDelivering quality software with minimal defects at speed. Expert in Functional testing, API testing and MySQL. Utilizes Agile methodologies. Experienced-QA lead at Simplify HealthCare\nMessage\nSuresh N\nSuresh N\n¬∑ 3rd+\n3rd+ degree connection\nFounder of EESHAN INFOTECH\nFounder of EESHAN INFOTECH\nMessage\nMrinal Chatterjee\nMrinal Chatterjee\n¬∑ 3rd+\n3rd+ degree connection\nCountry Head & SVP of Engineering -- We are growing & hiring in Bangalore !!!\nMessage\nJayaprakash Jayabalan\nJayaprakash Jayabalan\n¬∑ 3rd+\n3rd+ degree connection\nTechnical Lead at Euroland india\nTechnical Lead at Euroland india\nMessage\nSaikiran Krishnamurthy\nSaikiran Krishnamurthy\n¬∑ 3rd+\n3rd+ degree connection\nCo-founder & CEO, xto10x Technologies \nCo-founder & CEO, xto10x Technologies\nMessage\nShow all\nPeople you may know\nPeople you may know\nFrom Tejasvee's company\nFrom Tejasvee's company\nsaviour muoka\nsaviour muoka\nPRODUCT DESIGNER/CUSTOMER CARE REPRESENTATIVE\nConnect\nNeha Ganesh\nNeha Ganesh\nImmediate Joiner \n| Talent Acquisition | Recruitment Coordination |(ATS) | Candidate Screening | Sourcing Support |High-Volume Hiring |Process Improvement |Diversity and Inclusion Hiring\nConnect\nPrasika Prasad K\nPrasika Prasad K\nWorks at Walmart Global Tech \n\nStudent at SAI SHANKAR DEGREE COLLEGE, PONNAMPET\nConnect\nRanjani Kanappan\nRanjani Kanappan\nSAP HANA and BASIS consultant\nSAP HANA and BASIS consultant\nConnect\nBinu Thompson Deva Kumar\nBinu Thompson Deva Kumar\nSenior Analyst, People Service Generalist\nSenior Analyst, People Service Generalist\nConnect\nShow all\nYou might like\nYou might like\nPages for you\nPages for you\nSciAstra\nSciAstra\nE-Learning Providers\nE-Learning Providers\n37,200 followers\n37,200 followers\nFollow\nDragon Aviation Capital (Singapore) Pte. Ltd.\nDragon Aviation Capital (Singapore) Pte. Ltd.\nAviation and Aerospace Component Manufacturing\nAviation and Aerospace Component Manufacturing\n49,785 followers\n49,785 followers\nFollow\nShow all\nAbout\nAccessibility\nTalent Solutions\nProfessional Community Policies\nCareers\nMarketing Solutions\nPrivacy & Terms\nAd Choices\nAdvertising\nSales Solutions\nMobile\nSmall Business\nSafety Center\nQuestions?\nVisit our Help Center.\nManage your account and privacy\nGo to your Settings.\nRecommendation transparency\nLearn more about Recommended Content.\nSelect Language\n         ÿßŸÑÿπÿ±ÿ®Ÿäÿ© (Arabic)\n         ‡¶¨‡¶æ‡¶Ç‡¶≤‡¶æ (Bangla)\n         ƒåe≈°tina (Czech)\n         Dansk (Danish)\n         Deutsch (German)\n         ŒïŒªŒªŒ∑ŒΩŒπŒ∫Œ¨ (Greek)\n         English (English)\n         Espa√±ol (Spanish)\n         ŸÅÿßÿ±ÿ≥€å (Persian)\n         Suomi (Finnish)\n         Fran√ßais (French)\n         ‡§π‡§ø‡§Ç‡§¶‡•Ä (Hindi)\n         Magyar (Hungarian)\n         Bahasa Indonesia (Indonesian)\n         Italiano (Italian)\n         ◊¢◊ë◊®◊ô◊™ (Hebrew)\n         Êó•Êú¨Ë™û (Japanese)\n         ÌïúÍµ≠Ïñ¥ (Korean)\n         ‡§Æ‡§∞‡§æ‡§†‡•Ä (Marathi)\n         Bahasa Malaysia (Malay)\n         Nederlands (Dutch)\n         Norsk (Norwegian)\n         ‡®™‡©∞‡®ú‡®æ‡®¨‡©Ä (Punjabi)\n         Polski (Polish)\n         Portugu√™s (Portuguese)\n         Rom√¢nƒÉ (Romanian)\n         –†—É—Å—Å–∫–∏–π (Russian)\n         Svenska (Swedish)\n         ‡∞§‡±Ü‡∞≤‡±Å‡∞ó‡±Å (Telugu)\n         ‡∏†‡∏≤‡∏©‡∏≤‡πÑ‡∏ó‡∏¢ (Thai)\n         Tagalog (Tagalog)\n         T√ºrk√ße (Turkish)\n         –£–∫—Ä–∞—ó–Ω—Å—å–∫–∞ (Ukrainian)\n         Ti·∫øng Vi·ªát (Vietnamese)\n         ÁÆÄ‰Ωì‰∏≠Êñá (Chinese (Simplified))\n         Ê≠£È´î‰∏≠Êñá (Chinese (Traditional))\n     LinkedIn Corporation ¬© 2025\nStatus is online\nMessaging\nYou are on the messaging overlay. Press enter to open the list of conversations.\nCompose message\nYou are on the messaging overlay. Press enter to open the list of conversations.",
  "skills_text": "0 notifications total\nnew feed updates notifications\nHome\n1\n1 new network update notification\nMy Network\nJobs\nMessaging\nNotifications\nMe\nFor Business\nTry Premium for ‚Çπ0\nTejasvee Srikantan\nEngineering | Walmart | xto10x | Flipkart\nMore\nFollow\nMessage\nSkills\nAll\nIndustry Knowledge\nTools & Technologies\nInterpersonal Skills\nSoftware Development Life Cycle (SDLC)\nSoftware Development Life Cycle (SDLC)\n4 experiences across xto10x and 3 other companies\n4 experiences across xto10x and 3 other companies\n1 endorsement\n1 endorsement\nProject Management\nProject Management\n4 experiences across xto10x and 3 other companies\n4 experiences across xto10x and 3 other companies\nTeam Management\nTeam Management\n4 experiences across xto10x and 3 other companies\n4 experiences across xto10x and 3 other companies\nWeb Services\nWeb Services\n4 experiences across xto10x and 2 other companies\n4 experiences across xto10x and 2 other companies\nNode.js\nNode.js\n2 experiences across xto10x and 1 other company\n2 experiences across xto10x and 1 other company\nNoSQL\nNoSQL\n4 experiences across xto10x and 2 other companies\n4 experiences across xto10x and 2 other companies\nContinuous Integration (CI)\nContinuous Integration (CI)\n4 experiences across xto10x and 2 other companies\n4 experiences across xto10x and 2 other companies\nTeam Leadership\nTeam Leadership\n5 experiences across xto10x and 3 other companies\n5 experiences across xto10x and 3 other companies\nJava\nJava\n7 experiences across xto10x and 4 other companies\n7 experiences across xto10x and 4 other companies\nAgile Methodologies\nAgile Methodologies\n4 experiences across xto10x and 2 other companies\n4 experiences across xto10x and 2 other companies\nAmazon Web Services (AWS)\nAmazon Web Services (AWS)\n2 experiences across xto10x and 1 other company\n2 experiences across xto10x and 1 other company\nSoftware Development\nSoftware Development\n7 experiences across xto10x and 4 other companies\n7 experiences across xto10x and 4 other companies\nSQL\nSQL\n7 experiences across xto10x and 4 other companies\n7 experiences across xto10x and 4 other companies\nRequirements Analysis\nRequirements Analysis\n5 experiences across xto10x and 3 other companies\n5 experiences across xto10x and 3 other companies\nSoftware Development Methodologies\nSoftware Development Methodologies\n4 experiences across xto10x and 3 other companies\n4 experiences across xto10x and 3 other companies\nCore Java\nCore Java\n7 experiences across xto10x and 4 other companies\n7 experiences across xto10x and 4 other companies\nAgile Development\nAgile Development\n3 experiences across xto10x and 2 other companies\n3 experiences across xto10x and 2 other companies\nMore profiles for you\nMore profiles for you\nShubhangini Devalatkar\nShubhangini Devalatkar\n¬∑ 3rd+\n3rd+ degree connection\nDelivering quality software with minimal defects at speed. Expert in Functional testing, API testing and MySQL. Utilizes Agile methodologies. Experienced-QA lead at Simplify HealthCare\nMessage\nSuresh N\nSuresh N\n¬∑ 3rd+\n3rd+ degree connection\nFounder of EESHAN INFOTECH\nFounder of EESHAN INFOTECH\nMessage\nMrinal Chatterjee\nMrinal Chatterjee\n¬∑ 3rd+\n3rd+ degree connection\nCountry Head & SVP of Engineering -- We are growing & hiring in Bangalore !!!\nMessage\nJayaprakash Jayabalan\nJayaprakash Jayabalan\n¬∑ 3rd+\n3rd+ degree connection\nTechnical Lead at Euroland india\nTechnical Lead at Euroland india\nMessage\nSaikiran Krishnamurthy\nSaikiran Krishnamurthy\n¬∑ 3rd+\n3rd+ degree connection\nCo-founder & CEO, xto10x Technologies \nCo-founder & CEO, xto10x Technologies\nMessage\nShow more\nAbout\nAccessibility\nTalent Solutions\nProfessional Community Policies\nCareers\nMarketing Solutions\nPrivacy & Terms\nAd Choices\nAdvertising\nSales Solutions\nMobile\nSmall Business\nSafety Center\nQuestions?\nVisit our Help Center.\nManage your account and privacy\nGo to your Settings.\nRecommendation transparency\nLearn more about Recommended Content.\nSelect Language\n         ÿßŸÑÿπÿ±ÿ®Ÿäÿ© (Arabic)\n         ‡¶¨‡¶æ‡¶Ç‡¶≤‡¶æ (Bangla)\n         ƒåe≈°tina (Czech)\n         Dansk (Danish)\n         Deutsch (German)\n         ŒïŒªŒªŒ∑ŒΩŒπŒ∫Œ¨ (Greek)\n         English (English)\n         Espa√±ol (Spanish)\n         ŸÅÿßÿ±ÿ≥€å (Persian)\n         Suomi (Finnish)\n         Fran√ßais (French)\n         ‡§π‡§ø‡§Ç‡§¶‡•Ä (Hindi)\n         Magyar (Hungarian)\n         Bahasa Indonesia (Indonesian)\n         Italiano (Italian)\n         ◊¢◊ë◊®◊ô◊™ (Hebrew)\n         Êó•Êú¨Ë™û (Japanese)\n         ÌïúÍµ≠Ïñ¥ (Korean)\n         ‡§Æ‡§∞‡§æ‡§†‡•Ä (Marathi)\n         Bahasa Malaysia (Malay)\n         Nederlands (Dutch)\n         Norsk (Norwegian)\n         ‡®™‡©∞‡®ú‡®æ‡®¨‡©Ä (Punjabi)\n         Polski (Polish)\n         Portugu√™s (Portuguese)\n         Rom√¢nƒÉ (Romanian)\n         –†—É—Å—Å–∫–∏–π (Russian)\n         Svenska (Swedish)\n         ‡∞§‡±Ü‡∞≤‡±Å‡∞ó‡±Å (Telugu)\n         ‡∏†‡∏≤‡∏©‡∏≤‡πÑ‡∏ó‡∏¢ (Thai)\n         Tagalog (Tagalog)\n         T√ºrk√ße (Turkish)\n         –£–∫—Ä–∞—ó–Ω—Å—å–∫–∞ (Ukrainian)\n         Ti·∫øng Vi·ªát (Vietnamese)\n         ÁÆÄ‰Ωì‰∏≠Êñá (Chinese (Simplified))\n         Ê≠£È´î‰∏≠Êñá (Chinese (Traditional))\n     LinkedIn Corporation ¬© 2025\nStatus is online\nMessaging\nYou are on the messaging overlay. Press enter to open the list of conversations.\nCompose message\nYou are on the messaging overlay. Press enter to open the list of conversations.",
  "scraped_at": "2025-07-22 21:59:28",
  "has_skills": true,
  "cleaned_profile": {
    "name": "Tejasvee Srikantan",
    "profile_url": "https://in.linkedin.com/in/tjz",
    "current_position": {
      "title": "Senior Engineering Manager",
      "company": "Walmart Global Tech India",
      "location": "Bengaluru, Karnataka, India",
      "start_date": "Dec 2023",
      "end_date": "Present",
      "duration": "1 yr 8 mos"
    },
    "previous_positions": [
      {
        "title": "Engineering Manager",
        "company": "xto10x",
        "location": "Bengaluru, Karnataka, India",
        "start_date": "Mar 2020",
        "end_date": "Sep 2023",
        "duration": "3 yrs 7 mos"
      },
      {
        "title": "Tech Lead",
        "company": "xto10x",
        "start_date": "Jul 2019",
        "end_date": "Feb 2020",
        "duration": "8 mos"
      },
      {
        "title": "Software Development Engineer (SDE-3)",
        "company": "Flipkart",
        "location": "Bengaluru, Karnataka, India",
        "start_date": "Jan 2017",
        "end_date": "Jul 2019",
        "duration": "2 yrs 7 mos"
      },
      {
        "title": "Software Development Engineer (SDE-2)",
        "company": "Flipkart",
        "start_date": "May 2014",
        "end_date": "Dec 2016",
        "duration": "2 yrs 8 mos"
      },
      {
        "title": "Engineering Lead",
        "company": "OnMobile Global Limited",
        "location": "Bengaluru, Karnataka, India",
        "start_date": "Apr 2012",
        "end_date": "Apr 2014",
        "duration": "2 yrs 1 mo"
      },
      {
        "title": "Senior Software Engineer",
        "company": "OnMobile Global Limited",
        "start_date": "Apr 2010",
        "end_date": "Mar 2012",
        "duration": "2 yrs"
      },
      {
        "title": "Software Engineer",
        "company": "OnMobile Global Limited (On contract from Cerulean Information Technology)",
        "location": "Bengaluru, Karnataka, India",
        "start_date": "Feb 2006",
        "end_date": "Apr 2010",
        "duration": "4 yrs 3 mos"
      }
    ],
    "connections": 382,
    "followers": 390,
    "skills": [
      "Software Development Life Cycle (SDLC)",
      "Project Management",
      "Team Management",
      "Web Services",
      "Node.js",
      "NoSQL",
      "Continuous Integration (CI)",
      "Team Leadership",
      "Java",
      "Agile Methodologies",
      "Amazon Web Services (AWS)",
      "Software Development",
      "SQL",
      "Requirements Analysis",
      "Software Development Methodologies",
      "Core Java",
      "Agile Development"
    ],
    "interests": [
      "Matt Gray",
      "Alex Brogan"
    ]
  },
  "tokens_used": {
    "prompt_tokens": 3401,
    "completion_tokens": 704,
    "total_tokens": 4105
  }
}