{
  "url": "https://in.linkedin.com/in/rhythm-bhaskar-55616a22a",
  "raw_text": "0 notifications total\nnew feed updates notifications\nHome\n1\n1 new network update notification\nMy Network\nJobs\nMessaging\nNotifications\nMe\nFor Business\nTry Premium for ‚Çπ0\nRhythm Bhaskar\nBrand Marketing @xto10x | Consumer Insights | Psychologist\nxto10x\nDelhi University\nBengaluru, Karnataka, India Contact info\n500+ connections\nMessage\nFollow\nMore\nAbout\nAbout\nDedicated psychologist with a strong focus on leveraging insights to drive impactful market research, consumer insights, and UX research initiatives. As a skilled researcher, I have conducted extensive studies to uncover consumer triggers, barriers, and product-market fit. My expertise lies in utilizing both quantitative and qualitative methodologies to deliver actionable recommendations.\n\nWith a deep understanding of human behavior, I excel in analyzing data and providing valuable insights that drive effective marketing strategies and enhance consumer experiences. My background in private practice as a Psychotherapist has honed my ability to empathize and understand complex emotional needs.\n\nI believe that I‚Äôm a person with immense Creativity and Curiosity which makes me think out of the box during Problem Solving. I am passionate about Personal Growth, Mental health and Sustainability.\n‚Ä¶see more\nActivity\nActivity\n693 followers\n693 followers\nPosts\nComments\nLoaded 6 Posts posts\nRhythm Bhaskar reposted this\nArya S V\nArya S V\n   ‚Ä¢ 3rd+\nVerified ‚Ä¢ 3rd+\nHelping startups scale || xto10x || Ex- Swiggy / Bounce / P&G || IIT Bombay. Dakshana. JNV.\nHelping startups scale || xto10x || Ex- Swiggy / Bounce / P&G || IIT Bombay. Dakshana. JNV.\n8mo ‚Ä¢ \n 8 months ago ‚Ä¢ Visible to anyone on or off LinkedIn\nKiller campaign! Loved seeing the work shape up from behind the scenes (though from a distance üòÖ). Kudos to all the team involved\n\n‚Ä¶more\nZivame\nZivame\n142,445 followers\n142,445 followers\nThere‚Äôs a world of boobs out there - each one unique and special. But even today, most makers of bras don‚Äôt think beyond sizes. Our new campaign ‚ÄúThe Museum of Boobs‚Äù challenges this narrative, urging women to recognize and understand their unique breast profiles as an essential step in achieving their perfect fit.\n\nThis initiative is more than a campaign‚Äîit‚Äôs an artful celebration, an experience that brings people together to honor the diversity of breasts and the uniqueness of every body. It embodies a promise of Zivame‚Äôs dedication to pushing boundaries in design to craft intimate wear that seamlessly combines comfort, functionality, and an appreciation for every woman‚Äôs unique shape.\n\n‚Ä¶more\n10\n1 repost\nRhythm Bhaskar reposted this\nxto10x\nxto10x\n21,216 followers\n21,216 followers\n11mo ‚Ä¢ Edited ‚Ä¢ \n 11 months ago ‚Ä¢ Edited ‚Ä¢ Visible to anyone on or off LinkedIn\nWe often get asked: Is xto10x a learning company for founders? A SaaS company? Or a consulting company?\n\nIn reality, we‚Äôre all of these‚Äîand yet so much more. Our journey started with a simple but powerful mission: to make scaling easier for startups around the world.\n\nIn this video, our founders dive deep into the heart of xto10x:\nüéôÔ∏èshares why we started xto10x, drawing from his experience building Flipkart and recognizing the unique challenges that startups face when scaling.\nüéôÔ∏èshares what we solve for‚Äîaddressing the pain points that startups encounter as they grow, and guiding them through these challenges.\nüéôÔ∏èexplains how we solve these challenges, combining our deep operational experience with innovative solutions.\n\nWatch the video to get the full story!\n‚Ä¶more\n138\n14 reposts\nShow all posts\nExperience\nExperience\nBrand Marketing Consultant\nBrand Marketing Consultant\nxto10x ¬∑ Full-time\nxto10x ¬∑ Full-time\nSep 2023 - Present ¬∑ 1 yr 11 mos\nSep 2023 to Present ¬∑ 1 yr 11 mos\nBangalore Urban, Karnataka, India ¬∑ Hybrid\nBangalore Urban, Karnataka, India ¬∑ Hybrid\nPsychotherapist\nPsychotherapist\nPsychotherapist\nSelf-employed\nSelf-employed\nJul 2021 - Present ¬∑ 4 yrs 1 mo\nJul 2021 to Present ¬∑ 4 yrs 1 mo\nBangalore Urban, Karnataka, India ¬∑ On-site\nBangalore Urban, Karnataka, India ¬∑ On-site\n- Provided individual counseling to ~20 repeating clients and designed behavioral programs to help adults cope with various stressors\n- Provided individual counseling to ~20 repeating clients and designed behavioral programs to help adults cope with various stressors\nInterpersonal Skills, empathy and +5 skills\nELEVATE Insights | Marketing Research and Consulting\nELEVATE Insights | Marketing Research and Consulting\nFull-time ¬∑ 4 mos\nFull-time ¬∑ 4 mos\nConsumer Insghts Researcher\nConsumer Insghts Researcher\nJan 2023 - Feb 2023 ¬∑ 2 mos\nJan 2023 to Feb 2023 ¬∑ 2 mos\nBengaluru, Karnataka, India ¬∑ Hybrid\nBengaluru, Karnataka, India ¬∑ Hybrid\n-Conducted several Consumer Research studies utilizing both Quantitative and Qualitative methodologies to understand Triggers, Barriers, Brand fit analysis, and Product Market Fit.\n-Managed the entire research process including developing Interview Discussion Guides, Recruiting participants, leading the Interviews with Users, Analyzing data, and creating Research Reports\n-Analyzed Campaigns and provided insights to clients to improve their Marketing Strategies\nCollaborated with Clients to provide Actionable Recommendations based on research insights to improve their product offerings and Marketing Strategies\n-Created a Repository of Marketing Psychological Theories and Models of Behaviour Change for Elevate Insights which can be utilized for informed Marketing Initiatives, User Experience, and Consumer Insights\n-Created Tailored Consumer Insights Proposals for Pitching to Multiple Companies, resulting in successful new business acquisition.\n- Worked on projects with Carlsberg India, Disney+ Hotstar and LiveAltLife.\nProject Manager Internship\nProject Manager Internship\nNov 2022 - Dec 2022 ¬∑ 2 mos\nNov 2022 to Dec 2022 ¬∑ 2 mos\nIndia ¬∑ Remote\nIndia ¬∑ Remote\nTutor - Statistics, Research Methodology & CUET\nTutor - Statistics, Research Methodology & CUET\nUrbanPro.com ¬∑ Part-time\nUrbanPro.com ¬∑ Part-time\nJan 2022 - Jul 2022 ¬∑ 7 mos\nJan 2022 to Jul 2022 ¬∑ 7 mos\nDelhi, India\nDelhi, India\n‚Ä¢ Tutored Delhi University graduate students in Statistics and Research Methodology semester papers\n‚Ä¢ Tutored Delhi University graduate students in Statistics and Research Methodology semester papers\nCommunication, Teaching and +3 skills\nStudent Intern\nStudent Intern\nFortis Healthcare ¬∑ Internship\nFortis Healthcare ¬∑ Internship\nJun 2020 - Jun 2020 ¬∑ 1 mo\nJun 2020 to Jun 2020 ¬∑ 1 mo\nDelhi, India\nDelhi, India\nShow all 8 experiences\nEducation\nEducation\nDelhi University\nDelhi University\nMaster of Arts - MA, Psychology\nMaster of Arts - MA, Psychology\n2019 - 2021\n2019 - 2021\nGrade: First Division, 3.54 / 4.00 GPA\nGrade: First Division, 3.54 / 4.00 GPA\nActivities and societies: Extra curricular activities, Tutoring Undergraduates and 12th grade students, Volunteering.\nActivities and societies: Extra curricular activities, Tutoring Undergraduates and 12th grade students, Volunteering.\nCoursework : Human Cognition (Theory and Research), Social Psychology, Research Methodology and Statistics, Qualitative Research Methods, Psychometrics, Conflict Resolution and Peace Psychology, Development of Theory of MInd, Behavioural Medicine, Clinical Neuropsychology.\nStatistics, User Experience (UX) and +2 skills\nUniversity of Delhi, Gargi College\nUniversity of Delhi, Gargi College\nUniversity of Delhi, Gargi College\nBachelor of Arts - BA, Applied Psychology\nBachelor of Arts - BA, Applied Psychology\nAug 2016 - May 2019\nAug 2016 - May 2019\nGrade: First Division\nGrade: First Division\nCourse Work : General Psychology, Reserach Methodology and Data Processing in Psychology, psychological assessment, Media Psychology, Abnormal Psychology, Industrial/ Organisational Psychology, Psychology at work, Fundamentals of Statistics and Research, Effective Leadership, Communication Competece\nShow all 3 educations\nLicenses & certifications\nLicenses & certifications\nStart the UX Design Process: Empathize, Define, and Ideate\nStart the UX Design Process: Empathize, Define, and Ideate\n Google UX Design Professional\n Google UX Design Professional\nIssued Sep 2022\nIssued Sep 2022\nCredential ID RDEW682WNBLG\nCredential ID RDEW682WNBLG\nShow credential\nWireframing\nFoundations of User Experience (UX) Design\nFoundations of User Experience (UX) Design\n Google UX Design Professional\n Google UX Design Professional\nIssued Apr 2022\nIssued Apr 2022\nCredential ID 8A73AD67LLDG\nCredential ID 8A73AD67LLDG\nShow credential\nWireframing\nShow all 9 licenses & certifications\nProjects\nProjects\nMaster‚Äôs Dissertation: ‚ÄúExploring the Association between Psychological Flexibility, Student Stress & Anxiety among Indian University Students during COVID-19 Crisis‚Äù\nMaster‚Äôs Dissertation: ‚ÄúExploring the Association between Psychological Flexibility, Student Stress & Anxiety among Indian University Students during COVID-19 Crisis‚Äù\nJan 2021 - May 2021\nJan 2021 - May 2021\nAssociated with Delhi University\nAssociated with Delhi University\nFound using regression analysis, that the Psychological Flexibility negatively predicted (Œ≤ = -.049, t = -5.76, p < 0.001) anxiety among Indian University Students. Thus, highlighting the importance of Psychological Flexibility as a promising resource in reducing anxiety among Indian University Students during the pandemic, using Acceptance Commitment Therapy\n‚Ä¢ Completed the research under supervision of Dr. Ishita Bharadwaj\n‚Ä¢ Was in top 25% of the class to be awarded the opportunity to do dissertation project with the University of Delhi, North Campus\n‚Ä¢ The Paper has been reviewed & accepted, and is in process of being published.\n‚ÄúA Systems approach to addressing Substance Abuse in India: A Community based Psychoeducation Model for Pregnant Women‚Äù\n‚ÄúA Systems approach to addressing Substance Abuse in India: A Community based Psychoeducation Model for Pregnant Women‚Äù\nJul 2020 - Dec 2020\nJul 2020 - Dec 2020\nAssociated with Delhi University\nAssociated with Delhi University\nDesigned a systems model of tobacco cessation for pregnant women from socially disadvantaged background. The model included individual counselling for psychoeducation, relapse prevention and community wide initiatives for policy changes and community health literacy\nVolunteering\nVolunteering\nActivities Coordinator\nActivities Coordinator\nNational Service Scheme\nNational Service Scheme\nJul 2016 - Jul 2017 ¬∑ 1 yr 1 mo\nJul 2016 - Jul 2017 ¬∑ 1 yr 1 mo\nHelped raise awareness about blood donation drive on college campus. Made posters, advertised and helped organise the blood donation camp.\nHelped raise awareness about blood donation drive on college campus. Made posters, advertised and helped organise the blood donation camp.\nSkills\nSkills\nIBM SPSS\nIBM SPSS\nTutor - Statistics, Research Methodology & CUET at UrbanPro.com\nTutor - Statistics, Research Methodology & CUET at UrbanPro.com\n1 endorsement\n1 endorsement\nQualitative & Quantitative Research Methodologies\nQualitative & Quantitative Research Methodologies\nTutor - Statistics, Research Methodology & CUET at UrbanPro.com\nTutor - Statistics, Research Methodology & CUET at UrbanPro.com\nShow all 18 skills\nHonors & awards\nHonors & awards\nGraduate Aptitude Test of Engineering (GATE) Psychology\nGraduate Aptitude Test of Engineering (GATE) Psychology\nIssued by IIT Kharagpur ¬∑ Apr 2022\nIssued by IIT Kharagpur ¬∑ Apr 2022\nJunior Research Fellowship (JRF) Psychology\nJunior Research Fellowship (JRF) Psychology\nIssued by University Grant Commission (UGC) ¬∑ Mar 2022\nIssued by University Grant Commission (UGC) ¬∑ Mar 2022\nThe National Education Testing Bureau of University Grants Commision (UGC) conducts NET to determine eligibility for lectureship in India to ensure standrads for entrants in the teaching and research profession. The top 0.6% of all candidates are recognised by University Grant commission of India for Junior Research Fellowship (JRF).\n\n- Was able to clear the examination in first attempt.\n- Score : 200/300\n- 99.50 percentile score\n‚Ä¶see more\nInterests\nInterests\nTop Voices\nTop Voices\nCompanies\nCompanies\nGroups\nGroups\nSchools\nSchools\nVidit Aatrey\nVidit Aatrey\nFounder & CEO @ Meesho \nFounder & CEO @ Meesho\n295,792 followers\n295,792 followers\nFollow\nKunal Shah\nKunal Shah\nFounder : CRED, curious. \nFounder : CRED, curious.\n1,255,182 followers\n1,255,182 followers\nFollow\nShow all Top Voices\nMore profiles for you\nMore profiles for you\nTanmay A.\nTanmay A.\n¬∑ 3rd+\n3rd+ degree connection\nProduct @ xto10x | Helping startups scale smarter\nProduct @ xto10x | Helping startups scale smarter\nMessage\nSonali Jain\nSonali Jain\nSonali Jain\n¬∑ 3rd+\n3rd+ degree connection\nEmpowering AI startups @ Microsoft | ex - GM, Revenue & GTM at xto10x | ex-McKinsey | IIM-B, SRCC Gold Medalist\nFollow\nAnkit Gupta\nAnkit Gupta\n¬∑ 3rd+\n3rd+ degree connection\nGrowth Leader @ xto10x, ex-Flipkart | BITS Pilani & IIM Alum\nGrowth Leader @ xto10x, ex-Flipkart | BITS Pilani & IIM Alum\nMessage\nShiril Christo\nShiril Christo\n¬∑ 3rd+\n3rd+ degree connection\nHR Consultant | xto10x | Ex-Darwinbox | IBS Hyderabad (2018-2020)\nFollow\nKhushbu Sen\nKhushbu Sen\n¬∑ 3rd+\n3rd+ degree connection\nFinance and legal at xto10x\nFinance and legal at xto10x\nMessage\nShow all\nPeople you may know\nPeople you may know\nFrom Rhythm's school\nFrom Rhythm's school\nSonakshi Bhardwaj\nSonakshi Bhardwaj\nSales Professional at GEMS Education\nSales Professional at GEMS Education\nConnect\nMd. Sameer\nMd. Sameer\nStudent at Delhi University\nStudent at Delhi University\nConnect\nPooja Sharma\nPooja Sharma\nprofessional recruiter||\nTeam leader ||\nBusiness consultant||\nRemote work ||\n\n\nWork from home /fresher jobs - remote work/ part time / Full Time\nConnect\nTina Nanda\nTina Nanda\nDesigner at Freelance | Self-Employed\nDesigner at Freelance | Self-Employed\nConnect\nmitali bakshi\nmitali bakshi\nMarket Development Manager at UKG\nMarket Development Manager at UKG\nConnect\nShow all\nYou might like\nYou might like\nPages for you\nPages for you\nIndiGo (InterGlobe Aviation Ltd)\nIndiGo (InterGlobe Aviation Ltd)\nAirlines and Aviation\nAirlines and Aviation\n913,204 followers\n913,204 followers\nFollow\nDragon Aviation Capital (Singapore) Pte. Ltd.\nDragon Aviation Capital (Singapore) Pte. Ltd.\nAviation and Aerospace Component Manufacturing\nAviation and Aerospace Component Manufacturing\n49,784 followers\n49,784 followers\nFollow\nShow all\nAbout\nAccessibility\nTalent Solutions\nProfessional Community Policies\nCareers\nMarketing Solutions\nPrivacy & Terms\nAd Choices\nAdvertising\nSales Solutions\nMobile\nSmall Business\nSafety Center\nQuestions?\nVisit our Help Center.\nManage your account and privacy\nGo to your Settings.\nRecommendation transparency\nLearn more about Recommended Content.\nSelect Language\n         ÿßŸÑÿπÿ±ÿ®Ÿäÿ© (Arabic)\n         ‡¶¨‡¶æ‡¶Ç‡¶≤‡¶æ (Bangla)\n         ƒåe≈°tina (Czech)\n         Dansk (Danish)\n         Deutsch (German)\n         ŒïŒªŒªŒ∑ŒΩŒπŒ∫Œ¨ (Greek)\n         English (English)\n         Espa√±ol (Spanish)\n         ŸÅÿßÿ±ÿ≥€å (Persian)\n         Suomi (Finnish)\n         Fran√ßais (French)\n         ‡§π‡§ø‡§Ç‡§¶‡•Ä (Hindi)\n         Magyar (Hungarian)\n         Bahasa Indonesia (Indonesian)\n         Italiano (Italian)\n         ◊¢◊ë◊®◊ô◊™ (Hebrew)\n         Êó•Êú¨Ë™û (Japanese)\n         ÌïúÍµ≠Ïñ¥ (Korean)\n         ‡§Æ‡§∞‡§æ‡§†‡•Ä (Marathi)\n         Bahasa Malaysia (Malay)\n         Nederlands (Dutch)\n         Norsk (Norwegian)\n         ‡®™‡©∞‡®ú‡®æ‡®¨‡©Ä (Punjabi)\n         Polski (Polish)\n         Portugu√™s (Portuguese)\n         Rom√¢nƒÉ (Romanian)\n         –†—É—Å—Å–∫–∏–π (Russian)\n         Svenska (Swedish)\n         ‡∞§‡±Ü‡∞≤‡±Å‡∞ó‡±Å (Telugu)\n         ‡∏†‡∏≤‡∏©‡∏≤‡πÑ‡∏ó‡∏¢ (Thai)\n         Tagalog (Tagalog)\n         T√ºrk√ße (Turkish)\n         –£–∫—Ä–∞—ó–Ω—Å—å–∫–∞ (Ukrainian)\n         Ti·∫øng Vi·ªát (Vietnamese)\n         ÁÆÄ‰Ωì‰∏≠Êñá (Chinese (Simplified))\n         Ê≠£È´î‰∏≠Êñá (Chinese (Traditional))\n     LinkedIn Corporation ¬© 2025\nStatus is online\nMessaging\nYou are on the messaging overlay. Press enter to open the list of conversations.\nCompose message\nYou are on the messaging overlay. Press enter to open the list of conversations.",
  "skills_text": "ÈÅ∏ÊìáË™ûË®Ä\n                Bahasa Indonesia (Bahasa Indonesia)\n                Bahasa Malaysia (Malay)\n                ƒåe≈°tina (Czech)\n                Dansk (Danish)\n                Deutsch (German)\n                English (English)\n                Espa√±ol (Spanish)\n                ÁπÅÈ´î‰∏≠Êñá (Chinese (Traditional))\n                Fran√ßais (French)\n                ÌïúÍµ≠Ïñ¥ (Korean)\n                Italiano (Italian)\n                ÁÆÄ‰Ωì‰∏≠Êñá (Chinese (Simplified))\n                Nederlands (Dutch)\n                Êó•Êú¨Ë™û (Japanese)\n                Norsk (Norwegian)\n                Polski (Polish)\n                Portugu√™s (Portuguese)\n                Rom√¢nƒÉ (Romanian)\n                –†—É—Å—Å–∫–∏–π (Russian)\n                Svenska (Swedish)\n                Tagalog (Tagalog)\n                ‡∏†‡∏≤‡∏©‡∏≤‡πÑ‡∏ó‡∏¢ (Thai)\n                T√ºrk√ße (Turkish)\n                ÿßŸÑÿπÿ±ÿ®Ÿäÿ© (Arabic)\n          \n             Page not found\nUh oh, we can‚Äôt seem to find the page you‚Äôre looking for. Try going back to the previous page or see our Help Center for more information\nGo to your feed\n¬© 2022 User Agreement Privacy Policy Community Guidelines Cookie Policy Copyright Policy Guest Controls",
  "scraped_at": "2025-07-22 22:01:12",
  "has_skills": true,
  "cleaned_profile": {
    "name": "Rhythm Bhaskar",
    "profile_url": "https://in.linkedin.com/in/rhythm-bhaskar-55616a22a",
    "current_position": {
      "title": "Brand Marketing Consultant",
      "company": "xto10x",
      "location": "Bangalore Urban, Karnataka, India",
      "start_date": "Sep 2023",
      "end_date": "Present",
      "duration": "1 yr 11 mos"
    },
    "previous_positions": [
      {
        "title": "Psychotherapist",
        "company": "Self-employed",
        "location": "Bangalore Urban, Karnataka, India",
        "start_date": "Jul 2021",
        "end_date": "Present",
        "duration": "4 yrs 1 mo"
      },
      {
        "title": "Consumer Insights Researcher",
        "company": "ELEVATE Insights | Marketing Research and Consulting",
        "location": "Bengaluru, Karnataka, India",
        "start_date": "Jan 2023",
        "end_date": "Feb 2023",
        "duration": "2 mos"
      },
      {
        "title": "Project Manager Internship",
        "company": "ELEVATE Insights | Marketing Research and Consulting",
        "location": "India",
        "start_date": "Nov 2022",
        "end_date": "Dec 2022",
        "duration": "2 mos"
      },
      {
        "title": "Tutor - Statistics, Research Methodology & CUET",
        "company": "UrbanPro.com",
        "location": "Delhi, India",
        "start_date": "Jan 2022",
        "end_date": "Jul 2022",
        "duration": "7 mos"
      },
      {
        "title": "Student Intern",
        "company": "Fortis Healthcare",
        "location": "Delhi, India",
        "start_date": "Jun 2020",
        "end_date": "Jun 2020",
        "duration": "1 mo"
      }
    ],
    "education": [
      {
        "institution": "Delhi University",
        "degree": "Master of Arts - MA",
        "field_of_study": "Psychology",
        "years_attended": "2019 - 2021"
      },
      {
        "institution": "University of Delhi, Gargi College",
        "degree": "Bachelor of Arts - BA",
        "field_of_study": "Applied Psychology",
        "years_attended": "Aug 2016 - May 2019"
      }
    ],
    "connections": "500+",
    "followers": 693,
    "skills": [
      "IBM SPSS",
      "Qualitative & Quantitative Research Methodologies",
      "Interpersonal Skills",
      "Empathy",
      "Communication",
      "Teaching"
    ],
    "interests": [
      "Vidit Aatrey",
      "Kunal Shah"
    ]
  },
  "tokens_used": {
    "prompt_tokens": 4083,
    "completion_tokens": 638,
    "total_tokens": 4721
  }
}