{
  "url": "https://in.linkedin.com/in/mahathi-g",
  "raw_text": "0 notifications total\nnew feed updates notifications\nHome\n1\n1 new network update notification\nMy Network\nJobs\nMessaging\nNotifications\nMe\nFor Business\nTry Premium for ‚Çπ0\nMahathi has a {:badgeType} account\nMahathi Gopalakrishnan\nPrev. McKinsey, xto10x\nSt. Xavier's College\nBengaluru, Karnataka, India Contact info\n500+ connections\nMessage\nFollow\nMore\nAbout\nAbout\nHello! If you're here, you've found the internet manifestation of my quest to find work that feels like play. Welcome :)\n\nI'm driven by a curiosity surrounding what I can do to make people's personal and professional lives easier or more meaningful. My path (from consulting to edtech to founder development to entrepreneurship) has been shaped by this curiosity.\n\nEach step has taught me something valuable: how big companies transform even at their scales, how beautiful products grow, how founders learn and lead, and how to validate ideas directly with users.\n\nWhen I'm not working, you'll find me experimenting in the kitchen, training my voice to sing well all the songs I sing badly anyway, or reading!\n‚Ä¶see more\nActivity\nActivity\n1,794 followers\n1,794 followers\nPosts\nComments\nLoaded 9 Posts posts\nMahathi Gopalakrishnan\nMahathi Gopalakrishnan\nMahathi Gopalakrishnan\n   ‚Ä¢ 3rd+\nPremium ‚Ä¢ 3rd+\nPrev. McKinsey, xto10x\nPrev. McKinsey, xto10x\n9mo ‚Ä¢ \n 9 months ago ‚Ä¢ Visible to anyone on or off LinkedIn\nHello! Veni Gupta and I are looking to work with freelancers who can help with visual identity design/ brand identity design/ graphic design. Would love to work with folks who have experience with illustrations! \n\nPlease message if you're interested and amplify for good karma üôèüèª\n65\n22 comments\n1 repost\nMahathi Gopalakrishnan\nMahathi Gopalakrishnan\nMahathi Gopalakrishnan\n   ‚Ä¢ 3rd+\nPremium ‚Ä¢ 3rd+\nPrev. McKinsey, xto10x\nPrev. McKinsey, xto10x\n10mo ‚Ä¢ \n 10 months ago ‚Ä¢ Visible to anyone on or off LinkedIn\nHello! We are looking for a Fit Technician (expert in bras) for a freelance project. \n\nCurrent requirement is for one style. \n\nPlease reach out if interested!\n\nhashtag\n#lingerie \nhashtag\n#lingeriesupplier \nhashtag\n#innerwear \nhashtag\n#intimatewear \nhashtag\n#patternmaker \nhashtag\n#fittech \nhashtag\n#freelancepatternmaker\n26\n2 comments\n2 reposts\nShow all posts\nExperience\nExperience\nPersonal goal pursuit\nPersonal goal pursuit\nCareer Break\nCareer Break\nApr 2024 - Present ¬∑ 1 yr 4 mos\nApr 2024 to Present ¬∑ 1 yr 4 mos\nBengaluru, Karnataka, India\nBengaluru, Karnataka, India\nLearnt what it means to be intentional by experimenting (personally and professionally)\n\n- Explored entrepreneurship: My co-founder and I conducted research with 200+ users, developed samples with manufacturers across Asia, and began building brand identity; Discovered I'd love to start up when truly pulled by a problem + learnt about my strengths and what makes work fulfilling for me\n- Began expanding my brain dimensionally by relearning baking (I make banging cookies now) and learning to sing\n- Completed a 10-day Vipassana meditation course to build resilience and equanimity\nBuilding 10xAcademy\nBuilding 10xAcademy\nxto10x ¬∑ Full-time\nxto10x ¬∑ Full-time\nOct 2021 - Mar 2024 ¬∑ 2 yrs 6 mos\nOct 2021 to Mar 2024 ¬∑ 2 yrs 6 mos\nBengaluru, Karnataka, India\nBengaluru, Karnataka, India\nWore multiple hats to help founders navigate the messy middle of scaling up\n\n1. As part of the Leadership Learning team and the Growth Consulting team:\n- Led xto10x's flagship 3-month learning program for founders of B2C/ D2C growth-stage startups in partnership with Peak XV Partners (formerly Sequoia India & SEA) - pivoted the offering to focus on sustainable growth with deeper 1:1 mentorship and brought 7 startups (including Minimalist, Qoala, Eduvanz) through the program\n- Developed growth roadmaps for consumer startups looking to uncover new growth levers, by leveraging user research and app usage data. For e.g., helped India's first e-bike producer unlock a previously untapped market\n\n2. As a Product and Marketing Lead:\n- Created 'Leadership Quotient' from scratch - a first-of-its-kind tool that helps founders and startup leaders understand and elevate their leadership style. This was the first time I worked with developers and designers to bring a product to life, and I absolutely loved this experience!\n- Built founder-centric communities - launched 'The Startup Summit' (bringing 100+ new startups into xto10x's top-of-funnel) and 'The Startup Founders' Community' (creating trusted circles for 25+ growth-stage founders)\nGrowth & Strategy\nGrowth & Strategy\nToddle - Your Teaching Partner\nToddle - Your Teaching Partner\nMar 2021 - Sep 2021 ¬∑ 7 mos\nMar 2021 to Sep 2021 ¬∑ 7 mos\nBengaluru, Karnataka, India ¬∑ Remote\nBengaluru, Karnataka, India ¬∑ Remote\nHelped the team test and prove growth levers\n\n- Planned GTM strategy for a new vertical (Toddle for IBDP) and collaborated with COO and sales teams to identify the right staffing requirements to launch and scale the product's revenues significantly\n- Worked with the CEO to design and launch new GTM channels including affiliate programs in regions where we had low penetration (like LatAm) - drove meaningful revenue growth within just 3 months of starting the initiatives\nBusiness Analyst\nBusiness Analyst\nMcKinsey & Company\nMcKinsey & Company\nAug 2019 - Mar 2021 ¬∑ 1 yr 8 mos\nAug 2019 to Mar 2021 ¬∑ 1 yr 8 mos\nMumbai Metropolitan Region\nMumbai Metropolitan Region\nWorked on projects spanning retail, banking, education, and private equity\n\n- Designed a first-of-its-kind retail cost transformation program for a large Indian grocery retailer - independently led store cost transformation efforts and instituted an innovative part-time staffing model across their extensive store network of roughly 700 stores\n- Partnered with McKinsey's specialist change facilitation team (Aberkyn) to design and deliver a leadership development & cultural transformation program during the merger of three large public sector banks - created development plans for leaders to gain role clarity and build trust\n- Led strategic initiatives for an education non-profit, including implementing blended learning approaches and developing an expansion plan to diversify impact beyond Tier 1 cities\nEducation\nEducation\nSt. Xavier's College\nSt. Xavier's College\nBachelor of Arts, Economics and Statistics\nBachelor of Arts, Economics and Statistics\n2016 - 2019\n2016 - 2019\nActivities and societies: Economics Circle, Indian Music Group, Malhar (Annual Intercollegiate Festival)\nActivities and societies: Economics Circle, Indian Music Group, Malhar (Annual Intercollegiate Festival)\nProjects\nProjects\nA Study of the Female Labour Force Participation in Uttar Pradesh\nA Study of the Female Labour Force Participation in Uttar Pradesh\nSep 2018 - Present\nSep 2018 - Present\nA Study of the Fiscal and Monetary Policy Interface of Singapore and its Impact on Macroeconomic Management\nA Study of the Fiscal and Monetary Policy Interface of Singapore and its Impact on Macroeconomic Management\nFeb 2018 - Present\nFeb 2018 - Present\nSkills\nSkills\nMicrosoft Excel\nMicrosoft Excel\n3 endorsements\n3 endorsements\nMicrosoft Word\nMicrosoft Word\nShow all 8 skills\nLanguages\nLanguages\nEnglish\nEnglish\nFull professional proficiency\nFull professional proficiency\nFrench\nFrench\nElementary proficiency\nElementary proficiency\nShow all 5 languages\nOrganizations\nOrganizations\nMalhar\nMalhar\nOrganiser-in-Charge, Finance ¬∑ May 2018 - Aug 2018\nOrganiser-in-Charge, Finance ¬∑ May 2018 - Aug 2018\nIndian Music Group\nIndian Music Group\nTreasurer ¬∑ Jul 2017 - Apr 2018\nTreasurer ¬∑ Jul 2017 - Apr 2018\nInterests\nInterests\nTop Voices\nTop Voices\nCompanies\nCompanies\nGroups\nGroups\nSchools\nSchools\nMelinda French Gates\nMelinda French Gates\nFounder of Pivotal. Co-founder of the Gates Foundation. Author of The Moment of Lift.\nFounder of Pivotal. Co-founder of the Gates Foundation. Author of The Moment of Lift.\n6,658,450 followers\n6,658,450 followers\nFollow\nMark Cuban\nMark Cuban\nPresident\nPresident\n8,079,416 followers\n8,079,416 followers\nFollow\nShow all Top Voices\nMore profiles for you\nMore profiles for you\nCharu Gupta\nCharu Gupta\n¬∑ 3rd+\n3rd+ degree connection\nEIR at Urban Company | McKinsey | Lady Shri Ram College\nFollow\nAnjali I.\nAnjali I.\nAnjali I.\n¬∑ 3rd+\n3rd+ degree connection\nMcKinsey & Company\nMcKinsey & Company\nConnect\nSneha Dhawan\nSneha Dhawan\n¬∑ 3rd+\n3rd+ degree connection\nBuilding | Ex McKinsey & Company | Ex DB | St. Stephen‚Äôs College\nConnect\nPoorvi Gupta\nPoorvi Gupta\n¬∑ 3rd+\n3rd+ degree connection\nBuilding Blinkit | Prev. McKinsey\nBuilding Blinkit | Prev. McKinsey\nConnect\nRadhika Dikay\nRadhika Dikay\n¬∑ 3rd+\n3rd+ degree connection\nKearney | SXC'22 Economics & Statistics\nKearney | SXC'22 Economics & Statistics\nConnect\nShow all\nPeople you may know\nPeople you may know\nFrom Mahathi's school\nFrom Mahathi's school\nRahul Vyas\nRahul Vyas\nStudent at St. Xavier's College\nStudent at St. Xavier's College\nConnect\nSahil Singh\nSahil Singh\nSocial Worker at Tech Mahindra\nSocial Worker at Tech Mahindra\nConnect\nBerozgar Engineer\nBerozgar Engineer\nCivil Engineer @ SAP | Business Administration, Management\nCivil Engineer @ SAP | Business Administration, Management\nConnect\nGanesh Devadiga\nGanesh Devadiga\n--\"Results-Driven Accountant | 7+ Years of Experience in Financial Management & Compliance\"\nConnect\nFirdaus Khanam\nFirdaus Khanam\nHR Recruiter Of Niyukti placement \nHR Recruiter Of Niyukti placement\nConnect\nShow all\nYou might like\nYou might like\nPages for you\nPages for you\nServiceSetu Academics\nServiceSetu Academics\nHigher Education\nHigher Education\n35,208 followers\n35,208 followers\nFollow\nVisa Protect Risk Solutions\nVisa Protect Risk Solutions\nIT Services and IT Consulting\nIT Services and IT Consulting\n16,227 followers\n16,227 followers\nFollow\nShow all\nAbout\nAccessibility\nTalent Solutions\nProfessional Community Policies\nCareers\nMarketing Solutions\nPrivacy & Terms\nAd Choices\nAdvertising\nSales Solutions\nMobile\nSmall Business\nSafety Center\nQuestions?\nVisit our Help Center.\nManage your account and privacy\nGo to your Settings.\nRecommendation transparency\nLearn more about Recommended Content.\nSelect Language\n         ÿßŸÑÿπÿ±ÿ®Ÿäÿ© (Arabic)\n         ‡¶¨‡¶æ‡¶Ç‡¶≤‡¶æ (Bangla)\n         ƒåe≈°tina (Czech)\n         Dansk (Danish)\n         Deutsch (German)\n         ŒïŒªŒªŒ∑ŒΩŒπŒ∫Œ¨ (Greek)\n         English (English)\n         Espa√±ol (Spanish)\n         ŸÅÿßÿ±ÿ≥€å (Persian)\n         Suomi (Finnish)\n         Fran√ßais (French)\n         ‡§π‡§ø‡§Ç‡§¶‡•Ä (Hindi)\n         Magyar (Hungarian)\n         Bahasa Indonesia (Indonesian)\n         Italiano (Italian)\n         ◊¢◊ë◊®◊ô◊™ (Hebrew)\n         Êó•Êú¨Ë™û (Japanese)\n         ÌïúÍµ≠Ïñ¥ (Korean)\n         ‡§Æ‡§∞‡§æ‡§†‡•Ä (Marathi)\n         Bahasa Malaysia (Malay)\n         Nederlands (Dutch)\n         Norsk (Norwegian)\n         ‡®™‡©∞‡®ú‡®æ‡®¨‡©Ä (Punjabi)\n         Polski (Polish)\n         Portugu√™s (Portuguese)\n         Rom√¢nƒÉ (Romanian)\n         –†—É—Å—Å–∫–∏–π (Russian)\n         Svenska (Swedish)\n         ‡∞§‡±Ü‡∞≤‡±Å‡∞ó‡±Å (Telugu)\n         ‡∏†‡∏≤‡∏©‡∏≤‡πÑ‡∏ó‡∏¢ (Thai)\n         Tagalog (Tagalog)\n         T√ºrk√ße (Turkish)\n         –£–∫—Ä–∞—ó–Ω—Å—å–∫–∞ (Ukrainian)\n         Ti·∫øng Vi·ªát (Vietnamese)\n         ÁÆÄ‰Ωì‰∏≠Êñá (Chinese (Simplified))\n         Ê≠£È´î‰∏≠Êñá (Chinese (Traditional))\n     LinkedIn Corporation ¬© 2025\nStatus is online\nMessaging\nYou are on the messaging overlay. Press enter to open the list of conversations.\nCompose message\nYou are on the messaging overlay. Press enter to open the list of conversations.",
  "skills_text": "0 notifications total\nnew feed updates notifications\nHome\n1\n1 new network update notification\nMy Network\nJobs\nMessaging\nNotifications\nMe\nFor Business\nTry Premium for ‚Çπ0\nMahathi Gopalakrishnan\nPrev. McKinsey, xto10x\nMore\nFollow\nMessage\nSkills\nAll\nIndustry Knowledge\nTools & Technologies\nInterpersonal Skills\nMicrosoft Excel\nMicrosoft Excel\n3 endorsements\n3 endorsements\nMicrosoft Word\nMicrosoft Word\nMicrosoft PowerPoint\nMicrosoft PowerPoint\nResearch\nResearch\nLeadership\nLeadership\n5 endorsements\n5 endorsements\nTeamwork\nTeamwork\n2 endorsements\n2 endorsements\nPrimary Research\nPrimary Research\nSecondary Research\nSecondary Research\nMore profiles for you\nMore profiles for you\nCharu Gupta\nCharu Gupta\n¬∑ 3rd+\n3rd+ degree connection\nEIR at Urban Company | McKinsey | Lady Shri Ram College\nFollow\nAnjali I.\nAnjali I.\nAnjali I.\n¬∑ 3rd+\n3rd+ degree connection\nMcKinsey & Company\nMcKinsey & Company\nConnect\nSneha Dhawan\nSneha Dhawan\n¬∑ 3rd+\n3rd+ degree connection\nBuilding | Ex McKinsey & Company | Ex DB | St. Stephen‚Äôs College\nConnect\nPoorvi Gupta\nPoorvi Gupta\n¬∑ 3rd+\n3rd+ degree connection\nBuilding Blinkit | Prev. McKinsey\nBuilding Blinkit | Prev. McKinsey\nConnect\nRadhika Dikay\nRadhika Dikay\n¬∑ 3rd+\n3rd+ degree connection\nKearney | SXC'22 Economics & Statistics\nKearney | SXC'22 Economics & Statistics\nConnect\nShow more\nAbout\nAccessibility\nTalent Solutions\nProfessional Community Policies\nCareers\nMarketing Solutions\nPrivacy & Terms\nAd Choices\nAdvertising\nSales Solutions\nMobile\nSmall Business\nSafety Center\nQuestions?\nVisit our Help Center.\nManage your account and privacy\nGo to your Settings.\nRecommendation transparency\nLearn more about Recommended Content.\nSelect Language\n         ÿßŸÑÿπÿ±ÿ®Ÿäÿ© (Arabic)\n         ‡¶¨‡¶æ‡¶Ç‡¶≤‡¶æ (Bangla)\n         ƒåe≈°tina (Czech)\n         Dansk (Danish)\n         Deutsch (German)\n         ŒïŒªŒªŒ∑ŒΩŒπŒ∫Œ¨ (Greek)\n         English (English)\n         Espa√±ol (Spanish)\n         ŸÅÿßÿ±ÿ≥€å (Persian)\n         Suomi (Finnish)\n         Fran√ßais (French)\n         ‡§π‡§ø‡§Ç‡§¶‡•Ä (Hindi)\n         Magyar (Hungarian)\n         Bahasa Indonesia (Indonesian)\n         Italiano (Italian)\n         ◊¢◊ë◊®◊ô◊™ (Hebrew)\n         Êó•Êú¨Ë™û (Japanese)\n         ÌïúÍµ≠Ïñ¥ (Korean)\n         ‡§Æ‡§∞‡§æ‡§†‡•Ä (Marathi)\n         Bahasa Malaysia (Malay)\n         Nederlands (Dutch)\n         Norsk (Norwegian)\n         ‡®™‡©∞‡®ú‡®æ‡®¨‡©Ä (Punjabi)\n         Polski (Polish)\n         Portugu√™s (Portuguese)\n         Rom√¢nƒÉ (Romanian)\n         –†—É—Å—Å–∫–∏–π (Russian)\n         Svenska (Swedish)\n         ‡∞§‡±Ü‡∞≤‡±Å‡∞ó‡±Å (Telugu)\n         ‡∏†‡∏≤‡∏©‡∏≤‡πÑ‡∏ó‡∏¢ (Thai)\n         Tagalog (Tagalog)\n         T√ºrk√ße (Turkish)\n         –£–∫—Ä–∞—ó–Ω—Å—å–∫–∞ (Ukrainian)\n         Ti·∫øng Vi·ªát (Vietnamese)\n         ÁÆÄ‰Ωì‰∏≠Êñá (Chinese (Simplified))\n         Ê≠£È´î‰∏≠Êñá (Chinese (Traditional))\n     LinkedIn Corporation ¬© 2025\nStatus is online\nMessaging\nYou are on the messaging overlay. Press enter to open the list of conversations.\nCompose message\nYou are on the messaging overlay. Press enter to open the list of conversations.",
  "scraped_at": "2025-07-22 23:14:06",
  "has_skills": true,
  "cleaned_profile": {
    "name": "Mahathi Gopalakrishnan",
    "profile_url": "https://in.linkedin.com/in/mahathi-g",
    "current_position": {
      "title": "Personal goal pursuit",
      "company": "Career Break",
      "location": "Bengaluru, Karnataka, India",
      "start_date": "Apr 2024",
      "end_date": "Present",
      "duration": "1 yr 4 mos"
    },
    "previous_positions": [
      {
        "title": "Building 10xAcademy",
        "company": "xto10x",
        "location": "Bengaluru, Karnataka, India",
        "start_date": "Oct 2021",
        "end_date": "Mar 2024",
        "duration": "2 yrs 6 mos"
      },
      {
        "title": "Growth & Strategy",
        "company": "Toddle - Your Teaching Partner",
        "location": "Bengaluru, Karnataka, India",
        "start_date": "Mar 2021",
        "end_date": "Sep 2021",
        "duration": "7 mos"
      },
      {
        "title": "Business Analyst",
        "company": "McKinsey & Company",
        "location": "Mumbai Metropolitan Region",
        "start_date": "Aug 2019",
        "end_date": "Mar 2021",
        "duration": "1 yr 8 mos"
      }
    ],
    "education": [
      {
        "institution": "St. Xavier's College",
        "degree": "Bachelor of Arts",
        "field_of_study": "Economics and Statistics",
        "years_attended": "2016 - 2019"
      }
    ],
    "connections": "500+",
    "followers": 1794,
    "skills": [
      "Microsoft Excel",
      "Microsoft Word",
      "Microsoft PowerPoint",
      "Research",
      "Leadership",
      "Teamwork",
      "Primary Research",
      "Secondary Research"
    ],
    "interests": [
      "Melinda French Gates",
      "Mark Cuban"
    ]
  },
  "tokens_used": {
    "prompt_tokens": 3600,
    "completion_tokens": 460,
    "total_tokens": 4060
  }
}