{
  "url": "https://in.linkedin.com/in/ninaad-lohakare-632bb613a",
  "raw_text": "0 notifications total\nnew feed updates notifications\nHome\n1\n1 new network update notification\nMy Network\nJobs\nMessaging\nNotifications\nMe\nFor Business\nTry Premium for ₹0\nNinaad Lohakare\nToddle | xto10x | AB InBev\nToddle - Your Teaching Partner\nIndian Institute of Technology, Kharagpur\nBengaluru, Karnataka, India Contact info\n500+ connections\nMessage\nFollow\nMore\nAbout\nAbout\nSpearheading Toddle’s growth in EMEA\nSpearheading Toddle’s growth in EMEA\nActivity\nActivity\n7,507 followers\n7,507 followers\nPosts\nComments\nLoaded 9 Posts posts\nNinaad Lohakare\nNinaad Lohakare\n   • 3rd+\nVerified • 3rd+\nToddle | xto10x | AB InBev\nToddle | xto10x | AB InBev\n3w • \n 3 weeks ago • Visible to anyone on or off LinkedIn\nMy man 🫡\nBosch Mobility\nBosch Mobility\n218,146 followers\n218,146 followers\nAt Bosch, our engineers push boundaries — both on the test bench and on the track.\n\nBehind every smooth ride is a system built with precision. From optimizing powertrain performance to enhancing the rider experience, we constantly engineer solutions that deliver more power, greater efficiency, and unmatched comfort — mile after mile.\n\nAs we mark 10 years ofin two-wheeler mobility, the Rider Stories celebrates engineers like— those who ride, build, and redefine what’s possible.\n\nThe final story of the series drops soon. Stay tuned. 😊\n\nRide\n\n&\n…more\n7\nNinaad Lohakare reposted this\nToddle - Your Teaching Partner\nToddle - Your Teaching Partner\n71,475 followers\n71,475 followers\n5mo • \n 5 months ago • Visible to anyone on or off LinkedIn\nToddle Demo Day 4.0 is here. This changes so much for educators. 👇\n\nJoin us as we bring the power of AI to the most demanding aspects of teaching: curriculum design, assessment, and grading.\n\nImagine what you can achieve with:\n🔥 A limitlessly creative curriculum planning assistant to elevate every step of planning, from units to lesson plans.\n🔥 AI-powered worksheets that transform simple objectives into high-quality assessments in seconds.\n🔥 A smart grading companion that takes a great first pass at evaluating student work, cutting your grading workload in half.\n\nCome see it live on March 13, or sign up to get the recording.\n\n…more\nActivate to view larger image,\n1/5\nActivate to view larger image,\n116\n2 comments\n34 reposts\nShow all posts\nExperience\nExperience\nAssociate Director, Growth\nAssociate Director, Growth\nToddle - Your Teaching Partner · Full-time\nToddle - Your Teaching Partner · Full-time\nJun 2024 - Present · 1 yr 2 mos\nJun 2024 to Present · 1 yr 2 mos\nBengaluru, Karnataka, India\nBengaluru, Karnataka, India\nLeading the Europe, Middle East & Africa expansion for Toddle\nLeading the Europe, Middle East & Africa expansion for Toddle\nBuilding 10xScale\nBuilding 10xScale\nxto10x · Full-time\nxto10x · Full-time\nApr 2022 - May 2024 · 2 yrs 2 mos\nApr 2022 to May 2024 · 2 yrs 2 mos\nLed engagements with 10+ startups in sectors like FinTech, AgriTech, Vertical SaaS, Logistics & Consumer\n- Worked deeply with the founders of a series A startup on ideation & execution of projects like org design, business model redesign, employee NPS & leadership training; Helped setup capabilities like business finance, OKRs, PMO\n- Built the roadmap to reduce monthly burn for a client by $1M via efficiencies such as LTV growth via account farming, CAC optimization and Org restructuring; project currently under implementation with a $300k savings already realized\n- Leveraged insights from engagements to create playbooks for B2B burn reduction, account management & leadership development\n- Involved in deep community building initiatives, spearheaded the xto10x foundation day celebration with a footfall of 50+ startups & VCs\nProblem Solving, Management Consulting and +2 skills\nGlobal Management Trainee\nGlobal Management Trainee\nAB InBev India · Full-time\nAB InBev India · Full-time\nJul 2021 - Mar 2022 · 9 mos\nJul 2021 to Mar 2022 · 9 mos\n7 out of 2000+ applicants across India hand-picked to be a part of the flagship global leadership program at the world’s largest brewer\n7 out of 2000+ applicants across India hand-picked to be a part of the flagship global leadership program at the world’s largest brewer\nProblem Solving, Sales and +2 skills\nVice President\nVice President\nTechnology Students' Gymkhana, IIT Kharagpur\nTechnology Students' Gymkhana, IIT Kharagpur\nApr 2019 - Jul 2020 · 1 yr 4 mos\nApr 2019 to Jul 2020 · 1 yr 4 mos\nElected by an electorate of 11,798 students to Chair the Students Senate (highest student position at IIT KGP)\n• Led 50+ office bearers & 150+ fest coordinators; executed 100+ year-long events; managed 18 societies and a total budget of INR 140 m\n• Part of the core team created to tackle Covid-19, ensured safety the 25k+ campus residents; making it the only COVID-free area in KGP\n• Arranged safe and legal transport for 300+ students from cyclone-affected rural regions by working with the district and state authorities\n• Promptly established preventive systems like Quarantine ward, Medical QRT, Thermal Scanners, Campus Lockdown and Essentials Delivery\n• Ideated the academic plan for the affected and next semester, liaised with the administration to get it approved in the Institute Senate\n• Co-Conveyer for the 54th Inter-IIT Sports Meet; managed a total budget of INR 40 m; saw a footfall of 2348 students, faculty and officers\nMarket Analyst Intern \nMarket Analyst Intern\nFutures First · Internship\nFutures First · Internship\nMay 2020 - Jun 2020 · 2 mos\nMay 2020 to Jun 2020 · 2 mos\nProject: Tasked at trading derivatives in the global oil markets by conducting trend analysis and market study\n• Realized a 65% success rate generating a profit of $ 5200 during the period; executed a total of 350+ trades exceeding all given targets\n• Conducted trend-line and price analysis to identify trade entry and exit points for Crude Oil (CL), Heating Oil (HO) and Gasoline (RBOB)\n• Realized a success rate of 53% in automated trades; developed algorithms using Algo Design Lab and identified optimum stop-losses\nShow all 15 experiences\nEducation\nEducation\nIndian Institute of Technology, Kharagpur\nIndian Institute of Technology, Kharagpur\nDual Degree , Mechanical Engineering\nDual Degree , Mechanical Engineering\n2016 - 2021\n2016 - 2021\nActivities and societies: Vice-President, TSG | Entrepreneurship Cell | Cultural\nActivities and societies: Vice-President, TSG | Entrepreneurship Cell | Cultural\nDr. Ambedkar College, Nagpur\nDr. Ambedkar College, Nagpur\nHigher Secondary School Certificate, Bifocal : Electronics\nHigher Secondary School Certificate, Bifocal : Electronics\nGrade: HSSC - 92.40% \nGrade: HSSC - 92.40%\nActivities and societies: Debate | Public Speaking | Student Council\nActivities and societies: Debate | Public Speaking | Student Council\nShow all 3 educations\nVolunteering\nVolunteering\nCadet\nCadet\nNATIONAL CADET CORPS - India\nNATIONAL CADET CORPS - India\nJul 2016 - Apr 2018 · 1 yr 10 mos\nJul 2016 - Apr 2018 · 1 yr 10 mos\nSocial Services\nSocial Services\nQualified the B-Certificate examination | Awarded best cadet in the division\nQualified the B-Certificate examination | Awarded best cadet in the division\nScout\nScout\nThe Bharat Scouts and Guides\nThe Bharat Scouts and Guides\nJul 2010 - Apr 2013 · 2 yrs 10 mos\nJul 2010 - Apr 2013 · 2 yrs 10 mos\nDisaster and Humanitarian Relief\nDisaster and Humanitarian Relief\nCleared Rajyapuraskar exam | Awarded best scout in the camp | Selected for Rashtrapati scout\nCleared Rajyapuraskar exam | Awarded best scout in the camp | Selected for Rashtrapati scout\nSkills\nSkills\nAttention to Detail\nAttention to Detail\nBuilding 10xScale at xto10x\nBuilding 10xScale at xto10x\nStartup Development\nStartup Development\nBuilding 10xScale at xto10x\nBuilding 10xScale at xto10x\nShow all 16 skills\nCourses\nCourses\nAccounting Fundamentals\nAccounting Fundamentals\nReading Financial Statements\nReading Financial Statements\nShow all 3 courses\nHonors & awards\nHonors & awards\nAmrit Barman Memorial Award\nAmrit Barman Memorial Award\nIssued by Technology Students' Gymkhana, IIT Kharagpur · Apr 2021\nIssued by Technology Students' Gymkhana, IIT Kharagpur · Apr 2021\nAssociated with Technology Students' Gymkhana, IIT Kharagpur\nAssociated with Technology Students' Gymkhana, IIT Kharagpur\nAnnual recognition awarded for displaying exemplary student leadership\nAnnual recognition awarded for displaying exemplary student leadership\nP&G Technical Games\nP&G Technical Games\nIssued by P&G · Jul 2020\nIssued by P&G · Jul 2020\nAssociated with Indian Institute of Technology, Kharagpur\nAssociated with Indian Institute of Technology, Kharagpur\nWon the silver medal in this national supply chain case challenge\nWon the silver medal in this national supply chain case challenge\nShow all 3 honors & awards\nLanguages\nLanguages\nEnglish\nEnglish\nHindi\nHindi\nShow all 3 languages\nInterests\nInterests\nTop Voices\nTop Voices\nCompanies\nCompanies\nGroups\nGroups\nNewsletters\nNewsletters\nSchools\nSchools\nAravind Srinivas\nAravind Srinivas\nAravind Srinivas\nCofounder & CEO, Perplexity\nCofounder & CEO, Perplexity\n506,577 followers\n506,577 followers\nFollow\nVaibhav Domkundwar\nVaibhav Domkundwar\nFounder & CEO at Better Capital. Baby steps at DF (DomkundwarFoundation). 3X Founder. Berkeley Engineering.\nFounder & CEO at Better Capital. Baby steps at DF (DomkundwarFoundation). 3X Founder. Berkeley Engineering.\n89,603 followers\n89,603 followers\nFollow\nShow all Top Voices\nMore profiles for you\nMore profiles for you\nMandavi Jayakar\nMandavi Jayakar\nMandavi Jayakar\n· 3rd+\n3rd+ degree connection\nAssociate Director, People & Culture | People Strategy • Culture Design • Talent Growth | SaaS | EdTech\nFollow\nSidhant Goyal\nSidhant Goyal\n· 3rd+\n3rd+ degree connection\nVC turned Operator | Building software for educators\nVC turned Operator | Building software for educators\nFollow\nMisbah Jafary\nMisbah Jafary\n· 3rd+\n3rd+ degree connection\nHiring for growth roles | Cofounder, CRO\nHiring for growth roles | Cofounder, CRO\nConnect\nManvi Nilaya\nManvi Nilaya\n· 3rd+\n3rd+ degree connection\nAssociate Program Manager @Toddle • DTU (DCE)\nAssociate Program Manager @Toddle • DTU (DCE)\nConnect\nYeesheshvi Bhadana\nYeesheshvi Bhadana\n· 3rd+\n3rd+ degree connection\nDirector at Toddle | Ex-McKinsey\nDirector at Toddle | Ex-McKinsey\nFollow\nShow all\nPeople you may know\nPeople you may know\nFrom Ninaad's school\nFrom Ninaad's school\nKareena kumari\nKareena kumari\nMtech (IIT Kharagpur:2024-26):Gate AG AIR 81(2024)||B.Tech(G.B.pant University of Agriculture and technology:2020-24)\nConnect\nShivalika Das\nShivalika Das\nPursuing Masters in Public Policy, Law and Governance @IIT Kgp || M.Sc in Botany from Calcutta University\nConnect\nAditi Singh\nAditi Singh\nASM@SPRINGFEST2025 | Mathematics\nASM@SPRINGFEST2025 | Mathematics\nConnect\nRupsa Chakraborty\nRupsa Chakraborty\nPost grad student of Chemistry at Indian Institute of Technology, Kharagpur (2024-2026) IIT JAM CY AIR 213\nGraduated from Maulana Azad College, University of Calcutta (2021 - 2024)\nConnect\nPranav Kumar Panasa\nPranav Kumar Panasa\nPranav Kumar Panasa\nPre-final year at Indian Institute of Technology Kharagpur | Aerospace Engineering (2023 - 2027)\nConnect\nShow all\nYou might like\nYou might like\nPages for you\nPages for you\nServiceSetu Academics\nServiceSetu Academics\nHigher Education\nHigher Education\n35,208 followers\n35,208 followers\nFollow\nProfessional Learning International\nProfessional Learning International\nEducation Administration Programs\nEducation Administration Programs\n2,089 followers\n2,089 followers\nFollow\nShow all\nAbout\nAccessibility\nTalent Solutions\nProfessional Community Policies\nCareers\nMarketing Solutions\nPrivacy & Terms\nAd Choices\nAdvertising\nSales Solutions\nMobile\nSmall Business\nSafety Center\nQuestions?\nVisit our Help Center.\nManage your account and privacy\nGo to your Settings.\nRecommendation transparency\nLearn more about Recommended Content.\nSelect Language\n         العربية (Arabic)\n         বাংলা (Bangla)\n         Čeština (Czech)\n         Dansk (Danish)\n         Deutsch (German)\n         Ελληνικά (Greek)\n         English (English)\n         Español (Spanish)\n         فارسی (Persian)\n         Suomi (Finnish)\n         Français (French)\n         हिंदी (Hindi)\n         Magyar (Hungarian)\n         Bahasa Indonesia (Indonesian)\n         Italiano (Italian)\n         עברית (Hebrew)\n         日本語 (Japanese)\n         한국어 (Korean)\n         मराठी (Marathi)\n         Bahasa Malaysia (Malay)\n         Nederlands (Dutch)\n         Norsk (Norwegian)\n         ਪੰਜਾਬੀ (Punjabi)\n         Polski (Polish)\n         Português (Portuguese)\n         Română (Romanian)\n         Русский (Russian)\n         Svenska (Swedish)\n         తెలుగు (Telugu)\n         ภาษาไทย (Thai)\n         Tagalog (Tagalog)\n         Türkçe (Turkish)\n         Українська (Ukrainian)\n         Tiếng Việt (Vietnamese)\n         简体中文 (Chinese (Simplified))\n         正體中文 (Chinese (Traditional))\n     LinkedIn Corporation © 2025\nStatus is online\nMessaging\nYou are on the messaging overlay. Press enter to open the list of conversations.\nCompose message\nYou are on the messaging overlay. Press enter to open the list of conversations.",
  "skills_text": "0 notifications total\nnew feed updates notifications\nHome\n1\n1 new network update notification\nMy Network\nJobs\nMessaging\nNotifications\nMe\nFor Business\nTry Premium for ₹0\nNinaad Lohakare\nToddle | xto10x | AB InBev\nMore\nFollow\nMessage\nSkills\nAll\nIndustry Knowledge\nTools & Technologies\nInterpersonal Skills\nAttention to Detail\nAttention to Detail\nBuilding 10xScale at xto10x\nBuilding 10xScale at xto10x\nStartup Development\nStartup Development\nBuilding 10xScale at xto10x\nBuilding 10xScale at xto10x\nSales\nSales\nGlobal Management Trainee at AB InBev India\nGlobal Management Trainee at AB InBev India\nSales Operations\nSales Operations\nGlobal Management Trainee at AB InBev India\nGlobal Management Trainee at AB InBev India\nSupply Chain Management\nSupply Chain Management\nGlobal Management Trainee at AB InBev India\nGlobal Management Trainee at AB InBev India\nManagement Consulting\nManagement Consulting\nBuilding 10xScale at xto10x\nBuilding 10xScale at xto10x\nProblem Solving\nProblem Solving\n2 experiences across xto10x and 1 other company\n2 experiences across xto10x and 1 other company\n1 endorsement\n1 endorsement\nPublic Speaking\nPublic Speaking\n21 endorsements\n21 endorsements\nGraphic Design\nGraphic Design\n6 endorsements\n6 endorsements\nReport Writing\nReport Writing\n10 endorsements\n10 endorsements\nCreative Writing\nCreative Writing\n5 endorsements\n5 endorsements\nMicrosoft Office\nMicrosoft Office\n5 endorsements\n5 endorsements\nLeadership\nLeadership\n7 endorsements\n7 endorsements\nManagement\nManagement\n10 endorsements\n10 endorsements\nAdobe Photoshop\nAdobe Photoshop\n5 endorsements\n5 endorsements\nTeamwork\nTeamwork\n9 endorsements\n9 endorsements\nMore profiles for you\nMore profiles for you\nMandavi Jayakar\nMandavi Jayakar\nMandavi Jayakar\n· 3rd+\n3rd+ degree connection\nAssociate Director, People & Culture | People Strategy • Culture Design • Talent Growth | SaaS | EdTech\nFollow\nSidhant Goyal\nSidhant Goyal\n· 3rd+\n3rd+ degree connection\nVC turned Operator | Building software for educators\nVC turned Operator | Building software for educators\nFollow\nMisbah Jafary\nMisbah Jafary\n· 3rd+\n3rd+ degree connection\nHiring for growth roles | Cofounder, CRO\nHiring for growth roles | Cofounder, CRO\nConnect\nManvi Nilaya\nManvi Nilaya\n· 3rd+\n3rd+ degree connection\nAssociate Program Manager @Toddle • DTU (DCE)\nAssociate Program Manager @Toddle • DTU (DCE)\nConnect\nYeesheshvi Bhadana\nYeesheshvi Bhadana\n· 3rd+\n3rd+ degree connection\nDirector at Toddle | Ex-McKinsey\nDirector at Toddle | Ex-McKinsey\nFollow\nShow more\nAbout\nAccessibility\nTalent Solutions\nProfessional Community Policies\nCareers\nMarketing Solutions\nPrivacy & Terms\nAd Choices\nAdvertising\nSales Solutions\nMobile\nSmall Business\nSafety Center\nQuestions?\nVisit our Help Center.\nManage your account and privacy\nGo to your Settings.\nRecommendation transparency\nLearn more about Recommended Content.\nSelect Language\n         العربية (Arabic)\n         বাংলা (Bangla)\n         Čeština (Czech)\n         Dansk (Danish)\n         Deutsch (German)\n         Ελληνικά (Greek)\n         English (English)\n         Español (Spanish)\n         فارسی (Persian)\n         Suomi (Finnish)\n         Français (French)\n         हिंदी (Hindi)\n         Magyar (Hungarian)\n         Bahasa Indonesia (Indonesian)\n         Italiano (Italian)\n         עברית (Hebrew)\n         日本語 (Japanese)\n         한국어 (Korean)\n         मराठी (Marathi)\n         Bahasa Malaysia (Malay)\n         Nederlands (Dutch)\n         Norsk (Norwegian)\n         ਪੰਜਾਬੀ (Punjabi)\n         Polski (Polish)\n         Português (Portuguese)\n         Română (Romanian)\n         Русский (Russian)\n         Svenska (Swedish)\n         తెలుగు (Telugu)\n         ภาษาไทย (Thai)\n         Tagalog (Tagalog)\n         Türkçe (Turkish)\n         Українська (Ukrainian)\n         Tiếng Việt (Vietnamese)\n         简体中文 (Chinese (Simplified))\n         正體中文 (Chinese (Traditional))\n     LinkedIn Corporation © 2025\nStatus is online\nMessaging\nYou are on the messaging overlay. Press enter to open the list of conversations.\nCompose message\nYou are on the messaging overlay. Press enter to open the list of conversations.",
  "scraped_at": "2025-07-22 23:14:58",
  "has_skills": true,
  "cleaned_profile": {
    "name": "Ninaad Lohakare",
    "profile_url": "https://in.linkedin.com/in/ninaad-lohakare-632bb613a",
    "current_position": {
      "title": "Associate Director, Growth",
      "company": "Toddle - Your Teaching Partner",
      "location": "Bengaluru, Karnataka, India",
      "start_date": "Jun 2024",
      "end_date": "Present",
      "duration": "1 yr 2 mos"
    },
    "previous_positions": [
      {
        "title": "Building 10xScale",
        "company": "xto10x",
        "location": null,
        "start_date": "Apr 2022",
        "end_date": "May 2024",
        "duration": "2 yrs 2 mos"
      },
      {
        "title": "Global Management Trainee",
        "company": "AB InBev India",
        "location": null,
        "start_date": "Jul 2021",
        "end_date": "Mar 2022",
        "duration": "9 mos"
      },
      {
        "title": "Vice President",
        "company": "Technology Students' Gymkhana, IIT Kharagpur",
        "location": null,
        "start_date": "Apr 2019",
        "end_date": "Jul 2020",
        "duration": "1 yr 4 mos"
      },
      {
        "title": "Market Analyst Intern",
        "company": "Futures First",
        "location": null,
        "start_date": "May 2020",
        "end_date": "Jun 2020",
        "duration": "2 mos"
      }
    ],
    "education": [
      {
        "institution": "Indian Institute of Technology, Kharagpur",
        "degree": "Dual Degree",
        "field_of_study": "Mechanical Engineering",
        "years_attended": "2016 - 2021"
      },
      {
        "institution": "Dr. Ambedkar College, Nagpur",
        "degree": "Higher Secondary School Certificate",
        "field_of_study": "Bifocal : Electronics",
        "years_attended": null
      }
    ],
    "connections": "500+",
    "followers": "7,507",
    "skills": [
      "Attention to Detail",
      "Building 10xScale",
      "Startup Development",
      "Sales",
      "Sales Operations",
      "Supply Chain Management",
      "Management Consulting",
      "Problem Solving",
      "Public Speaking",
      "Graphic Design",
      "Report Writing",
      "Creative Writing",
      "Microsoft Office",
      "Leadership",
      "Management",
      "Adobe Photoshop",
      "Teamwork"
    ],
    "interests": [
      "Bosch Mobility",
      "Toddle - Your Teaching Partner",
      "Aravind Srinivas",
      "Vaibhav Domkundwar"
    ]
  },
  "tokens_used": {
    "prompt_tokens": 4458,
    "completion_tokens": 638,
    "total_tokens": 5096
  }
}