{
  "url": "https://in.linkedin.com/in/avinash-dontamsetty",
  "raw_text": "0 notifications total\nnew feed updates notifications\nHome\n1\n1 new network update notification\nMy Network\nJobs\nMessaging\nNotifications\nMe\nFor Business\nTry Premium for â‚¹0\nAvinash has a {:badgeType} account\nAvinash Dontamsetty\nBuilding Shopdeck | xto10x | Credit Suisse\nShopDeck (Previously NuShop)\nBirla Institute of Technology and Science\nBengaluru, Karnataka, India Contact info\n6,075 followers\n500+ connections\nFollow\nMessage\nMore\nAbout\nAbout\nStriving to enable organizations to live to their fullest potential!\nStriving to enable organizations to live to their fullest potential!\nActivity\nActivity\n6,075 followers\n6,075 followers\nFollow\nPosts\nComments\nLoaded 9 Posts posts\nAvinash Dontamsetty reposted this\nHarmin Shah\nHarmin Shah\nHarmin Shah\n   â€¢ 3rd+\nPremium â€¢ 3rd+\nFounder, ShopDeck | Hiring, reach out at harmin@blitzscale.co\nFounder, ShopDeck | Hiring, reach out at harmin@blitzscale.co\n6mo â€¢ \n 6 months ago â€¢ Visible to anyone on or off LinkedIn\nğŸš€ Weâ€™re Hiring: Growth Leads at Shopdeck!\nAt Shopdeck, weâ€™re on a mission to Democratise D2C Online Commerce, empowering emerging D2C brands with an all-in-one stack for sustainable growth and profitability.\n\nWeâ€™re looking for Growth Leads who will work closely with founders of emerging D2C brands to drive business strategy, optimize revenue, and scale operationsâ€”all while ensuring profitability.\n\nWhatâ€™s in it for you?\nâœ¨ Impactful Work: Solve real-world challenges with D2C founders.\nğŸ¯ Hands-on Learning: Dive deep into revenue optimization, pricing, marketing strategies, and logistics.\nğŸ“¦ Category Expertise: Build specialized skills across consumer product categories.\nğŸŒŸ Culture of Growth: Thrive in a supportive, forward-thinking team.\n\nWeâ€™re Looking For:\n- 0-3 years of experience.\n- Strong analytical, problem-solving, and communication skills (Hindi & English).\n- A passion for D2C brands and an entrepreneurial mindset.\n- Ability to join full-time within 30 days.\n\nReady to make an impact?\nğŸ‘‰ Apply here:\n\nHelp us spread the word by sharing this opportunity within your network!\n\n\n\nâ€¦more\nGoogle Forms: Sign-in\naccounts.google.com\n132\n20 comments\n9 reposts\nAvinash Dontamsetty\nAvinash Dontamsetty\n   â€¢ 3rd+\nPremium â€¢ 3rd+\nBuilding Shopdeck | xto10x | Credit Suisse\nBuilding Shopdeck | xto10x | Credit Suisse\n7mo â€¢ Edited â€¢ \n 7 months ago â€¢ Edited â€¢ Visible to anyone on or off LinkedIn\nEagerly looking forward to the incredible scaling journey ahead :) \n\nâ€¦more\nHarmin Shah\nHarmin Shah\nHarmin Shah\n   â€¢ 3rd+\nPremium â€¢ 3rd+\nFounder, ShopDeck | Hiring, reach out at harmin@blitzscale.co\nFounder, ShopDeck | Hiring, reach out at harmin@blitzscale.co\nAt ShopDeck, our mission has always been simple yet powerful: to make D2C profitable for everyone. Today, weâ€™re overjoyed to share a significant milestone on this journey â€” weâ€™ve raised $8 million in funding! Deep gratitude for the incredible belief and support of,,, and.\n\nShopDeck is a D2C-in-a-box solution which helps brands sell profitably on their own channel. Shopdeck is a trusted growth partner for every brand with big dreams in the D2C space.\n\nThis funding fuels our passion to do more. We will focus on enhancing the AI-powered tech stack to drive deeper insights and automation, expanding on-ground operations to support sellers across Tier-2 and Tier-3 cities, scaling the team and executing our go-to-market strategies.\n\nTo every team member, customer, investor, and supporter who has been part of this incredible journey, thank you. This is just the beginning. Weâ€™re building the future of D2C, letâ€™s keep growing together!\n\nA big thanks to,,&for their continued support.\n\nA heartfelt thanks to our incredible team& all the others â€” this achievement wouldn't have been possible without your dedication and hard work!\nâ€¦more\nD2C enabler ShopDeck raises $8M from Bessemer, existing investors\nyourstory.com\n4\nShow all posts\nExperience\nExperience\nFounders' Office\nFounders' Office\nShopDeck (Previously NuShop) Â· Full-time\nShopDeck (Previously NuShop) Â· Full-time\nSep 2024 - Present Â· 11 mos\nSep 2024 to Present Â· 11 mos\nBengaluru, Karnataka, India\nBengaluru, Karnataka, India\nxto10x\nxto10x\nFull-time Â· 3 yrs 5 mos\nFull-time Â· 3 yrs 5 mos\nSenior Consultant\nSenior Consultant\nSep 2022 - Sep 2024 Â· 2 yrs 1 mo\nSep 2022 to Sep 2024 Â· 2 yrs 1 mo\nConsultant\nConsultant\nMay 2021 - Sep 2022 Â· 1 yr 5 mos\nMay 2021 to Sep 2022 Â· 1 yr 5 mos\nBengaluru, Karnataka, India\nBengaluru, Karnataka, India\nStartups redefine the world. We want to enable this change globally. Working with the smartest founders and helping their teams scale in an effective manner is the path we chose to create meaningful impact. Long-term sustainable growth and scale happen when there is strength across all important aspects of an organization not just with the core product and the customers, and that's what we help startups with.\n\nxto10x | Scaling is hard. We make it a little easier.\nxto10x | Scaling is hard. We make it a little easier.\nWe partner with startups on their journey to transform initial business momentum into at-scale impact and world-class organisations.\nWe partner with startups on their journey to transform initial business momentum into at-scale impact and world-class organisations.\nCo-Founder and Chief Consultant \nCo-Founder and Chief Consultant\nThe Startup Collab Project\nThe Startup Collab Project\nDec 2019 - May 2021 Â· 1 yr 6 mos\nDec 2019 to May 2021 Â· 1 yr 6 mos\nA lot of times startups and entrepreneurs need a third-person perspective and in many cases, even solid strategic advise to validate decision making. This is where we step in. We are your soundboard. We bring in a fresh external perspective along with an igniting passion for entrepreneurship. Our expertise lies in GTM Strategy, Financial modelling, Customer Analytics & Organization Development.\n\n\nReach out to us at thestartupcollabproject@gmail.com\nSummer Management Trainee\nSummer Management Trainee\nOYO\nOYO\nApr 2020 - May 2020 Â· 2 mos\nApr 2020 to May 2020 Â· 2 mos\nCredit Suisse\nCredit Suisse\n2 yrs 6 mos\n2 yrs 6 mos\nFinancial Analyst - Prime Services\nFinancial Analyst - Prime Services\nJun 2017 - Jun 2019 Â· 2 yrs 1 mo\nJun 2017 to Jun 2019 Â· 2 yrs 1 mo\nMumbai Metropolitan Region\nMumbai Metropolitan Region\nIntern\nIntern\nJan 2017 - Jun 2017 Â· 6 mos\nJan 2017 to Jun 2017 Â· 6 mos\nMumbai Area, India\nMumbai Area, India\nEducation\nEducation\nBirla Institute of Technology and Science, Pilani\nBirla Institute of Technology and Science, Pilani\nMSc (Hons) Economics & B.E(Hons) E.C.E\nMSc (Hons) Economics & B.E(Hons) E.C.E\nTata Institute of Social Sciences\nTata Institute of Social Sciences\nMaster's degree, Organisation Development, Change and Leadership\nMaster's degree, Organisation Development, Change and Leadership\nLicenses & certifications\nLicenses & certifications\nDigital Large Scale Intervention Process (LSIP)\nDigital Large Scale Intervention Process (LSIP)\nTata Institute of Social Sciences\nTata Institute of Social Sciences\nIssued Jan 2021\nIssued Jan 2021\nShow credential\nBusiness Growth Strategy\nBusiness Growth Strategy\nUniversity of Virginia Darden School of Business\nUniversity of Virginia Darden School of Business\nIssued Jul 2020\nIssued Jul 2020\nCredential ID DCYPN42BE557\nCredential ID DCYPN42BE557\nShow credential\nShow all 6 licenses & certifications\nProjects\nProjects\nDesign and Study Of Communication Systems\nDesign and Study Of Communication Systems\nJan 2016 - Apr 2016\nJan 2016 - Apr 2016\nAssociated with Birla Institute of Technology and Science\nAssociated with Birla Institute of Technology and Science\nPerformed various hardware implementations of communication systems(DSB-SC, FM, AM etc . ) using EMONA kit. Simulation for the same implementations in simulink(MATLAB). \nCertain improvements were suggested in the currently existing lab manual for â€œCommunication systemsâ€ of BITS PILANI Hyderabad Campus.\nEvaluation of Mutual Funds\nEvaluation of Mutual Funds\nJan 2016 - Apr 2016\nJan 2016 - Apr 2016\nAssociated with Birla Institute of Technology and Science\nAssociated with Birla Institute of Technology and Science\nDifferent techniques (Sharpe ratio, Sortino Ratio, SDR Sharpe Ratio, Gain to Pain ratio) of evaluating the performance of a mutual fund were examined.All the performance metrics were computed for AXIS Bankâ€™s family of mutual funds.\nBased on the analysis, the best possible metric for evaluation of the mutual funds was selected.\n\n\nVolunteering\nVolunteering\nIntern\nIntern\nAIESEC\nAIESEC\nJun 2013 Â· 1 mo\nJun 2013 Â· 1 mo\nEducation\nEducation\nVolunteered for a six-week cultural exchange program in Novosibirsk, Russia. I worked on a project called Sunshine - spreading the idea of global peace and integration , alongside an international team of students from more than seven different countries. We created & deployed a learning module for global peace across various schools at Novosibirsk.\nVolunteer\nVolunteer\nNirmaan Organization\nNirmaan Organization\nSep 2012 - Dec 2012 Â· 4 mos\nSep 2012 - Dec 2012 Â· 4 mos\nEducation\nEducation\nWas involved in village adoption programs around Shameerpet (Pothaipally village), wherein I taught science to the students of classes 6 and 7.\nWas involved in village adoption programs around Shameerpet (Pothaipally village), wherein I taught science to the students of classes 6 and 7.\nShow all 4 volunteer experiences\nSkills\nSkills\nTeam Management\nTeam Management\nAakash Jain profile picture\nEndorsed by Aakash Jain who is highly skilled at this\nEndorsed byAakash Jainwho is highly skilled at this\nEndorsed by 2 colleagues at Credit Suisse\nEndorsed by 2 colleagues at Credit Suisse\n22 endorsements\n22 endorsements\nMarketing\nMarketing\n13 endorsements\n13 endorsements\nShow all 19 skills\nRecommendations\nRecommendations\nReceived\nReceived\nGiven\nGiven\nRicha Sinha\nRicha Sinha\nFacilitating Leadership through Executive Coaching and enabling Employee Experience through Design Thinking and Digital interventions\nFacilitating Leadership through Executive Coaching and enabling Employee Experience through Design Thinking and Digital interventions\nJune 18, 2021, Richa managed Avinash directly\nJune 18, 2021,RichamanagedAvinashdirectly\nIn 2020, Avinash did his summer internship in my team. He is extremely energetic, eager to take on new areas, do the necessary research by himself and produce results that's of surprisingly high value! He added immense value to the team with his ability to listen, learn and deliver. He's a self starter and if he puts his mind to something he does everything in his capacity to deliver it to conclusion. Avinash is headed for success. All the best!\nIn 2020, Avinash did his summer internship in my team. He is extremely energetic, eager to take on new areas, do the necessary research by himself and produce results that's of surprisingly high value! He added immense value to the team with his ability to listen, learn and deliver. He's a self starter and if he puts his mind to something he does everything in his capacity to deliver it to conclusion. Avinash is headed for success. All the best!\nPooja Kaul\nPooja Kaul\nFounder Organiko || Forbes 30U30 Asia|| Princess of Wales The Diana Award 2020 || Ministry of MSME Emerging Woman Entrepreneur 2022|| 75 Womenpreneurs of India by Niti Aayog\nFounder Organiko || Forbes 30U30 Asia|| Princess of Wales The Diana Award 2020 || Ministry of MSME Emerging Woman Entrepreneur 2022|| 75 Womenpreneurs of India by Niti Aayog\nFebruary 11, 2021, Pooja was Avinashâ€™s client\nFebruary 11, 2021,Poojawas Avinashâ€™s client\nI highly recommend Avinash's expertise to any person looking for a Business Developer Or Consultant. He makes sure all the deadlines meet and that also with the highest standards. He is a hardworking and dedicated person who will complete your project in a given time frame. I would recommend and endorse Avinash and would love to work with him again.\n\n\nI highly recommend Avinash's expertise to any person looking for a Business Developer Or Consultant. He makes sure all the deadlines meet and that also with the highest standards. He is a hardworking and dedicated person who will complete your project in a given time frame. I would recommend and endorse Avinash and would love to work with him again.\nShow all 5 received\nInterests\nInterests\nTop Voices\nTop Voices\nCompanies\nCompanies\nGroups\nGroups\nNewsletters\nNewsletters\nSchools\nSchools\nPrukalpa âš¡\nPrukalpa âš¡\nFounder & Co-CEO at Atlan | Forbes30, Fortune40, TED Speaker\nFounder & Co-CEO at Atlan | Forbes30, Fortune40, TED Speaker\n43,697 followers\n43,697 followers\nFollow\nRishabh Mariwala\nRishabh Mariwala\nRishabh Mariwala\nFounder & Managing Partner - Sharrp Ventures | Director - Marico Ltd. & Kaya Ltd. | Consumer Investor\nFounder & Managing Partner - Sharrp Ventures | Director - Marico Ltd. & Kaya Ltd. | Consumer Investor\n52,285 followers\n52,285 followers\nFollow\nShow all Top Voices\nMore profiles for you\nMore profiles for you\nVijay Lohchab\nVijay Lohchab\nÂ· 3rd+\n3rd+ degree connection\nBusiness Leader | Strategy, GTM & Ops | Founder's Office | Built & scaled Teams, P&L, and Products\nFollow\nHarmin Shah\nHarmin Shah\nHarmin Shah\nÂ· 3rd+\n3rd+ degree connection\nFounder, ShopDeck | Hiring, reach out at harmin@blitzscale.co\nConnect\nKhan Mahvish\nKhan Mahvish\nÂ· 3rd+\n3rd+ degree connection\nStrategic Program Manager | Data-Driven Operations Excellence | E-commerce Analytics & Consulting\nConnect\nUrvish Sukhadia\nUrvish Sukhadia\nÂ· 3rd+\n3rd+ degree connection\nProgram Manager - Shopdeck | Brand Management @ Manyavar-Mohey | MBA, IIM Shillong | B.Tech, PDEU\nConnect\nRishabh Verma\nRishabh Verma\nÂ· 3rd+\n3rd+ degree connection\nFounder, ShopDeck | Hiring. Reach out to me on rishabh@blitzscale.co\nConnect\nShow all\nPeople you may know\nPeople you may know\nFrom Avinash's school\nFrom Avinash's school\nTumushime Yvette\nTumushime Yvette\nAfrican Leadership University\nAfrican Leadership University\nConnect\nbrian Kemboi\nbrian Kemboi\nStudent at University of Oxford\nStudent at University of Oxford\nConnect\nØ¹Ø¨Ø¯Ø§Ù„ØºÙØ§Ø± Ø¹ÙŠØ¯\nØ¹Ø¨Ø¯Ø§Ù„ØºÙØ§Ø± Ø¹ÙŠØ¯\nØ¹Ø¨Ø¯Ø§Ù„ØºÙØ§Ø± Ø¹ÙŠØ¯\n--\n--\nConnect\nMohamed Osman\nMohamed Osman\nØ·Ø§Ù„Ø¨ ÙÙŠ Ø¬Ø§Ù…Ø¹Ø© Ø¢Ù„Ù…Ù„Ùƒ Ø³Ù„ÙŠÙ…Ø§Ù† Ø§Ù„Ø¯ÙˆÙ„ÙŠÙ‡\nØ·Ø§Ù„Ø¨ ÙÙŠ Ø¬Ø§Ù…Ø¹Ø© Ø¢Ù„Ù…Ù„Ùƒ Ø³Ù„ÙŠÙ…Ø§Ù† Ø§Ù„Ø¯ÙˆÙ„ÙŠÙ‡\nConnect\nMonica Waithira\nMonica Waithira\nSoftware Programmer at Keeta\nSoftware Programmer at Keeta\nConnect\nShow all\nYou might like\nYou might like\nPages for you\nPages for you\nTechnical Books Library\nTechnical Books Library\nE-learning\nE-learning\n348,262 followers\n348,262 followers\nFollow\nAirbus\nAirbus\nAviation and Aerospace Component Manufacturing\nAviation and Aerospace Component Manufacturing\n2,568,101 followers\n2,568,101 followers\nFollow\nShow all\nAbout\nAccessibility\nTalent Solutions\nProfessional Community Policies\nCareers\nMarketing Solutions\nPrivacy & Terms\nAd Choices\nAdvertising\nSales Solutions\nMobile\nSmall Business\nSafety Center\nQuestions?\nVisit our Help Center.\nManage your account and privacy\nGo to your Settings.\nRecommendation transparency\nLearn more about Recommended Content.\nSelect Language\n         Ø§Ù„Ø¹Ø±Ø¨ÙŠØ© (Arabic)\n         à¦¬à¦¾à¦‚à¦²à¦¾ (Bangla)\n         ÄŒeÅ¡tina (Czech)\n         Dansk (Danish)\n         Deutsch (German)\n         Î•Î»Î»Î·Î½Î¹ÎºÎ¬ (Greek)\n         English (English)\n         EspaÃ±ol (Spanish)\n         ÙØ§Ø±Ø³ÛŒ (Persian)\n         Suomi (Finnish)\n         FranÃ§ais (French)\n         à¤¹à¤¿à¤‚à¤¦à¥€ (Hindi)\n         Magyar (Hungarian)\n         Bahasa Indonesia (Indonesian)\n         Italiano (Italian)\n         ×¢×‘×¨×™×ª (Hebrew)\n         æ—¥æœ¬èª (Japanese)\n         í•œêµ­ì–´ (Korean)\n         à¤®à¤°à¤¾à¤ à¥€ (Marathi)\n         Bahasa Malaysia (Malay)\n         Nederlands (Dutch)\n         Norsk (Norwegian)\n         à¨ªà©°à¨œà¨¾à¨¬à©€ (Punjabi)\n         Polski (Polish)\n         PortuguÃªs (Portuguese)\n         RomÃ¢nÄƒ (Romanian)\n         Ğ ÑƒÑÑĞºĞ¸Ğ¹ (Russian)\n         Svenska (Swedish)\n         à°¤à±†à°²à±à°—à± (Telugu)\n         à¸ à¸²à¸©à¸²à¹„à¸—à¸¢ (Thai)\n         Tagalog (Tagalog)\n         TÃ¼rkÃ§e (Turkish)\n         Ğ£ĞºÑ€Ğ°Ñ—Ğ½ÑÑŒĞºĞ° (Ukrainian)\n         Tiáº¿ng Viá»‡t (Vietnamese)\n         ç®€ä½“ä¸­æ–‡ (Chinese (Simplified))\n         æ­£é«”ä¸­æ–‡ (Chinese (Traditional))\n     LinkedIn Corporation Â© 2025\nStatus is online\nMessaging\nYou are on the messaging overlay. Press enter to open the list of conversations.\nCompose message\nYou are on the messaging overlay. Press enter to open the list of conversations.",
  "skills_text": "é¸æ“‡èªè¨€\n                Bahasa Indonesia (Bahasa Indonesia)\n                Bahasa Malaysia (Malay)\n                ÄŒeÅ¡tina (Czech)\n                Dansk (Danish)\n                Deutsch (German)\n                English (English)\n                EspaÃ±ol (Spanish)\n                ç¹é«”ä¸­æ–‡ (Chinese (Traditional))\n                FranÃ§ais (French)\n                í•œêµ­ì–´ (Korean)\n                Italiano (Italian)\n                ç®€ä½“ä¸­æ–‡ (Chinese (Simplified))\n                Nederlands (Dutch)\n                æ—¥æœ¬èª (Japanese)\n                Norsk (Norwegian)\n                Polski (Polish)\n                PortuguÃªs (Portuguese)\n                RomÃ¢nÄƒ (Romanian)\n                Ğ ÑƒÑÑĞºĞ¸Ğ¹ (Russian)\n                Svenska (Swedish)\n                Tagalog (Tagalog)\n                à¸ à¸²à¸©à¸²à¹„à¸—à¸¢ (Thai)\n                TÃ¼rkÃ§e (Turkish)\n                Ø§Ù„Ø¹Ø±Ø¨ÙŠØ© (Arabic)\n          \n             Page not found\nUh oh, we canâ€™t seem to find the page youâ€™re looking for. Try going back to the previous page or see our Help Center for more information\nGo to your feed\nÂ© 2022 User Agreement Privacy Policy Community Guidelines Cookie Policy Copyright Policy Guest Controls",
  "scraped_at": "2025-07-23 00:30:10",
  "has_skills": true,
  "cleaned_profile": {
    "name": "Avinash Dontamsetty",
    "profile_url": "https://in.linkedin.com/in/avinash-dontamsetty",
    "current_position": {
      "title": "Founders' Office",
      "company": "ShopDeck (Previously NuShop)",
      "location": "Bengaluru, Karnataka, India",
      "start_date": "Sep 2024",
      "end_date": "Present",
      "duration": "11 mos"
    },
    "previous_positions": [
      {
        "title": "Senior Consultant",
        "company": "xto10x",
        "location": "Bengaluru, Karnataka, India",
        "start_date": "Sep 2022",
        "end_date": "Sep 2024",
        "duration": "2 yrs 1 mo"
      },
      {
        "title": "Consultant",
        "company": "xto10x",
        "location": "Bengaluru, Karnataka, India",
        "start_date": "May 2021",
        "end_date": "Sep 2022",
        "duration": "1 yr 5 mos"
      },
      {
        "title": "Co-Founder and Chief Consultant",
        "company": "The Startup Collab Project",
        "start_date": "Dec 2019",
        "end_date": "May 2021",
        "duration": "1 yr 6 mos"
      },
      {
        "title": "Summer Management Trainee",
        "company": "OYO",
        "start_date": "Apr 2020",
        "end_date": "May 2020",
        "duration": "2 mos"
      },
      {
        "title": "Financial Analyst - Prime Services",
        "company": "Credit Suisse",
        "location": "Mumbai Metropolitan Region",
        "start_date": "Jun 2017",
        "end_date": "Jun 2019",
        "duration": "2 yrs 1 mo"
      },
      {
        "title": "Intern",
        "company": "Credit Suisse",
        "location": "Mumbai Area, India",
        "start_date": "Jan 2017",
        "end_date": "Jun 2017",
        "duration": "6 mos"
      }
    ],
    "education": [
      {
        "institution": "Birla Institute of Technology and Science, Pilani",
        "degree": "MSc (Hons) Economics & B.E(Hons) E.C.E"
      },
      {
        "institution": "Tata Institute of Social Sciences",
        "degree": "Master's degree",
        "field_of_study": "Organisation Development, Change and Leadership"
      }
    ],
    "connections": "500+",
    "followers": "6,075",
    "skills": [
      "Team Management",
      "Marketing"
    ],
    "interests": [
      "Prukalpa âš¡",
      "Rishabh Mariwala"
    ]
  },
  "tokens_used": {
    "prompt_tokens": 4287,
    "completion_tokens": 638,
    "total_tokens": 4925
  }
}