{
  "url": "https://in.linkedin.com/in/chaitanyaavatapalli",
  "raw_text": "0 notifications total\nnew feed updates notifications\nHome\n1\n1 new network update notification\nMy Network\nJobs\nMessaging\nNotifications\nMe\nFor Business\nTry Premium for ‚Çπ0\nChaitanya Avatapalli\nRebuilding the world's trust in its food | Founder's Office at The Whole Truth\nThe Whole Truth Foods\nJamnalal Bajaj Institute of Management Studies (JBIMS)\nMumbai, Maharashtra, India Contact info\n9,107 followers\n500+ connections\nFollow\nMessage\nMore\nAbout\nAbout\nChaitanya is a seasoned professional with a deep experience of working with startups and high growth companies. He is currently a management consultant at xto10x, where he advises early-stage and growth-stage companies on a range of strategic and operational issues.\n\nWith expertise in entrepreneurship, strategy & operations, and people & culture transformation, Chaitanya brings a unique perspective to his work. He has worked with clients across multiple industries, including B2B SaaS, e-commerce, EdTech, FinTech and HealthTech.\n\nPrior to joining xto10x, Chaitanya has had a diverse career with stints in consulting, B2B SaaS Sales, and entrepreneurial ventures. He has successfully led product launches, business expansions, and process improvements, consistently delivering measurable results.\n\nChaitanya holds a Master's degree in Organization Development, Change & Leadership from Tata Institute of Social Sciences and is a PhD scholar at Jamnalal Bajaj Institute of Management Studies.\n‚Ä¶see more\nActivity\nActivity\n9,107 followers\n9,107 followers\nFollow\nLoaded 3 Comments posts\nChaitanya Avatapalli commented on a post ‚Ä¢ 1mo\n1mo\nHearty Congratulations, Ritu üëè\nHearty Congratulations, Ritu üëè \nChaitanya Avatapalli commented on a post ‚Ä¢ 4mo\n4mo\nVery helpful. Thank you Arun Vigneswaran. Can I get a copy of the report please?\nVery helpful. Thank you Arun Vigneswaran. Can I get a copy of the report please?\nChaitanya Avatapalli commented on a post ‚Ä¢ 5mo\n5mo\nFind me a COO whom the newest intern feels comfortable roasting, yet has the utmost respect for #Man #Myth #Legend\nFind me a COO whom the newest intern feels comfortable roasting, yet has the utmost respect for #Man #Myth #Legend\nShow all comments\nExperience\nExperience\nEntrepreneur-in-Residence, Founder's Office\nEntrepreneur-in-Residence, Founder's Office\nThe Whole Truth Foods ¬∑ Full-time\nThe Whole Truth Foods ¬∑ Full-time\nMay 2023 - Present ¬∑ 2 yrs 3 mos\nMay 2023 to Present ¬∑ 2 yrs 3 mos\nMumbai, Maharashtra, India ¬∑ Hybrid\nMumbai, Maharashtra, India ¬∑ Hybrid\n> Leading Founder's Office, Human Potential & International Expansion teams @ The Whole Truth\n> Leading Founder's Office, Human Potential & International Expansion teams @ The Whole Truth\nxto10x\nxto10x\nFull-time ¬∑ 2 yrs 9 mos\nFull-time ¬∑ 2 yrs 9 mos\nOrganization Effectiveness Consulting\nOrganization Effectiveness Consulting\nSep 2020 - May 2023 ¬∑ 2 yrs 9 mos\nSep 2020 to May 2023 ¬∑ 2 yrs 9 mos\n> Full-stack people & culture consulting services for high-growth companies\n> Help startups design org & people practices: Organization Design, Organization Manifesto & Culture Design, Performance & Rewards and Manager Capability Development\n> Engage with top tier startups and high-growth companies to diagnose Organization Health through eNPS\nManager Capability Programs\nManager Capability Programs\nDec 2021 - Dec 2022 ¬∑ 1 yr 1 mo\nDec 2021 to Dec 2022 ¬∑ 1 yr 1 mo\n> Building manager capability program offerings from xto10x: 10xManagers for mid and senior managers, 10xFTM for First Time Managers\n> Building & delivering manager capability assessments for high growth companies\nWhy does manager capability matter?\nWhy does manager capability matter?\nCo-Founder\nCo-Founder\ni labs, TISS\ni labs, TISS\nJan 2019 - Jun 2020 ¬∑ 1 yr 6 mos\nJan 2019 to Jun 2020 ¬∑ 1 yr 6 mos\nMumbai Metropolitan Region\nMumbai Metropolitan Region\ni labs is a student-led community that promotes the spirit of entrepreneurship at TISS through stories, jugaad and action projects\ni labs is a student-led community that promotes the spirit of entrepreneurship at TISS through stories, jugaad and action projects\nFounder & CEO\nFounder & CEO\ninfiskill ¬∑ Full-time\ninfiskill ¬∑ Full-time\nNov 2016 - Nov 2018 ¬∑ 2 yrs 1 mo\nNov 2016 to Nov 2018 ¬∑ 2 yrs 1 mo\nMumbai Area, India\nMumbai Area, India\ninfiskill is a platform that provides real world skill development opportunities to students and facilitates fresh talent acquisition for businesses\n\nKey innovation in the learning & development and assessments space\nCore Team Member, Entrepreneurship Cell\nCore Team Member, Entrepreneurship Cell\nXLRI Jamshedpur\nXLRI Jamshedpur\nAug 2017 - May 2018 ¬∑ 10 mos\nAug 2017 to May 2018 ¬∑ 10 mos\nJamshedpur \nJamshedpur\nShow all 8 experiences\nEducation\nEducation\nJamnalal Bajaj Institute of Management Studies (JBIMS)\nJamnalal Bajaj Institute of Management Studies (JBIMS)\nDoctor of Philosophy - PhD, Business Administration and Management, General\nDoctor of Philosophy - PhD, Business Administration and Management, General\n2022 - 2026\n2022 - 2026\nActivities and societies: Research Areas-\n1. Role evolution of Founder/ CEO in high-growth startups through the scaling journey\n2. Impact of founder personal beliefs of organization culture in high-growth startups\nDropped out to pursue more exciting things in current life stage :)\nDropped out to pursue more exciting things in current life stage :)\nTata Institute of Social Sciences\nTata Institute of Social Sciences\nMasters in Organisation Development, Change and Leadership, School of Management & Labor Studies, TISS Mumbai\nMasters in Organisation Development, Change and Leadership, School of Management & Labor Studies, TISS Mumbai\n2018 - 2020\n2018 - 2020\nGrade: 7.3/10\nGrade: 7.3/10\nActivities and societies: 1. Placement Committee 2018-20\n2. TISS Football Team 2018-20\n3. Founder, TISS Champions League 2018-19, 2019-20\n4. Co-Founder, i labs- TISS Mumbai\nShow all 5 educations\nLicenses & certifications\nLicenses & certifications\nJunior Research Fellow- Management\nJunior Research Fellow- Management\nUniversity Grants Commission (UGC)\nUniversity Grants Commission (UGC)\nIssued Dec 2020\nIssued Dec 2020\nShow credential\nDigital Transformation Specialist Certifications\nDigital Transformation Specialist Certifications\nBoston Consulting Group (BCG)\nBoston Consulting Group (BCG)\nIssued May 2020\nIssued May 2020\nShow credential\nShow all 5 licenses & certifications\nVolunteering\nVolunteering\nPresident at Interact Club\nPresident at Interact Club\nRotary International\nRotary International\nJun 2009 - Apr 2010 ¬∑ 11 mos\nJun 2009 - Apr 2010 ¬∑ 11 mos\nSocial Services\nSocial Services\nTeam Member\nTeam Member\nAIESEC\nAIESEC\nMay 2015 - Jan 2016 ¬∑ 9 mos\nMay 2015 - Jan 2016 ¬∑ 9 mos\nSkills\nSkills\nManagement\nManagement\n19 endorsements\n19 endorsements\nTeam Management\nTeam Management\nEndorsed by Devika Gulla who is highly skilled at this\nEndorsed byDevika Gullawho is highly skilled at this\n16 endorsements\n16 endorsements\nShow all 11 skills\nTest scores\nTest scores\nJRF- UGC NET (Management)\nJRF- UGC NET (Management)\nScore: 200/300 ¬∑ Oct 2020\nScore: 200/300 ¬∑ Oct 2020\nTISSNET 2018\nTISSNET 2018\nScore: 76/100 ¬∑ Jan 2018\nScore: 76/100 ¬∑ Jan 2018\nAssociated with Tata Institute of Social Sciences\nAssociated with Tata Institute of Social Sciences\nLanguages\nLanguages\nEnglish\nEnglish\nHindi\nHindi\nShow all 4 languages\nInterests\nInterests\nTop Voices\nTop Voices\nCompanies\nCompanies\nGroups\nGroups\nNewsletters\nNewsletters\nSchools\nSchools\nRaj Kunkolienkar\nRaj Kunkolienkar\nFree Agent | Prev. built Stoa, AltMBA for India\nFree Agent | Prev. built Stoa, AltMBA for India\n53,745 followers\n53,745 followers\nFollow\nSahil Bloom\nSahil Bloom\nNYT Bestselling Author of The 5 Types of Wealth\nNYT Bestselling Author of The 5 Types of Wealth\n649,304 followers\n649,304 followers\nFollow\nShow all Top Voices\nMore profiles for you\nMore profiles for you\nRachna Aggarwal\nRachna Aggarwal\n¬∑ 3rd+\n3rd+ degree connection\nChef at The Whole Truth Foods \nChef at The Whole Truth Foods\nConnect\nAmishi Parasrampuria\nAmishi Parasrampuria\n¬∑ 3rd+\n3rd+ degree connection\nHead of Partnerships @ The Whole Truth Foods| TEDX Speaker | NAAEE 30Under30\nFollow\nSahil Narang\nSahil Narang\nSahil Narang\n¬∑ 3rd+\n3rd+ degree connection\nD2C | The Whole Truth | Re-building world‚Äôs trust in its food\nConnect\nAashna Rane\nAashna Rane\n¬∑ 3rd+\n3rd+ degree connection\nCommunity Builder, Culture Designer, Polymath\nCommunity Builder, Culture Designer, Polymath\nFollow\nShrey Khanna\nShrey Khanna\n¬∑ 3rd+\n3rd+ degree connection\nRe-building the world‚Äôs trust in its food | Category Manager at The Whole Truth\nFollow\nShow all\nPeople you may know\nPeople you may know\nFrom Chaitanya's school\nFrom Chaitanya's school\nAnkit Shrivastav\nAnkit Shrivastav\nSAP HANA Certified\nSAP HANA Certified\nConnect\nRohan Rathod\nRohan Rathod\nJBIMS '26 | Strategy Intern Publicis\nJBIMS '26 | Strategy Intern Publicis\nConnect\nRupesh Shinde\nRupesh Shinde\nAGM - Project Planning\nAGM - Project Planning\nConnect\nYashika _\nYashika _\nLaw student at Banasthali Vidyapith\nLaw student at Banasthali Vidyapith\nConnect\nVaibhav Shiledar\nVaibhav Shiledar\nCareer Commune | JBIMS Mumbai | Finance | Management Strategy\nConnect\nShow all\nYou might like\nYou might like\nPages for you\nPages for you\nAcademic Careers - Engineering Faculty jobs\nAcademic Careers - Engineering Faculty jobs\nEducation\nEducation\n11,593 followers\n11,593 followers\nFollow\nDesai Brothers Ltd.\nDesai Brothers Ltd.\nFood and Beverage Services\nFood and Beverage Services\n12,697 followers\n12,697 followers\nFollow\nShow all\nAbout\nAccessibility\nTalent Solutions\nProfessional Community Policies\nCareers\nMarketing Solutions\nPrivacy & Terms\nAd Choices\nAdvertising\nSales Solutions\nMobile\nSmall Business\nSafety Center\nQuestions?\nVisit our Help Center.\nManage your account and privacy\nGo to your Settings.\nRecommendation transparency\nLearn more about Recommended Content.\nSelect Language\n         ÿßŸÑÿπÿ±ÿ®Ÿäÿ© (Arabic)\n         ‡¶¨‡¶æ‡¶Ç‡¶≤‡¶æ (Bangla)\n         ƒåe≈°tina (Czech)\n         Dansk (Danish)\n         Deutsch (German)\n         ŒïŒªŒªŒ∑ŒΩŒπŒ∫Œ¨ (Greek)\n         English (English)\n         Espa√±ol (Spanish)\n         ŸÅÿßÿ±ÿ≥€å (Persian)\n         Suomi (Finnish)\n         Fran√ßais (French)\n         ‡§π‡§ø‡§Ç‡§¶‡•Ä (Hindi)\n         Magyar (Hungarian)\n         Bahasa Indonesia (Indonesian)\n         Italiano (Italian)\n         ◊¢◊ë◊®◊ô◊™ (Hebrew)\n         Êó•Êú¨Ë™û (Japanese)\n         ÌïúÍµ≠Ïñ¥ (Korean)\n         ‡§Æ‡§∞‡§æ‡§†‡•Ä (Marathi)\n         Bahasa Malaysia (Malay)\n         Nederlands (Dutch)\n         Norsk (Norwegian)\n         ‡®™‡©∞‡®ú‡®æ‡®¨‡©Ä (Punjabi)\n         Polski (Polish)\n         Portugu√™s (Portuguese)\n         Rom√¢nƒÉ (Romanian)\n         –†—É—Å—Å–∫–∏–π (Russian)\n         Svenska (Swedish)\n         ‡∞§‡±Ü‡∞≤‡±Å‡∞ó‡±Å (Telugu)\n         ‡∏†‡∏≤‡∏©‡∏≤‡πÑ‡∏ó‡∏¢ (Thai)\n         Tagalog (Tagalog)\n         T√ºrk√ße (Turkish)\n         –£–∫—Ä–∞—ó–Ω—Å—å–∫–∞ (Ukrainian)\n         Ti·∫øng Vi·ªát (Vietnamese)\n         ÁÆÄ‰Ωì‰∏≠Êñá (Chinese (Simplified))\n         Ê≠£È´î‰∏≠Êñá (Chinese (Traditional))\n     LinkedIn Corporation ¬© 2025\nStatus is online\nMessaging\nYou are on the messaging overlay. Press enter to open the list of conversations.\nCompose message\nYou are on the messaging overlay. Press enter to open the list of conversations.",
  "skills_text": "0 notifications total\nnew feed updates notifications\nHome\n1\n1 new network update notification\nMy Network\nJobs\nMessaging\nNotifications\nMe\nFor Business\nTry Premium for ‚Çπ0\nChaitanya Avatapalli\nRebuilding the world's trust in its food | Founder's Office at The Whole Truth\nMore\nMessage\nFollow\nSkills\nAll\nIndustry Knowledge\nInterpersonal Skills\nManagement\nManagement\n19 endorsements\n19 endorsements\nTeam Management\nTeam Management\nEndorsed by Devika Gulla who is highly skilled at this\nEndorsed byDevika Gullawho is highly skilled at this\n16 endorsements\n16 endorsements\nEntrepreneurship\nEntrepreneurship\n8 endorsements\n8 endorsements\nBusiness Development\nBusiness Development\n22 endorsements\n22 endorsements\nMarketing\nMarketing\n4 endorsements\n4 endorsements\nBusiness Strategy\nBusiness Strategy\n4 endorsements\n4 endorsements\nStart-ups\nStart-ups\n2 endorsements\n2 endorsements\nPeople and Culture \nPeople and Culture\n1 endorsement\n1 endorsement\nLeadership\nLeadership\n8 endorsements\n8 endorsements\nNegotiation\nNegotiation\nStart-up Consulting\nStart-up Consulting\nMore profiles for you\nMore profiles for you\nRachna Aggarwal\nRachna Aggarwal\n¬∑ 3rd+\n3rd+ degree connection\nChef at The Whole Truth Foods \nChef at The Whole Truth Foods\nConnect\nAmishi Parasrampuria\nAmishi Parasrampuria\n¬∑ 3rd+\n3rd+ degree connection\nHead of Partnerships @ The Whole Truth Foods| TEDX Speaker | NAAEE 30Under30\nFollow\nSahil Narang\nSahil Narang\nSahil Narang\n¬∑ 3rd+\n3rd+ degree connection\nD2C | The Whole Truth | Re-building world‚Äôs trust in its food\nConnect\nAashna Rane\nAashna Rane\n¬∑ 3rd+\n3rd+ degree connection\nCommunity Builder, Culture Designer, Polymath\nCommunity Builder, Culture Designer, Polymath\nFollow\nShrey Khanna\nShrey Khanna\n¬∑ 3rd+\n3rd+ degree connection\nRe-building the world‚Äôs trust in its food | Category Manager at The Whole Truth\nFollow\nShow more\nAbout\nAccessibility\nTalent Solutions\nProfessional Community Policies\nCareers\nMarketing Solutions\nPrivacy & Terms\nAd Choices\nAdvertising\nSales Solutions\nMobile\nSmall Business\nSafety Center\nQuestions?\nVisit our Help Center.\nManage your account and privacy\nGo to your Settings.\nRecommendation transparency\nLearn more about Recommended Content.\nSelect Language\n         ÿßŸÑÿπÿ±ÿ®Ÿäÿ© (Arabic)\n         ‡¶¨‡¶æ‡¶Ç‡¶≤‡¶æ (Bangla)\n         ƒåe≈°tina (Czech)\n         Dansk (Danish)\n         Deutsch (German)\n         ŒïŒªŒªŒ∑ŒΩŒπŒ∫Œ¨ (Greek)\n         English (English)\n         Espa√±ol (Spanish)\n         ŸÅÿßÿ±ÿ≥€å (Persian)\n         Suomi (Finnish)\n         Fran√ßais (French)\n         ‡§π‡§ø‡§Ç‡§¶‡•Ä (Hindi)\n         Magyar (Hungarian)\n         Bahasa Indonesia (Indonesian)\n         Italiano (Italian)\n         ◊¢◊ë◊®◊ô◊™ (Hebrew)\n         Êó•Êú¨Ë™û (Japanese)\n         ÌïúÍµ≠Ïñ¥ (Korean)\n         ‡§Æ‡§∞‡§æ‡§†‡•Ä (Marathi)\n         Bahasa Malaysia (Malay)\n         Nederlands (Dutch)\n         Norsk (Norwegian)\n         ‡®™‡©∞‡®ú‡®æ‡®¨‡©Ä (Punjabi)\n         Polski (Polish)\n         Portugu√™s (Portuguese)\n         Rom√¢nƒÉ (Romanian)\n         –†—É—Å—Å–∫–∏–π (Russian)\n         Svenska (Swedish)\n         ‡∞§‡±Ü‡∞≤‡±Å‡∞ó‡±Å (Telugu)\n         ‡∏†‡∏≤‡∏©‡∏≤‡πÑ‡∏ó‡∏¢ (Thai)\n         Tagalog (Tagalog)\n         T√ºrk√ße (Turkish)\n         –£–∫—Ä–∞—ó–Ω—Å—å–∫–∞ (Ukrainian)\n         Ti·∫øng Vi·ªát (Vietnamese)\n         ÁÆÄ‰Ωì‰∏≠Êñá (Chinese (Simplified))\n         Ê≠£È´î‰∏≠Êñá (Chinese (Traditional))\n     LinkedIn Corporation ¬© 2025\nStatus is online\nMessaging\nYou are on the messaging overlay. Press enter to open the list of conversations.\nCompose message\nYou are on the messaging overlay. Press enter to open the list of conversations.",
  "scraped_at": "2025-07-23 00:33:07",
  "has_skills": true,
  "cleaned_profile": {
    "name": "Chaitanya Avatapalli",
    "profile_url": "https://in.linkedin.com/in/chaitanyaavatapalli",
    "current_position": {
      "title": "Entrepreneur-in-Residence, Founder's Office",
      "company": "The Whole Truth Foods",
      "location": "Mumbai, Maharashtra, India",
      "start_date": "May 2023",
      "end_date": null,
      "duration": "2 yrs 3 mos"
    },
    "previous_positions": [
      {
        "title": "Organization Effectiveness Consulting",
        "company": "xto10x",
        "location": null,
        "start_date": "Sep 2020",
        "end_date": "May 2023",
        "duration": "2 yrs 9 mos"
      },
      {
        "title": "Manager Capability Programs",
        "company": "xto10x",
        "location": null,
        "start_date": "Dec 2021",
        "end_date": "Dec 2022",
        "duration": "1 yr 1 mo"
      },
      {
        "title": "Co-Founder",
        "company": "i labs, TISS",
        "location": "Mumbai Metropolitan Region",
        "start_date": "Jan 2019",
        "end_date": "Jun 2020",
        "duration": "1 yr 6 mos"
      },
      {
        "title": "Founder & CEO",
        "company": "infiskill",
        "location": "Mumbai Area, India",
        "start_date": "Nov 2016",
        "end_date": "Nov 2018",
        "duration": "2 yrs 1 mo"
      },
      {
        "title": "Core Team Member, Entrepreneurship Cell",
        "company": "XLRI Jamshedpur",
        "location": "Jamshedpur",
        "start_date": "Aug 2017",
        "end_date": "May 2018",
        "duration": "10 mos"
      }
    ],
    "education": [
      {
        "institution": "Jamnalal Bajaj Institute of Management Studies (JBIMS)",
        "degree": "Doctor of Philosophy - PhD",
        "field_of_study": "Business Administration and Management, General",
        "years_attended": "2022 - 2026"
      },
      {
        "institution": "Tata Institute of Social Sciences",
        "degree": "Masters in Organisation Development, Change and Leadership",
        "field_of_study": "School of Management & Labor Studies, TISS Mumbai",
        "years_attended": "2018 - 2020"
      }
    ],
    "connections": "500+",
    "followers": "9,107",
    "skills": [
      "Management",
      "Team Management",
      "Entrepreneurship",
      "Business Development",
      "Marketing",
      "Business Strategy",
      "Start-ups",
      "People and Culture",
      "Leadership",
      "Negotiation",
      "Start-up Consulting"
    ],
    "interests": [
      "Raj Kunkolienkar",
      "Sahil Bloom"
    ]
  },
  "tokens_used": {
    "prompt_tokens": 3734,
    "completion_tokens": 675,
    "total_tokens": 4409
  }
}