{
  "url": "https://in.linkedin.com/in/gaurav-choudhary",
  "raw_text": "0 notifications total\nnew feed updates notifications\nHome\n1\n1 new network update notification\nMy Network\nJobs\nMessaging\nNotifications\nMe\nFor Business\nTry Premium for ‚Çπ0\nGaurav Choudhary\nProduct Leader @ xto10x | Ex Myntra | Ex OLA | IIT Kanpur\nxto10x\nIndian Institute of Technology, Kanpur\nBengaluru, Karnataka, India Contact info\n4,551 followers\n500+ connections\nFollow\nMessage\nMore\nAbout\nAbout\nI have a strong track record of helping organisations by identifying the right problems to solve by staying close to the customer and mapping the organisation‚Äôs strengths. \n\nGraduated from IIT Kanpur with a B.Tech in Civil Engineering and minor degree in Industrial and Management Engineering.\n\nStrengths: Problem Solver, Customer Empathy, Data Driven and Product Development.\n\nTechnologies: Python, R, SQL, Hive, C, Plotly, Dash, etc.\n‚Ä¶see more\nActivity\nActivity\n4,551 followers\n4,551 followers\nFollow\nPosts\nComments\nLoaded 9 Posts posts\nGaurav Choudhary\nGaurav Choudhary\n ‚Ä¢ 3rd+\n3rd+\nProduct Leader @ xto10x | Ex Myntra | Ex OLA | IIT Kanpur\nProduct Leader @ xto10x | Ex Myntra | Ex OLA | IIT Kanpur\n2w ‚Ä¢ \n 2 weeks ago ‚Ä¢ Visible to anyone on or off LinkedIn\nNothing beats seeing the incredible results our customers experience from the features the team (Tanmay A., Shivam Gupta, T DINESHKUMAR, Rama Bhat) is shipping.\nHuge thanks to,for being key partners in this journey!\n‚Ä¶more\nPeopleCues\nPeopleCues\n735 followers\n735 followers\n6-week review cycles were the norm. Until now.\n\nAt Angel One, performance reviews that once took 4‚Äì6 weeks now wrap up in just 2‚Äì4, and that shift means everything. Huge thanks to Angel One team for the kind words, and for recognizing what we truly care about:\nüìà ‚ÄúYou‚Äôve moved the needle on the metrics that matter in a performance review.‚Äù ‚Äì\nü§ñ ‚ÄúThe AI-led SBI feedback engine has completely changed the quality of feedback.‚Äù ‚Äì\n\nIt‚Äôs a reminder that meaningful change at work doesn‚Äôt need to be loud, just well-designed.\nIf a better review experience helps employees feel heard and managers make sharper decisions, we‚Äôre doing our job right.\n\nWhat‚Äôs one underrated shift that‚Äôs made a big difference in your org? Comment below.\n\n\n\n‚Ä¶more\n7\nGaurav Choudhary reposted this\nRahul Mathur\nRahul Mathur\n   ‚Ä¢ 3rd+\nInfluencer ‚Ä¢ 3rd+\nPre-Seed Investor @DeVC || Prev: Founder @Verak (acq. by ID)\nPre-Seed Investor @DeVC || Prev: Founder @Verak (acq. by ID)\nVisit my website\n1mo ‚Ä¢ \n 1 month ago ‚Ä¢ Visible to anyone on or off LinkedIn\nA year after Binny Bansal sold his $1bn stake in Flipkart in 2018, he began laying the foundations for his next venture: a ‚ÄúMcKinsey for Startups‚Äù ‚§µÔ∏è\n\nAt an event in Bangalore last year, Binny explained his motivations for setting up xto10x ‚Üí ‚ÄúInstead of making a thousand mistakes, if we can help other startups make a hundred or even a few hundred, that would be worth it.‚Äù ‚Üí succinct yet powerful.\n\nBinny partnered with Saikiran who worked at Flipkart and was a Senior Partner @ McKinsey for 15 years prior; Sai is a co-founder of the firm along with Neeraj Aggarwal (ex VP at Flipkart)\n\n3 years after founding, the firm was profitable. And, on 9th Feb ‚Äò22, Binny topped the company up with $25M in funding (from his own pocket). We don‚Äôt have latest data on company performance, since it is SG domiciled, but FY23 was ~$14M in revenue & profitable.\n\nxto10x combines the traditional ‚ÄòMcKinsey model‚Äô i.e. consulting (70% of revenue) with a ‚Äòbuilders approach‚Äô i.e. product / software led engagements (30% of revenue)\n\n‚ÄúPeopleCues‚Äù is their software platform, priced at ~$8 per seat per month, which comprises\n\n(a) OKR management\n(b) Performance management\n(c) Culture & Employee NPS (eNPS)\n\nIn addition to the software, they offer consulting services like:\n(1) Coaching ‚Üí Pre-IPO coaching & founder coaching\n(2) Strategy ‚Üí Org Design, Leadership hiring etc\n(3) Hands-on ‚Üí Growth engine design & implementation\n\nüí°Very similar to McKinsey & its MBB peers, xto10x focuses on having small teams working deeply with large clients (200+ names including CRED, Groww, Razorpay, Meesho etc). Btw, many people don‚Äôt know that McKinsey also has a LOT of software which it sells to clients (topic for another post) - so the two firms are quite similar!\n\nWhat makes xto10x unique is that alongside consulting fees, it sometimes take an equity stake in companies it works with ‚Üí per TRACXN, it has equity in ~35 companies (mostly at the Series B stage). HENCE, it has real skin in the game üí™\n\n‚û°Ô∏èThe goal ofis clear from the name itself ‚Üí to help founders on the X to 10X journey. As their website says: ‚ÄúScaling is hard. We make it easier.‚Äù This is an interesting n::1 business!\n\n‚Ä¶more\n537\n26 comments\n10 reposts\nShow all posts\nExperience\nExperience\nxto10x\nxto10x\nFull-time ¬∑ 6 yrs 4 mos\nFull-time ¬∑ 6 yrs 4 mos\nProduct Leader\nProduct Leader\nJan 2023 - Present ¬∑ 2 yrs 7 mos\nJan 2023 to Present ¬∑ 2 yrs 7 mos\nBengaluru, Karnataka, India ¬∑ On-site\nBengaluru, Karnataka, India ¬∑ On-site\nProduct Management and Machine Learning\nSenior Product Manager\nSenior Product Manager\nJun 2021 - Jan 2023 ¬∑ 1 yr 8 mos\nJun 2021 to Jan 2023 ¬∑ 1 yr 8 mos\nBengaluru, Karnataka, India\nBengaluru, Karnataka, India\nProduct Management and Machine Learning\nProduct Manager\nProduct Manager\nApr 2019 - Jun 2021 ¬∑ 2 yrs 3 mos\nApr 2019 to Jun 2021 ¬∑ 2 yrs 3 mos\nBengaluru, Karnataka, India\nBengaluru, Karnataka, India\nProduct Management and Machine Learning\nSenior Analyst - Business Insights\nSenior Analyst - Business Insights\nMyntra\nMyntra\nJun 2018 - Mar 2019 ¬∑ 10 mos\nJun 2018 to Mar 2019 ¬∑ 10 mos\nBangaon, West Bengal, India\nBangaon, West Bengal, India\nMachine Learning\nAssociate Product Manager\nAssociate Product Manager\nOla (ANI Technologies Pvt Ltd)\nOla (ANI Technologies Pvt Ltd)\nJul 2016 - Jun 2018 ¬∑ 2 yrs\nJul 2016 to Jun 2018 ¬∑ 2 yrs\nBengaluru, Karnataka, India\nBengaluru, Karnataka, India\nProduct Management and Machine Learning\nSummer Intern\nSummer Intern\nAdoro\nAdoro\nMay 2015 - Jul 2015 ¬∑ 3 mos\nMay 2015 to Jul 2015 ¬∑ 3 mos\nMumbai Metropolitan Region\nMumbai Metropolitan Region\nAdoro is a fashion-focused social-network for women to discover & shop products and trends that are liked, curated, updated real-time from across the web.\n\nThe project involved \"Optimization of personalized user recommendation engine\". Recommendation engine has been created which incorporates the user's past behavior (items previously purchased or selected and score given to those items) as well as decision made by other users. Suggested new attributes which increases the accuracy of recommendation engine.\nMachine Learning\nIntern\nIntern\nIntern\nKeshar Infrastrucutres\nKeshar Infrastrucutres\nMay 2014 - Jul 2014 ¬∑ 3 mos\nMay 2014 to Jul 2014 ¬∑ 3 mos\nGwalior Area, India\nGwalior Area, India\nThe project involved ‚ÄúEfficient planning and cost estimation of construction project‚Äù. Bottom-Up Analysis is being currently employed in this project to find out the exact amount of materials used in construction. The method was tested to compare the exact amount used and amount calculated and it performed very well with an accuracy of 94.56%.\nShow all 9 experiences\nEducation\nEducation\nIndian Institute of Technology, Kanpur\nIndian Institute of Technology, Kanpur\nBachelor's of Technology (B.Tech), Civil Engineering\nBachelor's of Technology (B.Tech), Civil Engineering\n2012 - 2016\n2012 - 2016\nActivities and societies: Secretary of the Rubik's Cube Hobby Group, Robotics Club, Basketball as Compulsory Physical Activity, Antaragni(Annual Cultural Festival), Techkriti(Annual Technical Festival)\nActivities and societies: Secretary of the Rubik's Cube Hobby Group, Robotics Club, Basketball as Compulsory Physical Activity, Antaragni(Annual Cultural Festival), Techkriti(Annual Technical Festival)\nProjects\nProjects\nFinite Element Methods\nFinite Element Methods\nMar 2015 - Present\nMar 2015 - Present\nAssociated with Indian Institute of Technology, Kanpur\nAssociated with Indian Institute of Technology, Kanpur\n- Built a mathematical model using MATLAB for prediction of crack behavior of cantilever beam attaining an accuracy of 92%\n- Analysed the beam and plotted a 3D stress curve displaying maximum stress or load limit of the beam\nOther contributors\nOther contributors\nCartography of Aurobindo Ashram, Nainital\nCartography of Aurobindo Ashram, Nainital\nDec 2014 - Present\nDec 2014 - Present\nAssociated with Indian Institute of Technology, Kanpur\nAssociated with Indian Institute of Technology, Kanpur\n- Investigated the drivability of the road from ashram gate to Barahpathar and computed the gradient to assess if it is under permissible limit or not (Permissible gradient being 1:10)\n- Map has been prepared and will be helpful for the committee to expand Ashram premises\nOther contributors\nOther contributors\nShow all 3 projects\nVolunteering\nVolunteering\nMentor\nMentor\nMentor\nBlue Star Basketball Club, Gwalior\nBlue Star Basketball Club, Gwalior\nJul 2009 - Apr 2010 ¬∑ 10 mos\nJul 2009 - Apr 2010 ¬∑ 10 mos\nAnimal Welfare\nAnimal Welfare\nSkills\nSkills\nProduct Management\nProduct Management\n4 experiences across xto10x and 1 other company\n4 experiences across xto10x and 1 other company\nMachine Learning\nMachine Learning\n6 experiences across xto10x and 3 other companies\n6 experiences across xto10x and 3 other companies\nShow all 21 skills\nCourses\nCourses\nConstruction Management\nConstruction Management\nCE441A\nCE441A\nAssociated with Indian Institute of Technology, Kanpur\nAssociated with Indian Institute of Technology, Kanpur\nEconomic Analysis for Management\nEconomic Analysis for Management\nMBA606A\nMBA606A\nAssociated with Indian Institute of Technology, Kanpur\nAssociated with Indian Institute of Technology, Kanpur\nShow all 7 courses\nTest scores\nTest scores\nAIEEE\nAIEEE\nScore: SR 461 ¬∑ Jun 2012\nScore: SR 461 ¬∑ Jun 2012\nPET\nPET\nScore: SR 149 ¬∑ Jun 2012\nScore: SR 149 ¬∑ Jun 2012\nSecured State Rank 149 in Pre-Engineering Test (PET) among 120 thousand students\nSecured State Rank 149 in Pre-Engineering Test (PET) among 120 thousand students\nShow all 3 test scores\nLanguages\nLanguages\nEnglish\nEnglish\nFull professional proficiency\nFull professional proficiency\nHindi\nHindi\nFull professional proficiency\nFull professional proficiency\nInterests\nInterests\nTop Voices\nTop Voices\nCompanies\nCompanies\nGroups\nGroups\nNewsletters\nNewsletters\nSchools\nSchools\nSwati Bhargava\nSwati Bhargava\nCo-Founder, CashKaro & EarnKaro | Host ‚Äì The BAD Podcast | Insta @Swatidb\nCo-Founder, CashKaro & EarnKaro | Host ‚Äì The BAD Podcast | Insta @Swatidb\n109,822 followers\n109,822 followers\nFollow\nRay Dalio\nRay Dalio\nFounder, CIO Mentor, and Member of the Bridgewater Board\nFounder, CIO Mentor, and Member of the Bridgewater Board\n2,757,707 followers\n2,757,707 followers\nFollow\nShow all Top Voices\nCauses\nCauses\nEducation ‚Ä¢ Environment ‚Ä¢ Human Rights\nEducation ‚Ä¢ Environment ‚Ä¢ Human Rights\nMore profiles for you\nMore profiles for you\nPiyush Gupta\nPiyush Gupta\n¬∑ 3rd+\n3rd+ degree connection\nHead of Product - Loop | Ex-Zepto, Gojek, Ola\nHead of Product - Loop | Ex-Zepto, Gojek, Ola\nConnect\nDurgesh Suthar\nDurgesh Suthar\n¬∑ 3rd+\n3rd+ degree connection\nEngineering Leader at Scapia| Ex-Entrepreneur | Ex-Flipkart, xto10x, IIT Roorkee\nFollow\nKaran Singhania\nKaran Singhania\n¬∑ 3rd+\n3rd+ degree connection\nProduct@MPL | Ex-Myntra | Ex- Rupeek | Ex - Flipkart\nProduct@MPL | Ex-Myntra | Ex- Rupeek | Ex - Flipkart\nConnect\nHimani Yadav\nHimani Yadav\n¬∑ 3rd+\n3rd+ degree connection\nFounder & CEO of Onya Diamonds| Ex-Mygate, xto10x, InMobi, Ola | IIT Guwahati\nFollow\nTanmay A.\nTanmay A.\n¬∑ 3rd+\n3rd+ degree connection\nProduct @ xto10x | Helping startups scale smarter\nProduct @ xto10x | Helping startups scale smarter\nConnect\nShow all\nPeople you may know\nPeople you may know\nFrom Gaurav's school\nFrom Gaurav's school\nNatnael Ashenafi\nNatnael Ashenafi\nPhD candidate at IITK ‚ÄúSolid Mechanics and Design‚Äù\nPhD candidate at IITK ‚ÄúSolid Mechanics and Design‚Äù\nConnect\nAshish .\nAshish .\nAshish .\nSoftware\nSoftware\nConnect\nRitik Yadav\nRitik Yadav\nIIT Kanpur'26 | MSc Mathematics\nIIT Kanpur'26 | MSc Mathematics\nConnect\nDivyanshi Diwakar\nDivyanshi Diwakar\nIITK M Tech'26 (Environmental Engineering) || KNIT'24 || Loreto Convent'19\nConnect\nAyushi kumari\nAyushi kumari\nStudent at Geeta University | aspiring software engineer | B.Tech'28\nConnect\nShow all\nYou might like\nYou might like\nPages for you\nPages for you\nSciAstra\nSciAstra\nE-Learning Providers\nE-Learning Providers\n37,213 followers\n37,213 followers\nFollow\nEntrepreneurial Mindset\nEntrepreneurial Mindset\nThink Tanks\nThink Tanks\n1,220,101 followers\n1,220,101 followers\nFollow\nShow all\nAbout\nAccessibility\nTalent Solutions\nProfessional Community Policies\nCareers\nMarketing Solutions\nPrivacy & Terms\nAd Choices\nAdvertising\nSales Solutions\nMobile\nSmall Business\nSafety Center\nQuestions?\nVisit our Help Center.\nManage your account and privacy\nGo to your Settings.\nRecommendation transparency\nLearn more about Recommended Content.\nSelect Language\n         ÿßŸÑÿπÿ±ÿ®Ÿäÿ© (Arabic)\n         ‡¶¨‡¶æ‡¶Ç‡¶≤‡¶æ (Bangla)\n         ƒåe≈°tina (Czech)\n         Dansk (Danish)\n         Deutsch (German)\n         ŒïŒªŒªŒ∑ŒΩŒπŒ∫Œ¨ (Greek)\n         English (English)\n         Espa√±ol (Spanish)\n         ŸÅÿßÿ±ÿ≥€å (Persian)\n         Suomi (Finnish)\n         Fran√ßais (French)\n         ‡§π‡§ø‡§Ç‡§¶‡•Ä (Hindi)\n         Magyar (Hungarian)\n         Bahasa Indonesia (Indonesian)\n         Italiano (Italian)\n         ◊¢◊ë◊®◊ô◊™ (Hebrew)\n         Êó•Êú¨Ë™û (Japanese)\n         ÌïúÍµ≠Ïñ¥ (Korean)\n         ‡§Æ‡§∞‡§æ‡§†‡•Ä (Marathi)\n         Bahasa Malaysia (Malay)\n         Nederlands (Dutch)\n         Norsk (Norwegian)\n         ‡®™‡©∞‡®ú‡®æ‡®¨‡©Ä (Punjabi)\n         Polski (Polish)\n         Portugu√™s (Portuguese)\n         Rom√¢nƒÉ (Romanian)\n         –†—É—Å—Å–∫–∏–π (Russian)\n         Svenska (Swedish)\n         ‡∞§‡±Ü‡∞≤‡±Å‡∞ó‡±Å (Telugu)\n         ‡∏†‡∏≤‡∏©‡∏≤‡πÑ‡∏ó‡∏¢ (Thai)\n         Tagalog (Tagalog)\n         T√ºrk√ße (Turkish)\n         –£–∫—Ä–∞—ó–Ω—Å—å–∫–∞ (Ukrainian)\n         Ti·∫øng Vi·ªát (Vietnamese)\n         ÁÆÄ‰Ωì‰∏≠Êñá (Chinese (Simplified))\n         Ê≠£È´î‰∏≠Êñá (Chinese (Traditional))\n     LinkedIn Corporation ¬© 2025\nStatus is online\nMessaging\nYou are on the messaging overlay. Press enter to open the list of conversations.\nCompose message\nYou are on the messaging overlay. Press enter to open the list of conversations.",
  "skills_text": "0 notifications total\nnew feed updates notifications\nHome\n1\n1 new network update notification\nMy Network\nJobs\nMessaging\nNotifications\nMe\nFor Business\nTry Premium for ‚Çπ0\nGaurav Choudhary\nProduct Leader @ xto10x | Ex Myntra | Ex OLA | IIT Kanpur\nMore\nMessage\nFollow\nSkills\nAll\nIndustry Knowledge\nTools & Technologies\nInterpersonal Skills\nProduct Management\nProduct Management\n4 experiences across xto10x and 1 other company\n4 experiences across xto10x and 1 other company\nMachine Learning\nMachine Learning\n6 experiences across xto10x and 3 other companies\n6 experiences across xto10x and 3 other companies\nMatlab\nMatlab\n5 endorsements\n5 endorsements\nMySQL\nMySQL\n6 endorsements\n6 endorsements\nMicrosoft Excel\nMicrosoft Excel\n7 endorsements\n7 endorsements\nSQL\nSQL\n4 endorsements\n4 endorsements\nPython\nPython\n4 endorsements\n4 endorsements\nC++\nC++\n4 endorsements\n4 endorsements\nPrimavera P6\nPrimavera P6\n2 endorsements\n2 endorsements\nProject Management\nProject Management\n3 endorsements\n3 endorsements\nProgramming\nProgramming\n3 endorsements\n3 endorsements\nAlgorithms\nAlgorithms\n4 endorsements\n4 endorsements\nRubik's Cube\nRubik's Cube\n2 endorsements\n2 endorsements\nBasketball\nBasketball\n2 endorsements\n2 endorsements\nMicrosoft Word\nMicrosoft Word\n3 endorsements\n3 endorsements\nMicrosoft Office\nMicrosoft Office\n4 endorsements\n4 endorsements\nCivil Engineering\nCivil Engineering\n3 endorsements\n3 endorsements\nC\nC\n2 endorsements\n2 endorsements\nHTML\nHTML\n2 endorsements\n2 endorsements\nPowerPoint\nPowerPoint\n2 endorsements\n2 endorsements\nManagement\nManagement\n3 endorsements\n3 endorsements\nMore profiles for you\nMore profiles for you\nPiyush Gupta\nPiyush Gupta\n¬∑ 3rd+\n3rd+ degree connection\nHead of Product - Loop | Ex-Zepto, Gojek, Ola\nHead of Product - Loop | Ex-Zepto, Gojek, Ola\nConnect\nDurgesh Suthar\nDurgesh Suthar\n¬∑ 3rd+\n3rd+ degree connection\nEngineering Leader at Scapia| Ex-Entrepreneur | Ex-Flipkart, xto10x, IIT Roorkee\nFollow\nKaran Singhania\nKaran Singhania\n¬∑ 3rd+\n3rd+ degree connection\nProduct@MPL | Ex-Myntra | Ex- Rupeek | Ex - Flipkart\nProduct@MPL | Ex-Myntra | Ex- Rupeek | Ex - Flipkart\nConnect\nHimani Yadav\nHimani Yadav\n¬∑ 3rd+\n3rd+ degree connection\nFounder & CEO of Onya Diamonds| Ex-Mygate, xto10x, InMobi, Ola | IIT Guwahati\nFollow\nTanmay A.\nTanmay A.\n¬∑ 3rd+\n3rd+ degree connection\nProduct @ xto10x | Helping startups scale smarter\nProduct @ xto10x | Helping startups scale smarter\nConnect\nShow more\nAbout\nAccessibility\nTalent Solutions\nProfessional Community Policies\nCareers\nMarketing Solutions\nPrivacy & Terms\nAd Choices\nAdvertising\nSales Solutions\nMobile\nSmall Business\nSafety Center\nQuestions?\nVisit our Help Center.\nManage your account and privacy\nGo to your Settings.\nRecommendation transparency\nLearn more about Recommended Content.\nSelect Language\n         ÿßŸÑÿπÿ±ÿ®Ÿäÿ© (Arabic)\n         ‡¶¨‡¶æ‡¶Ç‡¶≤‡¶æ (Bangla)\n         ƒåe≈°tina (Czech)\n         Dansk (Danish)\n         Deutsch (German)\n         ŒïŒªŒªŒ∑ŒΩŒπŒ∫Œ¨ (Greek)\n         English (English)\n         Espa√±ol (Spanish)\n         ŸÅÿßÿ±ÿ≥€å (Persian)\n         Suomi (Finnish)\n         Fran√ßais (French)\n         ‡§π‡§ø‡§Ç‡§¶‡•Ä (Hindi)\n         Magyar (Hungarian)\n         Bahasa Indonesia (Indonesian)\n         Italiano (Italian)\n         ◊¢◊ë◊®◊ô◊™ (Hebrew)\n         Êó•Êú¨Ë™û (Japanese)\n         ÌïúÍµ≠Ïñ¥ (Korean)\n         ‡§Æ‡§∞‡§æ‡§†‡•Ä (Marathi)\n         Bahasa Malaysia (Malay)\n         Nederlands (Dutch)\n         Norsk (Norwegian)\n         ‡®™‡©∞‡®ú‡®æ‡®¨‡©Ä (Punjabi)\n         Polski (Polish)\n         Portugu√™s (Portuguese)\n         Rom√¢nƒÉ (Romanian)\n         –†—É—Å—Å–∫–∏–π (Russian)\n         Svenska (Swedish)\n         ‡∞§‡±Ü‡∞≤‡±Å‡∞ó‡±Å (Telugu)\n         ‡∏†‡∏≤‡∏©‡∏≤‡πÑ‡∏ó‡∏¢ (Thai)\n         Tagalog (Tagalog)\n         T√ºrk√ße (Turkish)\n         –£–∫—Ä–∞—ó–Ω—Å—å–∫–∞ (Ukrainian)\n         Ti·∫øng Vi·ªát (Vietnamese)\n         ÁÆÄ‰Ωì‰∏≠Êñá (Chinese (Simplified))\n         Ê≠£È´î‰∏≠Êñá (Chinese (Traditional))\n     LinkedIn Corporation ¬© 2025\nStatus is online\nMessaging\nYou are on the messaging overlay. Press enter to open the list of conversations.\nCompose message\nYou are on the messaging overlay. Press enter to open the list of conversations.",
  "scraped_at": "2025-07-23 00:35:23",
  "has_skills": true,
  "cleaned_profile": {
    "name": "Gaurav Choudhary",
    "profile_url": "https://in.linkedin.com/in/gaurav-choudhary",
    "current_position": {
      "title": "Product Leader",
      "company": "xto10x",
      "location": "Bengaluru, Karnataka, India",
      "start_date": "Jan 2023",
      "end_date": "Present",
      "duration": "2 yrs 7 mos"
    },
    "previous_positions": [
      {
        "title": "Senior Product Manager",
        "company": "xto10x",
        "location": "Bengaluru, Karnataka, India",
        "start_date": "Jun 2021",
        "end_date": "Jan 2023",
        "duration": "1 yr 8 mos"
      },
      {
        "title": "Product Manager",
        "company": "xto10x",
        "location": "Bengaluru, Karnataka, India",
        "start_date": "Apr 2019",
        "end_date": "Jun 2021",
        "duration": "2 yrs 3 mos"
      },
      {
        "title": "Senior Analyst - Business Insights",
        "company": "Myntra",
        "location": "Bangaon, West Bengal, India",
        "start_date": "Jun 2018",
        "end_date": "Mar 2019",
        "duration": "10 mos"
      },
      {
        "title": "Associate Product Manager",
        "company": "Ola (ANI Technologies Pvt Ltd)",
        "location": "Bengaluru, Karnataka, India",
        "start_date": "Jul 2016",
        "end_date": "Jun 2018",
        "duration": "2 yrs"
      },
      {
        "title": "Summer Intern",
        "company": "Adoro",
        "location": "Mumbai Metropolitan Region",
        "start_date": "May 2015",
        "end_date": "Jul 2015",
        "duration": "3 mos"
      },
      {
        "title": "Intern",
        "company": "Keshar Infrastructures",
        "location": "Gwalior Area, India",
        "start_date": "May 2014",
        "end_date": "Jul 2014",
        "duration": "3 mos"
      }
    ],
    "education": [
      {
        "institution": "Indian Institute of Technology, Kanpur",
        "degree": "Bachelor's of Technology (B.Tech)",
        "field_of_study": "Civil Engineering",
        "years_attended": "2012 - 2016"
      }
    ],
    "connections": "500+",
    "followers": "4,551",
    "skills": [
      "Product Management",
      "Machine Learning",
      "Matlab",
      "MySQL",
      "Microsoft Excel",
      "SQL",
      "Python",
      "C++",
      "Primavera P6",
      "Project Management",
      "Programming",
      "Algorithms",
      "Rubik's Cube",
      "Basketball",
      "Microsoft Word",
      "Microsoft Office",
      "Civil Engineering",
      "C",
      "HTML",
      "PowerPoint",
      "Management"
    ],
    "interests": [
      "Swati Bhargava",
      "Ray Dalio"
    ]
  },
  "tokens_used": {
    "prompt_tokens": 4810,
    "completion_tokens": 727,
    "total_tokens": 5537
  }
}