{
  "url": "https://in.linkedin.com/in/shirilchristo",
  "raw_text": "0 notifications total\nnew feed updates notifications\nHome\n1\n1 new network update notification\nMy Network\nJobs\nMessaging\nNotifications\nMe\nFor Business\nTry Premium for ‚Çπ0\nShiril Christo\nShe/Her\nHR Consultant | xto10x | Ex-Darwinbox | IBS Hyderabad (2018-2020)\nxto10x\nIBS Hyderabad\nBengaluru, Karnataka, India Contact info\n1,042 followers\n500+ connections\nFollow\nMessage\nMore\nAbout\nAbout\nHR Professional with 4+ years of experience in HR Consultancy and developing HR Strategies.\nHR Professional with 4+ years of experience in HR Consultancy and developing HR Strategies.\nActivity\nActivity\n1,042 followers\n1,042 followers\nFollow\nLoaded 3 Comments posts\nShiril Christo commented on a post ‚Ä¢ 1mo\n1mo\nüëè Well deserved, Ayush\nüëè Well deserved, Ayush\nShiril Christo commented on a post ‚Ä¢ 2mo\n2mo\nCongrats Mansi! üéâ\nCongrats Mansi! üéâ\nShiril Christo commented on a post ‚Ä¢ 2mo\n2mo\nCongrats Sunanda! üéâ\nCongrats Sunanda! üéâ\nShow all comments\nExperience\nExperience\nHuman Resources Consultant\nHuman Resources Consultant\nxto10x ¬∑ Full-time\nxto10x ¬∑ Full-time\nApr 2022 - Present ¬∑ 3 yrs 4 mos\nApr 2022 to Present ¬∑ 3 yrs 4 mos\nBengaluru, Karnataka, India ¬∑ Remote\nBengaluru, Karnataka, India ¬∑ Remote\nHR Consulting, Organizational Consulting and +2 skills\nDarwinbox\nDarwinbox\nFull-time ¬∑ 2 yrs 2 mos\nFull-time ¬∑ 2 yrs 2 mos\nCustomer Success Consultant\nCustomer Success Consultant\nOct 2021 - Apr 2022 ¬∑ 7 mos\nOct 2021 to Apr 2022 ¬∑ 7 mos\nMumbai, Maharashtra, India\nMumbai, Maharashtra, India\nCustomer Success Associate\nCustomer Success Associate\nMar 2021 - Jan 2022 ¬∑ 11 mos\nMar 2021 to Jan 2022 ¬∑ 11 mos\nBengaluru, Karnataka, India\nBengaluru, Karnataka, India\nManagement Trainee\nManagement Trainee\nMar 2020 - Mar 2021 ¬∑ 1 yr 1 mo\nMar 2020 to Mar 2021 ¬∑ 1 yr 1 mo\nHyderabad, Telangana, India\nHyderabad, Telangana, India\nHR Intern\nHR Intern\nRexnord Corporation\nRexnord Corporation\nFeb 2019 - May 2019 ¬∑ 4 mos\nFeb 2019 to May 2019 ¬∑ 4 mos\nHyderabad, Telangana, India\nHyderabad, Telangana, India\nEducation\nEducation\nIBS Hyderabad\nIBS Hyderabad\nMaster of Business Administration - MBA, HR\nMaster of Business Administration - MBA, HR\n2018 - 2020\n2018 - 2020\nChhattisgarh Swami Vivekanand Technical University, Bhilai\nChhattisgarh Swami Vivekanand Technical University, Bhilai\nChhattisgarh Swami Vivekanand Technical University, Bhilai\nBachelor of Engineering - BE, Electrical, Electronics and Communications Engineering\nBachelor of Engineering - BE, Electrical, Electronics and Communications Engineering\n2013 - 2017\n2013 - 2017\nShow all 4 educations\nSkills\nSkills\nInterpersonal Skills\nInterpersonal Skills\nHuman Resources Consultant at xto10x\nHuman Resources Consultant at xto10x\nHR Consulting\nHR Consulting\nHuman Resources Consultant at xto10x\nHuman Resources Consultant at xto10x\nShow all 22 skills\nInterests\nInterests\nTop Voices\nTop Voices\nCompanies\nCompanies\nGroups\nGroups\nNewsletters\nNewsletters\nSchools\nSchools\nVidit Aatrey\nVidit Aatrey\nFounder & CEO @ Meesho \nFounder & CEO @ Meesho\n295,796 followers\n295,796 followers\nFollow\nLeena Nair\nLeena Nair\nCHANEL Global CEO\nCHANEL Global CEO\n504,985 followers\n504,985 followers\nFollow\nShow all Top Voices\nMore profiles for you\nMore profiles for you\nMonisha Das\nMonisha Das\n¬∑ 3rd+\n3rd+ degree connection\nCRED | Ex-xto10x | Ex-Meesho | Professional Stalker\nCRED | Ex-xto10x | Ex-Meesho | Professional Stalker\nMessage\nArun Vigneswaran\nArun Vigneswaran\n¬∑ 3rd+\n3rd+ degree connection\nHead of People practice @ xto10x | Ex-Flipkart | TISS\nHead of People practice @ xto10x | Ex-Flipkart | TISS\nMessage\nRahul Jagannathan\nRahul Jagannathan\n¬∑ 3rd+\n3rd+ degree connection\nPeople Practice at xto10x | Leadership roles in startups | ICF Credentialed Coach | Hogan Certified | Music Hobbyist\nMessage\nAnkit Hetamsaria\nAnkit Hetamsaria\nAnkit Hetamsaria\n¬∑ 3rd+\n3rd+ degree connection\nxto10x | Ex-Founder Bambinos.live | Cure.fit | Flipkart\nMessage\nNikhil Tyagi\nNikhil Tyagi\n¬∑ 3rd+\n3rd+ degree connection\nHelping companies in their journey to scale from x to 10x! Talk to me about P&L Transformation, CX/Growth strategy, People & Culture or Leadership Coaching programs\nMessage\nShow all\nPeople you may know\nPeople you may know\nFrom Shiril's school\nFrom Shiril's school\nYasir Ali\nYasir Ali\nTeam Lead Manager at PTCL.Official\nTeam Lead Manager at PTCL.Official\nKishoRe RathoRe\nKishoRe RathoRe\nSenior Computer Operator, Admin & Accountant\nSenior Computer Operator, Admin & Accountant\nZahid Hussain Mallah\nZahid Hussain Mallah\nJobless\nJobless\nMuhammad Nawaz\nMuhammad Nawaz\nAttended Quaid-e-Awam University of Engineering, Sciences and Technology Nawabshah\nAbhinav M Krant\nAbhinav M Krant\nMarketing & Public Relations Enthusiast | Digital & Social Media Marketeer | Brand Management | MBA at IBS Hyderabad 2024-26 | Events & Operations Head of Club Samavesh | Debating Head of Club Speak Up\nShow all\nYou might like\nYou might like\nPages for you\nPages for you\nIndian Aviation Career\nIndian Aviation Career\nAirlines and Aviation\nAirlines and Aviation\n57,404 followers\n57,404 followers\nFollow\nServiceSetu Academics\nServiceSetu Academics\nHigher Education\nHigher Education\n35,213 followers\n35,213 followers\nFollow\nShow all\nAbout\nAccessibility\nTalent Solutions\nProfessional Community Policies\nCareers\nMarketing Solutions\nPrivacy & Terms\nAd Choices\nAdvertising\nSales Solutions\nMobile\nSmall Business\nSafety Center\nQuestions?\nVisit our Help Center.\nManage your account and privacy\nGo to your Settings.\nRecommendation transparency\nLearn more about Recommended Content.\nSelect Language\n         ÿßŸÑÿπÿ±ÿ®Ÿäÿ© (Arabic)\n         ‡¶¨‡¶æ‡¶Ç‡¶≤‡¶æ (Bangla)\n         ƒåe≈°tina (Czech)\n         Dansk (Danish)\n         Deutsch (German)\n         ŒïŒªŒªŒ∑ŒΩŒπŒ∫Œ¨ (Greek)\n         English (English)\n         Espa√±ol (Spanish)\n         ŸÅÿßÿ±ÿ≥€å (Persian)\n         Suomi (Finnish)\n         Fran√ßais (French)\n         ‡§π‡§ø‡§Ç‡§¶‡•Ä (Hindi)\n         Magyar (Hungarian)\n         Bahasa Indonesia (Indonesian)\n         Italiano (Italian)\n         ◊¢◊ë◊®◊ô◊™ (Hebrew)\n         Êó•Êú¨Ë™û (Japanese)\n         ÌïúÍµ≠Ïñ¥ (Korean)\n         ‡§Æ‡§∞‡§æ‡§†‡•Ä (Marathi)\n         Bahasa Malaysia (Malay)\n         Nederlands (Dutch)\n         Norsk (Norwegian)\n         ‡®™‡©∞‡®ú‡®æ‡®¨‡©Ä (Punjabi)\n         Polski (Polish)\n         Portugu√™s (Portuguese)\n         Rom√¢nƒÉ (Romanian)\n         –†—É—Å—Å–∫–∏–π (Russian)\n         Svenska (Swedish)\n         ‡∞§‡±Ü‡∞≤‡±Å‡∞ó‡±Å (Telugu)\n         ‡∏†‡∏≤‡∏©‡∏≤‡πÑ‡∏ó‡∏¢ (Thai)\n         Tagalog (Tagalog)\n         T√ºrk√ße (Turkish)\n         –£–∫—Ä–∞—ó–Ω—Å—å–∫–∞ (Ukrainian)\n         Ti·∫øng Vi·ªát (Vietnamese)\n         ÁÆÄ‰Ωì‰∏≠Êñá (Chinese (Simplified))\n         Ê≠£È´î‰∏≠Êñá (Chinese (Traditional))\n     LinkedIn Corporation ¬© 2025\nStatus is online\nMessaging\nYou are on the messaging overlay. Press enter to open the list of conversations.\nCompose message\nYou are on the messaging overlay. Press enter to open the list of conversations.",
  "skills_text": "0 notifications total\nnew feed updates notifications\nHome\n1\n1 new network update notification\nMy Network\nJobs\nMessaging\nNotifications\nMe\nFor Business\nTry Premium for ‚Çπ0\nShiril Christo\n(She/Her)\nHR Consultant | xto10x | Ex-Darwinbox | IBS Hyderabad (2018-2020)\nMore\nMessage\nFollow\nSkills\nAll\nIndustry Knowledge\nTools & Technologies\nInterpersonal Skills\nInterpersonal Skills\nInterpersonal Skills\nHuman Resources Consultant at xto10x\nHuman Resources Consultant at xto10x\nHR Consulting\nHR Consulting\nHuman Resources Consultant at xto10x\nHuman Resources Consultant at xto10x\nOrganizational Consulting\nOrganizational Consulting\nHuman Resources Consultant at xto10x\nHuman Resources Consultant at xto10x\nAnalytical Skills\nAnalytical Skills\nHuman Resources Consultant at xto10x\nHuman Resources Consultant at xto10x\nData Analysis\nData Analysis\n3 endorsements\n3 endorsements\nInterpersonal Communication\nInterpersonal Communication\n4 endorsements\n4 endorsements\nQuantitative Research\nQuantitative Research\n2 endorsements\n2 endorsements\nC (Programming Language)\nC (Programming Language)\n1 endorsement\n1 endorsement\nC++\nC++\n1 endorsement\n1 endorsement\nData Analytics\nData Analytics\n1 endorsement\n1 endorsement\nDigital Marketing\nDigital Marketing\n1 endorsement\n1 endorsement\nMarket Research\nMarket Research\n1 endorsement\n1 endorsement\nMySQL\nMySQL\n1 endorsement\n1 endorsement\nGoogle Analytics\nGoogle Analytics\n1 endorsement\n1 endorsement\nGoogle Ads\nGoogle Ads\n1 endorsement\n1 endorsement\nTeam Management\nTeam Management\n1 endorsement\n1 endorsement\nCommunication\nCommunication\nCustomer Relationship Management (CRM)\nCustomer Relationship Management (CRM)\nTraining & Development\nTraining & Development\nRecruiting\nRecruiting\nHuman Resources Information Systems (HRIS)\nHuman Resources Information Systems (HRIS)\nDarwinbox\nDarwinbox\nMore profiles for you\nMore profiles for you\nMonisha Das\nMonisha Das\n¬∑ 3rd+\n3rd+ degree connection\nCRED | Ex-xto10x | Ex-Meesho | Professional Stalker\nCRED | Ex-xto10x | Ex-Meesho | Professional Stalker\nMessage\nArun Vigneswaran\nArun Vigneswaran\n¬∑ 3rd+\n3rd+ degree connection\nHead of People practice @ xto10x | Ex-Flipkart | TISS\nHead of People practice @ xto10x | Ex-Flipkart | TISS\nMessage\nRahul Jagannathan\nRahul Jagannathan\n¬∑ 3rd+\n3rd+ degree connection\nPeople Practice at xto10x | Leadership roles in startups | ICF Credentialed Coach | Hogan Certified | Music Hobbyist\nMessage\nAnkit Hetamsaria\nAnkit Hetamsaria\nAnkit Hetamsaria\n¬∑ 3rd+\n3rd+ degree connection\nxto10x | Ex-Founder Bambinos.live | Cure.fit | Flipkart\nMessage\nNikhil Tyagi\nNikhil Tyagi\n¬∑ 3rd+\n3rd+ degree connection\nHelping companies in their journey to scale from x to 10x! Talk to me about P&L Transformation, CX/Growth strategy, People & Culture or Leadership Coaching programs\nMessage\nShow more\nAbout\nAccessibility\nTalent Solutions\nProfessional Community Policies\nCareers\nMarketing Solutions\nPrivacy & Terms\nAd Choices\nAdvertising\nSales Solutions\nMobile\nSmall Business\nSafety Center\nQuestions?\nVisit our Help Center.\nManage your account and privacy\nGo to your Settings.\nRecommendation transparency\nLearn more about Recommended Content.\nSelect Language\n         ÿßŸÑÿπÿ±ÿ®Ÿäÿ© (Arabic)\n         ‡¶¨‡¶æ‡¶Ç‡¶≤‡¶æ (Bangla)\n         ƒåe≈°tina (Czech)\n         Dansk (Danish)\n         Deutsch (German)\n         ŒïŒªŒªŒ∑ŒΩŒπŒ∫Œ¨ (Greek)\n         English (English)\n         Espa√±ol (Spanish)\n         ŸÅÿßÿ±ÿ≥€å (Persian)\n         Suomi (Finnish)\n         Fran√ßais (French)\n         ‡§π‡§ø‡§Ç‡§¶‡•Ä (Hindi)\n         Magyar (Hungarian)\n         Bahasa Indonesia (Indonesian)\n         Italiano (Italian)\n         ◊¢◊ë◊®◊ô◊™ (Hebrew)\n         Êó•Êú¨Ë™û (Japanese)\n         ÌïúÍµ≠Ïñ¥ (Korean)\n         ‡§Æ‡§∞‡§æ‡§†‡•Ä (Marathi)\n         Bahasa Malaysia (Malay)\n         Nederlands (Dutch)\n         Norsk (Norwegian)\n         ‡®™‡©∞‡®ú‡®æ‡®¨‡©Ä (Punjabi)\n         Polski (Polish)\n         Portugu√™s (Portuguese)\n         Rom√¢nƒÉ (Romanian)\n         –†—É—Å—Å–∫–∏–π (Russian)\n         Svenska (Swedish)\n         ‡∞§‡±Ü‡∞≤‡±Å‡∞ó‡±Å (Telugu)\n         ‡∏†‡∏≤‡∏©‡∏≤‡πÑ‡∏ó‡∏¢ (Thai)\n         Tagalog (Tagalog)\n         T√ºrk√ße (Turkish)\n         –£–∫—Ä–∞—ó–Ω—Å—å–∫–∞ (Ukrainian)\n         Ti·∫øng Vi·ªát (Vietnamese)\n         ÁÆÄ‰Ωì‰∏≠Êñá (Chinese (Simplified))\n         Ê≠£È´î‰∏≠Êñá (Chinese (Traditional))\n     LinkedIn Corporation ¬© 2025\nStatus is online\nMessaging\nYou are on the messaging overlay. Press enter to open the list of conversations.\nCompose message\nYou are on the messaging overlay. Press enter to open the list of conversations.",
  "scraped_at": "2025-07-23 01:47:16",
  "has_skills": true,
  "cleaned_profile": {
    "name": "Shiril Christo",
    "pronouns": "She/Her",
    "profile_url": "https://in.linkedin.com/in/shirilchristo",
    "current_position": {
      "title": "Human Resources Consultant",
      "company": "xto10x",
      "location": "Bengaluru, Karnataka, India",
      "start_date": "Apr 2022",
      "end_date": "Present",
      "duration": "3 yrs 4 mos"
    },
    "previous_positions": [
      {
        "title": "Customer Success Consultant",
        "company": "Darwinbox",
        "location": "Mumbai, Maharashtra, India",
        "start_date": "Oct 2021",
        "end_date": "Apr 2022",
        "duration": "7 mos"
      },
      {
        "title": "Customer Success Associate",
        "company": "Darwinbox",
        "location": "Bengaluru, Karnataka, India",
        "start_date": "Mar 2021",
        "end_date": "Jan 2022",
        "duration": "11 mos"
      },
      {
        "title": "Management Trainee",
        "company": "Darwinbox",
        "location": "Hyderabad, Telangana, India",
        "start_date": "Mar 2020",
        "end_date": "Mar 2021",
        "duration": "1 yr 1 mo"
      },
      {
        "title": "HR Intern",
        "company": "Rexnord Corporation",
        "location": "Hyderabad, Telangana, India",
        "start_date": "Feb 2019",
        "end_date": "May 2019",
        "duration": "4 mos"
      }
    ],
    "education": [
      {
        "institution": "IBS Hyderabad",
        "degree": "Master of Business Administration - MBA",
        "field_of_study": "HR",
        "years_attended": "2018 - 2020"
      },
      {
        "institution": "Chhattisgarh Swami Vivekanand Technical University, Bhilai",
        "degree": "Bachelor of Engineering - BE",
        "field_of_study": "Electrical, Electronics and Communications Engineering",
        "years_attended": "2013 - 2017"
      }
    ],
    "connections": "500+",
    "followers": "1,042",
    "skills": [
      "Interpersonal Skills",
      "HR Consulting",
      "Organizational Consulting",
      "Analytical Skills",
      "Data Analysis",
      "Interpersonal Communication",
      "Quantitative Research",
      "C (Programming Language)",
      "C++",
      "Data Analytics",
      "Digital Marketing",
      "Market Research",
      "MySQL",
      "Google Analytics",
      "Google Ads",
      "Team Management",
      "Communication",
      "Customer Relationship Management (CRM)",
      "Training & Development",
      "Recruiting",
      "Human Resources Information Systems (HRIS)"
    ],
    "interests": [
      "Vidit Aatrey",
      "Leena Nair"
    ]
  },
  "tokens_used": {
    "prompt_tokens": 3000,
    "completion_tokens": 671,
    "total_tokens": 3671
  }
}