{
  "url": "https://in.linkedin.com/in/deekshaverma",
  "raw_text": "0 notifications total\nnew feed updates notifications\nHome\n1\n1 new network update notification\nMy Network\nJobs\nMessaging\nNotifications\nMe\nFor Business\nTry Premium for ₹0\nDeeksha Verma\nSenior Software Developer @ xto10x | BE in Computer Science\nxto10x\nChitkara University\nBengaluru, Karnataka, India Contact info\n500+ connections\nMessage\nFollow\nMore\nOpen to work\nSenior Software Developer roles\nShow details\nActivity\nActivity\n1,496 followers\n1,496 followers\nDeeksha hasn’t posted yet\nRecent posts Deeksha shares will be displayed here.\nShow all activity\nExperience\nExperience\nxto10x\nxto10x\nFull-time · 6 yrs 1 mo\nFull-time · 6 yrs 1 mo\nSenior Software Developer\nSenior Software Developer\nJul 2021 - Present · 4 yrs 1 mo\nJul 2021 to Present · 4 yrs 1 mo\nOptimization Techniques, Startups and +14 skills\nFrontend Developer\nFrontend Developer\nJul 2019 - Jul 2021 · 2 yrs 1 mo\nJul 2019 to Jul 2021 · 2 yrs 1 mo\nOptimization Techniques, Startups and +12 skills\nFrontend Developer\nFrontend Developer\nWesence\nWesence\nSep 2018 - Jun 2019 · 10 mos\nSep 2018 to Jun 2019 · 10 mos\nBengaluru Area, India\nBengaluru Area, India\nStartups, Version Control and +8 skills\nFrontend Developer\nFrontend Developer\nEvive | goevive.com\nEvive | goevive.com\nSep 2017 - Aug 2018 · 1 yr\nSep 2017 to Aug 2018 · 1 yr\nBengaluru, Karnataka, India\nBengaluru, Karnataka, India\nStartups, Version Control and +7 skills\nEducation\nEducation\nChitkara University\nChitkara University\nBachelor of Engineering - BE, Computer Science\nBachelor of Engineering - BE, Computer Science\n2014 - 2018\n2014 - 2018\nLicenses & certifications\nLicenses & certifications\nCritical Thinking\nCritical Thinking\nLinkedIn\nLinkedIn\nIssued May 2022\nIssued May 2022\nShow credential\nStrategic Thinking\nStrategic Thinking\nLinkedIn\nLinkedIn\nIssued May 2022\nIssued May 2022\nShow credential\nSkills\nSkills\nCommunication\nCommunication\n4 experiences across xto10x and 3 other companies\n4 experiences across xto10x and 3 other companies\nData Structures\nData Structures\n4 experiences across xto10x and 3 other companies\n4 experiences across xto10x and 3 other companies\nShow all 43 skills\nInterests\nInterests\nCompanies\nCompanies\nSchools\nSchools\nViasat\nViasat\n179,541 followers\n179,541 followers\nFollow\nLegalMatch\nLegalMatch\n26,107 followers\n26,107 followers\nFollow\nShow all companies\nMore profiles for you\nMore profiles for you\nRama Bhat\nRama Bhat\n· 3rd+\n3rd+ degree connection\nCHROs & HRBPs trust me to fix ENPS & OKRs | Xto10X\nCHROs & HRBPs trust me to fix ENPS & OKRs | Xto10X\nMessage\nSurabhi Kedia\nSurabhi Kedia\n· 3rd+\n3rd+ degree connection\nEngineering @Wayfair | xTo10x | Informatica | Backend Developer\nMessage\nSaikiran Krishnamurthy\nSaikiran Krishnamurthy\n· 3rd+\n3rd+ degree connection\nCo-founder & CEO, xto10x Technologies \nCo-founder & CEO, xto10x Technologies\nMessage\nVinay Kenguva\nVinay Kenguva\n· 3rd+\n3rd+ degree connection\nSoftware Developer @Xto10X | Leetcode : 1000+ problems | Ex Lendingkrt, Chqbook | Java, SpringBoot | FinTech | IIIT Guwahati '23\nFollow\nAshutosh Yadav\nAshutosh Yadav\n· 3rd+\n3rd+ degree connection\nSDE 1 @xto10x\nSDE 1 @xto10x\nMessage\nShow all\nPeople you may know\nPeople you may know\nFrom Deeksha's school\nFrom Deeksha's school\nvaibhav garg\nvaibhav garg\n🎓BBA Professional Student\n📍Chitkara University\n🎓BBA Professional Student 📍Chitkara University\nConnect\nMuskaan Rana\nMuskaan Rana\nAttended Chitkara University\nAttended Chitkara University\nConnect\nGauri Bansal\nGauri Bansal\nComputer Science Engineering Student at Chitkara University | Future Software Engineer |Project Management Intern at Pehchaan the street school\nConnect\nAkshita Sharma\nAkshita Sharma\nStudent at chitkara University\nStudent at chitkara University\nConnect\nSargam Garg\nSargam Garg\nStudent at Chitkara University\nStudent at Chitkara University\nConnect\nShow all\nYou might like\nYou might like\nPages for you\nPages for you\nServiceSetu Academics\nServiceSetu Academics\nHigher Education\nHigher Education\n35,213 followers\n35,213 followers\nFollow\nTexas Instruments India\nTexas Instruments India\nSemiconductor Manufacturing\nSemiconductor Manufacturing\n58,316 followers\n58,316 followers\nFollow\nShow all\nAbout\nAccessibility\nTalent Solutions\nProfessional Community Policies\nCareers\nMarketing Solutions\nPrivacy & Terms\nAd Choices\nAdvertising\nSales Solutions\nMobile\nSmall Business\nSafety Center\nQuestions?\nVisit our Help Center.\nManage your account and privacy\nGo to your Settings.\nRecommendation transparency\nLearn more about Recommended Content.\nSelect Language\n         العربية (Arabic)\n         বাংলা (Bangla)\n         Čeština (Czech)\n         Dansk (Danish)\n         Deutsch (German)\n         Ελληνικά (Greek)\n         English (English)\n         Español (Spanish)\n         فارسی (Persian)\n         Suomi (Finnish)\n         Français (French)\n         हिंदी (Hindi)\n         Magyar (Hungarian)\n         Bahasa Indonesia (Indonesian)\n         Italiano (Italian)\n         עברית (Hebrew)\n         日本語 (Japanese)\n         한국어 (Korean)\n         मराठी (Marathi)\n         Bahasa Malaysia (Malay)\n         Nederlands (Dutch)\n         Norsk (Norwegian)\n         ਪੰਜਾਬੀ (Punjabi)\n         Polski (Polish)\n         Português (Portuguese)\n         Română (Romanian)\n         Русский (Russian)\n         Svenska (Swedish)\n         తెలుగు (Telugu)\n         ภาษาไทย (Thai)\n         Tagalog (Tagalog)\n         Türkçe (Turkish)\n         Українська (Ukrainian)\n         Tiếng Việt (Vietnamese)\n         简体中文 (Chinese (Simplified))\n         正體中文 (Chinese (Traditional))\n     LinkedIn Corporation © 2025\nStatus is online\nMessaging\nYou are on the messaging overlay. Press enter to open the list of conversations.\nCompose message\nYou are on the messaging overlay. Press enter to open the list of conversations.",
  "skills_text": "選擇語言\n                Bahasa Indonesia (Bahasa Indonesia)\n                Bahasa Malaysia (Malay)\n                Čeština (Czech)\n                Dansk (Danish)\n                Deutsch (German)\n                English (English)\n                Español (Spanish)\n                繁體中文 (Chinese (Traditional))\n                Français (French)\n                한국어 (Korean)\n                Italiano (Italian)\n                简体中文 (Chinese (Simplified))\n                Nederlands (Dutch)\n                日本語 (Japanese)\n                Norsk (Norwegian)\n                Polski (Polish)\n                Português (Portuguese)\n                Română (Romanian)\n                Русский (Russian)\n                Svenska (Swedish)\n                Tagalog (Tagalog)\n                ภาษาไทย (Thai)\n                Türkçe (Turkish)\n                العربية (Arabic)\n          \n             Page not found\nUh oh, we can’t seem to find the page you’re looking for. Try going back to the previous page or see our Help Center for more information\nGo to your feed\n© 2022 User Agreement Privacy Policy Community Guidelines Cookie Policy Copyright Policy Guest Controls",
  "scraped_at": "2025-07-23 01:48:07",
  "has_skills": true,
  "cleaned_profile": {
    "name": "Deeksha Verma",
    "profile_url": "https://in.linkedin.com/in/deekshaverma",
    "current_position": {
      "title": "Senior Software Developer",
      "company": "xto10x",
      "location": "Bengaluru, Karnataka, India",
      "start_date": "Jul 2021",
      "end_date": "Present",
      "duration": "4 yrs 1 mo"
    },
    "previous_positions": [
      {
        "title": "Frontend Developer",
        "company": "xto10x",
        "location": "Bengaluru, Karnataka, India",
        "start_date": "Jul 2019",
        "end_date": "Jul 2021",
        "duration": "2 yrs 1 mo"
      },
      {
        "title": "Frontend Developer",
        "company": "Wesence",
        "location": "Bengaluru Area, India",
        "start_date": "Sep 2018",
        "end_date": "Jun 2019",
        "duration": "10 mos"
      },
      {
        "title": "Frontend Developer",
        "company": "Evive | goevive.com",
        "location": "Bengaluru, Karnataka, India",
        "start_date": "Sep 2017",
        "end_date": "Aug 2018",
        "duration": "1 yr"
      }
    ],
    "education": {
      "institution": "Chitkara University",
      "degree": "Bachelor of Engineering - BE",
      "field_of_study": "Computer Science",
      "years_attended": "2014 - 2018"
    },
    "connections": "500+",
    "followers": "1,496",
    "skills": [
      "Optimization Techniques",
      "Startups",
      "Version Control",
      "Communication",
      "Data Structures"
    ],
    "interests": [
      "Viasat",
      "LegalMatch"
    ]
  },
  "tokens_used": {
    "prompt_tokens": 1916,
    "completion_tokens": 435,
    "total_tokens": 2351
  }
}