{
  "url": "https://in.linkedin.com/in/pawan-raghuveer-62b00ba",
  "raw_text": "0 notifications total\nnew feed updates notifications\nHome\n1\n1 new network update notification\nMy Network\nJobs\nMessaging\nNotifications\nMe\nFor Business\nTry Premium for â‚¹0\nPawan has a {:badgeType} account\nPawan Raghuveer\nOperations Excellence at xto10x\nxto10x\nIndian Institute of Management, Bangalore\nBengaluru, Karnataka, India Contact info\n500+ connections\nMessage\nFollow\nMore\nAbout\nAbout\nScaling partner and mentor for growth stage startups. Created impact in 50+ startups across key areas of scaling like burn reduction, ops & supply chain design, input tracking & governance, and workforce management. \n10+ years of experience in scaling up internet kitchens, food delivery, fitness, e-commerce and FMCG supply chain. \nScaling partner and mentor for growth stage startups. Created impact in 50+ startups across key areas of scaling like burn reduction, ops & supply chain design, input tracking & governance, and workforce management. 10+ years of experience in scaling up internet kitchens, food delivery, fitness, e-commerce and FMCG supply chain.\nFeatured\nFeatured\nPost\nPost\nOver the last 13 years, Iâ€™ve had a ring side view of the startup ecosystem through my journey helping scale,and 50+ startups as part of. While there are many milestones in a startupâ€™s journey, none come close to the dream of having a successful IPO. Itâ€™s great to see the evolution of the ecosystem to a place where this dream is becoming a real possibility for many startups.\n\nAt xto10x, our mission is to help great startups transform product-market fit and initial momentum into world-class, at-scale companies. A crucial milestone in that journey is the transition to the public markets. 75+ startups from the Indian startup ecosystem are planning to do just that in the near future. We feel privileged to be able to play a meaningful role in their journeys through the xto10x IPO Academy â€” the ultimate launchpad for founders aiming to go public in the next two to three years.\n\nThis will be a cohort-based program for startup founders who are planning to go public soon and will cover the entire â€œwish-listâ€ of topics to get IPO ready. We have an outstanding star cast of faculty composed of public market investors, industry stalwarts, ex-SEBI officials, i-bankers, founders whoâ€™ve taken their companies public, and more.\n\nClick the link below to register for the curtain-raiser: â€œSetting higher standards to build enduring public companiesâ€ by Mohandas Pai, open to all startup founders and CXOs. This session is scheduled on 13th September in Bangalore.\n\n\n\n35\nPost\nPost\nI wrote a series of posts on \nhashtag\n#linkedin a couple of years back on \n#operations excellence topics like control tower, planning, operations design, managing blue collared employees and customer experience. There was a steely resolve to convert these thoughts into a playbook that could be useful for the\necosystem. I then joined xto10x and as a team we worked with more than 30\ncompanies where we applied these concepts and helped them succeed. We then articulated these into practical frameworks & actionable insights that we believed could help many other startups in their growth phase. This was the genesis of the 10xOps Academy, a 10 week program in Operations Excellence for founders & Ops leaders. Itâ€™s intended to help decode all the necessary capabilities for scaling operations while allowing companies to go deep on 1-2 critical areas - with an objective of helping create a Ops excellence roadmap for the next 18 months.\nWas great to see this vision come to life as our first ever batch of\ngraduated this week. Heartfelt gratitude & congratulations toteams.\nAs our second batch is set to kickoff next week, Iâ€™m excited about the widespread impact this program can have across the ecosystem.\nCongratulations to our Batch-1 graduates!\n34\nPost\nPost\nWeâ€™re signing up companies for the second 10x Ops Academy batch thatâ€™s set to start in mid Feb.\n\nPing me if youâ€™re looking to scale your operations setup - this could be the single most important step you take to setup your operations for success.\n\nLooking forward to 2 months of learning and impact with rockstar founders and ops leaders.\n10x Ops Academy | New program launch\n24\nPost\nPost\nI recently completed 2 outstanding years at.\n\nAs I reflect - I feel satisfaction & gratitude on one hand, and hunger & belief on the other.\n\nhashtag\n#satisfactionabout how I have evolved as an individual - 10x better problem solver, 10x better at conversations, 10x more mindful. Satisfaction that our work during this time has created loads of impact in the\n.\n\ntowards the entire\necosystem that has welcomed me and the offerings that I have taken to them. Gratitude towards the entireteam for being great friends & mentors. Gratitude towards my Ops & CX Practice team - who have always been with me through highs of success and the anxiety of creation. Itâ€™s deeply inspiring to be on a team of achievers & well wishers.\n\nto achieve much more individually & as a company - each of the modules we have developed has found relevance in its own big way and thereâ€™s impatience to crack the code on every meaningful problem that startups face during their hyper growth stage.\n\nthat we are onto something magical as a company and the only people who can stop us is ourselves if we fall out of the cycle of dreaming, experimenting and making it happen.\n\nWe are just getting started.\n\nIâ€™m just getting started.\nActivity\nActivity\n8,537 followers\n8,537 followers\nPosts\nComments\nVideos\nLoaded 9 Posts posts\nPawan Raghuveer\nPawan Raghuveer\nPawan Raghuveer\n   â€¢ 3rd+\nPremium â€¢ 3rd+\nOperations Excellence at xto10x\nOperations Excellence at xto10x\n1mo â€¢ Edited â€¢ \n 1 month ago â€¢ Edited â€¢ Visible to anyone on or off LinkedIn\nWe successfully concluded the scaling companies by xto10x program this week under the aegis of MonshaatSA \n\nOver the last few months, weâ€™ve been engaged with 15 exciting companies fromon different scaling topics like business design, org design and leadership, branding and marketing, operations excellence, and people excellence. It was indeed a great pleasure to see all companies take away value and scaling roadmaps from the program.\n\nOn behalf of the entire team at, Iâ€™d like to extend heartfelt gratitude to their excellencies the governor and vice governors offor placing faith in us, andandfor their constant support and collaboration.\n\nA special mention to our partnersfor working hand in hand with us to achieve success in the program.\n\nAnd finally to entire team atthat worked hard behind the scenes with a single minded mission of creating value for all the scaling companies.\n\nWe look forward to creating many more success stories with you all!\nâ€¦more\nEng. Abdulrahman Alsmail\nEng. Abdulrahman Alsmail\nEng. Abdulrahman Alsmail\n   â€¢ 3rd+\nVerified â€¢ 3rd+\nGeneral Manager of Enterprises Growth at MonshaatSA\nGeneral Manager of Enterprises Growth at MonshaatSA\nØ¶Ù…Ù† Ø¨Ø±Ù†Ø§Ù…Ø¬ Ø·Ù…ÙˆØ­ Ù„Ø¯Ø¹Ù… Ø§Ù„Ø´Ø±ÙƒØ§Øª Ù…ØªØ³Ø§Ø±Ø¹Ø© Ø§Ù„Ù†Ù…ÙˆØŒ Ù†ÙØ°Ù†Ø§ Ù…Ø¤Ø®Ø±Ù‹Ø§ Ø¨Ø±Ù†Ø§Ù…Ø¬ÙŠÙ† Ù…Ù…ÙŠØ²ÙŠÙ† Ø¨Ø§Ù„Ø´Ø±Ø§ÙƒØ© Ù…Ø¹ Endeavor Saudi Arabia :\n\nğŸ”¹ Scaling Founders by\n\nğŸ”¹ Scaling Companies by\n\nÙˆØ§Ø®ØªØªÙ…Ù†Ø§ Ø§Ù„Ø¨Ø±Ù†Ø§Ù…Ø¬ÙŠÙ† Ø¨Ù„Ù‚Ø§Ø¡ Ù…Ø´ØªØ±Ùƒ Ù…Ø¹ Ø³Ø¹Ø§Ø¯Ø© Ù…Ø­Ø§ÙØ¸ Ù…Ù†Ø´Ø¢ØªØŒ Ø­ÙŠØ« Ø´Ø§Ø±ÙƒØª Ø§Ù„Ù…Ù†Ø´Ø¢Øª Ø§Ù„Ù…Ø³ØªÙÙŠØ¯Ø© ØªØ¬Ø§Ø±Ø¨Ù‡Ø§ ÙˆØ¥Ù†Ø¬Ø§Ø²Ø§ØªÙ‡Ø§ØŒ ÙˆÙ†Ø§Ù‚Ø´Ù†Ø§ Ø£Ø¨Ø±Ø² Ø§Ù„ØªØ­Ø¯ÙŠØ§Øª ÙˆØ§Ù„ÙØ±Øµ Ø§Ù„ØªÙŠ ØªØ³Ù‡Ù… ÙÙŠ Ø§Ø³ØªØ¯Ø§Ù…Ø© Ù†Ù…ÙˆÙ‡Ø§.\n\nÙ‡Ø°Ù‡ Ø§Ù„Ù„Ù‚Ø§Ø¡Ø§Øª ØªØ¹ÙƒØ³ Ø¥ÙŠÙ…Ø§Ù†Ù†Ø§ Ø¨Ø£Ù‡Ù…ÙŠØ© Ø§Ù„ØªÙ…ÙƒÙŠÙ† Ø§Ù„Ù…Ø¨Ø§Ø´Ø±ØŒ ÙˆØ®Ù„Ù‚ Ø¨ÙŠØ¦Ø© ØªÙØ§Ø¹Ù„ÙŠØ© Ø¨ÙŠÙ† Ø±ÙˆØ§Ø¯ Ø§Ù„Ø£Ø¹Ù…Ø§Ù„ ÙˆØ§Ù„Ø¬Ù‡Ø§Øª Ø§Ù„Ø¯Ø§Ø¹Ù…Ø© Ù„ØªØ³Ø±ÙŠØ¹ Ø±Ø­Ù„Ø© Ø§Ù„Ù†Ù…Ùˆ ÙˆØ§Ù„ØªÙˆØ³Ø¹.\n\nÙƒÙ„ Ø§Ù„Ø´ÙƒØ± Ù„Ø´Ø±ÙƒØ§Ø¦Ù†Ø§ØŒ ÙˆÙ„Ù„Ù…Ù†Ø´Ø¢Øª Ø§Ù„Ù…Ù„Ù‡Ù…Ø© Ø§Ù„ØªÙŠ ÙƒØ§Ù†Øª Ø¬Ø²Ø¡Ù‹Ø§ Ù…Ù† Ù‡Ø°Ù‡ Ø§Ù„ØªØ¬Ø±Ø¨Ø©.\n\nÙƒÙ„ Ø§Ù„Ø´ÙƒØ± Ù„Ù‚ÙŠØ§Ø¯Ø§Øª Ø§Ù†Ø¯ÙŠÙÙˆØ±Ùˆ\nÙˆÙ‚ÙŠØ§Ø¯Ø§Øª Ø§Ù„Ø¨Ø±Ù†Ø§Ù…Ø¬\nØ´ÙƒØ± Ø®Ø§Øµ Ù„Ù…Ø¯ÙŠØ± Ø§Ù„Ù…Ø´Ø±ÙˆØ¹Ø¹Ù„Ù‰ ÙƒØ§ÙØ© Ø¬Ù‡ÙˆØ¯Ù‡Ø§ Ø®Ù„Ø§Ù„ ÙØªØ±Ø© Ø³Øª Ø´Ù‡ÙˆØ± ÙˆØ¹Ù„Ù‰ Ù‚ÙŠØ§Ø¯ØªÙ‡ Ù„Ù„Ù…Ù„Ù Ø¨Ù†Ø¬Ø§Ø­ ÙˆØªØ­Ù‚ÙŠÙ‚ Ø§Ù„Ø§Ø«Ø±.\nÙˆÙ†ØªØ·Ù„Ø¹ Ø¥Ù„Ù‰ Ù…ÙˆØ§ØµÙ„Ø© Ø¯Ø¹Ù… Ø§Ù„Ù…Ø²ÙŠØ¯ Ù…Ù† Ù‚ØµØµ Ø§Ù„Ù†Ø¬Ø§Ø­ ğŸ’¼ğŸš€\n\n#\nâ€¦more\nShow translation\nActivate to view larger image,\n1/3\nActivate to view larger image,\n55\n8 comments\n2 reposts\nPawan Raghuveer\nPawan Raghuveer\nPawan Raghuveer\n   â€¢ 3rd+\nPremium â€¢ 3rd+\nOperations Excellence at xto10x\nOperations Excellence at xto10x\n1mo â€¢ \n 1 month ago â€¢ Visible to anyone on or off LinkedIn\nEver wondered how to unlock 5â€“7% CM1 in a D2C business through operations excellence?\n\nThatâ€™s exactly what we set out to explore in our founders-only roundtables this April and May.\n\nThese sessions brought together sharp, curious, and candid founders. The magic? It wasnâ€™t just about learningâ€”it was about collective problem-solving seeded byâ€˜s tested frameworks, real-life case studies, and rich founder experiences. Every question sparked insights. Every challenge turned into a shared opportunity for growth.\n\nWe deep-dived into logistics and warehouse costs and levers to control them, the true impact of delivery speed and accurate promise on profitability, the constant trade-off between cost efficiency and customer delight, and in the process we busted myths like â€œfaster = costlierâ€\n\nThe outcome? Actionable takeaways, new ways of thinking, and a community of founders helping each other win.\n\nCheck out the highlights to see these powerful conversations in action.\n\nBig thanks to all the founders who made these sessions truly special with their openness and insight.\n\nGagandeep M.\n\nâ€¦more\n133\n1 comment\n9 reposts\nShow all posts\nExperience\nExperience\nGeneral Manager\nGeneral Manager\nxto10x Â· Full-time\nxto10x Â· Full-time\nNov 2020 - Present Â· 4 yrs 9 mos\nNov 2020 to Present Â· 4 yrs 9 mos\nBengaluru, Karnataka, India\nBengaluru, Karnataka, India\nMentored and partnered with 50+ growth stage companies across e-commerce, EdTech, HealthTech on topics across operations excellence and customer experience like P&L improvement, NPS improvement, speed improvement, and reliability improvement\nCure.Fit\nCure.Fit\n2 yrs 1 mo\n2 yrs 1 mo\nOperations, Cult.fit\nOperations, Cult.fit\nFull-time\nFull-time\nAug 2020 - Nov 2020 Â· 4 mos\nAug 2020 to Nov 2020 Â· 4 mos\nBengaluru, Karnataka, India\nBengaluru, Karnataka, India\nOperations, Eat.fit\nOperations, Eat.fit\nNov 2018 - Aug 2020 Â· 1 yr 10 mos\nNov 2018 to Aug 2020 Â· 1 yr 10 mos\nBengaluru, Karnataka, India\nBengaluru, Karnataka, India\nManaging supply chain and operations of the Curefit's cloud kitchen business: Leadership areas include kitchen operations, logistics operations, network design, and sourcing.\nProblem solving for unit economics goals: understanding drivers of cost and margin, identify and lead projects for structural improvement of P&L and balance sheet.\nPeople management at scale: Ensuring high performance outcomes and happiness for multi layered organisation in a systematic way while ensuring hyper growth for business and quality for customer.\nFlipkart\nFlipkart\n6 yrs 9 mos\n6 yrs 9 mos\nDirector - City Logistics Design\nDirector - City Logistics Design\nNov 2016 - Oct 2018 Â· 2 yrs\nNov 2016 to Oct 2018 Â· 2 yrs\nBengaluru Area, India\nBengaluru Area, India\nDeveloping the city logistics framework for best in class customer experience, seller experience and cost efficiency. \nProcess innovation and solution design for ekart e commerce pickup and delivery, e-quick (hyperlocal delivery) and ekart courier.\nNurturing a team of hard hitting innovators and supply chain subject matter experts.\nDirector - Last Mile Design, ekart\nDirector - Last Mile Design, ekart\nJan 2016 - Oct 2016 Â· 10 mos\nJan 2016 to Oct 2016 Â· 10 mos\nBengaluru, Karnataka, India\nBengaluru, Karnataka, India\nLast Mile Logistics planning, Process and business transformation, team management\nLast Mile Logistics planning, Process and business transformation, team management\nAssociate Director - Planning & Engineering (Logistics)\nAssociate Director - Planning & Engineering (Logistics)\nJan 2014 - Dec 2015 Â· 2 yrs\nJan 2014 to Dec 2015 Â· 2 yrs\nBengaluru, Karnataka, India\nBengaluru, Karnataka, India\nResponsible for resource planning, capability planning & process re-engineering for logistics function. \nLeading project management team responsible for planning & execution of cross functional projects across Marketplace, End mile, Line-haul and other supply chain processes.\nShow all 4 experiences\nITC Limited\nITC Limited\nFull-time Â· 1 yr 9 mos\nFull-time Â· 1 yr 9 mos\nAssistant Manager - Supply Chain Analytics\nAssistant Manager - Supply Chain Analytics\nApr 2011 - Feb 2012 Â· 11 mos\nApr 2011 to Feb 2012 Â· 11 mos\nGreater Kolkata Area\nGreater Kolkata Area\nAnalysis & management of inventory spread, fill rates, sales loss, order management process, product freshness & distributor investment across product categories (Biscuits, Snacks, Confectionery, Toilet soaps & Shampoos)\nAnalysis & management of inventory spread, fill rates, sales loss, order management process, product freshness & distributor investment across product categories (Biscuits, Snacks, Confectionery, Toilet soaps & Shampoos)\nAssistant Manager - Marketing\nAssistant Manager - Marketing\nJun 2010 - Mar 2011 Â· 10 mos\nJun 2010 to Mar 2011 Â· 10 mos\nChandigarh, India\nChandigarh, India\nSales & Distribution of all ITC products in the Jammu & Kashmir and Himachal Pradesh areas.\nSales & Distribution of all ITC products in the Jammu & Kashmir and Himachal Pradesh areas.\nSummer Intern in CMK at Singapore\nSummer Intern in CMK at Singapore\nProcter & Gamble\nProcter & Gamble\nApr 2009 - Jun 2009 Â· 3 mos\nApr 2009 to Jun 2009 Â· 3 mos\nDevised line extension strategies for a leading skin care brand in the Asia Pacific region in the area of media, PR and in shop execution\nDevised line extension strategies for a leading skin care brand in the Asia Pacific region in the area of media, PR and in shop execution\nShow all 11 experiences\nEducation\nEducation\nIndian Institute of Management Bangalore\nIndian Institute of Management Bangalore\nMBA, Marketing & Strategy\nMBA, Marketing & Strategy\n2008 - 2010\n2008 - 2010\nActivities and societies: Editor, tejas@iimb, an online publication on the lines of Knowledge@Wharton; \nSenior Coordinator, Alumni Committee: coordinated Anusmaran 09, the global Alumni meet at Singapore; \nMember, cricket team at IIMB\nUniversitÃ© libre de Bruxelles\nUniversitÃ© libre de Bruxelles\nMBA, Management\nMBA, Management\n2009 - 2009\n2009 - 2009\nActivities and societies: International Exchange student at Solvay Business School: Courses attended include Euromarketing, Project Management, IT & e commerce\nActivities and societies: International Exchange student at Solvay Business School: Courses attended include Euromarketing, Project Management, IT & e commerce\nProjects:\nMarketing of European regional traditions like Christmas &amp; use of Christmas markets as a channel\nMarketing opportunities using IT: Augmented reality\nShow all 3 educations\nSkills\nSkills\nBusiness Strategy\nBusiness Strategy\nEndorsed by Prashant Kumar who is highly skilled at this\nEndorsed byPrashant Kumarwho is highly skilled at this\nEndorsed by 5 colleagues at Curefit\nEndorsed by 5 colleagues at Curefit\n57 endorsements\n57 endorsements\nTeam Management\nTeam Management\nEndorsed by Rohit Kunal and 17 others who are highly skilled at this\nEndorsed byRohit Kunaland 17 others who are highly skilled at this\nEndorsed by 3 colleagues at xto10x\nEndorsed by 3 colleagues at xto10x\n91 endorsements\n91 endorsements\nShow all 24 skills\nRecommendations\nRecommendations\nReceived\nReceived\nGiven\nGiven\nMritunjoy Ojha\nMritunjoy Ojha\nMritunjoy Ojha\nSenior Manager Customer Facing Team, Supply Chain\nSenior Manager Customer Facing Team, Supply Chain\nAugust 21, 2020, Mritunjoy managed Pawan directly\nAugust 21, 2020,MritunjoymanagedPawandirectly\nI worked with Pawan very closely. He is very sharp and having extra ordinary observation skills. He has helped ITC in setting up new process during his sting in Supply chain vertical. His analytical skills has led to high two digit growth in Foods category in Jammu branch. \nI worked with Pawan very closely. He is very sharp and having extra ordinary observation skills. He has helped ITC in setting up new process during his sting in Supply chain vertical. His analytical skills has led to high two digit growth in Foods category in Jammu branch.\nPuneet Jain\nPuneet Jain\nPuneet Jain\n@Work\n@Work\nJune 12, 2015, Puneet reported directly to Pawan\nJune 12, 2015,Puneetreported directly toPawan\nI have known Pawan for last two years. I have worked under him for a year. He is one of the best guys i have worked with. Blessed with sharp mind, top notch managerial skills and time management, he is a great guy to work for. He has been very watchful of his team. He drives inclusive growth and problem solving. The best thing about him is his approach to solve problems. He targets both short term and long term solutions so as to reap short term gains and manage long term strategy planning. Always looking forward to work with him.\nI have known Pawan for last two years. I have worked under him for a year. He is one of the best guys i have worked with. Blessed with sharp mind, top notch managerial skills and time management, he is a great guy to work for. He has been very watchful of his team. He drives inclusive growth and problem solving. The best thing about him is his approach to solve problems. He targets both short term and long term solutions so as to reap short term gains and manage long term strategy planning. Always looking forward to work with him.\nShow all 5 received\nInterests\nInterests\nTop Voices\nTop Voices\nCompanies\nCompanies\nGroups\nGroups\nNewsletters\nNewsletters\nSchools\nSchools\nArindam Paul\nArindam Paul\nBuilding Atomberg \nBuilding Atomberg\n127,660 followers\n127,660 followers\nFollow\nHarsh Mariwala\nHarsh Mariwala\nChairman - Marico Limited | Investor | Philanthropist | Author | Keynote Speaker\nChairman - Marico Limited | Investor | Philanthropist | Author | Keynote Speaker\n169,102 followers\n169,102 followers\nFollow\nShow all Top Voices\nMore profiles for you\nMore profiles for you\nRaja Dutta\nRaja Dutta\nÂ· 3rd+\n3rd+ degree connection\nSupply Chain and Logistics Professional\nSupply Chain and Logistics Professional\nFollow\nRohit Sharma\nRohit Sharma\nRohit Sharma\nÂ· 3rd+\n3rd+ degree connection\nCEO- Delivery Org\nCEO- Delivery Org\nFollow\nNeeraj Aggarwal\nNeeraj Aggarwal\nÂ· 3rd+\n3rd+ degree connection\nCo-founder at xto10x | GM at Cure.fit | Vice President, Operations at Flipkart\nMessage\nVikas Sharma\nVikas Sharma\nÂ· 3rd+\n3rd+ degree connection\nCOO, Zepto\nCOO, Zepto\nFollow\nWahab Basarikatti\nWahab Basarikatti\nÂ· 3rd+\n3rd+ degree connection\nSupply Chain Leader | Business Strategy Expert | Operations Transformation | Process Improvement | ISB\nMessage\nShow all\nPeople you may know\nPeople you may know\nFrom Pawan's school\nFrom Pawan's school\nMarion Joyner Wesonga\nMarion Joyner Wesonga\nTax Compliance & Consultancy Expert\nTax Compliance & Consultancy Expert\nConnect\nKunal Rai\nKunal Rai\nPhD [DS] (IIMB) | Integrated BS-MS [PHY] (IISERB)\nPhD [DS] (IIMB) | Integrated BS-MS [PHY] (IISERB)\nConnect\nPRIYANSHI OHARIYA\nPRIYANSHI OHARIYA\nPRIYANSHI OHARIYA\nIIM BANGALORE '27 | JNU DELHI '28\nIIM BANGALORE '27 | JNU DELHI '28\nConnect\nRishi Teja Mandadi\nRishi Teja Mandadi\nEconomics Student | Passionate about Finance and Research\nEconomics Student | Passionate about Finance and Research\nConnect\nShreshtha Kasliwal\nShreshtha Kasliwal\nStudent at Mithibai College of Arts Chauhan Institute of Science| Student at Indian Institute of Management- Bangalore (IIMB-BBA-DBE)\nConnect\nShow all\nYou might like\nYou might like\nPages for you\nPages for you\nSciAstra\nSciAstra\nE-Learning Providers\nE-Learning Providers\n37,215 followers\n37,215 followers\nFollow\nSakthi Aircraft Industry\nSakthi Aircraft Industry\nAirlines and Aviation\nAirlines and Aviation\n1,184 followers\n1,184 followers\nFollow\nShow all\nAbout\nAccessibility\nTalent Solutions\nProfessional Community Policies\nCareers\nMarketing Solutions\nPrivacy & Terms\nAd Choices\nAdvertising\nSales Solutions\nMobile\nSmall Business\nSafety Center\nQuestions?\nVisit our Help Center.\nManage your account and privacy\nGo to your Settings.\nRecommendation transparency\nLearn more about Recommended Content.\nSelect Language\n         Ø§Ù„Ø¹Ø±Ø¨ÙŠØ© (Arabic)\n         à¦¬à¦¾à¦‚à¦²à¦¾ (Bangla)\n         ÄŒeÅ¡tina (Czech)\n         Dansk (Danish)\n         Deutsch (German)\n         Î•Î»Î»Î·Î½Î¹ÎºÎ¬ (Greek)\n         English (English)\n         EspaÃ±ol (Spanish)\n         ÙØ§Ø±Ø³ÛŒ (Persian)\n         Suomi (Finnish)\n         FranÃ§ais (French)\n         à¤¹à¤¿à¤‚à¤¦à¥€ (Hindi)\n         Magyar (Hungarian)\n         Bahasa Indonesia (Indonesian)\n         Italiano (Italian)\n         ×¢×‘×¨×™×ª (Hebrew)\n         æ—¥æœ¬èª (Japanese)\n         í•œêµ­ì–´ (Korean)\n         à¤®à¤°à¤¾à¤ à¥€ (Marathi)\n         Bahasa Malaysia (Malay)\n         Nederlands (Dutch)\n         Norsk (Norwegian)\n         à¨ªà©°à¨œà¨¾à¨¬à©€ (Punjabi)\n         Polski (Polish)\n         PortuguÃªs (Portuguese)\n         RomÃ¢nÄƒ (Romanian)\n         Ğ ÑƒÑÑĞºĞ¸Ğ¹ (Russian)\n         Svenska (Swedish)\n         à°¤à±†à°²à±à°—à± (Telugu)\n         à¸ à¸²à¸©à¸²à¹„à¸—à¸¢ (Thai)\n         Tagalog (Tagalog)\n         TÃ¼rkÃ§e (Turkish)\n         Ğ£ĞºÑ€Ğ°Ñ—Ğ½ÑÑŒĞºĞ° (Ukrainian)\n         Tiáº¿ng Viá»‡t (Vietnamese)\n         ç®€ä½“ä¸­æ–‡ (Chinese (Simplified))\n         æ­£é«”ä¸­æ–‡ (Chinese (Traditional))\n     LinkedIn Corporation Â© 2025\nStatus is online\nMessaging\nYou are on the messaging overlay. Press enter to open the list of conversations.\nCompose message\nYou are on the messaging overlay. Press enter to open the list of conversations.",
  "skills_text": "0 notifications total\nnew feed updates notifications\nHome\n1\n1 new network update notification\nMy Network\nJobs\nMessaging\nNotifications\nMe\nFor Business\nTry Premium for â‚¹0\nPawan Raghuveer\nOperations Excellence at xto10x\nMore\nFollow\nMessage\nSkills\nAll\nIndustry Knowledge\nInterpersonal Skills\nBusiness Strategy\nBusiness Strategy\nEndorsed by Prashant Kumar who is highly skilled at this\nEndorsed byPrashant Kumarwho is highly skilled at this\nEndorsed by 5 colleagues at Curefit\nEndorsed by 5 colleagues at Curefit\n57 endorsements\n57 endorsements\nTeam Management\nTeam Management\nEndorsed by Rohit Kunal and 17 others who are highly skilled at this\nEndorsed byRohit Kunaland 17 others who are highly skilled at this\nEndorsed by 3 colleagues at xto10x\nEndorsed by 3 colleagues at xto10x\n91 endorsements\n91 endorsements\nSupply Chain Management\nSupply Chain Management\nEndorsed by Nitin Bhan and 14 others who are highly skilled at this\nEndorsed byNitin Bhanand 14 others who are highly skilled at this\nEndorsed by 5 colleagues at Curefit\nEndorsed by 5 colleagues at Curefit\n86 endorsements\n86 endorsements\nSupply Chain\nSupply Chain\n45 endorsements\n45 endorsements\nOperations Management\nOperations Management\n20 endorsements\n20 endorsements\nProject Management\nProject Management\n27 endorsements\n27 endorsements\nVendor Management\nVendor Management\n16 endorsements\n16 endorsements\nSix Sigma\nSix Sigma\nAnalytics\nAnalytics\n29 endorsements\n29 endorsements\nBusiness Development\nBusiness Development\n34 endorsements\n34 endorsements\nFMCG\nFMCG\n26 endorsements\n26 endorsements\nMarketing Strategy\nMarketing Strategy\n12 endorsements\n12 endorsements\nAnalysis\nAnalysis\n13 endorsements\n13 endorsements\nBusiness Analytics\nBusiness Analytics\n7 endorsements\n7 endorsements\nProcurement\nProcurement\n5 endorsements\n5 endorsements\nMarket Research\nMarket Research\n1 endorsement\n1 endorsement\nManagement\nManagement\n6 endorsements\n6 endorsements\nLogistics Management\nLogistics Management\nProblem Solving\nProblem Solving\n1 endorsement\n1 endorsement\nOperational Excellence\nOperational Excellence\n1 endorsement\n1 endorsement\nTime Management\nTime Management\nCustomer Experience\nCustomer Experience\nPeople Management\nPeople Management\n1 endorsement\n1 endorsement\nStrategy\nStrategy\n1 endorsement\n1 endorsement\nMore profiles for you\nMore profiles for you\nRaja Dutta\nRaja Dutta\nÂ· 3rd+\n3rd+ degree connection\nSupply Chain and Logistics Professional\nSupply Chain and Logistics Professional\nFollow\nRohit Sharma\nRohit Sharma\nRohit Sharma\nÂ· 3rd+\n3rd+ degree connection\nCEO- Delivery Org\nCEO- Delivery Org\nFollow\nNeeraj Aggarwal\nNeeraj Aggarwal\nÂ· 3rd+\n3rd+ degree connection\nCo-founder at xto10x | GM at Cure.fit | Vice President, Operations at Flipkart\nMessage\nVikas Sharma\nVikas Sharma\nÂ· 3rd+\n3rd+ degree connection\nCOO, Zepto\nCOO, Zepto\nFollow\nWahab Basarikatti\nWahab Basarikatti\nÂ· 3rd+\n3rd+ degree connection\nSupply Chain Leader | Business Strategy Expert | Operations Transformation | Process Improvement | ISB\nMessage\nShow more\nAbout\nAccessibility\nTalent Solutions\nProfessional Community Policies\nCareers\nMarketing Solutions\nPrivacy & Terms\nAd Choices\nAdvertising\nSales Solutions\nMobile\nSmall Business\nSafety Center\nQuestions?\nVisit our Help Center.\nManage your account and privacy\nGo to your Settings.\nRecommendation transparency\nLearn more about Recommended Content.\nSelect Language\n         Ø§Ù„Ø¹Ø±Ø¨ÙŠØ© (Arabic)\n         à¦¬à¦¾à¦‚à¦²à¦¾ (Bangla)\n         ÄŒeÅ¡tina (Czech)\n         Dansk (Danish)\n         Deutsch (German)\n         Î•Î»Î»Î·Î½Î¹ÎºÎ¬ (Greek)\n         English (English)\n         EspaÃ±ol (Spanish)\n         ÙØ§Ø±Ø³ÛŒ (Persian)\n         Suomi (Finnish)\n         FranÃ§ais (French)\n         à¤¹à¤¿à¤‚à¤¦à¥€ (Hindi)\n         Magyar (Hungarian)\n         Bahasa Indonesia (Indonesian)\n         Italiano (Italian)\n         ×¢×‘×¨×™×ª (Hebrew)\n         æ—¥æœ¬èª (Japanese)\n         í•œêµ­ì–´ (Korean)\n         à¤®à¤°à¤¾à¤ à¥€ (Marathi)\n         Bahasa Malaysia (Malay)\n         Nederlands (Dutch)\n         Norsk (Norwegian)\n         à¨ªà©°à¨œà¨¾à¨¬à©€ (Punjabi)\n         Polski (Polish)\n         PortuguÃªs (Portuguese)\n         RomÃ¢nÄƒ (Romanian)\n         Ğ ÑƒÑÑĞºĞ¸Ğ¹ (Russian)\n         Svenska (Swedish)\n         à°¤à±†à°²à±à°—à± (Telugu)\n         à¸ à¸²à¸©à¸²à¹„à¸—à¸¢ (Thai)\n         Tagalog (Tagalog)\n         TÃ¼rkÃ§e (Turkish)\n         Ğ£ĞºÑ€Ğ°Ñ—Ğ½ÑÑŒĞºĞ° (Ukrainian)\n         Tiáº¿ng Viá»‡t (Vietnamese)\n         ç®€ä½“ä¸­æ–‡ (Chinese (Simplified))\n         æ­£é«”ä¸­æ–‡ (Chinese (Traditional))\n     LinkedIn Corporation Â© 2025\nStatus is online\nMessaging\nYou are on the messaging overlay. Press enter to open the list of conversations.\nCompose message\nYou are on the messaging overlay. Press enter to open the list of conversations.",
  "scraped_at": "2025-07-23 01:50:00",
  "has_skills": true,
  "cleaned_profile": {
    "name": "Pawan Raghuveer",
    "profile_url": "https://in.linkedin.com/in/pawan-raghuveer-62b00ba",
    "current_position": {
      "title": "General Manager",
      "company": "xto10x",
      "location": "Bengaluru, Karnataka, India",
      "start_date": "Nov 2020",
      "end_date": "Present",
      "duration": "4 yrs 9 mos"
    },
    "previous_positions": [
      {
        "title": "Operations, Cult.fit",
        "company": "Cure.Fit",
        "location": "Bengaluru, Karnataka, India",
        "start_date": "Aug 2020",
        "end_date": "Nov 2020",
        "duration": "4 mos"
      },
      {
        "title": "Operations, Eat.fit",
        "company": "Cure.Fit",
        "location": "Bengaluru, Karnataka, India",
        "start_date": "Nov 2018",
        "end_date": "Aug 2020",
        "duration": "1 yr 10 mos"
      },
      {
        "title": "Director - City Logistics Design",
        "company": "Flipkart",
        "location": "Bengaluru Area, India",
        "start_date": "Nov 2016",
        "end_date": "Oct 2018",
        "duration": "2 yrs"
      },
      {
        "title": "Director - Last Mile Design, ekart",
        "company": "Flipkart",
        "location": "Bengaluru, Karnataka, India",
        "start_date": "Jan 2016",
        "end_date": "Oct 2016",
        "duration": "10 mos"
      },
      {
        "title": "Associate Director - Planning & Engineering (Logistics)",
        "company": "Flipkart",
        "location": "Bengaluru, Karnataka, India",
        "start_date": "Jan 2014",
        "end_date": "Dec 2015",
        "duration": "2 yrs"
      },
      {
        "title": "Assistant Manager - Supply Chain Analytics",
        "company": "ITC Limited",
        "location": "Greater Kolkata Area",
        "start_date": "Apr 2011",
        "end_date": "Feb 2012",
        "duration": "11 mos"
      },
      {
        "title": "Assistant Manager - Marketing",
        "company": "ITC Limited",
        "location": "Chandigarh, India",
        "start_date": "Jun 2010",
        "end_date": "Mar 2011",
        "duration": "10 mos"
      },
      {
        "title": "Summer Intern in CMK at Singapore",
        "company": "Procter & Gamble",
        "location": "Singapore",
        "start_date": "Apr 2009",
        "end_date": "Jun 2009",
        "duration": "3 mos"
      }
    ],
    "education": [
      {
        "institution": "Indian Institute of Management Bangalore",
        "degree": "MBA",
        "field_of_study": "Marketing & Strategy",
        "years_attended": "2008 - 2010"
      },
      {
        "institution": "UniversitÃ© libre de Bruxelles",
        "degree": "MBA",
        "field_of_study": "Management",
        "years_attended": "2009 - 2009"
      }
    ],
    "connections": "500+",
    "followers": "8,537",
    "skills": [
      "Business Strategy",
      "Team Management",
      "Supply Chain Management",
      "Supply Chain",
      "Operations Management",
      "Project Management",
      "Vendor Management",
      "Six Sigma",
      "Analytics",
      "Business Development",
      "FMCG",
      "Marketing Strategy",
      "Analysis",
      "Business Analytics",
      "Procurement",
      "Market Research",
      "Management",
      "Logistics Management",
      "Problem Solving",
      "Operational Excellence",
      "Time Management",
      "Customer Experience",
      "People Management",
      "Strategy"
    ],
    "interests": [
      "Arindam Paul",
      "Harsh Mariwala"
    ]
  },
  "tokens_used": {
    "prompt_tokens": 6202,
    "completion_tokens": 923,
    "total_tokens": 7125
  }
}