{
  "url": "https://in.linkedin.com/in/ashutoshyadav18",
  "raw_text": "0 notifications total\nnew feed updates notifications\nHome\n1\n1 new network update notification\nMy Network\nJobs\nMessaging\nNotifications\nMe\nFor Business\nTry Premium for ₹0\nAshutosh Yadav\nSDE 1 @xto10x\nLovely Professional University\nBengaluru, Karnataka, India Contact info\n500+ connections\nMessage\nFollow\nMore\nAbout\nAbout\nAshutosh Yadav is a certified full stack developer based in Haryana, India, currently working as an SDE 1 at @xto10x, where he contributes to the development of the innovative SaaS tool, PeopleCues. With a strong technical foundation, Ashutosh specializes in a diverse tech stack that includes Java with Spring Boot, Node.js, Express.js, SCSS, React.js, AWS and various database technologies such as PostgreSQL, MySQL, and MongoDB. His primary focus is on backend development using Java and Spring Boot, along with cloud solutions leveraging AWS and the Serverless framework.\n\nIn addition to his professional expertise, Ashutosh has a keen interest in video editing, chess, and cybersecurity, showcasing his multifaceted skills and passion for continuous learning.\n…see more\nTop skills\nTop skills\nJava • JavaScript • Spring Boot • React.js • Amazon Web Services (AWS)\nJava • JavaScript • Spring Boot • React.js • Amazon Web Services (AWS)\nActivity\nActivity\n618 followers\n618 followers\nLoaded 2 Comments posts\nAshutosh Yadav commented on a post • 1mo\n1mo\nKeep shining, Anjali ⭐\nKeep shining, Anjali ⭐\nAshutosh Yadav commented on a post • 8mo\n8mo\nCongrats Jasbir! 🎉\nCongrats Jasbir! 🎉\nShow all comments\nExperience\nExperience\nxto10x\nxto10x\n1 yr 3 mos\n1 yr 3 mos\nOn-site\nOn-site\nSDE 1\nSDE 1\nFull-time\nFull-time\nNov 2024 - Present · 9 mos\nNov 2024 to Present · 9 mos\nBengaluru, Karnataka, India\nBengaluru, Karnataka, India\nJava, Amazon Web Services (AWS) and +5 skills\nFull stack Developer Intern\nFull stack Developer Intern\nInternship\nInternship\nMay 2024 - Oct 2024 · 6 mos\nMay 2024 to Oct 2024 · 6 mos\nJava, Amazon Web Services (AWS) and +5 skills\nEducation\nEducation\nLovely Professional University\nLovely Professional University\nBachelor of Technology - BTech\nBachelor of Technology - BTech\nLicenses & certifications\nLicenses & certifications\nFull Stack Development \nFull Stack Development\nNational Skill Development Corporation\nNational Skill Development Corporation\nIssued Mar 2024\nIssued Mar 2024\nCredential ID vjhnxh8t3mtfgg3q\nCredential ID vjhnxh8t3mtfgg3q\nFull Stack Development Certificate \nFull Stack Development Certificate\nProjects\nProjects\nX Clone\nX Clone\nJan 2024 - Mar 2024\nJan 2024 - Mar 2024\nXclone is an full stack ecommerce website made with MERN stack some of the key features include:\n\nHere are some of the key features :\n\n𝟭) 𝗦𝗶𝗴𝗻𝗶𝗻/𝗦𝗶𝗴𝗻𝘂𝗽:\n\nI implemented proper validation and authentication using Yup, Zod, and JWT. The main routes are protected.\n\n𝟮)𝗧𝘄𝗲𝗲𝘁:\n\nA user can tweet, and each tweet has four options: comments, likes, reposts, and posts.\n\n•The posts section contains both quoted and simple tweets.\n\n•The repost section contains only the reposted content.\n\n•The likes section contains posts liked by the user.\n\n•The comments section contains the tweet itself along with the user’s comments on the tweet.\n\n𝟯)𝗣𝗿𝗼𝗳𝗶𝗹𝗲:\n\nA user can update their profile, including their name, bio, password, profile image, and cover image. Users can also view their followers and who they are following.\n\n𝟰)𝗙𝗼𝗹𝗹𝗼𝘄/𝗨𝗻𝗳𝗼𝗹𝗹𝗼𝘄:\n\nUsers have the ability to follow and unfollow each other.\n\n𝟱)𝗦𝗲𝗮𝗿𝗰𝗵 𝗙𝘂𝗻𝗰𝘁𝗶𝗼𝗻𝗮𝗹𝗶𝘁𝘆:\n\nI implemented a search functionality that works on the concept of debouncing. This allows users to search for each other, view profiles, and follow or unfollow each other.\n\n𝟲) 𝗧𝗶𝗺𝗲 𝘀𝘆𝗻𝗰𝗵𝗿𝗼𝗻𝗶𝘇𝗮𝘁𝗶𝗼𝗻\n\nImplemented a time display feature for all tweet posts. If a tweet was posted less than 60 seconds ago, it will display ‘Just now’. If the tweet was posted less than an hour ago, the time will be displayed in minutes (e.g., ‘1 min’, ‘12 min’). The same format applies to days and months.\n\n𝗧𝗲𝗰𝗵 𝗦𝘁𝗮𝗰𝗸 𝗢𝘃𝗲𝗿𝘃𝗶𝗲𝘄:\n\n𝗖𝗹𝗶𝗲𝗻𝘁-𝗦𝗶𝗱𝗲:\n\nReact.js (frontend library)\nAxios (for API calls)\nYup (for form validation)\n\n𝗦𝗲𝗿𝘃𝗲𝗿-𝗦𝗶𝗱𝗲:\n\nNode.js and Express.js (server-side language)\nMongoDB (database)\nCloudinary and Multer (for storing images)\nJWT and Bcrypt (for authentication)\nZod (for validation)\nHTML5, React.js and +4 skills\nX Clone\nX Clone\nNextCart\nNextCart\nDec 2023 - Jan 2024\nDec 2023 - Jan 2024\nNextCart is an full stack ecommerce website made with MERN stack some of the key features include:\n\n𝟭) 𝗔𝗱𝗺𝗶𝗻 𝗗𝗮𝘀𝗵𝗯𝗼𝗮𝗿𝗱:\n\nManage products (Add/Edit/Delete products)\n\nManage orders (Update delivery status)\n\nChange profile details (Name, email, address, description, image, password)\n\n𝟮) 𝗨𝘀𝗲𝗿 𝗣𝗮𝗻𝗲𝗹:\n\nAdd products to cart (Modify quantity or delete products from cart)\n\nPlace orders (View delivery status)\n\nChange profile details (Name, email, address, description, image, password)\n\nDelete account (Only user accounts can be deleted)\n\n𝟯) 𝗦𝗲𝗮𝗿𝗰𝗵 𝗣𝗿𝗼𝗱𝘂𝗰𝘁𝘀:\n\nImplemented search functionality with proper debouncing to avoid unnecessary requests.\n\n𝟰) 𝗣𝗿𝗼𝗽𝗲𝗿 𝗔𝘂𝘁𝗵𝗲𝗻𝘁𝗶𝗰𝗮𝘁𝗶𝗼𝗻:\n\nOnly registered users can add products to the cart.\n\nUser IDs can be deleted, while admin IDs cannot.\n\nImplemented protected routes; for instance, if a user attempts to access a profile page or any protected route through manual routing, they will be redirected to the login page.\n\n𝗧𝗲𝗰𝗵 𝗦𝘁𝗮𝗰𝗸 𝗢𝘃𝗲𝗿𝘃𝗶𝗲𝘄:\n\n𝗖𝗹𝗶𝗲𝗻𝘁 𝗦𝗶𝗱𝗲:\n\n1) React Js.\n\n2) Context API (for state management)\n\n3) Owl Carousel (for image carousels)\n\n𝗦𝗲𝗿𝘃𝗲𝗿 𝗦𝗶𝗱𝗲:\n\n1) Node.js & Express\n\n2) MongoDB (as Database)\n\n3) JWT (for authentication)\n\n4) Cloudinary and Multer (for image storage)\nNextCart\nNextCart\nSkills\nSkills\nLaravel\nLaravel\n2 experiences at xto10x\n2 experiences at xto10x\nPHP\nPHP\n2 experiences at xto10x\n2 experiences at xto10x\nShow all 17 skills\nPublications\nPublications\nSmart attendance system using face recognition\nSmart attendance system using face recognition\nSSRN · Apr 10, 2024\nSSRN · Apr 10, 2024\nShow publication\nInterests\nInterests\nCompanies\nCompanies\nNewsletters\nNewsletters\nxto10x\nxto10x\n21,217 followers\n21,217 followers\nFollow\nPeopleCues\nPeopleCues\n735 followers\n735 followers\nFollow\nMore profiles for you\nMore profiles for you\nAshish Mishra\nAshish Mishra\n· 3rd+\n3rd+ degree connection\nSenior Software Engineer, Full stack developer\nSenior Software Engineer, Full stack developer\nMessage\nTejasvee Srikantan\nTejasvee Srikantan\n· 3rd+\n3rd+ degree connection\nEngineering | Walmart | xto10x | Flipkart\nEngineering | Walmart | xto10x | Flipkart\nMessage\nSagar Panwar\nSagar Panwar\n· 3rd+\n3rd+ degree connection\nbla bla bla..\nbla bla bla..\nMessage\nBhaveek Jain\nBhaveek Jain\n· 3rd+\n3rd+ degree connection\nTech @xto10x | Fullstack Developer - React(Nextjs)\nTech @xto10x | Fullstack Developer - React(Nextjs)\nMessage\nSmriti Pillai\nSmriti Pillai\n· 3rd+\n3rd+ degree connection\nSDE-1 at xto10x | Ex - Exotel \nSDE-1 at xto10x | Ex - Exotel\nMessage\nShow all\nPeople you may know\nPeople you may know\nFrom Ashutosh's school\nFrom Ashutosh's school\nTinashe Chivenge\nTinashe Chivenge\nStudent at Lovely Professional University\nStudent at Lovely Professional University\nConnect\nRatidzoyashe Agnes\nRatidzoyashe Agnes\nRatidzoyashe Agnes\nStudent at Lovely Professional University\nStudent at Lovely Professional University\nConnect\nAsha Thakuli\nAsha Thakuli\nStudent at Lovely Professional University\nStudent at Lovely Professional University\nConnect\nJulius joseph Julius\nJulius joseph Julius\nJulius joseph Julius\nStudent at Lovely Professional University\nStudent at Lovely Professional University\nConnect\nJaya Sharma\nJaya Sharma\nStudent at Lovely Professional University\nStudent at Lovely Professional University\nConnect\nShow all\nYou might like\nYou might like\nPages for you\nPages for you\nGAL AeroStaff Ltd\nGAL AeroStaff Ltd\nStaffing and Recruiting\nStaffing and Recruiting\n8,823 followers\n8,823 followers\nFollow\nServiceSetu Academics\nServiceSetu Academics\nHigher Education\nHigher Education\n35,213 followers\n35,213 followers\nFollow\nShow all\nAbout\nAccessibility\nTalent Solutions\nProfessional Community Policies\nCareers\nMarketing Solutions\nPrivacy & Terms\nAd Choices\nAdvertising\nSales Solutions\nMobile\nSmall Business\nSafety Center\nQuestions?\nVisit our Help Center.\nManage your account and privacy\nGo to your Settings.\nRecommendation transparency\nLearn more about Recommended Content.\nSelect Language\n         العربية (Arabic)\n         বাংলা (Bangla)\n         Čeština (Czech)\n         Dansk (Danish)\n         Deutsch (German)\n         Ελληνικά (Greek)\n         English (English)\n         Español (Spanish)\n         فارسی (Persian)\n         Suomi (Finnish)\n         Français (French)\n         हिंदी (Hindi)\n         Magyar (Hungarian)\n         Bahasa Indonesia (Indonesian)\n         Italiano (Italian)\n         עברית (Hebrew)\n         日本語 (Japanese)\n         한국어 (Korean)\n         मराठी (Marathi)\n         Bahasa Malaysia (Malay)\n         Nederlands (Dutch)\n         Norsk (Norwegian)\n         ਪੰਜਾਬੀ (Punjabi)\n         Polski (Polish)\n         Português (Portuguese)\n         Română (Romanian)\n         Русский (Russian)\n         Svenska (Swedish)\n         తెలుగు (Telugu)\n         ภาษาไทย (Thai)\n         Tagalog (Tagalog)\n         Türkçe (Turkish)\n         Українська (Ukrainian)\n         Tiếng Việt (Vietnamese)\n         简体中文 (Chinese (Simplified))\n         正體中文 (Chinese (Traditional))\n     LinkedIn Corporation © 2025\nStatus is online\nMessaging\nYou are on the messaging overlay. Press enter to open the list of conversations.\nCompose message\nYou are on the messaging overlay. Press enter to open the list of conversations.",
  "skills_text": "0 notifications total\nnew feed updates notifications\nHome\n1\n1 new network update notification\nMy Network\nJobs\nMessaging\nNotifications\nMe\nFor Business\nTry Premium for ₹0\nAshutosh Yadav\nSDE 1 @xto10x\nMore\nFollow\nMessage\nSkills\nAll\nIndustry Knowledge\nTools & Technologies\nLaravel\nLaravel\n2 experiences at xto10x\n2 experiences at xto10x\nPHP\nPHP\n2 experiences at xto10x\n2 experiences at xto10x\nSpring Boot\nSpring Boot\n2 experiences at xto10x\n2 experiences at xto10x\nSpring Framework\nSpring Framework\n2 experiences at xto10x\n2 experiences at xto10x\nJava\nJava\n2 experiences at xto10x\n2 experiences at xto10x\nAmazon Web Services (AWS)\nAmazon Web Services (AWS)\n2 experiences at xto10x\n2 experiences at xto10x\nServerless Framework\nServerless Framework\n2 experiences at xto10x\n2 experiences at xto10x\nmongo\nmongo\nX Clone\nX Clone\nHTML5\nHTML5\nX Clone\nX Clone\nCascading Style Sheets (CSS)\nCascading Style Sheets (CSS)\nX Clone\nX Clone\nExpress.js\nExpress.js\nX Clone\nX Clone\nJSON Web Token (JWT)\nJSON Web Token (JWT)\nJavaScript\nJavaScript\nReact.js\nReact.js\nX Clone\nX Clone\nNode.js\nNode.js\nX Clone\nX Clone\nMongoDB\nMongoDB\nAfter Effects\nAfter Effects\nMore profiles for you\nMore profiles for you\nAshish Mishra\nAshish Mishra\n· 3rd+\n3rd+ degree connection\nSenior Software Engineer, Full stack developer\nSenior Software Engineer, Full stack developer\nMessage\nTejasvee Srikantan\nTejasvee Srikantan\n· 3rd+\n3rd+ degree connection\nEngineering | Walmart | xto10x | Flipkart\nEngineering | Walmart | xto10x | Flipkart\nMessage\nSagar Panwar\nSagar Panwar\n· 3rd+\n3rd+ degree connection\nbla bla bla..\nbla bla bla..\nMessage\nBhaveek Jain\nBhaveek Jain\n· 3rd+\n3rd+ degree connection\nTech @xto10x | Fullstack Developer - React(Nextjs)\nTech @xto10x | Fullstack Developer - React(Nextjs)\nMessage\nSmriti Pillai\nSmriti Pillai\n· 3rd+\n3rd+ degree connection\nSDE-1 at xto10x | Ex - Exotel \nSDE-1 at xto10x | Ex - Exotel\nMessage\nShow more\nAbout\nAccessibility\nTalent Solutions\nProfessional Community Policies\nCareers\nMarketing Solutions\nPrivacy & Terms\nAd Choices\nAdvertising\nSales Solutions\nMobile\nSmall Business\nSafety Center\nQuestions?\nVisit our Help Center.\nManage your account and privacy\nGo to your Settings.\nRecommendation transparency\nLearn more about Recommended Content.\nSelect Language\n         العربية (Arabic)\n         বাংলা (Bangla)\n         Čeština (Czech)\n         Dansk (Danish)\n         Deutsch (German)\n         Ελληνικά (Greek)\n         English (English)\n         Español (Spanish)\n         فارسی (Persian)\n         Suomi (Finnish)\n         Français (French)\n         हिंदी (Hindi)\n         Magyar (Hungarian)\n         Bahasa Indonesia (Indonesian)\n         Italiano (Italian)\n         עברית (Hebrew)\n         日本語 (Japanese)\n         한국어 (Korean)\n         मराठी (Marathi)\n         Bahasa Malaysia (Malay)\n         Nederlands (Dutch)\n         Norsk (Norwegian)\n         ਪੰਜਾਬੀ (Punjabi)\n         Polski (Polish)\n         Português (Portuguese)\n         Română (Romanian)\n         Русский (Russian)\n         Svenska (Swedish)\n         తెలుగు (Telugu)\n         ภาษาไทย (Thai)\n         Tagalog (Tagalog)\n         Türkçe (Turkish)\n         Українська (Ukrainian)\n         Tiếng Việt (Vietnamese)\n         简体中文 (Chinese (Simplified))\n         正體中文 (Chinese (Traditional))\n     LinkedIn Corporation © 2025\nStatus is online\nMessaging\nYou are on the messaging overlay. Press enter to open the list of conversations.\nCompose message\nYou are on the messaging overlay. Press enter to open the list of conversations.",
  "scraped_at": "2025-07-23 01:50:26",
  "has_skills": true,
  "cleaned_profile": {
    "name": "Ashutosh Yadav",
    "profile_url": "https://in.linkedin.com/in/ashutoshyadav18",
    "current_position": {
      "title": "SDE 1",
      "company": "xto10x",
      "location": "Bengaluru, Karnataka, India",
      "start_date": "Nov 2024",
      "end_date": "Present",
      "duration": "9 mos"
    },
    "previous_positions": [
      {
        "title": "Full stack Developer Intern",
        "company": "xto10x",
        "location": "Bengaluru, Karnataka, India",
        "start_date": "May 2024",
        "end_date": "Oct 2024",
        "duration": "6 mos"
      }
    ],
    "education": {
      "institution": "Lovely Professional University",
      "degree": "Bachelor of Technology - BTech",
      "field_of_study": null,
      "years_attended": null
    },
    "connections": "500+",
    "followers": 618,
    "skills": [
      "Java",
      "JavaScript",
      "Spring Boot",
      "React.js",
      "Amazon Web Services (AWS)",
      "Laravel",
      "PHP",
      "Spring Framework",
      "Serverless Framework",
      "mongo",
      "HTML5",
      "Cascading Style Sheets (CSS)",
      "Express.js",
      "JSON Web Token (JWT)",
      "Node.js",
      "MongoDB",
      "After Effects"
    ],
    "interests": [
      "xto10x",
      "PeopleCues"
    ]
  },
  "tokens_used": {
    "prompt_tokens": 3853,
    "completion_tokens": 360,
    "total_tokens": 4213
  }
}