{
  "url": "https://in.linkedin.com/in/pr7nce",
  "raw_text": "0 notifications total\nnew feed updates notifications\nHome\n1\n1 new network update notification\nMy Network\nJobs\nMessaging\nNotifications\nMe\nFor Business\nTry Premium for ₹0\nPraneeth Gummalla\nSDE-1 @xto10x | IIT BHU '23\nxto10x\nIndian Institute of Technology (Banaras Hindu University), Varanasi\nBengaluru, Karnataka, India Contact info\n500+ connections\nMessage\nFollow\nMore\nAbout\nAbout\nI am a skilled Professional with over 1 year of experience as a Backend Developer seeking a challenging position in an organization where I can leverage my skills and positively contribute towards the company's growth and success. Possess hands-on experience with automation tools such as Git/GitLab, Django, PostgreSQL, WebRTC. I am adept at collaborating with cross-functional teams to ensure seamless integration and communication skills and can easily adapt to any environment.\n…see more\nActivity\nActivity\n957 followers\n957 followers\nPraneeth hasn’t posted yet\nRecent posts Praneeth shares will be displayed here.\nShow all activity\nExperience\nExperience\nSDE - 1\nSDE - 1\nxto10x · Full-time\nxto10x · Full-time\nSep 2024 - Present · 11 mos\nSep 2024 to Present · 11 mos\nBengaluru, Karnataka, India\nBengaluru, Karnataka, India\nSDE\nSDE\nK12 Techno Services Pvt. Ltd. · Full-time\nK12 Techno Services Pvt. Ltd. · Full-time\nJun 2023 - Jul 2024 · 1 yr 2 mos\nJun 2023 to Jul 2024 · 1 yr 2 mos\nBengaluru, Karnataka, India\nBengaluru, Karnataka, India\nBackend Developer\nBackend Developer\nVasukam · Internship\nVasukam · Internship\nMay 2022 - Jul 2022 · 3 mos\nMay 2022 to Jul 2022 · 3 mos\nNew Delhi, Delhi, India\nNew Delhi, Delhi, India\nEducation\nEducation\nIndian Institute of Technology (Banaras Hindu University), Varanasi\nIndian Institute of Technology (Banaras Hindu University), Varanasi\n2018 - 2023\n2018 - 2023\nSkills\nSkills\nGoogle Cloud Platform (GCP)\nGoogle Cloud Platform (GCP)\nAmazon Web Services (AWS)\nAmazon Web Services (AWS)\nShow all 11 skills\nInterests\nInterests\nTop Voices\nTop Voices\nCompanies\nCompanies\nGroups\nGroups\nRaj Vikramaditya\nRaj Vikramaditya\nBuilding takeUforward(1M+ Users) | Ex - Google, Media.net, Amazon | YouTuber(800K+) | JGEC\nBuilding takeUforward(1M+ Users) | Ex - Google, Media.net, Amazon | YouTuber(800K+) | JGEC\n826,401 followers\n826,401 followers\nFollow\nAnkit Kumar\nAnkit Kumar\nCEO, Workforwin\nCEO, Workforwin\n48,964 followers\n48,964 followers\nFollow\nShow all Top Voices\nMore profiles for you\nMore profiles for you\nKushpal Yadav\nKushpal Yadav\n· 3rd+\n3rd+ degree connection\nSoftware Engineer at LiftoffLLC\nSoftware Engineer at LiftoffLLC\nMessage\nYAGYA SONI\nYAGYA SONI\n· 3rd+\n3rd+ degree connection\nGraduate of Indian Institute of Technology (Banaras Hindu University), Varanasi\nMessage\nAMIT ANAND\nAMIT ANAND\n· 3rd+\n3rd+ degree connection\nEngineering Leader | Head of Tech @ K12 | Ex-Founder | Scaled SaaS & EdTech Platforms | Ex-MaterialDepot, StanChart | 0→1 Product Innovator\nFollow\nSaikiran Krishnamurthy\nSaikiran Krishnamurthy\n· 3rd+\n3rd+ degree connection\nCo-founder & CEO, xto10x Technologies \nCo-founder & CEO, xto10x Technologies\nMessage\nSmriti Pillai\nSmriti Pillai\n· 3rd+\n3rd+ degree connection\nSDE-1 at xto10x | Ex - Exotel \nSDE-1 at xto10x | Ex - Exotel\nMessage\nShow all\nPeople you may know\nPeople you may know\nFrom Praneeth's school\nFrom Praneeth's school\nAbhishek Kumar Pandey\nAbhishek Kumar Pandey\nAttended Indian Institute of Technology (Banaras Hindu University), Varanasi || students' parliament\nConnect\nYuvraj Jain\nYuvraj Jain\nIndian Institute of Technology (Banaras Hindu University), Varanasi\nConnect\nAkshat Bhatt\nAkshat Bhatt\nCSE Undergrad @ IIT BHU | Aspiring Full-Stack & AI Enthusiast\nConnect\nParmeet Singh\nParmeet Singh\nSenior chemistry lecturer at Gravity Classes\nSenior chemistry lecturer at Gravity Classes\nConnect\nSuhani Garg\nSuhani Garg\nAttended Indian Institute of Technology (Banaras Hindu University), Varanasi\nConnect\nShow all\nYou might like\nYou might like\nPages for you\nPages for you\nSciAstra\nSciAstra\nE-Learning Providers\nE-Learning Providers\n37,200 followers\n37,200 followers\nFollow\nIndiGo (InterGlobe Aviation Ltd)\nIndiGo (InterGlobe Aviation Ltd)\nAirlines and Aviation\nAirlines and Aviation\n913,194 followers\n913,194 followers\nFollow\nShow all\nAbout\nAccessibility\nTalent Solutions\nProfessional Community Policies\nCareers\nMarketing Solutions\nPrivacy & Terms\nAd Choices\nAdvertising\nSales Solutions\nMobile\nSmall Business\nSafety Center\nQuestions?\nVisit our Help Center.\nManage your account and privacy\nGo to your Settings.\nRecommendation transparency\nLearn more about Recommended Content.\nSelect Language\n         العربية (Arabic)\n         বাংলা (Bangla)\n         Čeština (Czech)\n         Dansk (Danish)\n         Deutsch (German)\n         Ελληνικά (Greek)\n         English (English)\n         Español (Spanish)\n         فارسی (Persian)\n         Suomi (Finnish)\n         Français (French)\n         हिंदी (Hindi)\n         Magyar (Hungarian)\n         Bahasa Indonesia (Indonesian)\n         Italiano (Italian)\n         עברית (Hebrew)\n         日本語 (Japanese)\n         한국어 (Korean)\n         मराठी (Marathi)\n         Bahasa Malaysia (Malay)\n         Nederlands (Dutch)\n         Norsk (Norwegian)\n         ਪੰਜਾਬੀ (Punjabi)\n         Polski (Polish)\n         Português (Portuguese)\n         Română (Romanian)\n         Русский (Russian)\n         Svenska (Swedish)\n         తెలుగు (Telugu)\n         ภาษาไทย (Thai)\n         Tagalog (Tagalog)\n         Türkçe (Turkish)\n         Українська (Ukrainian)\n         Tiếng Việt (Vietnamese)\n         简体中文 (Chinese (Simplified))\n         正體中文 (Chinese (Traditional))\n     LinkedIn Corporation © 2025\nStatus is online\nMessaging\nYou are on the messaging overlay. Press enter to open the list of conversations.\nCompose message\nYou are on the messaging overlay. Press enter to open the list of conversations.",
  "skills_text": "0 notifications total\nnew feed updates notifications\nHome\n1\n1 new network update notification\nMy Network\nJobs\nMessaging\nNotifications\nMe\nFor Business\nTry Premium for ₹0\nPraneeth Gummalla\nSDE-1 @xto10x | IIT BHU '23\nMore\nFollow\nMessage\nSkills\nAll\nIndustry Knowledge\nTools & Technologies\nGoogle Cloud Platform (GCP)\nGoogle Cloud Platform (GCP)\nAmazon Web Services (AWS)\nAmazon Web Services (AWS)\nDjango\nDjango\nSpring Boot\nSpring Boot\nJava\nJava\nPython (Programming Language)\nPython (Programming Language)\nWeb Development\nWeb Development\nNode.js\nNode.js\nReact.js\nReact.js\nData Structures\nData Structures\nC++\nC++\nMore profiles for you\nMore profiles for you\nKushpal Yadav\nKushpal Yadav\n· 3rd+\n3rd+ degree connection\nSoftware Engineer at LiftoffLLC\nSoftware Engineer at LiftoffLLC\nMessage\nYAGYA SONI\nYAGYA SONI\n· 3rd+\n3rd+ degree connection\nGraduate of Indian Institute of Technology (Banaras Hindu University), Varanasi\nMessage\nAMIT ANAND\nAMIT ANAND\n· 3rd+\n3rd+ degree connection\nEngineering Leader | Head of Tech @ K12 | Ex-Founder | Scaled SaaS & EdTech Platforms | Ex-MaterialDepot, StanChart | 0→1 Product Innovator\nFollow\nSaikiran Krishnamurthy\nSaikiran Krishnamurthy\n· 3rd+\n3rd+ degree connection\nCo-founder & CEO, xto10x Technologies \nCo-founder & CEO, xto10x Technologies\nMessage\nSmriti Pillai\nSmriti Pillai\n· 3rd+\n3rd+ degree connection\nSDE-1 at xto10x | Ex - Exotel \nSDE-1 at xto10x | Ex - Exotel\nMessage\nShow more\nAbout\nAccessibility\nTalent Solutions\nProfessional Community Policies\nCareers\nMarketing Solutions\nPrivacy & Terms\nAd Choices\nAdvertising\nSales Solutions\nMobile\nSmall Business\nSafety Center\nQuestions?\nVisit our Help Center.\nManage your account and privacy\nGo to your Settings.\nRecommendation transparency\nLearn more about Recommended Content.\nSelect Language\n         العربية (Arabic)\n         বাংলা (Bangla)\n         Čeština (Czech)\n         Dansk (Danish)\n         Deutsch (German)\n         Ελληνικά (Greek)\n         English (English)\n         Español (Spanish)\n         فارسی (Persian)\n         Suomi (Finnish)\n         Français (French)\n         हिंदी (Hindi)\n         Magyar (Hungarian)\n         Bahasa Indonesia (Indonesian)\n         Italiano (Italian)\n         עברית (Hebrew)\n         日本語 (Japanese)\n         한국어 (Korean)\n         मराठी (Marathi)\n         Bahasa Malaysia (Malay)\n         Nederlands (Dutch)\n         Norsk (Norwegian)\n         ਪੰਜਾਬੀ (Punjabi)\n         Polski (Polish)\n         Português (Portuguese)\n         Română (Romanian)\n         Русский (Russian)\n         Svenska (Swedish)\n         తెలుగు (Telugu)\n         ภาษาไทย (Thai)\n         Tagalog (Tagalog)\n         Türkçe (Turkish)\n         Українська (Ukrainian)\n         Tiếng Việt (Vietnamese)\n         简体中文 (Chinese (Simplified))\n         正體中文 (Chinese (Traditional))\n     LinkedIn Corporation © 2025\nStatus is online\nMessaging\nYou are on the messaging overlay. Press enter to open the list of conversations.\nCompose message\nYou are on the messaging overlay. Press enter to open the list of conversations.",
  "scraped_at": "2025-07-22 21:57:18",
  "has_skills": true,
  "cleaned_profile": {
    "name": "Praneeth Gummalla",
    "profile_url": "https://in.linkedin.com/in/pr7nce",
    "current_position": {
      "title": "SDE - 1",
      "company": "xto10x",
      "location": "Bengaluru, Karnataka, India",
      "start_date": "Sep 2024",
      "end_date": "Present",
      "duration": "11 mos"
    },
    "previous_positions": [
      {
        "title": "SDE",
        "company": "K12 Techno Services Pvt. Ltd.",
        "location": "Bengaluru, Karnataka, India",
        "start_date": "Jun 2023",
        "end_date": "Jul 2024",
        "duration": "1 yr 2 mos"
      },
      {
        "title": "Backend Developer",
        "company": "Vasukam",
        "location": "New Delhi, Delhi, India",
        "start_date": "May 2022",
        "end_date": "Jul 2022",
        "duration": "3 mos"
      }
    ],
    "education": {
      "institution": "Indian Institute of Technology (Banaras Hindu University), Varanasi",
      "years_attended": "2018 - 2023"
    },
    "connections": "500+",
    "followers": 957,
    "skills": [
      "Google Cloud Platform (GCP)",
      "Amazon Web Services (AWS)",
      "Django",
      "Spring Boot",
      "Java",
      "Python (Programming Language)",
      "Web Development",
      "Node.js",
      "React.js",
      "Data Structures",
      "C++"
    ],
    "interests": [
      "Raj Vikramaditya",
      "Ankit Kumar"
    ]
  },
  "tokens_used": {
    "prompt_tokens": 2472,
    "completion_tokens": 396,
    "total_tokens": 2868
  }
}