{
  "url": "https://in.linkedin.com/in/aashishsolanky",
  "raw_text": "0 notifications total\nnew feed updates notifications\nHome\n1\n1 new network update notification\nMy Network\nJobs\nMessaging\nNotifications\nMe\nFor Business\nTry Premium for ‚Çπ0\nAashish Solanky\nHexaware | IIM Lucknow | xto10x | Cognizant | Unstop Global Rank 29 (2023)\nHexaware Technologies\nIndian Institute of Management, Lucknow\nMumbai, Maharashtra, India Contact info\n6,729 followers\n500+ connections\nFollow\nMessage\nMore\nAbout\nAbout\nüöÄ MBA From IIM Lucknow üöÄ |üéØ Master of Stakeholder Management üéØ | üí° Forte at Implementation & Process Optimization üí° | üå± Open to Growth & Product Roles üå± | Let's collaborate and transform ideas into reality! üîó\n\nIT Consultant in BFSI Presales at Hexaware, managing multi-million dollar RFI/RFP deals and driving digital transformation for clients. Previously a Software Engineer at Cognizant, I have also been a founding member in multiple startups, including my own, leading 0-to-1 execution and business growth. An MBA from IIM Lucknow and a B.Tech graduate from Tezpur University, I specialize in presales, solutioning, stakeholder management, and digital strategy. Always open to collaborations that drive innovation and impact.\n#InnovationDriven #TechTrailblazer #FutureReady\n‚Ä¶see more\nTop skills\nTop skills\nCreative Problem Solving ‚Ä¢ Team Management ‚Ä¢ Business Strategy ‚Ä¢ Market Research ‚Ä¢ Management\nCreative Problem Solving ‚Ä¢ Team Management ‚Ä¢ Business Strategy ‚Ä¢ Market Research ‚Ä¢ Management\nActivity\nActivity\n6,729 followers\n6,729 followers\nFollow\nLoaded 3 Comments posts\nAashish Solanky commented on a post ‚Ä¢ 1mo\n1mo\nSolid insights! üîê GenAI + security is the future. Loved the focus on proactive threat detection‚Äîkeen to see how this shapes real-world SecOps\nSolid insights! üîê GenAI + security is the future. Loved the focus on proactive threat detection‚Äîkeen to see how this shapes real-world SecOps\nAashish Solanky commented on a post ‚Ä¢ 2mo\n2mo\nCongratulation Kusha Agrawal\nCongratulation Kusha Agrawal\nAashish Solanky commented on a post ‚Ä¢ 2mo\n2mo\nCongratulations Ravish KT\nCongratulations Ravish KT\nShow all comments\nExperience\nExperience\nHexaware Technologies\nHexaware Technologies\nFull-time ¬∑ 1 yr 3 mos\nFull-time ¬∑ 1 yr 3 mos\nConsultant\nConsultant\nMay 2025 - Present ¬∑ 3 mos\nMay 2025 to Present ¬∑ 3 mos\nPune, Maharashtra, India\nPune, Maharashtra, India\nSenior Management Trainee\nSenior Management Trainee\nMay 2024 - May 2025 ¬∑ 1 yr 1 mo\nMay 2024 to May 2025 ¬∑ 1 yr 1 mo\nMumbai, Maharashtra, India ¬∑ On-site\nMumbai, Maharashtra, India ¬∑ On-site\nBusiness Project Management, Multiple Projects Simultaneously and +2 skills\nPlacement Systems\nPlacement Systems\nIndian Institute of Management, Lucknow ¬∑ Full-time\nIndian Institute of Management, Lucknow ¬∑ Full-time\nNov 2022 - Nov 2023 ¬∑ 1 yr 1 mo\nNov 2022 to Nov 2023 ¬∑ 1 yr 1 mo\nLucknow, Uttar Pradesh, India ¬∑ On-site\nLucknow, Uttar Pradesh, India ¬∑ On-site\nCreative Problem Solving, Quickness and +14 skills\nSummer Intern\nSummer Intern\nxto10x ¬∑ Internship\nxto10x ¬∑ Internship\nApr 2023 - Jun 2023 ¬∑ 3 mos\nApr 2023 to Jun 2023 ¬∑ 3 mos\nRemote ¬∑ Remote\nRemote ¬∑ Remote\nCreative Problem Solving, Market Research and +23 skills\nAssociate Consultant\nAssociate Consultant\nIMS Learning Resources Pvt. Ltd. ¬∑ Full-time\nIMS Learning Resources Pvt. Ltd. ¬∑ Full-time\nMar 2022 - May 2022 ¬∑ 3 mos\nMar 2022 to May 2022 ¬∑ 3 mos\nBhopal, Madhya Pradesh, India\nBhopal, Madhya Pradesh, India\nCreative Problem Solving, Market Research and +21 skills\nCognizant\nCognizant\nFull-time ¬∑ 1 yr 4 mos\nFull-time ¬∑ 1 yr 4 mos\nPune, Maharashtra, India\nPune, Maharashtra, India\nSoftware Engineer\nSoftware Engineer\nDec 2021 - Mar 2022 ¬∑ 4 mos\nDec 2021 to Mar 2022 ¬∑ 4 mos\nWorked as Application Support Engineer for a Retirement Service Client from States.\n1. Responsible for solving production bugs.\n2. Work included performing log analysis and code analysis.\n3. Trained in Java, Azure, Spring.\nCreative Problem Solving, Growth Hacking and +6 skills\nProgrammer Analyst Trainee\nProgrammer Analyst Trainee\nDec 2020 - Dec 2021 ¬∑ 1 yr 1 mo\nDec 2020 to Dec 2021 ¬∑ 1 yr 1 mo\nCreative Problem Solving, Presentations and +5 skills\nShow all 12 experiences\nEducation\nEducation\nIndian Institute of Management, Lucknow\nIndian Institute of Management, Lucknow\nMaster of Business Administration - MBA\nMaster of Business Administration - MBA\nJun 2022 - Mar 2024\nJun 2022 - Mar 2024\nConsulting, Analytics and +11 skills\nTezpur University\nTezpur University\nBachelor of Technology, Electrical, Electronics and Communications Engineering\nBachelor of Technology, Electrical, Electronics and Communications Engineering\n2016 - 2020\n2016 - 2020\nShow all 3 educations\nLicenses & certifications\nLicenses & certifications\nMicrosoft Certified Azure Fundamentals\nMicrosoft Certified Azure Fundamentals\nMicrosoft\nMicrosoft\nIssued Feb 2022\nIssued Feb 2022\nEFSET 74/100\nEFSET 74/100 \nEFSET 74/100\nefset.org\nefset.org\nIssued Sep 2021\nIssued Sep 2021\nCredential ID C2\nCredential ID C2\nShow all 3 licenses & certifications\nProjects\nProjects\nApnaPolicy\nApnaPolicy\nMar 2021 - Mar 2021\nMar 2021 - Mar 2021\nAssociated with Cognizant\nAssociated with Cognizant\nCreated Web Application using Spring Boot MVC, JPA, having admin, member, and agent as users.\nCreated Web Application using Spring Boot MVC, JPA, having admin, member, and agent as users.\nSkills\nSkills\nMultiple Projects Simultaneously\nMultiple Projects Simultaneously\nSenior Management Trainee at Hexaware Technologies\nSenior Management Trainee at Hexaware Technologies\nStrategy Alignment\nStrategy Alignment\nSenior Management Trainee at Hexaware Technologies\nSenior Management Trainee at Hexaware Technologies\nShow all 55 skills\nRecommendations\nRecommendations\nReceived\nReceived\nGiven\nGiven\nRoheet Bakare\nRoheet Bakare\nSenior Data Scientist @ Add On Support | Master of Science in Statistics\nSenior Data Scientist @ Add On Support | Master of Science in Statistics\nJanuary 3, 2021, Roheet worked with Aashish on the same team\nJanuary 3, 2021,Roheetworked withAashishon the same team\nAashish is a wonderful person to work with. We worked together for more than 1 year, very hardworking, and have also come up with innovative ideas to deal with any situation.\nAashish is a wonderful person to work with. We worked together for more than 1 year, very hardworking, and have also come up with innovative ideas to deal with any situation.\nNikhil Kumar\nNikhil Kumar\nDirector of Customer Success | Former Senior Operations Manager at Codingal (YC W21)\nDirector of Customer Success | Former Senior Operations Manager at Codingal (YC W21)\nSeptember 4, 2020, Nikhil worked with Aashish on the same team\nSeptember 4, 2020,Nikhilworked withAashishon the same team\nHard to find a professional like him, highly dedicated to his work, and very highly skilled.\nA very reliable man to have in the team, he can take responsibilities,lead a team and match critical deadlines as I have witnessed several times since the last 1 year I have been working with him..\n\n#puretalent\nHard to find a professional like him, highly dedicated to his work, and very highly skilled. A very reliable man to have in the team, he can take responsibilities,lead a team and match critical deadlines as I have witnessed several times since the last 1 year I have been working with him.. #puretalent\nLanguages\nLanguages\nEnglish\nEnglish\nProfessional working proficiency\nProfessional working proficiency\nFrench\nFrench\nElementary proficiency\nElementary proficiency\nShow all 3 languages\nInterests\nInterests\nTop Voices\nTop Voices\nCompanies\nCompanies\nGroups\nGroups\nNewsletters\nNewsletters\nSchools\nSchools\nAnkur Jhaveri\nAnkur Jhaveri\nBuilding ALT | Helping you discover high-return, non-traditional investments\nBuilding ALT | Helping you discover high-return, non-traditional investments\n48,447 followers\n48,447 followers\nFollow\nAnushree Kabra\nAnushree Kabra\nBusiness Psychologist by Education ~ Management Consultant by Profession @Accenture S&C | LinkedIn Top Voice | Passion Project- AllthingsIO\nBusiness Psychologist by Education ~ Management Consultant by Profession @Accenture S&C | LinkedIn Top Voice | Passion Project- AllthingsIO\n19,777 followers\n19,777 followers\nFollow\nShow all Top Voices\nEnglish\nFran√ßais\nMore profiles for you\nMore profiles for you\nAbhiraj Tak\nAbhiraj Tak\nAbhiraj Tak\n¬∑ 3rd+\n3rd+ degree connection\nIIM Ranchi | Hexaware | State Street | Samsung | Executive Member, Corporate Relations and Placement Committee | Member, Student Council | Ex-Infosys\nMessage\nRaja Sekhar Katta\nRaja Sekhar Katta\n¬∑ 3rd+\n3rd+ degree connection\nManager, Hexaware Technologies | MBA, DMS IIT Delhi | B.tech(CSE), IIT Jodhpur\nFollow\nSuranjana Goswami\nSuranjana Goswami\n¬∑ 3rd+\n3rd+ degree connection\nManager Global Presales @ Hexaware | Gold Medalist IIM Shillong MBA PGPEx 22-23 | IIT Kanpur | NIT Agartala | EADA BSchool Spain | Harvard Online Data Science | Ex-JIO Software Developer(R&D) Manager\nFollow\nGautham Suresh\nGautham Suresh\n¬∑ 3rd+\n3rd+ degree connection\nMarketing & Growth Hexaware Technologies | IIM Indore PGP '23 | SCTCE Trivandrum\nMessage\nVikash Singh\nVikash Singh\n¬∑ 3rd+\n3rd+ degree connection\nAssistant Manager @ Genpact | Strategy & Transformation | IIM K | BIT Mesra\nMessage\nShow all\nPeople you may know\nPeople you may know\nFrom Aashish's school\nFrom Aashish's school\nVISHNU S U\nVISHNU S U\nResearch Scholar in Agribusiness Management‚óè PhD'29 IIM Lucknow‚óè MBA'24 @ IABMI AAU Anand\nConnect\nParas Bhatt\nParas Bhatt\nIIM Lucknow'27 l B.Sc.(Hons.) Agriculture |GBPUA&T'24, Pantnagar\nConnect\nNeeraj Choudhary\nNeeraj Choudhary\nHead of Marketing at Blume Nigeria Limited\nHead of Marketing at Blume Nigeria Limited\nConnect\nGautam Singh\nGautam Singh\nSTUDENT AT CHANDRA BHANU KRISHI MAHAVIDYALAY || UNIVERSITY OF LUCKNOW||\nConnect\nSOMYA SHARMA\nSOMYA SHARMA\nSIP at Pernod Ricard India | IIM Lucknow'25 | Miranda House,DU'23 | Media Cell IIML‚Äô39\nConnect\nShow all\nYou might like\nYou might like\nPages for you\nPages for you\nDragon Aviation Capital (Singapore) Pte. Ltd.\nDragon Aviation Capital (Singapore) Pte. Ltd.\nAviation and Aerospace Component Manufacturing\nAviation and Aerospace Component Manufacturing\n49,784 followers\n49,784 followers\nFollow\nIndiGo (InterGlobe Aviation Ltd)\nIndiGo (InterGlobe Aviation Ltd)\nAirlines and Aviation\nAirlines and Aviation\n913,204 followers\n913,204 followers\nFollow\nShow all\nAbout\nAccessibility\nTalent Solutions\nProfessional Community Policies\nCareers\nMarketing Solutions\nPrivacy & Terms\nAd Choices\nAdvertising\nSales Solutions\nMobile\nSmall Business\nSafety Center\nQuestions?\nVisit our Help Center.\nManage your account and privacy\nGo to your Settings.\nRecommendation transparency\nLearn more about Recommended Content.\nSelect Language\n         ÿßŸÑÿπÿ±ÿ®Ÿäÿ© (Arabic)\n         ‡¶¨‡¶æ‡¶Ç‡¶≤‡¶æ (Bangla)\n         ƒåe≈°tina (Czech)\n         Dansk (Danish)\n         Deutsch (German)\n         ŒïŒªŒªŒ∑ŒΩŒπŒ∫Œ¨ (Greek)\n         English (English)\n         Espa√±ol (Spanish)\n         ŸÅÿßÿ±ÿ≥€å (Persian)\n         Suomi (Finnish)\n         Fran√ßais (French)\n         ‡§π‡§ø‡§Ç‡§¶‡•Ä (Hindi)\n         Magyar (Hungarian)\n         Bahasa Indonesia (Indonesian)\n         Italiano (Italian)\n         ◊¢◊ë◊®◊ô◊™ (Hebrew)\n         Êó•Êú¨Ë™û (Japanese)\n         ÌïúÍµ≠Ïñ¥ (Korean)\n         ‡§Æ‡§∞‡§æ‡§†‡•Ä (Marathi)\n         Bahasa Malaysia (Malay)\n         Nederlands (Dutch)\n         Norsk (Norwegian)\n         ‡®™‡©∞‡®ú‡®æ‡®¨‡©Ä (Punjabi)\n         Polski (Polish)\n         Portugu√™s (Portuguese)\n         Rom√¢nƒÉ (Romanian)\n         –†—É—Å—Å–∫–∏–π (Russian)\n         Svenska (Swedish)\n         ‡∞§‡±Ü‡∞≤‡±Å‡∞ó‡±Å (Telugu)\n         ‡∏†‡∏≤‡∏©‡∏≤‡πÑ‡∏ó‡∏¢ (Thai)\n         Tagalog (Tagalog)\n         T√ºrk√ße (Turkish)\n         –£–∫—Ä–∞—ó–Ω—Å—å–∫–∞ (Ukrainian)\n         Ti·∫øng Vi·ªát (Vietnamese)\n         ÁÆÄ‰Ωì‰∏≠Êñá (Chinese (Simplified))\n         Ê≠£È´î‰∏≠Êñá (Chinese (Traditional))\n     LinkedIn Corporation ¬© 2025\nStatus is online\nMessaging\nYou are on the messaging overlay. Press enter to open the list of conversations.\nCompose message\nYou are on the messaging overlay. Press enter to open the list of conversations.",
  "skills_text": "ÈÅ∏ÊìáË™ûË®Ä\n                Bahasa Indonesia (Bahasa Indonesia)\n                Bahasa Malaysia (Malay)\n                ƒåe≈°tina (Czech)\n                Dansk (Danish)\n                Deutsch (German)\n                English (English)\n                Espa√±ol (Spanish)\n                ÁπÅÈ´î‰∏≠Êñá (Chinese (Traditional))\n                Fran√ßais (French)\n                ÌïúÍµ≠Ïñ¥ (Korean)\n                Italiano (Italian)\n                ÁÆÄ‰Ωì‰∏≠Êñá (Chinese (Simplified))\n                Nederlands (Dutch)\n                Êó•Êú¨Ë™û (Japanese)\n                Norsk (Norwegian)\n                Polski (Polish)\n                Portugu√™s (Portuguese)\n                Rom√¢nƒÉ (Romanian)\n                –†—É—Å—Å–∫–∏–π (Russian)\n                Svenska (Swedish)\n                Tagalog (Tagalog)\n                ‡∏†‡∏≤‡∏©‡∏≤‡πÑ‡∏ó‡∏¢ (Thai)\n                T√ºrk√ße (Turkish)\n                ÿßŸÑÿπÿ±ÿ®Ÿäÿ© (Arabic)\n          \n             Page not found\nUh oh, we can‚Äôt seem to find the page you‚Äôre looking for. Try going back to the previous page or see our Help Center for more information\nGo to your feed\n¬© 2022 User Agreement Privacy Policy Community Guidelines Cookie Policy Copyright Policy Guest Controls",
  "scraped_at": "2025-07-22 22:01:40",
  "has_skills": true,
  "cleaned_profile": {
    "name": "Aashish Solanky",
    "profile_url": "https://in.linkedin.com/in/aashishsolanky",
    "current_position": {
      "title": "Consultant",
      "company": "Hexaware Technologies",
      "location": "Pune, Maharashtra, India",
      "start_date": "May 2025",
      "end_date": "Present",
      "duration": "3 mos"
    },
    "previous_positions": [
      {
        "title": "Senior Management Trainee",
        "company": "Hexaware Technologies",
        "location": "Mumbai, Maharashtra, India",
        "start_date": "May 2024",
        "end_date": "May 2025",
        "duration": "1 yr 1 mo"
      },
      {
        "title": "Placement Systems",
        "company": "Indian Institute of Management, Lucknow",
        "location": "Lucknow, Uttar Pradesh, India",
        "start_date": "Nov 2022",
        "end_date": "Nov 2023",
        "duration": "1 yr 1 mo"
      },
      {
        "title": "Summer Intern",
        "company": "xto10x",
        "location": "Remote",
        "start_date": "Apr 2023",
        "end_date": "Jun 2023",
        "duration": "3 mos"
      },
      {
        "title": "Associate Consultant",
        "company": "IMS Learning Resources Pvt. Ltd.",
        "location": "Bhopal, Madhya Pradesh, India",
        "start_date": "Mar 2022",
        "end_date": "May 2022",
        "duration": "3 mos"
      },
      {
        "title": "Software Engineer",
        "company": "Cognizant",
        "location": "Pune, Maharashtra, India",
        "start_date": "Dec 2021",
        "end_date": "Mar 2022",
        "duration": "4 mos"
      },
      {
        "title": "Programmer Analyst Trainee",
        "company": "Cognizant",
        "location": "Pune, Maharashtra, India",
        "start_date": "Dec 2020",
        "end_date": "Dec 2021",
        "duration": "1 yr 1 mo"
      }
    ],
    "education": [
      {
        "institution": "Indian Institute of Management, Lucknow",
        "degree": "Master of Business Administration - MBA",
        "field_of_study": "Consulting, Analytics",
        "years_attended": "Jun 2022 - Mar 2024"
      },
      {
        "institution": "Tezpur University",
        "degree": "Bachelor of Technology",
        "field_of_study": "Electrical, Electronics and Communications Engineering",
        "years_attended": "2016 - 2020"
      }
    ],
    "connections": "500+",
    "followers": "6,729",
    "skills": [
      "Creative Problem Solving",
      "Team Management",
      "Business Strategy",
      "Market Research",
      "Management",
      "Multiple Projects Simultaneously",
      "Strategy Alignment"
    ],
    "interests": [
      "Ankur Jhaveri",
      "Anushree Kabra",
      "Dragon Aviation Capital (Singapore) Pte. Ltd.",
      "IndiGo (InterGlobe Aviation Ltd)"
    ]
  },
  "tokens_used": {
    "prompt_tokens": 3390,
    "completion_tokens": 737,
    "total_tokens": 4127
  }
}