{
  "url": "https://in.linkedin.com/in/siddharth-m-2431395a",
  "raw_text": "0 notifications total\nnew feed updates notifications\nHome\n1\n1 new network update notification\nMy Network\nJobs\nMessaging\nNotifications\nMe\nFor Business\nTry Premium for â‚¹0\nSiddharth M.\nExecution Excellence at xto10x | ex-Deloitte | IIM Lucknow\nxto10x\nIndian Institute of Management, Lucknow\nBengaluru, Karnataka, India Contact info\n500+ connections\nMessage\nFollow\nMore\nAbout\nAbout\nAs an operating partner to Founders and leaders of Series A to C startups, I specialize in translating high-level strategies and AOPs into executable quarterly plans, and building accountability through OKRs, metrics, and structured reviews. I've also managed business critical projects for Founders such as entity restructuring and due diligence for fund raise. \nHave worked with a diverse set of start-ups across industries in India. \nBefore making the move to the start-up ecosystem, have worked with large corporates on building business plans and strategies, financial modelling, and business process reengineering.\nâ€¦see more\nTop skills\nTop skills\nAOP planning â€¢ Business finance â€¢ Strategic Planning â€¢ Objectives and Key Results (OKRs) â€¢ Chief of Staff\nAOP planning â€¢ Business finance â€¢ Strategic Planning â€¢ Objectives and Key Results (OKRs) â€¢ Chief of Staff\nActivity\nActivity\n1,096 followers\n1,096 followers\nPosts\nComments\nImages\nLoaded 4 Posts posts\nSiddharth M.\nSiddharth M.\n   â€¢ 3rd+\nVerified â€¢ 3rd+\nExecution Excellence at xto10x | ex-Deloitte | IIM Lucknow\nExecution Excellence at xto10x | ex-Deloitte | IIM Lucknow\n2mo â€¢ \n 2 months ago â€¢ Visible to anyone on or off LinkedIn\nğŸ¯ğŸ¬ ğ˜€ğ˜ğ—®ğ—¿ğ˜-ğ˜‚ğ—½ğ˜€. ğŸ°ğŸ¬ ğ—³ğ—¼ğ˜‚ğ—»ğ—±ğ—²ğ—¿ğ˜€. ğŸ­ ğ—°ğ—¼ğ—ºğ—ºğ—¼ğ—» ğ—½ğ—¿ğ—¼ğ—¯ğ—¹ğ—²ğ—º: ğ˜ğ—¼ğ—¼ ğ—ºğ—®ğ—»ğ˜† 'ğ˜†ğ—²ğ˜€ğ—²ğ˜€' ğ—®ğ—»ğ—± ğ—»ğ—¼ğ˜ ğ—²ğ—»ğ—¼ğ˜‚ğ—´ğ—µ ğ—³ğ—¼ğ—°ğ˜‚ğ˜€.\n\nHad a blast speaking at, IIM Bangaloreâ€™s incubation cell, last week on how OKRs can help startups stay focused.\nA room full of 40-odd early-stage founders â€” the energy was something else!\n\nWhat struck me most was how, despite working on wildly different problems â€” ğ™›ğ™§ğ™¤ğ™¢ ğ™«ğ™–ğ™˜ğ™˜ğ™ğ™£ğ™šğ™¨-ğ™–ğ™¨-ğ™–-ğ™¨ğ™šğ™§ğ™«ğ™ğ™˜ğ™š ğ™©ğ™¤ ğ™™ğ™§ğ™¤ğ™£ğ™š ğ™©ğ™šğ™˜ğ™ğ™£ğ™¤ğ™¡ğ™¤ğ™œğ™® â€” these 0â†’1 founders all faced one common challenge: ğ˜ğ—µğ—² ğ—±ğ—¶ğ—³ğ—³ğ—¶ğ—°ğ˜‚ğ—¹ğ˜ğ˜† ğ—¼ğ—³ ğ˜€ğ—®ğ˜†ğ—¶ğ—»ğ—´ ğ—»ğ—¼.\n\nIt showed up on loop during my interactions:\n- Building every feature that every customer asked for but does it solve the core problem?\n- Debating endlessly: Should we spend months polishing the product or hit the ground now and get raw customer feedback?\n- Shiny object syndrome: Jumping at every partnership opportunity while getting sidetracked from the next growth milestone.\n- Pivoting the product (or launching multiple products) after every customer conversation, making it impossible to build depth and momentum in any one area.\n\nItâ€™s not a lack of effort â€” if anything, ğ™ğ™©â€™ğ™¨ ğ™©ğ™¤ğ™¤ ğ™¢ğ™ªğ™˜ğ™ ğ™šğ™›ğ™›ğ™¤ğ™§ğ™© ğ™¨ğ™¥ğ™§ğ™šğ™–ğ™™ ğ™©ğ™¤ğ™¤ ğ™©ğ™ğ™ğ™£. In meme parlance - \"Attack 100%, damage 0%\".\n\nğ—Ÿğ—²ğ—®ğ—¿ğ—»ğ—¶ğ—»ğ—´ ğ˜ğ—¼ ğ˜€ğ—®ğ˜† ğ—»ğ—¼, ğ—³ğ—¼ğ—°ğ˜‚ğ˜€ğ—¶ğ—»ğ—´ ğ—¼ğ—» ğ˜ğ—µğ—² ğŸ¯â€“ğŸ° ğ—¼ğ˜‚ğ˜ğ—°ğ—¼ğ—ºğ—²ğ˜€ ğ˜ğ—µğ—®ğ˜ ğ˜ğ—¿ğ˜‚ğ—¹ğ˜† ğ—ºğ—®ğ˜ğ˜ğ—²ğ—¿, ğ—®ğ—»ğ—± ğ˜ğ˜‚ğ—»ğ—¶ğ—»ğ—´ ğ—¼ğ˜‚ğ˜ ğ—²ğ˜ƒğ—²ğ—¿ğ˜†ğ˜ğ—µğ—¶ğ—»ğ—´ ğ—²ğ—¹ğ˜€ğ—² ğ—®ğ˜€ ğ—»ğ—¼ğ—¶ğ˜€ğ—² ğ—°ğ—®ğ—» ğ—¯ğ—² ğ˜ğ—µğ—² ğ—±ğ—¶ğ—³ğ—³ğ—²ğ—¿ğ—²ğ—»ğ—°ğ—² ğ—¯ğ—²ğ˜ğ˜„ğ—²ğ—²ğ—» ğ—ºğ—¼ğ˜ƒğ—¶ğ—»ğ—´ ğ—³ğ—®ğ˜€ğ˜ ğ—¼ğ—¿ ğ—´ğ—²ğ˜ğ˜ğ—¶ğ—»ğ—´ ğ˜€ğ˜ğ˜‚ğ—°ğ—¸ ğ—¶ğ—» ğ—¯ğ˜‚ğ˜€ğ˜†ğ˜„ğ—¼ğ—¿ğ—¸.\n\nOKRs help you do exactly that: Pause. Prioritize. Focus.\n\nThanks to the amazing team at NSRCEL for invitingto the event, and to all the founders â€” wishing you sharp focus and big wins ahead! ğŸš€\n\nâ€¦more\nActivate to view larger image,\n1/5\nActivate to view larger image,\n135\n2 comments\nSiddharth M.\nSiddharth M.\n   â€¢ 3rd+\nVerified â€¢ 3rd+\nExecution Excellence at xto10x | ex-Deloitte | IIM Lucknow\nExecution Excellence at xto10x | ex-Deloitte | IIM Lucknow\n2yr â€¢ \n 2 years ago â€¢ Visible to anyone on or off LinkedIn\nxto10x\nxto10x\n21,215 followers\n21,215 followers\nKeen on joining startups but clueless when it comes to startup compensation? ğŸ¤”\n\nJoinand his team for a conversation on how startup benefits really work. A few things that will be covered are:\n1. Do I have to take a pay cut if I join a startup?\n2. How do ESOPs work anyway?\nIf you have these questions, find their answers during this webinar!\n\nHere's the link to register:\nâ€¦more\nActivate to view larger image,\nActivate to view larger image,\n2\nShow all posts\nExperience\nExperience\nSenior Consultant\nSenior Consultant\nxto10x\nxto10x\nJun 2021 - Present Â· 4 yrs 2 mos\nJun 2021 to Present Â· 4 yrs 2 mos\nConsultant\nConsultant\nDeloitte\nDeloitte\nJun 2018 - May 2021 Â· 3 yrs\nJun 2018 to May 2021 Â· 3 yrs\nMumbai Metropolitan Region\nMumbai Metropolitan Region\nOperations Transformation practice\nOperations Transformation practice\nSummer Intern\nSummer Intern\nEverest Group\nEverest Group\nApr 2017 - May 2017 Â· 2 mos\nApr 2017 to May 2017 Â· 2 mos\nGurugram, Haryana, India\nGurugram, Haryana, India\nMarket assessment | Cost of operations analysis | Location value proposition | Talent pool analysis | Operational risk factors\nMarket assessment | Cost of operations analysis | Location value proposition | Talent pool analysis | Operational risk factors\nInfosys\nInfosys\n2 yrs 8 mos\n2 yrs 8 mos\nAssociate Business Analyst\nAssociate Business Analyst\nJul 2015 - May 2016 Â· 11 mos\nJul 2015 to May 2016 Â· 11 mos\nPune/Pimpri-Chinchwad Area\nPune/Pimpri-Chinchwad Area\nSystems Engineer\nSystems Engineer\nOct 2013 - Jun 2015 Â· 1 yr 9 mos\nOct 2013 to Jun 2015 Â· 1 yr 9 mos\nPune\nPune\nEducation\nEducation\nIndian Institute of Management, Lucknow\nIndian Institute of Management, Lucknow\nMaster of Business Administration (MBA), Finance, Operations\nMaster of Business Administration (MBA), Finance, Operations\n2016 - 2018\n2016 - 2018\nActivities and societies: Business case competitions:\nNational winner, Strategia (Growth strategy case) | Two-time national finalist, XLRI (Operation strategy cases) | \nCampus runner up: RPG (M&A case) | EXL Analytics (Data analytics) | Nestle (Digital strategy for customer acquisition) |\n\nCommunities and responsibilities:\nCore member, Literary Club |\nHostel Representative |\nMember, Placement Support\nCFA Institute\nCFA Institute\nCFA Institute\nChartered Financial Analyst - Level 1 (cleared)\nChartered Financial Analyst - Level 1 (cleared)\nShow all 5 educations\nLicenses & certifications\nLicenses & certifications\nCFA - Level 1\nCFA - Level 1\nCFA Institute\nCFA Institute\nFRM Level 2\nFRM Level 2\nFRM Level 2\nGARP FRM Program\nGARP FRM Program\nShow all 4 licenses & certifications\nSkills\nSkills\nChief of Staff\nChief of Staff\nAOP planning\nAOP planning\nShow all 17 skills\nInterests\nInterests\nTop Voices\nTop Voices\nCompanies\nCompanies\nGroups\nGroups\nNewsletters\nNewsletters\nSchools\nSchools\nAnudeep Naik\nAnudeep Naik\nBusiness strategy, P&L owner, Sales & Ops | Edtech SME | LEAD School | KPMG | IIM B | NTPC | IIT R\nBusiness strategy, P&L owner, Sales & Ops | Edtech SME | LEAD School | KPMG | IIM B | NTPC | IIT R\n22,300 followers\n22,300 followers\nFollow\nRadhika Gupta\nRadhika Gupta\nMD & CEO, Edelweiss Mutual Fund | Author, Limitless and Mango Millionaire | Young Global Leader @ WEF | Shark Tank India\nMD & CEO, Edelweiss Mutual Fund | Author, Limitless and Mango Millionaire | Young Global Leader @ WEF | Shark Tank India\n787,378 followers\n787,378 followers\nFollow\nShow all Top Voices\nCauses\nCauses\nAnimal Welfare â€¢ Education â€¢ Environment â€¢ Health â€¢ Human Rights â€¢ Politics â€¢ Social Services\nAnimal Welfare â€¢ Education â€¢ Environment â€¢ Health â€¢ Human Rights â€¢ Politics â€¢ Social Services\nMore profiles for you\nMore profiles for you\nSrayon Datta\nSrayon Datta\nÂ· 3rd+\n3rd+ degree connection\nAll things TA!\nAll things TA!\nMessage\nNeeraj Aggarwal\nNeeraj Aggarwal\nÂ· 3rd+\n3rd+ degree connection\nCo-founder at xto10x | GM at Cure.fit | Vice President, Operations at Flipkart\nConnect\nSaikiran Krishnamurthy\nSaikiran Krishnamurthy\nÂ· 3rd+\n3rd+ degree connection\nCo-founder & CEO, xto10x Technologies \nCo-founder & CEO, xto10x Technologies\nConnect\nPawan Raghuveer\nPawan Raghuveer\nPawan Raghuveer\nÂ· 3rd+\n3rd+ degree connection\nOperations Excellence at xto10x\nOperations Excellence at xto10x\nConnect\nGaurav Choudhary\nGaurav Choudhary\nÂ· 3rd+\n3rd+ degree connection\nProduct Leader @ xto10x | Ex Myntra | Ex OLA | IIT Kanpur\nProduct Leader @ xto10x | Ex Myntra | Ex OLA | IIT Kanpur\nFollow\nShow all\nPeople you may know\nPeople you may know\nFrom Siddharth's school\nFrom Siddharth's school\nVISHNU S U\nVISHNU S U\nResearch Scholar in Agribusiness Managementâ— PhD'29 IIM Lucknowâ— MBA'24 @ IABMI AAU Anand\nConnect\nParas Bhatt\nParas Bhatt\nIIM Lucknow'27 l B.Sc.(Hons.) Agriculture |GBPUA&T'24, Pantnagar\nConnect\nKrishna Khandelwal\nKrishna Khandelwal\nIIM Lucknow (2025-27) | Physics Wallah | Nation with Namo | Sauce.VC | GOAT Brand Labs | D2C Ecommerce | Alpino Healthfoods\nConnect\nGautam Singh\nGautam Singh\nSTUDENT AT CHANDRA BHANU KRISHI MAHAVIDYALAY || UNIVERSITY OF LUCKNOW||\nConnect\nSOMYA SHARMA\nSOMYA SHARMA\nSIP at Pernod Ricard India | IIM Lucknow'25 | Miranda House,DU'23 | Media Cell IIMLâ€™39\nConnect\nShow all\nYou might like\nYou might like\nPages for you\nPages for you\nGlobal Airline Jobs\nGlobal Airline Jobs\nStaffing and Recruiting\nStaffing and Recruiting\n20,055 followers\n20,055 followers\nFollow\nIndian Aviation Career\nIndian Aviation Career\nAirlines and Aviation\nAirlines and Aviation\n57,388 followers\n57,388 followers\nFollow\nShow all\nAbout\nAccessibility\nTalent Solutions\nProfessional Community Policies\nCareers\nMarketing Solutions\nPrivacy & Terms\nAd Choices\nAdvertising\nSales Solutions\nMobile\nSmall Business\nSafety Center\nQuestions?\nVisit our Help Center.\nManage your account and privacy\nGo to your Settings.\nRecommendation transparency\nLearn more about Recommended Content.\nSelect Language\n         Ø§Ù„Ø¹Ø±Ø¨ÙŠØ© (Arabic)\n         à¦¬à¦¾à¦‚à¦²à¦¾ (Bangla)\n         ÄŒeÅ¡tina (Czech)\n         Dansk (Danish)\n         Deutsch (German)\n         Î•Î»Î»Î·Î½Î¹ÎºÎ¬ (Greek)\n         English (English)\n         EspaÃ±ol (Spanish)\n         ÙØ§Ø±Ø³ÛŒ (Persian)\n         Suomi (Finnish)\n         FranÃ§ais (French)\n         à¤¹à¤¿à¤‚à¤¦à¥€ (Hindi)\n         Magyar (Hungarian)\n         Bahasa Indonesia (Indonesian)\n         Italiano (Italian)\n         ×¢×‘×¨×™×ª (Hebrew)\n         æ—¥æœ¬èª (Japanese)\n         í•œêµ­ì–´ (Korean)\n         à¤®à¤°à¤¾à¤ à¥€ (Marathi)\n         Bahasa Malaysia (Malay)\n         Nederlands (Dutch)\n         Norsk (Norwegian)\n         à¨ªà©°à¨œà¨¾à¨¬à©€ (Punjabi)\n         Polski (Polish)\n         PortuguÃªs (Portuguese)\n         RomÃ¢nÄƒ (Romanian)\n         Ğ ÑƒÑÑĞºĞ¸Ğ¹ (Russian)\n         Svenska (Swedish)\n         à°¤à±†à°²à±à°—à± (Telugu)\n         à¸ à¸²à¸©à¸²à¹„à¸—à¸¢ (Thai)\n         Tagalog (Tagalog)\n         TÃ¼rkÃ§e (Turkish)\n         Ğ£ĞºÑ€Ğ°Ñ—Ğ½ÑÑŒĞºĞ° (Ukrainian)\n         Tiáº¿ng Viá»‡t (Vietnamese)\n         ç®€ä½“ä¸­æ–‡ (Chinese (Simplified))\n         æ­£é«”ä¸­æ–‡ (Chinese (Traditional))\n     LinkedIn Corporation Â© 2025\nStatus is online\nMessaging\nYou are on the messaging overlay. Press enter to open the list of conversations.\nCompose message\nYou are on the messaging overlay. Press enter to open the list of conversations.",
  "skills_text": "0 notifications total\nnew feed updates notifications\nHome\n1\n1 new network update notification\nMy Network\nJobs\nMessaging\nNotifications\nMe\nFor Business\nTry Premium for â‚¹0\nSiddharth M.\nExecution Excellence at xto10x | ex-Deloitte | IIM Lucknow\nMore\nFollow\nMessage\nSkills\nAll\nIndustry Knowledge\nTools & Technologies\nInterpersonal Skills\nChief of Staff\nChief of Staff\nAOP planning\nAOP planning\nBusiness finance\nBusiness finance\nStrategic Planning\nStrategic Planning\nBusiness Strategy\nBusiness Strategy\nObjectives and Key Results (OKRs)\nObjectives and Key Results (OKRs)\nBusiness Process Improvement\nBusiness Process Improvement\nProduct Management\nProduct Management\nMarket Assessments\nMarket Assessments\nEquity Research\nEquity Research\nMicrosoft Office\nMicrosoft Office\nMicrosoft Word\nMicrosoft Word\nMicrosoft Excel\nMicrosoft Excel\nMicrosoft PowerPoint\nMicrosoft PowerPoint\nTeamwork\nTeamwork\nData Analytics\nData Analytics\nDCF Valuation\nDCF Valuation\nMore profiles for you\nMore profiles for you\nSrayon Datta\nSrayon Datta\nÂ· 3rd+\n3rd+ degree connection\nAll things TA!\nAll things TA!\nMessage\nNeeraj Aggarwal\nNeeraj Aggarwal\nÂ· 3rd+\n3rd+ degree connection\nCo-founder at xto10x | GM at Cure.fit | Vice President, Operations at Flipkart\nConnect\nSaikiran Krishnamurthy\nSaikiran Krishnamurthy\nÂ· 3rd+\n3rd+ degree connection\nCo-founder & CEO, xto10x Technologies \nCo-founder & CEO, xto10x Technologies\nConnect\nPawan Raghuveer\nPawan Raghuveer\nPawan Raghuveer\nÂ· 3rd+\n3rd+ degree connection\nOperations Excellence at xto10x\nOperations Excellence at xto10x\nConnect\nGaurav Choudhary\nGaurav Choudhary\nÂ· 3rd+\n3rd+ degree connection\nProduct Leader @ xto10x | Ex Myntra | Ex OLA | IIT Kanpur\nProduct Leader @ xto10x | Ex Myntra | Ex OLA | IIT Kanpur\nFollow\nShow more\nAbout\nAccessibility\nTalent Solutions\nProfessional Community Policies\nCareers\nMarketing Solutions\nPrivacy & Terms\nAd Choices\nAdvertising\nSales Solutions\nMobile\nSmall Business\nSafety Center\nQuestions?\nVisit our Help Center.\nManage your account and privacy\nGo to your Settings.\nRecommendation transparency\nLearn more about Recommended Content.\nSelect Language\n         Ø§Ù„Ø¹Ø±Ø¨ÙŠØ© (Arabic)\n         à¦¬à¦¾à¦‚à¦²à¦¾ (Bangla)\n         ÄŒeÅ¡tina (Czech)\n         Dansk (Danish)\n         Deutsch (German)\n         Î•Î»Î»Î·Î½Î¹ÎºÎ¬ (Greek)\n         English (English)\n         EspaÃ±ol (Spanish)\n         ÙØ§Ø±Ø³ÛŒ (Persian)\n         Suomi (Finnish)\n         FranÃ§ais (French)\n         à¤¹à¤¿à¤‚à¤¦à¥€ (Hindi)\n         Magyar (Hungarian)\n         Bahasa Indonesia (Indonesian)\n         Italiano (Italian)\n         ×¢×‘×¨×™×ª (Hebrew)\n         æ—¥æœ¬èª (Japanese)\n         í•œêµ­ì–´ (Korean)\n         à¤®à¤°à¤¾à¤ à¥€ (Marathi)\n         Bahasa Malaysia (Malay)\n         Nederlands (Dutch)\n         Norsk (Norwegian)\n         à¨ªà©°à¨œà¨¾à¨¬à©€ (Punjabi)\n         Polski (Polish)\n         PortuguÃªs (Portuguese)\n         RomÃ¢nÄƒ (Romanian)\n         Ğ ÑƒÑÑĞºĞ¸Ğ¹ (Russian)\n         Svenska (Swedish)\n         à°¤à±†à°²à±à°—à± (Telugu)\n         à¸ à¸²à¸©à¸²à¹„à¸—à¸¢ (Thai)\n         Tagalog (Tagalog)\n         TÃ¼rkÃ§e (Turkish)\n         Ğ£ĞºÑ€Ğ°Ñ—Ğ½ÑÑŒĞºĞ° (Ukrainian)\n         Tiáº¿ng Viá»‡t (Vietnamese)\n         ç®€ä½“ä¸­æ–‡ (Chinese (Simplified))\n         æ­£é«”ä¸­æ–‡ (Chinese (Traditional))\n     LinkedIn Corporation Â© 2025\nStatus is online\nMessaging\nYou are on the messaging overlay. Press enter to open the list of conversations.\nCompose message\nYou are on the messaging overlay. Press enter to open the list of conversations.",
  "scraped_at": "2025-07-22 23:13:41",
  "has_skills": true,
  "cleaned_profile": {
    "name": "Siddharth M.",
    "profile_url": "https://in.linkedin.com/in/siddharth-m-2431395a",
    "current_position": {
      "title": "Senior Consultant",
      "company": "xto10x",
      "location": "Bengaluru, Karnataka, India",
      "start_date": "Jun 2021",
      "end_date": "Present",
      "duration": "4 yrs 2 mos"
    },
    "previous_positions": [
      {
        "title": "Consultant",
        "company": "Deloitte",
        "location": "Mumbai Metropolitan Region",
        "start_date": "Jun 2018",
        "end_date": "May 2021",
        "duration": "3 yrs"
      },
      {
        "title": "Summer Intern",
        "company": "Everest Group",
        "location": "Gurugram, Haryana, India",
        "start_date": "Apr 2017",
        "end_date": "May 2017",
        "duration": "2 mos"
      },
      {
        "title": "Associate Business Analyst",
        "company": "Infosys",
        "location": "Pune/Pimpri-Chinchwad Area",
        "start_date": "Jul 2015",
        "end_date": "May 2016",
        "duration": "11 mos"
      },
      {
        "title": "Systems Engineer",
        "company": "Infosys",
        "location": "Pune",
        "start_date": "Oct 2013",
        "end_date": "Jun 2015",
        "duration": "1 yr 9 mos"
      }
    ],
    "education": [
      {
        "institution": "Indian Institute of Management, Lucknow",
        "degree": "Master of Business Administration (MBA)",
        "field_of_study": "Finance, Operations",
        "years_attended": "2016 - 2018"
      },
      {
        "institution": "CFA Institute",
        "degree": "Chartered Financial Analyst - Level 1 (cleared)",
        "field_of_study": null,
        "years_attended": null
      }
    ],
    "connections": "500+",
    "followers": 1096,
    "skills": [
      "Chief of Staff",
      "AOP planning",
      "Business finance",
      "Strategic Planning",
      "Business Strategy",
      "Objectives and Key Results (OKRs)",
      "Business Process Improvement",
      "Product Management",
      "Market Assessments",
      "Equity Research",
      "Microsoft Office",
      "Microsoft Word",
      "Microsoft Excel",
      "Microsoft PowerPoint",
      "Teamwork",
      "Data Analytics",
      "DCF Valuation"
    ],
    "interests": [
      "Anudeep Naik",
      "Radhika Gupta"
    ]
  },
  "tokens_used": {
    "prompt_tokens": 4413,
    "completion_tokens": 622,
    "total_tokens": 5035
  }
}