{
  "url": "https://in.linkedin.com/in/tanmay-a-aa4338108",
  "raw_text": "0 notifications total\nnew feed updates notifications\nHome\n1\n1 new network update notification\nMy Network\nJobs\nMessaging\nNotifications\nMe\nFor Business\nTry Premium for â‚¹0\nTanmay A.\nHe/Him\nProduct @ xto10x | Helping startups scale smarter\nxto10x\nBengaluru, Karnataka, India Contact info\n500+ connections\nMessage\nFollow\nMore\nAbout\nAbout\nAt xto10x, I craft products and scale startups, helping founders drive sharper execution and faster growth. I love solving messy, real-world problems â€” and building systems that create 10x outcomes at scale.\nAt xto10x, I craft products and scale startups, helping founders drive sharper execution and faster growth. I love solving messy, real-world problems â€” and building systems that create 10x outcomes at scale.\nServices\nServices\nResearch Skills â€¢ Administrative Assistance â€¢ Brand Marketing â€¢ Content Marketing â€¢ Marketing Strategy â€¢ Business Consulting â€¢ Brand Consulting â€¢ Management Consulting â€¢ Marketing Consulting â€¢ Pricing Strategy\nResearch Skills â€¢ Administrative Assistance â€¢ Brand Marketing â€¢ Content Marketing â€¢ Marketing Strategy â€¢ Business Consulting â€¢ Brand Consulting â€¢ Management Consulting â€¢ Marketing Consulting â€¢ Pricing Strategy\nRequest services\nShow all services\nActivity\nActivity\n1,084 followers\n1,084 followers\nPosts\nComments\nVideos\nImages\nLoaded 9 Posts posts\nTanmay A. reposted this\nPeopleCues\nPeopleCues\n735 followers\n735 followers\n1w â€¢ Edited â€¢ \n 1 week ago â€¢ Edited â€¢ Visible to anyone on or off LinkedIn\nğ—™ğ—¿ğ˜‚ğ˜€ğ˜ğ—¿ğ—®ğ˜ğ—²ğ—± ğ˜„ğ—¶ğ˜ğ—µ ğ—šğ—²ğ—»ğ—²ğ—¿ğ—¶ğ—° ğ—™ğ—²ğ—²ğ—±ğ—¯ğ—®ğ—°ğ—¸? ğ—¥ğ—²ğ—®ğ—± ğ—¼ğ—» ğ˜ğ—¼ ğ˜€ğ—²ğ—² ğ—µğ—¼ğ˜„ ğ˜ğ—¼ ğ—³ğ—¶ğ˜… ğ—¶ğ˜\n\n\n\nFor too long, performance reviews have left true potential untapped, buried in ambiguity. We've allowed feedback that \"sounds good, but says littleâ€.\n\nğŸ” 60% of managers struggle with specificity.\nğŸš« 89% of peers skip key examples.\n\nIt's time for a revolution in feedback.\n\nğ—£ğ—¿ğ—²ğ˜€ğ—²ğ—»ğ˜ğ—¶ğ—»ğ—´ ğ—–ğ—¹ğ—¼ : ğ—¬ğ—¼ğ˜‚ğ—¿ ğ—”ğ—œ-ğ—½ğ—¼ğ˜„ğ—²ğ—¿ğ—²ğ—± ğ—³ğ—²ğ—²ğ—±ğ—¯ğ—®ğ—°ğ—¸ ğ—°ğ—¼ğ—®ğ—°ğ—µ\n\nClo acts as your co-pilot, transforming performance reviews into powerful, actionable intelligence. Seamlessly integrating the SBI framework, Clo ensures feedback is hyper-precise, highly meaningful, and directly fuels measurable transformation.\n\nThe result? ğŸ­ğŸ¬ğ—« ğ—ºğ—¼ğ—¿ğ—² ğ—®ğ—°ğ˜ğ—¶ğ—¼ğ—»ğ—®ğ—¯ğ—¹ğ—² ğ—³ğ—²ğ—²ğ—±ğ—¯ğ—®ğ—°ğ—¸, ğ—®ğ—°ğ—°ğ—²ğ—¹ğ—²ğ—¿ğ—®ğ˜ğ—¶ğ—»ğ—´ ğ—´ğ—¿ğ—¼ğ˜„ğ˜ğ—µ, ğ—¯ğ—¼ğ—¼ğ˜€ğ˜ğ—¶ğ—»ğ—´ ğ—²ğ—»ğ—´ğ—®ğ—´ğ—²ğ—ºğ—²ğ—»ğ˜, ğ—®ğ—»ğ—± ğ˜€ğ—²ğ—°ğ˜‚ğ—¿ğ—¶ğ—»ğ—´ ğ—½ğ—²ğ—®ğ—¸ ğ—½ğ—²ğ—¿ğ—³ğ—¼ğ—¿ğ—ºğ—®ğ—»ğ—°ğ—²\n\nğŸ”— This isn't just an upgrade, it's a paradigm shift. Ready to transform your feedback culture? Talk to us now!\n\n\n\nâ€¦more\nClo - AI powered feedback coach â€¢ 6 pages\n1/6\n180\n7 reposts\nTanmay A. reposted this\nPeopleCues\nPeopleCues\n735 followers\n735 followers\n1w â€¢ Edited â€¢ \n 1 week ago â€¢ Edited â€¢ Visible to anyone on or off LinkedIn\nğ—™ğ—¿ğ˜‚ğ˜€ğ˜ğ—¿ğ—®ğ˜ğ—²ğ—± ğ˜„ğ—¶ğ˜ğ—µ ğ—šğ—²ğ—»ğ—²ğ—¿ğ—¶ğ—° ğ—™ğ—²ğ—²ğ—±ğ—¯ğ—®ğ—°ğ—¸? ğ—¥ğ—²ğ—®ğ—± ğ—¼ğ—» ğ˜ğ—¼ ğ˜€ğ—²ğ—² ğ—µğ—¼ğ˜„ ğ˜ğ—¼ ğ—³ğ—¶ğ˜… ğ—¶ğ˜\n\n\n\nFor too long, performance reviews have left true potential untapped, buried in ambiguity. We've allowed feedback that \"sounds good, but says littleâ€.\n\nğŸ” 60% of managers struggle with specificity.\nğŸš« 89% of peers skip key examples.\n\nIt's time for a revolution in feedback.\n\nğ—£ğ—¿ğ—²ğ˜€ğ—²ğ—»ğ˜ğ—¶ğ—»ğ—´ ğ—–ğ—¹ğ—¼ : ğ—¬ğ—¼ğ˜‚ğ—¿ ğ—”ğ—œ-ğ—½ğ—¼ğ˜„ğ—²ğ—¿ğ—²ğ—± ğ—³ğ—²ğ—²ğ—±ğ—¯ğ—®ğ—°ğ—¸ ğ—°ğ—¼ğ—®ğ—°ğ—µ\n\nClo acts as your co-pilot, transforming performance reviews into powerful, actionable intelligence. Seamlessly integrating the SBI framework, Clo ensures feedback is hyper-precise, highly meaningful, and directly fuels measurable transformation.\n\nThe result? ğŸ­ğŸ¬ğ—« ğ—ºğ—¼ğ—¿ğ—² ğ—®ğ—°ğ˜ğ—¶ğ—¼ğ—»ğ—®ğ—¯ğ—¹ğ—² ğ—³ğ—²ğ—²ğ—±ğ—¯ğ—®ğ—°ğ—¸, ğ—®ğ—°ğ—°ğ—²ğ—¹ğ—²ğ—¿ğ—®ğ˜ğ—¶ğ—»ğ—´ ğ—´ğ—¿ğ—¼ğ˜„ğ˜ğ—µ, ğ—¯ğ—¼ğ—¼ğ˜€ğ˜ğ—¶ğ—»ğ—´ ğ—²ğ—»ğ—´ğ—®ğ—´ğ—²ğ—ºğ—²ğ—»ğ˜, ğ—®ğ—»ğ—± ğ˜€ğ—²ğ—°ğ˜‚ğ—¿ğ—¶ğ—»ğ—´ ğ—½ğ—²ğ—®ğ—¸ ğ—½ğ—²ğ—¿ğ—³ğ—¼ğ—¿ğ—ºğ—®ğ—»ğ—°ğ—²\n\nğŸ”— This isn't just an upgrade, it's a paradigm shift. Ready to transform your feedback culture? Talk to us now!\n\n\n\nâ€¦more\nClo - AI powered feedback coach â€¢ 6 pages\n1/6\n180\n7 reposts\nShow all posts\nExperience\nExperience\nxto10x\nxto10x\nFull-time Â· 3 yrs 2 mos\nFull-time Â· 3 yrs 2 mos\nBengaluru, Karnataka, India\nBengaluru, Karnataka, India\nSenior Product Manager\nSenior Product Manager\nJan 2024 - Present Â· 1 yr 7 mos\nJan 2024 to Present Â· 1 yr 7 mos\nHybrid\nHybrid\n- Leading product strategy for the PeopleCues product and work in scaling the product after the newly established PMF\n- Lead the Customer Success team to achieve high product adoption and deliver unmatched client\nexperience\n- Use floor-pillar-roof model to construct intelligent business models for portfolio companies\nProduct Development, Project Management and +4 skills\nxto10x\nxto10x\nProduct Manager / Business Consultant \nProduct Manager / Business Consultant\nJun 2022 - Dec 2023 Â· 1 yr 7 mos\nJun 2022 to Dec 2023 Â· 1 yr 7 mos\n- Use Greek temple model to construct intelligent business models for portfolio companies \n- Enabling Business Research through quantitative and qualitative engines\n- Strategising BAU/company aligned okrs and managing performance appraisal design for rapidly growing startups\n- Contribute effectively in the architecture of the company's saas product called PeopleCues\n- Engage, uphold and nurture clients from diverse industry verticals (Typical Client persona: Cofounder/Head of Strategy/Head of Human Resources)\nLeadership, Research and +2 skills\nPixis\nPixis\nFull-time Â· 1 yr 8 mos\nFull-time Â· 1 yr 8 mos\nEntrepreneur In Residence\nEntrepreneur In Residence\nDec 2021 - Jun 2022 Â· 7 mos\nDec 2021 to Jun 2022 Â· 7 mos\nCalifornia, United States\nCalifornia, United States\n- Quantitative Market Research in diversified industry verticals\n- Collecting data on consumers, competitors, and market place and consolidating information into actionable items, reports, and presentations\n- Interfacing with Clients to understand problem statements , objectives , target Groups and markets\nâ€¢ Use of AI Dashboard and statistical tools to estimate the Right sample\nâ€¢ Understanding business objectives and designing surveys to discover prospective/present customersâ€™ preferences\nâ€¢ Compiling and analysing statistical data using modern and traditional methods\n- Use of jira, salesforce, Microsoft Excel/Power Point, Tableau, MySQl(Basic), PartnerStack, SalesHive, G-suite\nâ€¢ Interpret large amounts of data\nâ€¢ Using of data collection methods (polls, panel integrations, surveys, etc)\nKey impact of this role:\nâ€¢ Directly worked with (CX Suite)Strategic Teams at global companies like Amazon, OnePlus, Aids Healthcare Foundation, Equitable, Canon, Bajaj Auto, HDFC Bank, ICICI Bank and many more. Helped solve problem statements and challenges that ultimately address the key brand strategies and make an impact in the market\nâ€¢ Handling day to day product strategy, coordinating between diversified teams , juggling between multiple roles and handling a team of not less than 10 people\nOther role:\nâ€¢ Coming up with price sheet calculators\nâ€¢ Affiliate Marketing\nâ€¢ Handling Partner CRMs\nâ€¢ Business Strategy for Expansion in USA - strategic Advisors\nâ€¢ Hiring Interns and full time employees for the company\nâ€¢ Working on product development and product strategy\nâ€¢ Working on building the SaaS platform for the company ( wireframe , templates , product positioning, etc)\nLeadership, Research and +1 skill\nBusiness Analyst\nBusiness Analyst\nApr 2021 - Dec 2021 Â· 9 mos\nApr 2021 to Dec 2021 Â· 9 mos\nSan Francisco, California, United States\nSan Francisco, California, United States\nLeadership, Research and +1 skill\nMarket Research Manager\nMarket Research Manager\nNov 2020 - Mar 2021 Â· 5 mos\nNov 2020 to Mar 2021 Â· 5 mos\nBengaluru, Karnataka, India\nBengaluru, Karnataka, India\nStatistical Data Analysis\nAccount Manager - Growth\nAccount Manager - Growth\nMyGate Â· Full-time\nMyGate Â· Full-time\nAug 2020 - Oct 2020 Â· 3 mos\nAug 2020 to Oct 2020 Â· 3 mos\nMumbai, Maharashtra, India\nMumbai, Maharashtra, India\nCultural Representative\nCultural Representative\nChrist University, Bangalore Â· Full-time\nChrist University, Bangalore Â· Full-time\nAug 2018 - Mar 2020 Â· 1 yr 8 mos\nAug 2018 to Mar 2020 Â· 1 yr 8 mos\nLeadership\nFinancial Modelling and Project Appraisal\nFinancial Modelling and Project Appraisal\nAditya Birla Finance Limited Â· Internship\nAditya Birla Finance Limited Â· Internship\nApr 2019 - May 2019 Â· 2 mos\nApr 2019 to May 2019 Â· 2 mos\nMumbai Metropolitan Region\nMumbai Metropolitan Region\nProject and Structured Finance - Financial Appraisal and Project Modeling \nProject and Structured Finance - Financial Appraisal and Project Modeling\nShow all 10 experiences\nEducation\nEducation\nChrist University, Bangalore\nChrist University, Bangalore\nBachelor of Business Administration - BBA, Business Administration and Management, General\nBachelor of Business Administration - BBA, Business Administration and Management, General\n2017 - 2020\n2017 - 2020\nLeadership\nTRINITY COLLEGE OF EDUCATION logo\nTRINITY COLLEGE OF EDUCATION\nTRINITY COLLEGE OF EDUCATION\n Grade 6 Electronic Keyboard, Music Performance, General\n Grade 6 Electronic Keyboard, Music Performance, General\n2015 - 2017\n2015 - 2017\nGrade: Merit\nGrade: Merit\nShow all 3 educations\nLicenses & certifications\nLicenses & certifications\nAnalysis for Managerial Decision-Making\nAnalysis for Managerial Decision-Making\nRice University\nRice University\nIssued Nov 2024\nIssued Nov 2024\nCredential ID VR4C8SK6O8O2\nCredential ID VR4C8SK6O8O2\nShow credential\nCoursera VR4C8SK6O8O2.pdf\nCoursera VR4C8SK6O8O2.pdf\nFundamentals of Quantitative Modeling\nFundamentals of Quantitative Modeling\nThe Wharton School\nThe Wharton School\nIssued Nov 2024\nIssued Nov 2024\nCredential ID FG5HX4CMYO04\nCredential ID FG5HX4CMYO04\nShow credential\nCoursera FG5HX4CMYO04.pdf\nCoursera FG5HX4CMYO04.pdf\nShow all 3 licenses & certifications\nVolunteering\nVolunteering\nStudent Volunteer\nStudent Volunteer\nStudent Volunteer\nE cure NGO\nE cure NGO\nJan 2018 Â· 1 mo\nJan 2018 Â· 1 mo\nEnvironment\nEnvironment\nSkills\nSkills\nProduct Development\nProduct Development\nSenior Product Manager at xto10x\nSenior Product Manager at xto10x\nEndorsed by 1 person in the last 6 months\nEndorsed by 1 person in the last 6 months\n1 endorsement\n1 endorsement\nProject Management\nProject Management\nSenior Product Manager at xto10x\nSenior Product Manager at xto10x\nEndorsed by 1 person in the last 6 months\nEndorsed by 1 person in the last 6 months\n1 endorsement\n1 endorsement\nShow all 29 skills\nInterests\nInterests\nTop Voices\nTop Voices\nCompanies\nCompanies\nGroups\nGroups\nNewsletters\nNewsletters\nSchools\nSchools\nPallavi Pareek\nPallavi Pareek\nHelping Companies Build Safe, Compliant & Harassment-Free Workplaces\nHelping Companies Build Safe, Compliant & Harassment-Free Workplaces\n32,135 followers\n32,135 followers\nFollow\nSatya Nadella\nSatya Nadella\nChairman and CEO at Microsoft\nChairman and CEO at Microsoft\n11,462,277 followers\n11,462,277 followers\nFollow\nShow all Top Voices\nMore profiles for you\nMore profiles for you\nSrinivaas Kartikk Takillapati\nSrinivaas Kartikk Takillapati\nÂ· 3rd+\n3rd+ degree connection\nInvestor Partnerships, Content\nInvestor Partnerships, Content\nFollow\nSaikiran Krishnamurthy\nSaikiran Krishnamurthy\nÂ· 3rd+\n3rd+ degree connection\nCo-founder & CEO, xto10x Technologies \nCo-founder & CEO, xto10x Technologies\nConnect\nGaurav Choudhary\nGaurav Choudhary\nÂ· 3rd+\n3rd+ degree connection\nProduct Leader @ xto10x | Ex Myntra | Ex OLA | IIT Kanpur\nProduct Leader @ xto10x | Ex Myntra | Ex OLA | IIT Kanpur\nFollow\nShivam Gupta\nShivam Gupta\nÂ· 3rd+\n3rd+ degree connection\nStudent at Indian Institute of Technology, Kanpur\nStudent at Indian Institute of Technology, Kanpur\nConnect\nPawan Raghuveer\nPawan Raghuveer\nPawan Raghuveer\nÂ· 3rd+\n3rd+ degree connection\nOperations Excellence at xto10x\nOperations Excellence at xto10x\nConnect\nShow all\nPeople you may know\nPeople you may know\nFrom Tanmay's school\nFrom Tanmay's school\nHridika Chandak\nHridika Chandak\nStudent at Christ University, Bangalore\nStudent at Christ University, Bangalore\nConnect\nHarshitha N A\nHarshitha N A\nArchitecture Student at Christ University\nArchitecture Student at Christ University\nConnect\nVivaan Ahuja\nVivaan Ahuja\nBBA 26 @CHRIST UNIVERSITY|EX-INTERN 'OYO'| EXPLORING BUSINESS\nConnect\nAditya Mhaisdhune\nAditya Mhaisdhune\nAditya Mhaisdhune\nStudent at Christ University, Bangalore\nStudent at Christ University, Bangalore\nConnect\nKavya K Prabhu\nKavya K Prabhu\nStudent at Christ University, Bangalore\nStudent at Christ University, Bangalore\nConnect\nShow all\nYou might like\nYou might like\nPages for you\nPages for you\nServiceSetu Academics\nServiceSetu Academics\nHigher Education\nHigher Education\n35,211 followers\n35,211 followers\nFollow\nFirstClub\nFirstClub\nTechnology, Information and Internet\nTechnology, Information and Internet\n9,511 followers\n9,511 followers\nFollow\nShow all\nAbout\nAccessibility\nTalent Solutions\nProfessional Community Policies\nCareers\nMarketing Solutions\nPrivacy & Terms\nAd Choices\nAdvertising\nSales Solutions\nMobile\nSmall Business\nSafety Center\nQuestions?\nVisit our Help Center.\nManage your account and privacy\nGo to your Settings.\nRecommendation transparency\nLearn more about Recommended Content.\nSelect Language\n         Ø§Ù„Ø¹Ø±Ø¨ÙŠØ© (Arabic)\n         à¦¬à¦¾à¦‚à¦²à¦¾ (Bangla)\n         ÄŒeÅ¡tina (Czech)\n         Dansk (Danish)\n         Deutsch (German)\n         Î•Î»Î»Î·Î½Î¹ÎºÎ¬ (Greek)\n         English (English)\n         EspaÃ±ol (Spanish)\n         ÙØ§Ø±Ø³ÛŒ (Persian)\n         Suomi (Finnish)\n         FranÃ§ais (French)\n         à¤¹à¤¿à¤‚à¤¦à¥€ (Hindi)\n         Magyar (Hungarian)\n         Bahasa Indonesia (Indonesian)\n         Italiano (Italian)\n         ×¢×‘×¨×™×ª (Hebrew)\n         æ—¥æœ¬èª (Japanese)\n         í•œêµ­ì–´ (Korean)\n         à¤®à¤°à¤¾à¤ à¥€ (Marathi)\n         Bahasa Malaysia (Malay)\n         Nederlands (Dutch)\n         Norsk (Norwegian)\n         à¨ªà©°à¨œà¨¾à¨¬à©€ (Punjabi)\n         Polski (Polish)\n         PortuguÃªs (Portuguese)\n         RomÃ¢nÄƒ (Romanian)\n         Ğ ÑƒÑÑĞºĞ¸Ğ¹ (Russian)\n         Svenska (Swedish)\n         à°¤à±†à°²à±à°—à± (Telugu)\n         à¸ à¸²à¸©à¸²à¹„à¸—à¸¢ (Thai)\n         Tagalog (Tagalog)\n         TÃ¼rkÃ§e (Turkish)\n         Ğ£ĞºÑ€Ğ°Ñ—Ğ½ÑÑŒĞºĞ° (Ukrainian)\n         Tiáº¿ng Viá»‡t (Vietnamese)\n         ç®€ä½“ä¸­æ–‡ (Chinese (Simplified))\n         æ­£é«”ä¸­æ–‡ (Chinese (Traditional))\n     LinkedIn Corporation Â© 2025\nStatus is online\nMessaging\nYou are on the messaging overlay. Press enter to open the list of conversations.\nCompose message\nYou are on the messaging overlay. Press enter to open the list of conversations.",
  "skills_text": "0 notifications total\nnew feed updates notifications\nHome\n1\n1 new network update notification\nMy Network\nJobs\nMessaging\nNotifications\nMe\nFor Business\nTry Premium for â‚¹0\nStatus is online\nTanmay A.\n(He/Him)\nProduct @ xto10x | Helping startups scale smarter\nMore\nFollow\nMessage\nSkills\nAll\nIndustry Knowledge\nTools & Technologies\nInterpersonal Skills\nProduct Development\nProduct Development\nSenior Product Manager at xto10x\nSenior Product Manager at xto10x\nEndorsed by 1 person in the last 6 months\nEndorsed by 1 person in the last 6 months\n1 endorsement\n1 endorsement\nProject Management\nProject Management\nSenior Product Manager at xto10x\nSenior Product Manager at xto10x\nEndorsed by 1 person in the last 6 months\nEndorsed by 1 person in the last 6 months\n1 endorsement\n1 endorsement\nCustomer Relationship Management (CRM)\nCustomer Relationship Management (CRM)\nSenior Product Manager at xto10x\nSenior Product Manager at xto10x\nEndorsed by 1 person in the last 6 months\nEndorsed by 1 person in the last 6 months\n1 endorsement\n1 endorsement\nCross-functional Coordination\nCross-functional Coordination\nSenior Product Manager at xto10x\nSenior Product Manager at xto10x\n1 endorsement\n1 endorsement\nGo-to-Market Strategy\nGo-to-Market Strategy\nSenior Product Manager at xto10x\nSenior Product Manager at xto10x\nFigma (Software)\nFigma (Software)\nMySQL\nMySQL\nStatistical Data Analysis\nStatistical Data Analysis\n4 experiences across xto10x and 1 other company\n4 experiences across xto10x and 1 other company\nAnalytical Skills\nAnalytical Skills\nProduct Manager / Business Consultant at xto10x\nProduct Manager / Business Consultant at xto10x\nCustomer Service\nCustomer Service\n2 endorsements\n2 endorsements\nMicrosoft Office\nMicrosoft Office\n2 endorsements\n2 endorsements\nMicrosoft Excel\nMicrosoft Excel\nPassed LinkedIn Skill Assessment\nPassed LinkedIn Skill Assessment\nLeadership\nLeadership\n5 experiences across xto10x and 3 other companies\n5 experiences across xto10x and 3 other companies\n2 educational experiences at Christ University, Bangalore\n2 educational experiences at Christ University, Bangalore\nStudent Volunteer\nStudent Volunteer\nMicrosoft Word\nMicrosoft Word\nManagement\nManagement\nPublic Speaking\nPublic Speaking\nResearch\nResearch\n3 experiences across xto10x and 1 other company\n3 experiences across xto10x and 1 other company\nSocial Media\nSocial Media\nTeam Leadership\nTeam Leadership\nSenior Product Manager at xto10x\nSenior Product Manager at xto10x\nJava\nJava\nR studio\nR studio\nSPSS\nSPSS\nPianist\nPianist\ncorporate strategy \ncorporate strategy\nMarketing\nMarketing\nFinancial Modeling\nFinancial Modeling\nfinancial appraisal \nfinancial appraisal\n10xGoals\n10xGoals\nMicrosoft PowerPoint\nMicrosoft PowerPoint\nPassed LinkedIn Skill Assessment\nPassed LinkedIn Skill Assessment\nMore profiles for you\nMore profiles for you\nSrinivaas Kartikk Takillapati\nSrinivaas Kartikk Takillapati\nÂ· 3rd+\n3rd+ degree connection\nInvestor Partnerships, Content\nInvestor Partnerships, Content\nFollow\nSaikiran Krishnamurthy\nSaikiran Krishnamurthy\nÂ· 3rd+\n3rd+ degree connection\nCo-founder & CEO, xto10x Technologies \nCo-founder & CEO, xto10x Technologies\nConnect\nGaurav Choudhary\nGaurav Choudhary\nÂ· 3rd+\n3rd+ degree connection\nProduct Leader @ xto10x | Ex Myntra | Ex OLA | IIT Kanpur\nProduct Leader @ xto10x | Ex Myntra | Ex OLA | IIT Kanpur\nFollow\nShivam Gupta\nShivam Gupta\nÂ· 3rd+\n3rd+ degree connection\nStudent at Indian Institute of Technology, Kanpur\nStudent at Indian Institute of Technology, Kanpur\nConnect\nPawan Raghuveer\nPawan Raghuveer\nPawan Raghuveer\nÂ· 3rd+\n3rd+ degree connection\nOperations Excellence at xto10x\nOperations Excellence at xto10x\nConnect\nShow more\nAbout\nAccessibility\nTalent Solutions\nProfessional Community Policies\nCareers\nMarketing Solutions\nPrivacy & Terms\nAd Choices\nAdvertising\nSales Solutions\nMobile\nSmall Business\nSafety Center\nQuestions?\nVisit our Help Center.\nManage your account and privacy\nGo to your Settings.\nRecommendation transparency\nLearn more about Recommended Content.\nSelect Language\n         Ø§Ù„Ø¹Ø±Ø¨ÙŠØ© (Arabic)\n         à¦¬à¦¾à¦‚à¦²à¦¾ (Bangla)\n         ÄŒeÅ¡tina (Czech)\n         Dansk (Danish)\n         Deutsch (German)\n         Î•Î»Î»Î·Î½Î¹ÎºÎ¬ (Greek)\n         English (English)\n         EspaÃ±ol (Spanish)\n         ÙØ§Ø±Ø³ÛŒ (Persian)\n         Suomi (Finnish)\n         FranÃ§ais (French)\n         à¤¹à¤¿à¤‚à¤¦à¥€ (Hindi)\n         Magyar (Hungarian)\n         Bahasa Indonesia (Indonesian)\n         Italiano (Italian)\n         ×¢×‘×¨×™×ª (Hebrew)\n         æ—¥æœ¬èª (Japanese)\n         í•œêµ­ì–´ (Korean)\n         à¤®à¤°à¤¾à¤ à¥€ (Marathi)\n         Bahasa Malaysia (Malay)\n         Nederlands (Dutch)\n         Norsk (Norwegian)\n         à¨ªà©°à¨œà¨¾à¨¬à©€ (Punjabi)\n         Polski (Polish)\n         PortuguÃªs (Portuguese)\n         RomÃ¢nÄƒ (Romanian)\n         Ğ ÑƒÑÑĞºĞ¸Ğ¹ (Russian)\n         Svenska (Swedish)\n         à°¤à±†à°²à±à°—à± (Telugu)\n         à¸ à¸²à¸©à¸²à¹„à¸—à¸¢ (Thai)\n         Tagalog (Tagalog)\n         TÃ¼rkÃ§e (Turkish)\n         Ğ£ĞºÑ€Ğ°Ñ—Ğ½ÑÑŒĞºĞ° (Ukrainian)\n         Tiáº¿ng Viá»‡t (Vietnamese)\n         ç®€ä½“ä¸­æ–‡ (Chinese (Simplified))\n         æ­£é«”ä¸­æ–‡ (Chinese (Traditional))\n     LinkedIn Corporation Â© 2025\nStatus is online\nMessaging\nYou are on the messaging overlay. Press enter to open the list of conversations.\nCompose message\nYou are on the messaging overlay. Press enter to open the list of conversations.",
  "scraped_at": "2025-07-23 00:30:34",
  "has_skills": true,
  "cleaned_profile": {
    "name": "Tanmay A.",
    "pronouns": "He/Him",
    "profile_url": "https://in.linkedin.com/in/tanmay-a-aa4338108",
    "current_position": {
      "title": "Senior Product Manager",
      "company": "xto10x",
      "location": "Bengaluru, Karnataka, India",
      "start_date": "Jan 2024",
      "end_date": "Present",
      "duration": "1 yr 7 mos"
    },
    "previous_positions": [
      {
        "title": "Product Manager / Business Consultant",
        "company": "xto10x",
        "location": "Bengaluru, Karnataka, India",
        "start_date": "Jun 2022",
        "end_date": "Dec 2023",
        "duration": "1 yr 7 mos"
      },
      {
        "title": "Entrepreneur In Residence",
        "company": "Pixis",
        "location": "California, United States",
        "start_date": "Dec 2021",
        "end_date": "Jun 2022",
        "duration": "7 mos"
      },
      {
        "title": "Business Analyst",
        "company": "Pixis",
        "location": "San Francisco, California, United States",
        "start_date": "Apr 2021",
        "end_date": "Dec 2021",
        "duration": "9 mos"
      },
      {
        "title": "Market Research Manager",
        "company": "Pixis",
        "location": "Bengaluru, Karnataka, India",
        "start_date": "Nov 2020",
        "end_date": "Mar 2021",
        "duration": "5 mos"
      },
      {
        "title": "Account Manager - Growth",
        "company": "MyGate",
        "location": "Mumbai, Maharashtra, India",
        "start_date": "Aug 2020",
        "end_date": "Oct 2020",
        "duration": "3 mos"
      },
      {
        "title": "Cultural Representative",
        "company": "Christ University, Bangalore",
        "location": "Bengaluru, Karnataka, India",
        "start_date": "Aug 2018",
        "end_date": "Mar 2020",
        "duration": "1 yr 8 mos"
      },
      {
        "title": "Financial Modelling and Project Appraisal",
        "company": "Aditya Birla Finance Limited",
        "location": "Mumbai Metropolitan Region",
        "start_date": "Apr 2019",
        "end_date": "May 2019",
        "duration": "2 mos"
      }
    ],
    "education": [
      {
        "institution": "Christ University, Bangalore",
        "degree": "Bachelor of Business Administration - BBA",
        "field_of_study": "Business Administration and Management, General",
        "years_attended": "2017 - 2020"
      },
      {
        "institution": "TRINITY COLLEGE OF EDUCATION",
        "degree": "Grade 6 Electronic Keyboard",
        "field_of_study": "Music Performance, General",
        "years_attended": "2015 - 2017",
        "grade": "Merit"
      }
    ],
    "connections": "500+",
    "followers": 1084,
    "skills": [
      "Product Development",
      "Project Management",
      "Customer Relationship Management (CRM)",
      "Cross-functional Coordination",
      "Go-to-Market Strategy",
      "Figma (Software)",
      "MySQL",
      "Statistical Data Analysis",
      "Analytical Skills",
      "Customer Service",
      "Microsoft Office",
      "Microsoft Excel",
      "Leadership",
      "Microsoft Word",
      "Management",
      "Public Speaking",
      "Research",
      "Social Media",
      "Team Leadership",
      "Java",
      "R studio",
      "SPSS",
      "Pianist",
      "Corporate Strategy",
      "Marketing",
      "Financial Modeling",
      "Financial Appraisal",
      "10xGoals",
      "Microsoft PowerPoint"
    ],
    "interests": [
      "Pallavi Pareek",
      "Satya Nadella"
    ]
  },
  "tokens_used": {
    "prompt_tokens": 5514,
    "completion_tokens": 916,
    "total_tokens": 6430
  }
}