{
  "url": "https://in.linkedin.com/in/varun-malik-165129103",
  "raw_text": "0 notifications total\nnew feed updates notifications\nHome\n1\n1 new network update notification\nMy Network\nJobs\nMessaging\nNotifications\nMe\nFor Business\nTry Premium for ‚Çπ0\nVarun Malik\nBuilding xto10x | ex-KPMG | XLRI\nxto10x\nXLRI Jamshedpur\nDelhi, India Contact info\n500+ connections\nMessage\nFollow\nMore\nAbout\nAbout\nA management consultant with close to 4 years of professional experience focusing on aligning people experience and optimizing performance against organizational goals and objectives, thereby facilitating excellence in strategy. Designed and implemented bespoke, data-driven strategic development initiatives across industries including financial services, edtech, media & entertainment, oil, and gas, renewable energy, and chemicals. \n\nKey focus areas:\n- Organization Design\n- M&A Due Diligence/HR audit\n- Competency Modeling\n- Total Rewards\n- HR analytics\n- Future Job Landscaping\n- SAP ERP Implementation\n‚Ä¶see more\nActivity\nActivity\n2,350 followers\n2,350 followers\nPosts\nComments\nDocuments\nLoaded 9 Posts posts\nVarun Malik\nVarun Malik\n ‚Ä¢ 3rd+\n3rd+\nBuilding xto10x | ex-KPMG | XLRI\nBuilding xto10x | ex-KPMG | XLRI\n5h ‚Ä¢ \n 5 hours ago ‚Ä¢ Visible to anyone on or off LinkedIn\nWe‚Äôre Hiring: People Excellence Consultant - Rewards @ xto10x\n\nIf you‚Äôre passionate about solving high-leverage rewards problems for startups from compensation benchmarking and incentive design to ESOP/RSU structuring, we‚Äôd love to talk.\n\nYou‚Äôll work closely with founders, CXOs, and a deeply committed team on real, high-impact org-building problems.\n\nWhile Total Rewards will be your core focus, you‚Äôll also get exposure to areas like org design, performance management, and broader HR transformation.\n\nRole Details:\nüìç Location: Bangalore (Hybrid - 2 days/week in office)\nüéì Background: Open to recent post-MBAs (2022-2024); startup or consulting experience is a plus\nüí∞ Compensation: Competitive mix of cash + ESOPs\n\nInterested?\nSend your resume + LinkedIn profile to&\n\n‚Ä¶more\nJob Description ‚Ä¢ 3 pages\n1/3\n27\n3 comments\n2 reposts\nVarun Malik reposted this\nRahul Mathur\nRahul Mathur\n   ‚Ä¢ 3rd+\nInfluencer ‚Ä¢ 3rd+\nPre-Seed Investor @DeVC || Prev: Founder @Verak (acq. by ID)\nPre-Seed Investor @DeVC || Prev: Founder @Verak (acq. by ID)\nVisit my website\n1mo ‚Ä¢ \n 1 month ago ‚Ä¢ Visible to anyone on or off LinkedIn\nA year after Binny Bansal sold his $1bn stake in Flipkart in 2018, he began laying the foundations for his next venture: a ‚ÄúMcKinsey for Startups‚Äù ‚§µÔ∏è\n\nAt an event in Bangalore last year, Binny explained his motivations for setting up xto10x ‚Üí ‚ÄúInstead of making a thousand mistakes, if we can help other startups make a hundred or even a few hundred, that would be worth it.‚Äù ‚Üí succinct yet powerful.\n\nBinny partnered with Saikiran who worked at Flipkart and was a Senior Partner @ McKinsey for 15 years prior; Sai is a co-founder of the firm along with Neeraj Aggarwal (ex VP at Flipkart)\n\n3 years after founding, the firm was profitable. And, on 9th Feb ‚Äò22, Binny topped the company up with $25M in funding (from his own pocket). We don‚Äôt have latest data on company performance, since it is SG domiciled, but FY23 was ~$14M in revenue & profitable.\n\nxto10x combines the traditional ‚ÄòMcKinsey model‚Äô i.e. consulting (70% of revenue) with a ‚Äòbuilders approach‚Äô i.e. product / software led engagements (30% of revenue)\n\n‚ÄúPeopleCues‚Äù is their software platform, priced at ~$8 per seat per month, which comprises\n\n(a) OKR management\n(b) Performance management\n(c) Culture & Employee NPS (eNPS)\n\nIn addition to the software, they offer consulting services like:\n(1) Coaching ‚Üí Pre-IPO coaching & founder coaching\n(2) Strategy ‚Üí Org Design, Leadership hiring etc\n(3) Hands-on ‚Üí Growth engine design & implementation\n\nüí°Very similar to McKinsey & its MBB peers, xto10x focuses on having small teams working deeply with large clients (200+ names including CRED, Groww, Razorpay, Meesho etc). Btw, many people don‚Äôt know that McKinsey also has a LOT of software which it sells to clients (topic for another post) - so the two firms are quite similar!\n\nWhat makes xto10x unique is that alongside consulting fees, it sometimes take an equity stake in companies it works with ‚Üí per TRACXN, it has equity in ~35 companies (mostly at the Series B stage). HENCE, it has real skin in the game üí™\n\n‚û°Ô∏èThe goal ofis clear from the name itself ‚Üí to help founders on the X to 10X journey. As their website says: ‚ÄúScaling is hard. We make it easier.‚Äù This is an interesting n::1 business!\n\n‚Ä¶more\n537\n26 comments\n10 reposts\nShow all posts\nExperience\nExperience\nPeople Excellence Consultant\nPeople Excellence Consultant\nxto10x ¬∑ Full-time\nxto10x ¬∑ Full-time\nFeb 2023 - Present ¬∑ 2 yrs 6 mos\nFeb 2023 to Present ¬∑ 2 yrs 6 mos\nDelhi, India ¬∑ Remote\nDelhi, India ¬∑ Remote\nRewards (ESOPS), Performance Management, Management Development Program and Organization Design\nRewards (ESOPS), Performance Management, Management Development Program and Organization Design\nEmployee Stock Ownership Plan (ESOP)\nKPMG India\nKPMG India\nFull-time ¬∑ 2 yrs 7 mos\nFull-time ¬∑ 2 yrs 7 mos\nSenior Consultant, People and Change Advisory\nSenior Consultant, People and Change Advisory\nApr 2022 - Feb 2023 ¬∑ 11 mos\nApr 2022 to Feb 2023 ¬∑ 11 mos\nGurugram, Haryana, India ¬∑ Hybrid\nGurugram, Haryana, India ¬∑ Hybrid\n- Completed 6 projects worth 3+cr across diverse HR capabilities like Competency Modelling, Leadership Coaching, Talent Assessment, Organization Design, M&A Due Diligence (HR), and Compensation & Benefits\n\n- Secured business worth 12+ Cr by selling projects in HR capabilities across diverse industries\nHR Consulting, Organizational Design and +2 skills\nManagement Consultant, People & Change Transformation\nManagement Consultant, People & Change Transformation\nAug 2020 - Apr 2022 ¬∑ 1 yr 9 mos\nAug 2020 to Apr 2022 ¬∑ 1 yr 9 mos\nMumbai, Maharashtra, India\nMumbai, Maharashtra, India\nSummer Intern\nSummer Intern\nAB InBev India\nAB InBev India\nApr 2019 - May 2019 ¬∑ 2 mos\nApr 2019 to May 2019 ¬∑ 2 mos\nBengaluru, Karnataka, India\nBengaluru, Karnataka, India\n- Helped solve the high attrition problem (>15%) at ABI by developing an attrition prediction model (predictive analytics) for 340 employees by running binary logistic regression on > 15 data points in SPSS\n\n- Designed a talent dashboard on Microsoft Power BI to track 50 HR metrics for 1522 employees\n\n- Designed talent interventions for specific situations in which HR metrics went below set thresholds\nData Analytics, HR Analytics and +2 skills\nAssistant System Engineer\nAssistant System Engineer\nTata Consultancy Services\nTata Consultancy Services\nOct 2016 - May 2018 ¬∑ 1 yr 8 mos\nOct 2016 to May 2018 ¬∑ 1 yr 8 mos\nGandhinagar, Gujarat\nGandhinagar, Gujarat\n- Implemented SAP HANA for a global logistics firm by configuring the system, developing the objects (Adobe forms, reports, and data objects) in SAP ABAP, and rolling out the project in 49 countries\n\n- Interacted with process team of 4 SAP Modules: HR, SD, FICO, and MM to meet technical requirements\nSAP ERP and Microsoft Excel\nEducation\nEducation\nXLRI Jamshedpur\nXLRI Jamshedpur\nPGDHRM, Human Resources Management and Services\nPGDHRM, Human Resources Management and Services\n2018 - 2020\n2018 - 2020\nActivities and societies: \nCRISP : Placement Preparation Committee\nTo prepare the Senior and the Junior batch for their Finals and SIPs and conduct a systematic process of CV Verification\nJamia Millia Islamia\nJamia Millia Islamia\nBachelor of Technology - BTech, Electrical and Electronics Engineering\nBachelor of Technology - BTech, Electrical and Electronics Engineering\n2012 - 2016\n2012 - 2016\nLicenses & certifications\nLicenses & certifications\nWriting a Business Case\nWriting a Business Case\nLinkedIn\nLinkedIn\nIssued Jun 2020\nIssued Jun 2020\nShow credential\nSkills\nSkills\nEmployee Stock Ownership Plan (ESOP)\nEmployee Stock Ownership Plan (ESOP)\nPeople Excellence Consultant at xto10x\nPeople Excellence Consultant at xto10x\nCompetency Framework Design\nCompetency Framework Design\nSenior Consultant, People and Change Advisory at KPMG India\nSenior Consultant, People and Change Advisory at KPMG India\nShow all 28 skills\nInterests\nInterests\nTop Voices\nTop Voices\nCompanies\nCompanies\nGroups\nGroups\nNewsletters\nNewsletters\nSchools\nSchools\nAdam Grant\nAdam Grant\nOrganizational psychologist at Wharton, #1 NYT bestselling author of HIDDEN POTENTIAL and THINK AGAIN, and host of the TED podcasts WorkLife and Re:Thinking\nOrganizational psychologist at Wharton, #1 NYT bestselling author of HIDDEN POTENTIAL and THINK AGAIN, and host of the TED podcasts WorkLife and Re:Thinking\n5,535,912 followers\n5,535,912 followers\nFollow\nJeff Weiner\nJeff Weiner\nExecutive Chairman at LinkedIn / Founding Partner Next Play Ventures\nExecutive Chairman at LinkedIn / Founding Partner Next Play Ventures\n10,404,005 followers\n10,404,005 followers\nFollow\nShow all Top Voices\nMore profiles for you\nMore profiles for you\nSaikiran Krishnamurthy\nSaikiran Krishnamurthy\n¬∑ 3rd+\n3rd+ degree connection\nCo-founder & CEO, xto10x Technologies \nCo-founder & CEO, xto10x Technologies\nConnect\nSrayon Datta\nSrayon Datta\n¬∑ 3rd+\n3rd+ degree connection\nAll things TA!\nAll things TA!\nMessage\nPraveen Nair\nPraveen Nair\n¬∑ 3rd+\n3rd+ degree connection\nBuilding 10x Talent - Hiring Practice\nBuilding 10x Talent - Hiring Practice\nFollow\nPawan Raghuveer\nPawan Raghuveer\nPawan Raghuveer\n¬∑ 3rd+\n3rd+ degree connection\nOperations Excellence at xto10x\nOperations Excellence at xto10x\nConnect\nNeeraj Aggarwal\nNeeraj Aggarwal\n¬∑ 3rd+\n3rd+ degree connection\nCo-founder at xto10x | GM at Cure.fit | Vice President, Operations at Flipkart\nConnect\nShow all\nPeople you may know\nPeople you may know\nFrom Varun's school\nFrom Varun's school\nShreya Talwar\nShreya Talwar\nStudent at XLRI Jamshedpur \nStudent at XLRI Jamshedpur\nConnect\nShubhankar Joshi\nShubhankar Joshi\nXLRI '26 PGDM (BM) | NSUT '24\nXLRI '26 PGDM (BM) | NSUT '24\nConnect\nBhamini Bachhas\nBhamini Bachhas\nXLRI JSR HRM‚Äô27 | Ex-InterGlobe | DU‚Äô23 | President @Enactus ARSD 2022-23 |\nConnect\nAman Kumar Pathak\nAman Kumar Pathak\nAman Kumar Pathak\nXLRI'26 - PGDM BM | CBS'23 - BMS(Finance)\nXLRI'26 - PGDM BM | CBS'23 - BMS(Finance)\nConnect\nOmkar Mutha\nOmkar Mutha\nDefence at Indian Air Force\nDefence at Indian Air Force\nConnect\nShow all\nYou might like\nYou might like\nPages for you\nPages for you\nAcademic Careers - Engineering Faculty jobs\nAcademic Careers - Engineering Faculty jobs\nEducation\nEducation\n11,593 followers\n11,593 followers\nFollow\nGlobal Airline Jobs\nGlobal Airline Jobs\nStaffing and Recruiting\nStaffing and Recruiting\n20,092 followers\n20,092 followers\nFollow\nShow all\nAbout\nAccessibility\nTalent Solutions\nProfessional Community Policies\nCareers\nMarketing Solutions\nPrivacy & Terms\nAd Choices\nAdvertising\nSales Solutions\nMobile\nSmall Business\nSafety Center\nQuestions?\nVisit our Help Center.\nManage your account and privacy\nGo to your Settings.\nRecommendation transparency\nLearn more about Recommended Content.\nSelect Language\n         ÿßŸÑÿπÿ±ÿ®Ÿäÿ© (Arabic)\n         ‡¶¨‡¶æ‡¶Ç‡¶≤‡¶æ (Bangla)\n         ƒåe≈°tina (Czech)\n         Dansk (Danish)\n         Deutsch (German)\n         ŒïŒªŒªŒ∑ŒΩŒπŒ∫Œ¨ (Greek)\n         English (English)\n         Espa√±ol (Spanish)\n         ŸÅÿßÿ±ÿ≥€å (Persian)\n         Suomi (Finnish)\n         Fran√ßais (French)\n         ‡§π‡§ø‡§Ç‡§¶‡•Ä (Hindi)\n         Magyar (Hungarian)\n         Bahasa Indonesia (Indonesian)\n         Italiano (Italian)\n         ◊¢◊ë◊®◊ô◊™ (Hebrew)\n         Êó•Êú¨Ë™û (Japanese)\n         ÌïúÍµ≠Ïñ¥ (Korean)\n         ‡§Æ‡§∞‡§æ‡§†‡•Ä (Marathi)\n         Bahasa Malaysia (Malay)\n         Nederlands (Dutch)\n         Norsk (Norwegian)\n         ‡®™‡©∞‡®ú‡®æ‡®¨‡©Ä (Punjabi)\n         Polski (Polish)\n         Portugu√™s (Portuguese)\n         Rom√¢nƒÉ (Romanian)\n         –†—É—Å—Å–∫–∏–π (Russian)\n         Svenska (Swedish)\n         ‡∞§‡±Ü‡∞≤‡±Å‡∞ó‡±Å (Telugu)\n         ‡∏†‡∏≤‡∏©‡∏≤‡πÑ‡∏ó‡∏¢ (Thai)\n         Tagalog (Tagalog)\n         T√ºrk√ße (Turkish)\n         –£–∫—Ä–∞—ó–Ω—Å—å–∫–∞ (Ukrainian)\n         Ti·∫øng Vi·ªát (Vietnamese)\n         ÁÆÄ‰Ωì‰∏≠Êñá (Chinese (Simplified))\n         Ê≠£È´î‰∏≠Êñá (Chinese (Traditional))\n     LinkedIn Corporation ¬© 2025\nStatus is online\nMessaging\nYou are on the messaging overlay. Press enter to open the list of conversations.\nCompose message\nYou are on the messaging overlay. Press enter to open the list of conversations.",
  "skills_text": "ÈÅ∏ÊìáË™ûË®Ä\n                Bahasa Indonesia (Bahasa Indonesia)\n                Bahasa Malaysia (Malay)\n                ƒåe≈°tina (Czech)\n                Dansk (Danish)\n                Deutsch (German)\n                English (English)\n                Espa√±ol (Spanish)\n                ÁπÅÈ´î‰∏≠Êñá (Chinese (Traditional))\n                Fran√ßais (French)\n                ÌïúÍµ≠Ïñ¥ (Korean)\n                Italiano (Italian)\n                ÁÆÄ‰Ωì‰∏≠Êñá (Chinese (Simplified))\n                Nederlands (Dutch)\n                Êó•Êú¨Ë™û (Japanese)\n                Norsk (Norwegian)\n                Polski (Polish)\n                Portugu√™s (Portuguese)\n                Rom√¢nƒÉ (Romanian)\n                –†—É—Å—Å–∫–∏–π (Russian)\n                Svenska (Swedish)\n                Tagalog (Tagalog)\n                ‡∏†‡∏≤‡∏©‡∏≤‡πÑ‡∏ó‡∏¢ (Thai)\n                T√ºrk√ße (Turkish)\n                ÿßŸÑÿπÿ±ÿ®Ÿäÿ© (Arabic)\n          \n             Page not found\nUh oh, we can‚Äôt seem to find the page you‚Äôre looking for. Try going back to the previous page or see our Help Center for more information\nGo to your feed\n¬© 2022 User Agreement Privacy Policy Community Guidelines Cookie Policy Copyright Policy Guest Controls",
  "scraped_at": "2025-07-23 00:31:04",
  "has_skills": true,
  "cleaned_profile": {
    "name": "Varun Malik",
    "profile_url": "https://in.linkedin.com/in/varun-malik-165129103",
    "current_position": {
      "title": "People Excellence Consultant",
      "company": "xto10x",
      "location": "Delhi, India",
      "start_date": "Feb 2023",
      "end_date": "Present",
      "duration": "2 yrs 6 mos"
    },
    "previous_positions": [
      {
        "title": "Senior Consultant, People and Change Advisory",
        "company": "KPMG India",
        "location": "Gurugram, Haryana, India",
        "start_date": "Apr 2022",
        "end_date": "Feb 2023",
        "duration": "11 mos"
      },
      {
        "title": "Management Consultant, People & Change Transformation",
        "company": "KPMG India",
        "location": "Mumbai, Maharashtra, India",
        "start_date": "Aug 2020",
        "end_date": "Apr 2022",
        "duration": "1 yr 9 mos"
      },
      {
        "title": "Summer Intern",
        "company": "AB InBev India",
        "location": "Bengaluru, Karnataka, India",
        "start_date": "Apr 2019",
        "end_date": "May 2019",
        "duration": "2 mos"
      },
      {
        "title": "Assistant System Engineer",
        "company": "Tata Consultancy Services",
        "location": "Gandhinagar, Gujarat",
        "start_date": "Oct 2016",
        "end_date": "May 2018",
        "duration": "1 yr 8 mos"
      }
    ],
    "education": [
      {
        "institution": "XLRI Jamshedpur",
        "degree": "PGDHRM",
        "field_of_study": "Human Resources Management and Services",
        "years_attended": "2018 - 2020"
      },
      {
        "institution": "Jamia Millia Islamia",
        "degree": "Bachelor of Technology - BTech",
        "field_of_study": "Electrical and Electronics Engineering",
        "years_attended": "2012 - 2016"
      }
    ],
    "connections": "500+",
    "followers": "2,350",
    "skills": [
      "Employee Stock Ownership Plan (ESOP)",
      "Competency Framework Design",
      "HR Consulting",
      "Organizational Design",
      "Data Analytics",
      "HR Analytics",
      "SAP ERP",
      "Microsoft Excel"
    ],
    "interests": [
      "Adam Grant",
      "Jeff Weiner"
    ]
  },
  "tokens_used": {
    "prompt_tokens": 3476,
    "completion_tokens": 594,
    "total_tokens": 4070
  }
}