{
  "url": "https://in.linkedin.com/in/snehaarao",
  "raw_text": "0 notifications total\nnew feed updates notifications\nHome\n1\n1 new network update notification\nMy Network\nJobs\nMessaging\nNotifications\nMe\nFor Business\nTry Premium for ₹0\nSneha Rao\nTalent development I Coach (ICF - ACC)\nTata Institute of Social Sciences\nMumbai, Maharashtra, India Contact info\n500+ connections\nMessage\nFollow\nMore\nAbout\nAbout\nI have worked in diverse industries such as manufacturing, consulting and IT, outdoors & adventure and performed a gamut of HR generalist and specialist roles in talent development and total rewards.\nI have worked in diverse industries such as manufacturing, consulting and IT, outdoors & adventure and performed a gamut of HR generalist and specialist roles in talent development and total rewards.\nServices\nServices\nHR Consulting • Leadership Development • Executive Coaching\nHR Consulting • Leadership Development • Executive Coaching\nRequest services\nShow all services\nActivity\nActivity\n863 followers\n863 followers\nPosts\nComments\nLoaded 9 Posts posts\nSneha Rao\nSneha Rao\n • 3rd+\n3rd+\nTalent development I Coach (ICF - ACC)\nTalent development I Coach (ICF - ACC)\n2mo • \n 2 months ago • Visible to anyone on or off LinkedIn\nI’m happy to share that I’ve obtained a new certification: Associate Certified Coach (ACC) from International Coaching Federation.\nThank youfor the enriching learning experience, support and guidance you've provided, with fun being the big bonus!\n…more\nCelebrating a New Certification\n88\n31 comments\nSneha Rao reposted this\nxto10x\nxto10x\n21,217 followers\n21,217 followers\n1yr • \n 1 year ago • Visible to anyone on or off LinkedIn\n✨ We're thrilled to share the success story of our collaboration with Meesho\n\nMeesho is renowned for its innovative approach to democratising e-commerce. One core reason behind this is the high-performing culture that every team member lives and breathes at Meesho, resulting in exceptional talent density within the organization. We are proud to have been their partners on this journey for four years and counting.\n\nA special mention toandfor making this a focus area since Meesho's early days. This line by them captures their culture perfectly: \"If Meesho was personified as an individual — how would she behave? How would she take decisions and communicate? That, in a nutshell, is our culture.\"\n\nA big thank you to the entire Meesho team,,,,,,,,,,,🙌\n\n…more\n125\n2 comments\n18 reposts\nShow all posts\nExperience\nExperience\nPeople Excellence team\nPeople Excellence team\nxto10x · Full-time\nxto10x · Full-time\nMar 2022 - Apr 2024 · 2 yrs 2 mos\nMar 2022 to Apr 2024 · 2 yrs 2 mos\nHuman Resources & Content Management\nHuman Resources & Content Management\nIndiahikes\nIndiahikes\nMar 2017 - Aug 2018 · 1 yr 6 mos\nMar 2017 to Aug 2018 · 1 yr 6 mos\nTalent & PMO\nTalent & PMO\npeel-works\npeel-works\nJul 2013 - Oct 2015 · 2 yrs 4 mos\nJul 2013 to Oct 2015 · 2 yrs 4 mos\nManager - Corporate HR\nManager - Corporate HR\nWhirlpool Corporation\nWhirlpool Corporation\nAug 2010 - Aug 2012 · 2 yrs 1 mo\nAug 2010 to Aug 2012 · 2 yrs 1 mo\nGurgaon, India\nGurgaon, India\nStrategic role responsible for Learning & Development, Employee engagement and Talent Management for APAC\n• Led the L&D function for India: responsible for planning, design and delivery of development programs\n• Led employee engagement for APAC: responsible for deploying the annual engagement survey, identifying and implementing engagment actions\n• Involved in HR strategy formulation, leadership succession planning, and talent development\nConsultant\nConsultant\nHewitt Associates\nHewitt Associates\nOct 2007 - Jan 2010 · 2 yrs 4 mos\nOct 2007 to Jan 2010 · 2 yrs 4 mos\nBengaluru, Karnataka, India\nBengaluru, Karnataka, India\nProject delivery and client management on several assignments in the areas of total rewards structure & design, compensation benchmarking, job evaluation and leadership development for clients based in India and Sri Lanka\nProject delivery and client management on several assignments in the areas of total rewards structure & design, compensation benchmarking, job evaluation and leadership development for clients based in India and Sri Lanka\nShow all 6 experiences\nEducation\nEducation\nTata Institute of Social Sciences\nTata Institute of Social Sciences\nM.A., PM&IR\nM.A., PM&IR\n2003 - 2005\n2003 - 2005\nActivities and societies: Placement Commitee\nActivities and societies: Placement Commitee\nNew York University\nNew York University\nCertificate - Leadership & Organziation Development\nCertificate - Leadership & Organziation Development\n2012\n2012\nAreas of study:\n- Organization development\n- High performance workplaces\n- Change management\n- Organizational behaviour\n- Strategy\n- Workplace communication\nShow all 6 educations\nLicenses & certifications\nLicenses & certifications\nAssociate Certified Coach (ACC)\nAssociate Certified Coach (ACC)\nInternational Coaching Federation\nInternational Coaching Federation\nIssued May 2025 · Expires May 2028\nIssued May 2025 · Expires May 2028\nShow credential\nTransactional analysis 101\nTransactional analysis 101\nNavgati\nNavgati\nIssued Apr 2024\nIssued Apr 2024\nShow credential\nNavgati - Completion of ITAA recognized introductory course in Transactional Analysis, issued by Navgati - 2024-04-24.png\nNavgati - Completion of ITAA recognized introductory course in Transactional Analysis, issued by Navgati - 2024-04-24.png\nShow all 3 licenses & certifications\nSkills\nSkills\nEmployee Engagement\nEmployee Engagement\nRahul Sahay profile picture\nEndorsed by Rahul Sahay who is highly skilled at this\nEndorsed byRahul Sahaywho is highly skilled at this\nEndorsed by 2 colleagues at Wipro\nEndorsed by 2 colleagues at Wipro\n4 endorsements\n4 endorsements\nTalent Management\nTalent Management\nKartik Iyengar has given an endorsement for this skill\nKartik Iyengarhas given an endorsement for this skill\n1 endorsement\n1 endorsement\nShow all 14 skills\nRecommendations\nRecommendations\nReceived\nReceived\nGiven\nGiven\nNidhi Ramachandran\nNidhi Ramachandran\nNidhi Ramachandran\nA coach who provides a safe space to reach your potential - with 20+ years of experience across consulting, the business of technology and human capital.\nA coach who provides a safe space to reach your potential - with 20+ years of experience across consulting, the business of technology and human capital.\nSeptember 27, 2018, Nidhi was senior to Sneha but didn't manage Sneha directly\nSeptember 27, 2018,Nidhiwas senior toSnehabut didn't manageSnehadirectly\nSneha is an extremely grounded HR professional with practical thoughts and fantastic documentation skills. She created HR processes for us at peel-works that are still in use after 3 years and havent required any updates. She is also extremely committed as a person and you can always be sure that a deadline given by her will be honoured.\nSneha is an extremely grounded HR professional with practical thoughts and fantastic documentation skills. She created HR processes for us at peel-works that are still in use after 3 years and havent required any updates. She is also extremely committed as a person and you can always be sure that a deadline given by her will be honoured.\nAnil Garg\nAnil Garg\nAnil Garg\nChange Management Consultant based in Atlanta\nChange Management Consultant based in Atlanta\nSeptember 12, 2013, Anil managed Sneha directly\nSeptember 12, 2013,AnilmanagedSnehadirectly\nSneha's responsibilities kept increasing as she exhibited tremendous capability to shoulder more. Her strategic insights, analytical abilities and ability to innovate led us to keep moving her to more value added roles within HR. Our faith was based to a large extent on her learning agility and adaptability. Truly a great asset in HR.\nSneha's responsibilities kept increasing as she exhibited tremendous capability to shoulder more. Her strategic insights, analytical abilities and ability to innovate led us to keep moving her to more value added roles within HR. Our faith was based to a large extent on her learning agility and adaptability. Truly a great asset in HR.\nShow all 4 received\nInterests\nInterests\nCompanies\nCompanies\nGroups\nGroups\nNewsletters\nNewsletters\nNavgati\nNavgati\n5,313 followers\n5,313 followers\nFollow\nThreeFish Consulting India\nThreeFish Consulting India\n3,514 followers\n3,514 followers\nFollow\nShow all companies\nCauses\nCauses\nCivil Rights and Social Action • Education • Environment\nCivil Rights and Social Action • Education • Environment\nMore profiles for you\nMore profiles for you\nSrayon Datta\nSrayon Datta\n· 3rd+\n3rd+ degree connection\nAll things TA!\nAll things TA!\nMessage\nPiyush Dixit\nPiyush Dixit\n· 3rd+\n3rd+ degree connection\nCo-founder and Executive Coach, Tanmaatra Consulting\nCo-founder and Executive Coach, Tanmaatra Consulting\nConnect\nAnkit Hetamsaria\nAnkit Hetamsaria\nAnkit Hetamsaria\n· 3rd+\n3rd+ degree connection\nxto10x | Ex-Founder Bambinos.live | Cure.fit | Flipkart\nConnect\nAruna Gopakumar\nAruna Gopakumar\n· 3rd+\n3rd+ degree connection\nDirector, The School of You & Navgati\nDirector, The School of You & Navgati\nConnect\nSamvidha Sinha\nSamvidha Sinha\n· 3rd+\n3rd+ degree connection\nEx-Google | Metric-driven, Cross-funnel Integrated Marketer | People & Operations | Xoogler.co Lead\nFollow\nShow all\nPeople you may know\nPeople you may know\nFrom Sneha's school\nFrom Sneha's school\nNamita Kalita\nNamita Kalita\nMaster's in International Relations || Project Management || Social Work and Community Development Initiatives\nConnect\nChandan Singh\nChandan Singh\nAdvertising and Public Relations, IIMC (2024-25) / Ex-Project Assistant at Ministry of Tourism, Govt. of India / Converted TISS Mumbai (Hospital Administration)\nConnect\nSantosh Kumar Singh\nSantosh Kumar Singh\nSr Assistant Director/Faculty BIPARD (Administrative Training Institute ) Bihar | Leading Rural Development Initiatives I Poverty alleviation interventions I Ph.D. (Practice Track) in Management at IIM Kozhikode I\nConnect\nShravan Pal\nShravan Pal\nStudent at Tata Institute of Social Sciences\nStudent at Tata Institute of Social Sciences\nConnect\nNeeta Chakma\nNeeta Chakma\nMaster of Social Work | Public Health | TISS'25\nMaster of Social Work | Public Health | TISS'25\nConnect\nShow all\nYou might like\nYou might like\nPages for you\nPages for you\nGAL AeroStaff Ltd\nGAL AeroStaff Ltd\nStaffing and Recruiting\nStaffing and Recruiting\n8,821 followers\n8,821 followers\nFollow\nServiceSetu Academics\nServiceSetu Academics\nHigher Education\nHigher Education\n35,211 followers\n35,211 followers\nFollow\nShow all\nAbout\nAccessibility\nTalent Solutions\nProfessional Community Policies\nCareers\nMarketing Solutions\nPrivacy & Terms\nAd Choices\nAdvertising\nSales Solutions\nMobile\nSmall Business\nSafety Center\nQuestions?\nVisit our Help Center.\nManage your account and privacy\nGo to your Settings.\nRecommendation transparency\nLearn more about Recommended Content.\nSelect Language\n         العربية (Arabic)\n         বাংলা (Bangla)\n         Čeština (Czech)\n         Dansk (Danish)\n         Deutsch (German)\n         Ελληνικά (Greek)\n         English (English)\n         Español (Spanish)\n         فارسی (Persian)\n         Suomi (Finnish)\n         Français (French)\n         हिंदी (Hindi)\n         Magyar (Hungarian)\n         Bahasa Indonesia (Indonesian)\n         Italiano (Italian)\n         עברית (Hebrew)\n         日本語 (Japanese)\n         한국어 (Korean)\n         मराठी (Marathi)\n         Bahasa Malaysia (Malay)\n         Nederlands (Dutch)\n         Norsk (Norwegian)\n         ਪੰਜਾਬੀ (Punjabi)\n         Polski (Polish)\n         Português (Portuguese)\n         Română (Romanian)\n         Русский (Russian)\n         Svenska (Swedish)\n         తెలుగు (Telugu)\n         ภาษาไทย (Thai)\n         Tagalog (Tagalog)\n         Türkçe (Turkish)\n         Українська (Ukrainian)\n         Tiếng Việt (Vietnamese)\n         简体中文 (Chinese (Simplified))\n         正體中文 (Chinese (Traditional))\n     LinkedIn Corporation © 2025\nStatus is online\nMessaging\nYou are on the messaging overlay. Press enter to open the list of conversations.\nCompose message\nYou are on the messaging overlay. Press enter to open the list of conversations.",
  "skills_text": "0 notifications total\nnew feed updates notifications\nHome\n1\n1 new network update notification\nMy Network\nJobs\nMessaging\nNotifications\nMe\nFor Business\nTry Premium for ₹0\nSneha Rao\nTalent development I Coach (ICF - ACC)\nMore\nFollow\nMessage\nSkills\nAll\nIndustry Knowledge\nEmployee Engagement\nEmployee Engagement\nRahul Sahay profile picture\nEndorsed by Rahul Sahay who is highly skilled at this\nEndorsed byRahul Sahaywho is highly skilled at this\nEndorsed by 2 colleagues at Wipro\nEndorsed by 2 colleagues at Wipro\n4 endorsements\n4 endorsements\nTalent Management\nTalent Management\nKartik Iyengar has given an endorsement for this skill\nKartik Iyengarhas given an endorsement for this skill\n1 endorsement\n1 endorsement\nPerformance Management\nPerformance Management\nKartik Iyengar has given an endorsement for this skill\nKartik Iyengarhas given an endorsement for this skill\n1 endorsement\n1 endorsement\nLearning & development\nLearning & development\nHR Consulting\nHR Consulting\nChange Management\nChange Management\nCompensation \nCompensation\nOrganizational Effectiveness\nOrganizational Effectiveness\nLeadership Development\nLeadership Development\nHuman Resources\nHuman Resources\nWorkshop Facilitation\nWorkshop Facilitation\nSuccession Planning\nSuccession Planning\nJob Evaluation\nJob Evaluation\nOnboarding\nOnboarding\nMore profiles for you\nMore profiles for you\nSrayon Datta\nSrayon Datta\n· 3rd+\n3rd+ degree connection\nAll things TA!\nAll things TA!\nMessage\nPiyush Dixit\nPiyush Dixit\n· 3rd+\n3rd+ degree connection\nCo-founder and Executive Coach, Tanmaatra Consulting\nCo-founder and Executive Coach, Tanmaatra Consulting\nConnect\nAnkit Hetamsaria\nAnkit Hetamsaria\nAnkit Hetamsaria\n· 3rd+\n3rd+ degree connection\nxto10x | Ex-Founder Bambinos.live | Cure.fit | Flipkart\nConnect\nAruna Gopakumar\nAruna Gopakumar\n· 3rd+\n3rd+ degree connection\nDirector, The School of You & Navgati\nDirector, The School of You & Navgati\nConnect\nSamvidha Sinha\nSamvidha Sinha\n· 3rd+\n3rd+ degree connection\nEx-Google | Metric-driven, Cross-funnel Integrated Marketer | People & Operations | Xoogler.co Lead\nFollow\nShow more\nAbout\nAccessibility\nTalent Solutions\nProfessional Community Policies\nCareers\nMarketing Solutions\nPrivacy & Terms\nAd Choices\nAdvertising\nSales Solutions\nMobile\nSmall Business\nSafety Center\nQuestions?\nVisit our Help Center.\nManage your account and privacy\nGo to your Settings.\nRecommendation transparency\nLearn more about Recommended Content.\nSelect Language\n         العربية (Arabic)\n         বাংলা (Bangla)\n         Čeština (Czech)\n         Dansk (Danish)\n         Deutsch (German)\n         Ελληνικά (Greek)\n         English (English)\n         Español (Spanish)\n         فارسی (Persian)\n         Suomi (Finnish)\n         Français (French)\n         हिंदी (Hindi)\n         Magyar (Hungarian)\n         Bahasa Indonesia (Indonesian)\n         Italiano (Italian)\n         עברית (Hebrew)\n         日本語 (Japanese)\n         한국어 (Korean)\n         मराठी (Marathi)\n         Bahasa Malaysia (Malay)\n         Nederlands (Dutch)\n         Norsk (Norwegian)\n         ਪੰਜਾਬੀ (Punjabi)\n         Polski (Polish)\n         Português (Portuguese)\n         Română (Romanian)\n         Русский (Russian)\n         Svenska (Swedish)\n         తెలుగు (Telugu)\n         ภาษาไทย (Thai)\n         Tagalog (Tagalog)\n         Türkçe (Turkish)\n         Українська (Ukrainian)\n         Tiếng Việt (Vietnamese)\n         简体中文 (Chinese (Simplified))\n         正體中文 (Chinese (Traditional))\n     LinkedIn Corporation © 2025\nStatus is online\nMessaging\nYou are on the messaging overlay. Press enter to open the list of conversations.\nCompose message\nYou are on the messaging overlay. Press enter to open the list of conversations.",
  "scraped_at": "2025-07-23 00:32:42",
  "has_skills": true,
  "cleaned_profile": {
    "name": "Sneha Rao",
    "profile_url": "https://in.linkedin.com/in/snehaarao",
    "current_position": {
      "title": "Talent development I Coach (ICF - ACC)",
      "company": "Tata Institute of Social Sciences",
      "location": "Mumbai, Maharashtra, India"
    },
    "previous_positions": [
      {
        "title": "People Excellence team",
        "company": "xto10x",
        "location": null,
        "start_date": "Mar 2022",
        "end_date": "Apr 2024",
        "duration": "2 yrs 2 mos"
      },
      {
        "title": "Human Resources & Content Management",
        "company": "Indiahikes",
        "location": null,
        "start_date": "Mar 2017",
        "end_date": "Aug 2018",
        "duration": "1 yr 6 mos"
      },
      {
        "title": "Talent & PMO",
        "company": "peel-works",
        "location": null,
        "start_date": "Jul 2013",
        "end_date": "Oct 2015",
        "duration": "2 yrs 4 mos"
      },
      {
        "title": "Manager - Corporate HR",
        "company": "Whirlpool Corporation",
        "location": "Gurgaon, India",
        "start_date": "Aug 2010",
        "end_date": "Aug 2012",
        "duration": "2 yrs 1 mo"
      },
      {
        "title": "Consultant",
        "company": "Hewitt Associates",
        "location": "Bengaluru, Karnataka, India",
        "start_date": "Oct 2007",
        "end_date": "Jan 2010",
        "duration": "2 yrs 4 mos"
      }
    ],
    "education": [
      {
        "institution": "Tata Institute of Social Sciences",
        "degree": "M.A.",
        "field_of_study": "PM&IR",
        "years_attended": "2003 - 2005"
      },
      {
        "institution": "New York University",
        "degree": "Certificate",
        "field_of_study": "Leadership & Organization Development",
        "years_attended": "2012"
      }
    ],
    "connections": "500+",
    "followers": 863,
    "skills": [
      "Employee Engagement",
      "Talent Management",
      "Performance Management",
      "Learning & development",
      "HR Consulting",
      "Change Management",
      "Compensation",
      "Organizational Effectiveness",
      "Leadership Development",
      "Human Resources",
      "Workshop Facilitation",
      "Succession Planning",
      "Job Evaluation",
      "Onboarding"
    ],
    "interests": [
      "Navgati",
      "ThreeFish Consulting India"
    ]
  },
  "tokens_used": {
    "prompt_tokens": 3854,
    "completion_tokens": 630,
    "total_tokens": 4484
  }
}