{
  "url": "https://in.linkedin.com/in/vignesh-sachudanandan-a07430281",
  "raw_text": "0 notifications total\nnew feed updates notifications\nHome\n1\n1 new network update notification\nMy Network\nJobs\nMessaging\nNotifications\nMe\nFor Business\nTry Premium for â‚¹0\nVignesh Sachudanandan\n--\nxto10x\nBengaluru, Karnataka, India Contact info\n49 connections\nMessage\nFollow\nMore\nActivity\nActivity\n49 followers\n49 followers\nLoaded 1 Comments post\nVignesh Sachudanandan commented on a post â€¢ 11mo\n11mo\nCongrats sir Deepak Rajanna ğŸ˜\nCongrats sir Deepak Rajanna ğŸ˜ \nShow all comments\nExperience\nExperience\nAdministrative Assistant\nAdministrative Assistant\nxto10x Â· Full-time\nxto10x Â· Full-time\nJun 2019 - Present Â· 6 yrs 2 mos\nJun 2019 to Present Â· 6 yrs 2 mos\nKarnataka, India\nKarnataka, India\nAdministrative Assistant\nAdministrative Assistant\nOla Â· Full-time\nOla Â· Full-time\nSep 2016 - May 2019 Â· 2 yrs 9 mos\nSep 2016 to May 2019 Â· 2 yrs 9 mos\nCNC machine operator\nCNC machine operator\nAL-ATIQI INDUSTRIES COMPANY LLC Â· Full-time\nAL-ATIQI INDUSTRIES COMPANY LLC Â· Full-time\nMar 2012 - Jul 2015 Â· 3 yrs 5 mos\nMar 2012 to Jul 2015 Â· 3 yrs 5 mos\nKuwait\nKuwait\nAdministrative Assistant\nAdministrative Assistant\nHandiman Services Ltd Â· Full-time\nHandiman Services Ltd Â· Full-time\nFeb 2010 - Feb 2011 Â· 1 yr 1 mo\nFeb 2010 to Feb 2011 Â· 1 yr 1 mo\nBengaluru, Karnataka, India\nBengaluru, Karnataka, India\nInterests\nInterests\nCompanies\nCompanies\nxto10x\nxto10x\n21,217 followers\n21,217 followers\nFollow\nDesign deFolio\nDesign deFolio\n688 followers\n688 followers\nFollow\nShow all companies\nMore profiles for you\nMore profiles for you\nRahul Jagannathan\nRahul Jagannathan\nÂ· 3rd+\n3rd+ degree connection\nPeople Practice at xto10x | Leadership roles in startups | ICF Credentialed Coach | Hogan Certified | Music Hobbyist\nConnect\nMeenu Kumar\nMeenu Kumar\nÂ· 3rd+\n3rd+ degree connection\nRussell Reynolds Associates\nRussell Reynolds Associates\nConnect\nVidhi Kedia\nVidhi Kedia\nÂ· 3rd+\n3rd+ degree connection\nStudent at St. Xavier's University\nStudent at St. Xavier's University\nConnect\nRishhi Mehra\nRishhi Mehra\nÂ· 3rd+\n3rd+ degree connection\nConnecting Talent with Opportunity\nConnecting Talent with Opportunity\nFollow\nKhushbu Sen\nKhushbu Sen\nÂ· 3rd+\n3rd+ degree connection\nFinance and legal at xto10x\nFinance and legal at xto10x\nConnect\nShow all\nPeople you may know\nPeople you may know\nFrom Vignesh's company\nFrom Vignesh's company\nCA Hari Prakash\nCA Hari Prakash\nxto10x || x- Ledger services Pvt Ltd ll x- Vasanth and Co.,|| CA (Dec 2021) ||\nConnect\nSaurabh Pandey\nSaurabh Pandey\nDigital Marketer | Social Media Manager | Influencer Marketing\nDigital Marketer | Social Media Manager | Influencer Marketing\nConnect\nBhavesh Parvatkar\nBhavesh Parvatkar\nSDE 2 at xto10x\nSDE 2 at xto10x\nConnect\nAshutosh Gaud\nAshutosh Gaud\nSenior Product Designer at xto10x | Ex-MoMoney | Ex-Parallelhq\nConnect\nKunal Shah\nKunal Shah\nxto10x Technologies | Urban Ladder | IIM Indore\nxto10x Technologies | Urban Ladder | IIM Indore\nConnect\nShow all\nYou might like\nYou might like\nPages for you\nPages for you\nAcademic Careers - Engineering Faculty jobs\nAcademic Careers - Engineering Faculty jobs\nEducation\nEducation\n11,593 followers\n11,593 followers\nFollow\nIndian Aviation Career\nIndian Aviation Career\nAirlines and Aviation\nAirlines and Aviation\n57,399 followers\n57,399 followers\nFollow\nShow all\nAbout\nAccessibility\nTalent Solutions\nProfessional Community Policies\nCareers\nMarketing Solutions\nPrivacy & Terms\nAd Choices\nAdvertising\nSales Solutions\nMobile\nSmall Business\nSafety Center\nQuestions?\nVisit our Help Center.\nManage your account and privacy\nGo to your Settings.\nRecommendation transparency\nLearn more about Recommended Content.\nSelect Language\n         Ø§Ù„Ø¹Ø±Ø¨ÙŠØ© (Arabic)\n         à¦¬à¦¾à¦‚à¦²à¦¾ (Bangla)\n         ÄŒeÅ¡tina (Czech)\n         Dansk (Danish)\n         Deutsch (German)\n         Î•Î»Î»Î·Î½Î¹ÎºÎ¬ (Greek)\n         English (English)\n         EspaÃ±ol (Spanish)\n         ÙØ§Ø±Ø³ÛŒ (Persian)\n         Suomi (Finnish)\n         FranÃ§ais (French)\n         à¤¹à¤¿à¤‚à¤¦à¥€ (Hindi)\n         Magyar (Hungarian)\n         Bahasa Indonesia (Indonesian)\n         Italiano (Italian)\n         ×¢×‘×¨×™×ª (Hebrew)\n         æ—¥æœ¬èª (Japanese)\n         í•œêµ­ì–´ (Korean)\n         à¤®à¤°à¤¾à¤ à¥€ (Marathi)\n         Bahasa Malaysia (Malay)\n         Nederlands (Dutch)\n         Norsk (Norwegian)\n         à¨ªà©°à¨œà¨¾à¨¬à©€ (Punjabi)\n         Polski (Polish)\n         PortuguÃªs (Portuguese)\n         RomÃ¢nÄƒ (Romanian)\n         Ğ ÑƒÑÑĞºĞ¸Ğ¹ (Russian)\n         Svenska (Swedish)\n         à°¤à±†à°²à±à°—à± (Telugu)\n         à¸ à¸²à¸©à¸²à¹„à¸—à¸¢ (Thai)\n         Tagalog (Tagalog)\n         TÃ¼rkÃ§e (Turkish)\n         Ğ£ĞºÑ€Ğ°Ñ—Ğ½ÑÑŒĞºĞ° (Ukrainian)\n         Tiáº¿ng Viá»‡t (Vietnamese)\n         ç®€ä½“ä¸­æ–‡ (Chinese (Simplified))\n         æ­£é«”ä¸­æ–‡ (Chinese (Traditional))\n     LinkedIn Corporation Â© 2025\nStatus is online\nMessaging\nYou are on the messaging overlay. Press enter to open the list of conversations.\nCompose message\nYou are on the messaging overlay. Press enter to open the list of conversations.",
  "skills_text": "0 notifications total\nnew feed updates notifications\nHome\n1\n1 new network update notification\nMy Network\nJobs\nMessaging\nNotifications\nMe\nFor Business\nTry Premium for â‚¹0\nVignesh Sachudanandan\n--\nMore\nFollow\nMessage\nSkills\nNothing to see for now\nNothing to see for now\nSkills that Vignesh adds will appear here.\nSkills that Vignesh adds will appear here.\nMore profiles for you\nMore profiles for you\nRahul Jagannathan\nRahul Jagannathan\nÂ· 3rd+\n3rd+ degree connection\nPeople Practice at xto10x | Leadership roles in startups | ICF Credentialed Coach | Hogan Certified | Music Hobbyist\nConnect\nMeenu Kumar\nMeenu Kumar\nÂ· 3rd+\n3rd+ degree connection\nRussell Reynolds Associates\nRussell Reynolds Associates\nConnect\nVidhi Kedia\nVidhi Kedia\nÂ· 3rd+\n3rd+ degree connection\nStudent at St. Xavier's University\nStudent at St. Xavier's University\nConnect\nRishhi Mehra\nRishhi Mehra\nÂ· 3rd+\n3rd+ degree connection\nConnecting Talent with Opportunity\nConnecting Talent with Opportunity\nFollow\nKhushbu Sen\nKhushbu Sen\nÂ· 3rd+\n3rd+ degree connection\nFinance and legal at xto10x\nFinance and legal at xto10x\nConnect\nShow more\nAbout\nAccessibility\nTalent Solutions\nProfessional Community Policies\nCareers\nMarketing Solutions\nPrivacy & Terms\nAd Choices\nAdvertising\nSales Solutions\nMobile\nSmall Business\nSafety Center\nQuestions?\nVisit our Help Center.\nManage your account and privacy\nGo to your Settings.\nRecommendation transparency\nLearn more about Recommended Content.\nSelect Language\n         Ø§Ù„Ø¹Ø±Ø¨ÙŠØ© (Arabic)\n         à¦¬à¦¾à¦‚à¦²à¦¾ (Bangla)\n         ÄŒeÅ¡tina (Czech)\n         Dansk (Danish)\n         Deutsch (German)\n         Î•Î»Î»Î·Î½Î¹ÎºÎ¬ (Greek)\n         English (English)\n         EspaÃ±ol (Spanish)\n         ÙØ§Ø±Ø³ÛŒ (Persian)\n         Suomi (Finnish)\n         FranÃ§ais (French)\n         à¤¹à¤¿à¤‚à¤¦à¥€ (Hindi)\n         Magyar (Hungarian)\n         Bahasa Indonesia (Indonesian)\n         Italiano (Italian)\n         ×¢×‘×¨×™×ª (Hebrew)\n         æ—¥æœ¬èª (Japanese)\n         í•œêµ­ì–´ (Korean)\n         à¤®à¤°à¤¾à¤ à¥€ (Marathi)\n         Bahasa Malaysia (Malay)\n         Nederlands (Dutch)\n         Norsk (Norwegian)\n         à¨ªà©°à¨œà¨¾à¨¬à©€ (Punjabi)\n         Polski (Polish)\n         PortuguÃªs (Portuguese)\n         RomÃ¢nÄƒ (Romanian)\n         Ğ ÑƒÑÑĞºĞ¸Ğ¹ (Russian)\n         Svenska (Swedish)\n         à°¤à±†à°²à±à°—à± (Telugu)\n         à¸ à¸²à¸©à¸²à¹„à¸—à¸¢ (Thai)\n         Tagalog (Tagalog)\n         TÃ¼rkÃ§e (Turkish)\n         Ğ£ĞºÑ€Ğ°Ñ—Ğ½ÑÑŒĞºĞ° (Ukrainian)\n         Tiáº¿ng Viá»‡t (Vietnamese)\n         ç®€ä½“ä¸­æ–‡ (Chinese (Simplified))\n         æ­£é«”ä¸­æ–‡ (Chinese (Traditional))\n     LinkedIn Corporation Â© 2025\nStatus is online\nMessaging\nYou are on the messaging overlay. Press enter to open the list of conversations.\nCompose message\nYou are on the messaging overlay. Press enter to open the list of conversations.",
  "scraped_at": "2025-07-23 00:34:01",
  "has_skills": true,
  "cleaned_profile": {
    "name": "Vignesh Sachudanandan",
    "profile_url": "https://in.linkedin.com/in/vignesh-sachudanandan-a07430281",
    "current_position": {
      "title": "Administrative Assistant",
      "company": "xto10x",
      "location": "Karnataka, India",
      "start_date": "Jun 2019",
      "end_date": "Present",
      "duration": "6 yrs 2 mos"
    },
    "previous_positions": [
      {
        "title": "Administrative Assistant",
        "company": "Ola",
        "location": "Karnataka, India",
        "start_date": "Sep 2016",
        "end_date": "May 2019",
        "duration": "2 yrs 9 mos"
      },
      {
        "title": "CNC machine operator",
        "company": "AL-ATIQI INDUSTRIES COMPANY LLC",
        "location": "Kuwait",
        "start_date": "Mar 2012",
        "end_date": "Jul 2015",
        "duration": "3 yrs 5 mos"
      },
      {
        "title": "Administrative Assistant",
        "company": "Handiman Services Ltd",
        "location": "Bengaluru, Karnataka, India",
        "start_date": "Feb 2010",
        "end_date": "Feb 2011",
        "duration": "1 yr 1 mo"
      }
    ],
    "connections": 49,
    "followers": 49,
    "interests": [
      "xto10x",
      "Design deFolio"
    ]
  },
  "tokens_used": {
    "prompt_tokens": 2102,
    "completion_tokens": 356,
    "total_tokens": 2458
  }
}