{
  "url": "https://in.linkedin.com/in/sri-sowmya-guddati",
  "raw_text": "0 notifications total\nnew feed updates notifications\nHome\n1\n1 new network update notification\nMy Network\nJobs\nMessaging\nNotifications\nMe\nFor Business\nTry Premium for ₹0\nSri Sowmya Guddati\nShe/Her\nCustomer Success Manager @xto10x | BITS Pilani\nxto10x\nBirla Institute of Technology and Science, Pilani\nBengaluru, Karnataka, India Contact info\n500+ connections\nMessage\nFollow\nMore\nAbout\nAbout\nA lifelong learner with a diverse academic and professional journey.\n\nI started with a foundation in Maths, Physics, and Chemistry, earned a Pharmacy degree, and then spent four years deeply immersed in UPSC preparation—gaining expertise in Polity, History, Economics, International Relations, Science & Tech, and Current Affairs. This experience not only expanded my knowledge but also sharpened my critical thinking, research, and problem-solving skills.\n\nBeyond academics, I have worked in content strategy, SEO, and stakeholder engagement. I have experience in website content development, editing, and SEO optimization, ensuring clarity, brand alignment, and enhanced visibility. Additionally, I have worked on user research, market analysis, and cross-functional coordination to drive strategic decisions.\n\n🔹 What Drives Me?\nThe joy of learning, meaningful conversations, and exploring new ideas.\n\n🔹 What Excites Me?\nPhilosophy, Psychology, Biographies, History, Geopolitics, Mental Health, and Contemporary Issues.\n\nWith a strong foundation in communication, problem-solving, and adaptability, I thrive in dynamic environments that require analytical thinking and collaboration. I’m always eager to engage in thought-provoking discussions and contribute meaningfully to impactful projects.\n\nLet’s connect! 🚀\n\n✉️ gsrisowmya13@gmail.com\n…see more\nActivity\nActivity\n572 followers\n572 followers\nPosts\nComments\nImages\nLoaded 2 Posts posts\nSri Sowmya Guddati\nSri Sowmya Guddati\n   • 3rd+\nVerified • 3rd+\nCustomer Success Manager @xto10x | BITS Pilani\nCustomer Success Manager @xto10x | BITS Pilani\n2w • \n 2 weeks ago • Visible to anyone on or off LinkedIn\nUnderstanding the product is one thing. Using it is another. Building it is a whole different experience. But hearing about it from our customers? That’s truly the most rewarding part. Proud to be part of theteam.\n…more\nPeopleCues\nPeopleCues\n735 followers\n735 followers\n6-week review cycles were the norm. Until now.\n\nAt Angel One, performance reviews that once took 4–6 weeks now wrap up in just 2–4, and that shift means everything. Huge thanks to Angel One team for the kind words, and for recognizing what we truly care about:\n📈 “You’ve moved the needle on the metrics that matter in a performance review.” –\n🤖 “The AI-led SBI feedback engine has completely changed the quality of feedback.” –\n\nIt’s a reminder that meaningful change at work doesn’t need to be loud, just well-designed.\nIf a better review experience helps employees feel heard and managers make sharper decisions, we’re doing our job right.\n\nWhat’s one underrated shift that’s made a big difference in your org? Comment below.\n\n\n\n…more\n1\nSri Sowmya Guddati\nSri Sowmya Guddati\n   • 3rd+\nVerified • 3rd+\nCustomer Success Manager @xto10x | BITS Pilani\nCustomer Success Manager @xto10x | BITS Pilani\n1mo • Edited • \n 1 month ago • Edited • Visible to anyone on or off LinkedIn\n🌟 Thrilled to begin a new journey with xto10x as a Customer Success Manager! 🌟\n\nThis isn’t just a new role—it’s a meaningful step toward doing the kind of work I truly care about: enabling growth, creating value, and being part of something bigger than myself.\n\nJoining the PeopleCues team has been incredibly energizing. From day one, the PeopleCues team has been welcoming, thoughtful, and incredibly driven. The vision, the people, the culture—everything about it feels like the perfect environment to learn deeply, contribute meaningfully, and grow intentionally. I’m here to listen, to act, and to grow—not just for myself, but with the people and partners I get to work with every day. I’m excited to immerse myself in the product, collaborate with brilliant minds, and bring an action- and results-driven mindset to everything I do.\n\nI’m especially grateful to everyone who’s supported me through this journey.\n—thank you for believing in me and giving me this opportunity.\n—thank you for your unwavering support and for making my onboarding experience so smooth and seamless.\nAnd a huge thank you to, for being a constant pillar of encouragement and support through every twist and turn. Your presence has made a world of difference.\n\nAs I look ahead, I’m driven by the opportunity to make a real impact—by helping our customers succeed, building strong relationships, and contributing to the growth of the product and the company.\n\nHere’s to learning, building, and growing—with intention and joy. The best is yet to come! 🚀\n…more\nActivate to view larger image,\nActivate to view larger image,\n126\n47 comments\nShow all posts\nExperience\nExperience\nCustomer Success Manager\nCustomer Success Manager\nxto10x · Full-time\nxto10x · Full-time\nMay 2025 - Present · 3 mos\nMay 2025 to Present · 3 mos\nBengaluru, Karnataka, India · Hybrid\nBengaluru, Karnataka, India · Hybrid\nContent Specialist\nContent Specialist\nSimplotel · Full-time\nSimplotel · Full-time\nJan 2025 - May 2025 · 5 mos\nJan 2025 to May 2025 · 5 mos\nBengaluru, Karnataka, India · On-site\nBengaluru, Karnataka, India · On-site\n• End-to-End Website Development:\n\nSkillfully oversee end-to-end content creation, ensuring seamless and engaging online experiences for multiple projects.\n\n• Content Editing:\n\nMeticulously edit content, enhancing quality with strategic techniques for brand alignment, clarity and industry best practices.\n\n• Strategic SEO Implementation:\n\nExpertise in leveraging on-site Search Engine Optimization (SEO) strategies to maximise online visibility and drive organic traffic.\n\n• Project Planning and Coordination:\n\nA strategic planner, I have effectively collaborated with cross-functional teams to align content initiatives with overarching project goals.\nWeb Content Writing, Content Strategy and +5 skills\nFounder's Office Intern\nFounder's Office Intern\nhashmint. · Internship\nhashmint. · Internship\nJul 2024 - Dec 2024 · 6 mos\nJul 2024 to Dec 2024 · 6 mos\nBengaluru, Karnataka, India · Hybrid\nBengaluru, Karnataka, India · Hybrid\n• Conducted user interviews with UPSC aspirants to gather insights on their challenges and needs.\n\n• Acted as a bridge between stakeholders, coordinating and scheduling meetings for smooth collaboration.\n\n• Performed market research on industry trends and competitors to inform business strategies.\n\n• Contributed to user engagement strategies, ensuring alignment with customer needs and market demands.\nCommunication, End User Research and +3 skills\nPersonal goal pursuit\nPersonal goal pursuit\nCareer Break\nCareer Break\nJul 2021 - Jul 2024 · 3 yrs 1 mo\nJul 2021 to Jul 2024 · 3 yrs 1 mo\nUPSC Preparation\nUPSC Preparation\nSecretary @ Department of Audiforce\nSecretary @ Department of Audiforce\nBirla Institute of Technology and Science, Pilani\nBirla Institute of Technology and Science, Pilani\nApr 2019 - Aug 2020 · 1 yr 5 mos\nApr 2019 to Aug 2020 · 1 yr 5 mos\nManagement and Leadership\nShow all 6 experiences\nEducation\nEducation\nBirla Institute of Technology and Science, Pilani\nBirla Institute of Technology and Science, Pilani\nBachelor's degree\nBachelor's degree\n2017 - 2021\n2017 - 2021\nActivities and societies: Nirmaan Organization, Department of Audiforce, Andhra Samithi, Pilani Atmanirbhar Resource Centre(PARC)\nActivities and societies: Nirmaan Organization, Department of Audiforce, Andhra Samithi, Pilani Atmanirbhar Resource Centre(PARC)\nBITS Pilani is the Alma mater of founders of Hotmail, SanDisk, Akamai, BlueJeans, Postman, Bigbasket \nand several Indian unicorns.\nBITS Pilani is the Alma mater of founders of Hotmail, SanDisk, Akamai, BlueJeans, Postman, Bigbasket and several Indian unicorns.\nIndependent Research\nIndira Gandhi National Open University (IGNOU), Delhi \nIndira Gandhi National Open University (IGNOU), Delhi\nMaster of Arts - MA, Political Science and Government\nMaster of Arts - MA, Political Science and Government\nJan 2022 - Jan 2024\nJan 2022 - Jan 2024\nLicenses & certifications\nLicenses & certifications\nMicroeconomics Principles\nMicroeconomics Principles\nUniversity of Illinois Urbana-Champaign\nUniversity of Illinois Urbana-Champaign\nIssued Dec 2020\nIssued Dec 2020\nCredential ID 77C4AGFYFY6G\nCredential ID 77C4AGFYFY6G\nShow credential\nIntroduction to Psychology \nIntroduction to Psychology\nYale University\nYale University\nIssued May 2020\nIssued May 2020\nCredential ID QNMAVAJPN8NJ\nCredential ID QNMAVAJPN8NJ\nShow credential\nShow all 3 licenses & certifications\nVolunteering\nVolunteering\nStudent Volunteer\nStudent Volunteer\nNirmaan Organization\nNirmaan Organization\nAug 2017 - May 2019 · 1 yr 10 mos\nAug 2017 - May 2019 · 1 yr 10 mos\nEducation\nEducation\n• Volunteered as part of the School Adoption Programme (SAP) in Nirmaan’s Pilani chapter, working with a team of 15 to uplift the only government school in the remote village of Baas.\n\n• Delivered English and Navodaya education to 50 middle school children on a weekly basis.\n\n• Re-introduced the art and craft workshop idea and executed biweekly for the whole school.\nStudent Volunteer\nStudent Volunteer\nPilani Atmanirbhar Resource Centre(PARC)\nPilani Atmanirbhar Resource Centre(PARC)\nAug 2020 - Dec 2020 · 5 mos\nAug 2020 - Dec 2020 · 5 mos\nSocial Services\nSocial Services\nSkills\nSkills\nCustomer Success\nCustomer Success\nFounder's Office Intern at hashmint.\nFounder's Office Intern at hashmint.\nEnd User Research\nEnd User Research\nFounder's Office Intern at hashmint.\nFounder's Office Intern at hashmint.\nShow all 26 skills\nLanguages\nLanguages\nEnglish\nEnglish\nNative or bilingual proficiency\nNative or bilingual proficiency\nHindi\nHindi\nFull professional proficiency\nFull professional proficiency\nShow all 3 languages\nInterests\nInterests\nTop Voices\nTop Voices\nCompanies\nCompanies\nGroups\nGroups\nNewsletters\nNewsletters\nSchools\nSchools\nKunal Bahl\nKunal Bahl\nEntrepreneur and Investor\nEntrepreneur and Investor\n860,960 followers\n860,960 followers\nFollow\nVidit Aatrey\nVidit Aatrey\nFounder & CEO @ Meesho \nFounder & CEO @ Meesho\n295,792 followers\n295,792 followers\nFollow\nShow all Top Voices\nMore profiles for you\nMore profiles for you\nSaksham Agarwal\nSaksham Agarwal\n· 3rd+\n3rd+ degree connection\nM&A Intern @ Deloitte | IIMK | Merilytics | InMobi | BITS Pilani\nM&A Intern @ Deloitte | IIMK | Merilytics | InMobi | BITS Pilani\nFollow\nShantanu Jaiswal\nShantanu Jaiswal\n· 3rd+\n3rd+ degree connection\nHelping Startups Scale | Customer Success Manager | Ex- Pixis\nConnect\nBharath Raju C.\nBharath Raju C.\nBharath Raju C.\n· 3rd+\n3rd+ degree connection\nSDE Deutsche Bank | Ex-Intern at IMI Mobile | Bits Pilani\nSDE Deutsche Bank | Ex-Intern at IMI Mobile | Bits Pilani\nConnect\nRohith Botu\nRohith Botu\n· 3rd+\n3rd+ degree connection\nOperations Practice @xto10x | Ex-Intern @Flipkart | BITS Pilani'24\nConnect\nLEBAKA SAI PAVAN KUMAR REDDY\nLEBAKA SAI PAVAN KUMAR REDDY\n· 3rd+\n3rd+ degree connection\nPhonePe | Ex-InMobi, Australia & New Zealand | Digital/Brand & Performance Marketing | BITS PILANI'22\nFollow\nShow all\nPeople you may know\nPeople you may know\nFrom Sri Sowmya's school\nFrom Sri Sowmya's school\nTumushime Yvette\nTumushime Yvette\nAfrican Leadership University\nAfrican Leadership University\nConnect\nbrian Kemboi\nbrian Kemboi\nStudent at University of Oxford\nStudent at University of Oxford\nConnect\nعبدالغفار عيد\nعبدالغفار عيد\nعبدالغفار عيد\n--\n--\nConnect\nMohamed Osman\nMohamed Osman\nطالب في جامعة آلملك سليمان الدوليه\nطالب في جامعة آلملك سليمان الدوليه\nConnect\nMonica Waithira\nMonica Waithira\nSoftware Programmer at Keeta\nSoftware Programmer at Keeta\nConnect\nShow all\nYou might like\nYou might like\nPages for you\nPages for you\nGlobal Airline Jobs\nGlobal Airline Jobs\nStaffing and Recruiting\nStaffing and Recruiting\n20,094 followers\n20,094 followers\nFollow\nServiceSetu Academics\nServiceSetu Academics\nHigher Education\nHigher Education\n35,211 followers\n35,211 followers\nFollow\nShow all\nAbout\nAccessibility\nTalent Solutions\nProfessional Community Policies\nCareers\nMarketing Solutions\nPrivacy & Terms\nAd Choices\nAdvertising\nSales Solutions\nMobile\nSmall Business\nSafety Center\nQuestions?\nVisit our Help Center.\nManage your account and privacy\nGo to your Settings.\nRecommendation transparency\nLearn more about Recommended Content.\nSelect Language\n         العربية (Arabic)\n         বাংলা (Bangla)\n         Čeština (Czech)\n         Dansk (Danish)\n         Deutsch (German)\n         Ελληνικά (Greek)\n         English (English)\n         Español (Spanish)\n         فارسی (Persian)\n         Suomi (Finnish)\n         Français (French)\n         हिंदी (Hindi)\n         Magyar (Hungarian)\n         Bahasa Indonesia (Indonesian)\n         Italiano (Italian)\n         עברית (Hebrew)\n         日本語 (Japanese)\n         한국어 (Korean)\n         मराठी (Marathi)\n         Bahasa Malaysia (Malay)\n         Nederlands (Dutch)\n         Norsk (Norwegian)\n         ਪੰਜਾਬੀ (Punjabi)\n         Polski (Polish)\n         Português (Portuguese)\n         Română (Romanian)\n         Русский (Russian)\n         Svenska (Swedish)\n         తెలుగు (Telugu)\n         ภาษาไทย (Thai)\n         Tagalog (Tagalog)\n         Türkçe (Turkish)\n         Українська (Ukrainian)\n         Tiếng Việt (Vietnamese)\n         简体中文 (Chinese (Simplified))\n         正體中文 (Chinese (Traditional))\n     LinkedIn Corporation © 2025\nStatus is online\nMessaging\nYou are on the messaging overlay. Press enter to open the list of conversations.\nCompose message\nYou are on the messaging overlay. Press enter to open the list of conversations.",
  "skills_text": "0 notifications total\nnew feed updates notifications\nHome\n1\n1 new network update notification\nMy Network\nJobs\nMessaging\nNotifications\nMe\nFor Business\nTry Premium for ₹0\nSri Sowmya Guddati\n(She/Her)\nCustomer Success Manager @xto10x | BITS Pilani\nMore\nFollow\nMessage\nSkills\nAll\nIndustry Knowledge\nTools & Technologies\nInterpersonal Skills\nCustomer Success\nCustomer Success\nFounder's Office Intern at hashmint.\nFounder's Office Intern at hashmint.\nEnd User Research\nEnd User Research\nFounder's Office Intern at hashmint.\nFounder's Office Intern at hashmint.\nMarket Research\nMarket Research\nFounder's Office Intern at hashmint.\nFounder's Office Intern at hashmint.\nJira\nJira\nContent Specialist at Simplotel\nContent Specialist at Simplotel\nWeb Content Writing\nWeb Content Writing\nContent Specialist at Simplotel\nContent Specialist at Simplotel\nContent Strategy\nContent Strategy\nContent Specialist at Simplotel\nContent Specialist at Simplotel\nSearch Engine Optimization (SEO)\nSearch Engine Optimization (SEO)\nContent Specialist at Simplotel\nContent Specialist at Simplotel\nContent Management Systems (CMS)\nContent Management Systems (CMS)\nContent Specialist at Simplotel\nContent Specialist at Simplotel\nZoho CRM\nZoho CRM\nContent Specialist at Simplotel\nContent Specialist at Simplotel\nClient Services\nClient Services\nContent Specialist at Simplotel\nContent Specialist at Simplotel\nCampaigns\nCampaigns\nStudent Volunteer\nStudent Volunteer\nIndependent Research\nIndependent Research\nBirla Institute of Technology and Science, Pilani\nBirla Institute of Technology and Science, Pilani\nOrganizational Leadership\nOrganizational Leadership\nJoint Secretary at Andhra Samithi BITS Pilani\nJoint Secretary at Andhra Samithi BITS Pilani\nEvent Management\nEvent Management\nJoint Secretary at Andhra Samithi BITS Pilani\nJoint Secretary at Andhra Samithi BITS Pilani\nPeople Management\nPeople Management\nJoint Secretary at Andhra Samithi BITS Pilani\nJoint Secretary at Andhra Samithi BITS Pilani\nManagement\nManagement\nSecretary @ Department of Audiforce at Birla Institute of Technology and Science, Pilani\nSecretary @ Department of Audiforce at Birla Institute of Technology and Science, Pilani\nInterpersonal Skills\nInterpersonal Skills\nLeadership\nLeadership\nSecretary @ Department of Audiforce at Birla Institute of Technology and Science, Pilani\nSecretary @ Department of Audiforce at Birla Institute of Technology and Science, Pilani\nTeam Coordination\nTeam Coordination\nTeamwork\nTeamwork\nCommunication\nCommunication\nFounder's Office Intern at hashmint.\nFounder's Office Intern at hashmint.\nProblem Solving\nProblem Solving\nFounder's Office Intern at hashmint.\nFounder's Office Intern at hashmint.\nMicrosoft Excel\nMicrosoft Excel\nMicrosoft Office\nMicrosoft Office\nPython (Programming Language)\nPython (Programming Language)\nSQL\nSQL\nMore profiles for you\nMore profiles for you\nSaksham Agarwal\nSaksham Agarwal\n· 3rd+\n3rd+ degree connection\nM&A Intern @ Deloitte | IIMK | Merilytics | InMobi | BITS Pilani\nM&A Intern @ Deloitte | IIMK | Merilytics | InMobi | BITS Pilani\nFollow\nShantanu Jaiswal\nShantanu Jaiswal\n· 3rd+\n3rd+ degree connection\nHelping Startups Scale | Customer Success Manager | Ex- Pixis\nConnect\nBharath Raju C.\nBharath Raju C.\nBharath Raju C.\n· 3rd+\n3rd+ degree connection\nSDE Deutsche Bank | Ex-Intern at IMI Mobile | Bits Pilani\nSDE Deutsche Bank | Ex-Intern at IMI Mobile | Bits Pilani\nConnect\nRohith Botu\nRohith Botu\n· 3rd+\n3rd+ degree connection\nOperations Practice @xto10x | Ex-Intern @Flipkart | BITS Pilani'24\nConnect\nLEBAKA SAI PAVAN KUMAR REDDY\nLEBAKA SAI PAVAN KUMAR REDDY\n· 3rd+\n3rd+ degree connection\nPhonePe | Ex-InMobi, Australia & New Zealand | Digital/Brand & Performance Marketing | BITS PILANI'22\nFollow\nShow more\nAbout\nAccessibility\nTalent Solutions\nProfessional Community Policies\nCareers\nMarketing Solutions\nPrivacy & Terms\nAd Choices\nAdvertising\nSales Solutions\nMobile\nSmall Business\nSafety Center\nQuestions?\nVisit our Help Center.\nManage your account and privacy\nGo to your Settings.\nRecommendation transparency\nLearn more about Recommended Content.\nSelect Language\n         العربية (Arabic)\n         বাংলা (Bangla)\n         Čeština (Czech)\n         Dansk (Danish)\n         Deutsch (German)\n         Ελληνικά (Greek)\n         English (English)\n         Español (Spanish)\n         فارسی (Persian)\n         Suomi (Finnish)\n         Français (French)\n         हिंदी (Hindi)\n         Magyar (Hungarian)\n         Bahasa Indonesia (Indonesian)\n         Italiano (Italian)\n         עברית (Hebrew)\n         日本語 (Japanese)\n         한국어 (Korean)\n         मराठी (Marathi)\n         Bahasa Malaysia (Malay)\n         Nederlands (Dutch)\n         Norsk (Norwegian)\n         ਪੰਜਾਬੀ (Punjabi)\n         Polski (Polish)\n         Português (Portuguese)\n         Română (Romanian)\n         Русский (Russian)\n         Svenska (Swedish)\n         తెలుగు (Telugu)\n         ภาษาไทย (Thai)\n         Tagalog (Tagalog)\n         Türkçe (Turkish)\n         Українська (Ukrainian)\n         Tiếng Việt (Vietnamese)\n         简体中文 (Chinese (Simplified))\n         正體中文 (Chinese (Traditional))\n     LinkedIn Corporation © 2025\nStatus is online\nMessaging\nYou are on the messaging overlay. Press enter to open the list of conversations.\nCompose message\nYou are on the messaging overlay. Press enter to open the list of conversations.",
  "scraped_at": "2025-07-23 00:36:11",
  "has_skills": true,
  "cleaned_profile": {
    "name": "Sri Sowmya Guddati",
    "pronouns": "She/Her",
    "profile_url": "https://in.linkedin.com/in/sri-sowmya-guddati",
    "current_position": {
      "title": "Customer Success Manager",
      "company": "xto10x",
      "location": "Bengaluru, Karnataka, India",
      "start_date": "May 2025",
      "end_date": "Present",
      "duration": "3 mos"
    },
    "previous_positions": [
      {
        "title": "Content Specialist",
        "company": "Simplotel",
        "location": "Bengaluru, Karnataka, India",
        "start_date": "Jan 2025",
        "end_date": "May 2025",
        "duration": "5 mos"
      },
      {
        "title": "Founder's Office Intern",
        "company": "hashmint.",
        "location": "Bengaluru, Karnataka, India",
        "start_date": "Jul 2024",
        "end_date": "Dec 2024",
        "duration": "6 mos"
      },
      {
        "title": "Secretary @ Department of Audiforce",
        "company": "Birla Institute of Technology and Science, Pilani",
        "location": "Pilani, India",
        "start_date": "Apr 2019",
        "end_date": "Aug 2020",
        "duration": "1 yr 5 mos"
      }
    ],
    "education": [
      {
        "institution": "Birla Institute of Technology and Science, Pilani",
        "degree": "Bachelor's degree",
        "field_of_study": null,
        "years_attended": "2017 - 2021"
      },
      {
        "institution": "Indira Gandhi National Open University (IGNOU), Delhi",
        "degree": "Master of Arts - MA",
        "field_of_study": "Political Science and Government",
        "years_attended": "Jan 2022 - Jan 2024"
      }
    ],
    "connections": "500+",
    "followers": 572,
    "skills": [
      "Customer Success",
      "End User Research",
      "Market Research",
      "Jira",
      "Web Content Writing",
      "Content Strategy",
      "Search Engine Optimization (SEO)",
      "Content Management Systems (CMS)",
      "Zoho CRM",
      "Client Services",
      "Campaigns",
      "Independent Research",
      "Organizational Leadership",
      "Event Management",
      "People Management",
      "Management",
      "Interpersonal Skills",
      "Leadership",
      "Team Coordination",
      "Teamwork",
      "Communication",
      "Problem Solving",
      "Microsoft Excel",
      "Microsoft Office",
      "Python (Programming Language)",
      "SQL"
    ],
    "interests": [
      "Kunal Bahl",
      "Vidit Aatrey"
    ]
  },
  "tokens_used": {
    "prompt_tokens": 4754,
    "completion_tokens": 641,
    "total_tokens": 5395
  }
}