{
  "url": "https://uk.linkedin.com/in/kabirmjoshi",
  "raw_text": "0 notifications total\nnew feed updates notifications\nHome\n1\n1 new network update notification\nMy Network\nJobs\nMessaging\nNotifications\nMe\nFor Business\nTry Premium for ₹0\nKabir M Joshi\nMPhil at Bayes Business School| Previously helping start-ups Scale at xto10x\nBayes Business School\nLondon, England, United Kingdom Contact info\n500+ connections\nMessage\nFollow\nMore\nAbout\nAbout\n- I’m a Doctoral candidate at the Bayes Business School. My research explores the area of organisation transformation and change. Additionally, I also explore the role that social networks play in making organisation and teams change ready.\n- Of particular interest to me is studying change and transformation in high growth ventures (start-ups).\n- I’m a Doctoral candidate at the Bayes Business School. My research explores the area of organisation transformation and change. Additionally, I also explore the role that social networks play in making organisation and teams change ready. - Of particular interest to me is studying change and transformation in high growth ventures (start-ups).\nActivity\nActivity\n3,425 followers\n3,425 followers\nPosts\nComments\nLoaded 9 Posts posts\nKabir M Joshi reposted this\nPermia Sensing\nPermia Sensing\n438 followers\n438 followers\n3w • \n 3 weeks ago • Visible to anyone on or off LinkedIn\nWe were honoured to be part of the UK-Karnataka innovation roundtable, showcasing tech that drives real world impact.\n\nThank you to theandfor hosting and supporting global collaboration.\n\n…more\nBritish High Commission in India\nBritish High Commission in India\n88,599 followers\n88,599 followers\nUK and Karnataka are harnessing the power of AI and cleantech to tackle global challenges – from sustainability to digital inclusion. At a roundtable co-hosted by the British Deputy High Commission in Bengaluru and, 15 cutting-edge start-ups from both regions showcased breakthrough solutions shaping a smarter, greener future.\n\nAs a proud Global Innovation Alliance partner, the UK is committed to supporting Karnataka’s thriving innovation ecosystem - driving inclusive growth, creating jobs, and enabling cross-border tech partnerships that deliver real-world impact.\n\n||||\n\nImages Credit:\n…more\nActivate to view larger image,\n1/4\nActivate to view larger image,\n20\n4 reposts\nKabir M Joshi reposted this\nPermia Sensing\nPermia Sensing\n438 followers\n438 followers\n3w • \n 3 weeks ago • Visible to anyone on or off LinkedIn\nAt Permia, we’re revolutionising palm tree management—empowering farmers with early, actionable insights to protect their crops, boost yields, and build resilience against pests and diseases. \n\nSee how our tech is changing the future of \nhashtag\n#Coconut, \nhashtag\n#Dates, \nhashtag\n#PalmOil and \nhashtag\n#ArecaNut farming👇\n\n\n\n…more\nPermia Sensing\nyoutube.com\n23\n4 reposts\nShow all posts\nExperience\nExperience\nMPhil - Management and Organisations (September 2022)\nMPhil - Management and Organisations (September 2022)\nBayes Business School · Full-time\nBayes Business School · Full-time\nOct 2021 - Present · 3 yrs 10 mos\nOct 2021 to Present · 3 yrs 10 mos\nQualitative Research, Change Management and +3 skills\nChief of Staff\nChief of Staff\nPermia Sensing · Part-time\nPermia Sensing · Part-time\nMar 2024 - Sep 2024 · 7 mos\nMar 2024 to Sep 2024 · 7 mos\nOn-site\nOn-site\nSupporting the CEO in the development and execution of 90 day plans \n \nWorking with the CTO to ensure a structured technology development \nroadmap is in place\n\nWorking with the CEO to execute strategic initiatives including the establishment of sales and operations in new markets.\n\nDriving operational efficiency by identifying and implementing process improvements\n\nActing as a liaison between operations, technology and management to ensure\nfocus on organisational objectives is maintained across all areas\nPeople and Culture\nPeople and Culture\nxto10x Technologies Pvt Ltd · Full-time\nxto10x Technologies Pvt Ltd · Full-time\nApr 2020 - Feb 2021 · 11 mos\nApr 2020 to Feb 2021 · 11 mos\nBengaluru, Karnataka, India\nBengaluru, Karnataka, India\n- People excellence consulting for India' top tier start ups in areas of Manager Development, \n Performance management, leadership effectiveness\n - Building internal HR practices to make xto10x one of the best places to work\n- Building people and culture products that aim to become the industry currency\nPerformance Management, Human Resource Development and +2 skills\nSummer Intern\nSummer Intern\nIntel Corporation\nIntel Corporation\nApr 2019 - May 2019 · 2 mos\nApr 2019 to May 2019 · 2 mos\nBengaluru, Karnataka, India\nBengaluru, Karnataka, India\nDiversity & Inclusion and Change Management\nField Intern\nField Intern\nYSC Consulting\nYSC Consulting\nJan 2019 - Feb 2019 · 2 mos\nJan 2019 to Feb 2019 · 2 mos\nMumbai Metropolitan Region\nMumbai Metropolitan Region\nPsychometrics, Organizational Psychology and +2 skills\nShow all 10 experiences\nEducation\nEducation\nBayes Business School\nBayes Business School\nMPhil - Management and Organisation, Organization behaviour\nMPhil - Management and Organisation, Organization behaviour\nOct 2021 - Sep 2022\nOct 2021 - Sep 2022\nTata Institute of Social Sciences\nTata Institute of Social Sciences\nMaster in Organisation Development, Change and Leadership, School of Management, TISS Mumbai\nMaster in Organisation Development, Change and Leadership, School of Management, TISS Mumbai\n2018 - 2020\n2018 - 2020\nGrade: 7.5/10\nGrade: 7.5/10\nPerformance Management, Leadership Development and +2 skills\nShow all 5 educations\nLicenses & certifications\nLicenses & certifications\nManaging Talent\nManaging Talent\nCoursera Course Certificates\nCoursera Course Certificates\nIssued Feb 2016\nIssued Feb 2016\nCredential ID JU65CBCRQA4Y\nCredential ID JU65CBCRQA4Y\nShow credential\nAdvanced Diploma in Wine and Spirits\nAdvanced Diploma in Wine and Spirits\nAdvanced Diploma in Wine and Spirits\nWSET — Wine & Spirit Education Trust\nWSET — Wine & Spirit Education Trust\nIssued Jan 2014\nIssued Jan 2014\nProjects\nProjects\nAnalyzing the performance appraisal system of hourly employees at ford India private limited.\nAnalyzing the performance appraisal system of hourly employees at ford India private limited.\nApr 2015 - Present\nApr 2015 - Present\nA qualitative analysis of Ford's performance management system.\nA qualitative analysis of Ford's performance management system.\nPsychological Contract-Towards Explicitness\nPsychological Contract-Towards Explicitness\nFeb 2015 - Present\nFeb 2015 - Present\nAssociated with Christ University, Bangalore\nAssociated with Christ University, Bangalore\nA Conceptual research paper aimed at developing a model for making Psychological contract explicit.\nA Conceptual research paper aimed at developing a model for making Psychological contract explicit.\nOther contributors\nOther contributors\nShow all 3 projects\nVolunteering\nVolunteering\nResearch Volunteer\nResearch Volunteer\nJanaagraha Centre for Citizenship and Democracy\nJanaagraha Centre for Citizenship and Democracy\nJun 2015 - Aug 2015 · 3 mos\nJun 2015 - Aug 2015 · 3 mos\nPolitics\nPolitics\nAs a Research volunteer,I Helped the organisation to carry out a pilot evaluation of their Civic Education Program titled \"Bala Janaagraha\"\nAs a Research volunteer,I Helped the organisation to carry out a pilot evaluation of their Civic Education Program titled \"Bala Janaagraha\"\nSkills\nSkills\nData Analysis\nData Analysis\nMPhil - Management and Organisations (September 2022) at Bayes Business School\nMPhil - Management and Organisations (September 2022) at Bayes Business School\n1 endorsement\n1 endorsement\nResearch Methods\nResearch Methods\nMPhil - Management and Organisations (September 2022) at Bayes Business School\nMPhil - Management and Organisations (September 2022) at Bayes Business School\n1 endorsement\n1 endorsement\nShow all 29 skills\nRecommendations\nRecommendations\nReceived\nReceived\nGiven\nGiven\nVernon Coelho\nVernon Coelho\nVernon Coelho\nHead of Department at Institute of Hotel Management\nHead of Department at Institute of Hotel Management\nJuly 21, 2016, Vernon was Kabir’s mentor\nJuly 21, 2016,Vernonwas Kabir’s mentor\nKabir was a student of mine and I am happy to write this recommendation for him. As a student, Kabir proved to be a sincere, dedicated and hardworking individual. He was extremely keen on Food and Beverages and took a deep interest in the subject. We often had lively debates and conversations on the subject. I am sure Kabir will be an asset to the organization he joins and I wish him the best in his career\nKabir was a student of mine and I am happy to write this recommendation for him. As a student, Kabir proved to be a sincere, dedicated and hardworking individual. He was extremely keen on Food and Beverages and took a deep interest in the subject. We often had lively debates and conversations on the subject. I am sure Kabir will be an asset to the organization he joins and I wish him the best in his career\n\n\n\n\nCourses\nCourses\nFinance For Non-Finance\nFinance For Non-Finance\nAssociated with Christ University, Bangalore\nAssociated with Christ University, Bangalore\nLanguages\nLanguages\nEnglish\nEnglish\nFull professional proficiency\nFull professional proficiency\nHindi\nHindi\nProfessional working proficiency\nProfessional working proficiency\nShow all 5 languages\nInterests\nInterests\nTop Voices\nTop Voices\nCompanies\nCompanies\nGroups\nGroups\nNewsletters\nNewsletters\nSchools\nSchools\nRaj Kunkolienkar\nRaj Kunkolienkar\nFree Agent | Prev. built Stoa, AltMBA for India\nFree Agent | Prev. built Stoa, AltMBA for India\n53,746 followers\n53,746 followers\nFollow\nNarendra Modi\nNarendra Modi\nPrime Minister of India\nPrime Minister of India\n4,842,668 followers\n4,842,668 followers\nFollow\nShow all Top Voices\nCauses\nCauses\nDisaster and Humanitarian Relief • Economic Empowerment • Politics • Social Services\nDisaster and Humanitarian Relief • Economic Empowerment • Politics • Social Services\nMore profiles for you\nMore profiles for you\nAndre Spicer\nAndre Spicer\n· 3rd+\n3rd+ degree connection\nExecutive Dean and Professor at Bayes Business School, City St George's, University of London.\nFollow\nDebjyoti Chakravorty\nDebjyoti Chakravorty\n· 3rd+\n3rd+ degree connection\nPhD Fellow in Management | Marginalized Workers, Poverty, Social Movements, Temporality (Imaginaries of Past & Future, Collective Memory), Narrative & History Reconstruction, Postcolonialism, Ethnography\nMessage\nDr Helen Tracey\nDr Helen Tracey\n· 3rd+\n3rd+ degree connection\nInterim Deputy Head of Leadership and HRM Department Assistant Professor in LHRM at Northumbria University\nMessage\nRose Mibu\nRose Mibu\n· 3rd+\n3rd+ degree connection\nMSc in Strategic Marketing Student - Imperial College Business School\nFollow\nAkane Vallery Uchida, CAIA®\nAkane Vallery Uchida, CAIA®\n· 3rd+\n3rd+ degree connection\nGerman/Japanese doctoral researcher in Management (Entrepreneurship) | Alternative investments and financial markets experience\nMessage\nShow all\nPeople you may know\nPeople you may know\nFrom Kabir's school\nFrom Kabir's school\nNaveed Khan\nNaveed Khan\n--\n--\nConnect\nAmma Abora\nAmma Abora\nFOUNDER || CEO AIDE CHEMISTS LTD || PHARMACY RETAIL CONSULTANT || SUPPLY CHAIN EXPERT || SPEAKER\nConnect\nRaul Filipe Diniz\nRaul Filipe Diniz\nDirector da Direcção de Mercados Financeiros no Banco SOL\nConnect\nAaryan Garg\nAaryan Garg\nStudent at Bayes Business School, London\nStudent at Bayes Business School, London\nConnect\nMikaela Christofi\nMikaela Christofi\nGlobal Sales Internship at Aleph Group\nGlobal Sales Internship at Aleph Group\nConnect\nShow all\nYou might like\nYou might like\nPages for you\nPages for you\nSciAstra\nSciAstra\nE-Learning Providers\nE-Learning Providers\n37,215 followers\n37,215 followers\nFollow\nAcademic Careers - Engineering Faculty jobs\nAcademic Careers - Engineering Faculty jobs\nEducation\nEducation\n11,593 followers\n11,593 followers\nFollow\nShow all\nAbout\nAccessibility\nTalent Solutions\nProfessional Community Policies\nCareers\nMarketing Solutions\nPrivacy & Terms\nAd Choices\nAdvertising\nSales Solutions\nMobile\nSmall Business\nSafety Center\nQuestions?\nVisit our Help Center.\nManage your account and privacy\nGo to your Settings.\nRecommendation transparency\nLearn more about Recommended Content.\nSelect Language\n         العربية (Arabic)\n         বাংলা (Bangla)\n         Čeština (Czech)\n         Dansk (Danish)\n         Deutsch (German)\n         Ελληνικά (Greek)\n         English (English)\n         Español (Spanish)\n         فارسی (Persian)\n         Suomi (Finnish)\n         Français (French)\n         हिंदी (Hindi)\n         Magyar (Hungarian)\n         Bahasa Indonesia (Indonesian)\n         Italiano (Italian)\n         עברית (Hebrew)\n         日本語 (Japanese)\n         한국어 (Korean)\n         मराठी (Marathi)\n         Bahasa Malaysia (Malay)\n         Nederlands (Dutch)\n         Norsk (Norwegian)\n         ਪੰਜਾਬੀ (Punjabi)\n         Polski (Polish)\n         Português (Portuguese)\n         Română (Romanian)\n         Русский (Russian)\n         Svenska (Swedish)\n         తెలుగు (Telugu)\n         ภาษาไทย (Thai)\n         Tagalog (Tagalog)\n         Türkçe (Turkish)\n         Українська (Ukrainian)\n         Tiếng Việt (Vietnamese)\n         简体中文 (Chinese (Simplified))\n         正體中文 (Chinese (Traditional))\n     LinkedIn Corporation © 2025\nStatus is online\nMessaging\nYou are on the messaging overlay. Press enter to open the list of conversations.\nCompose message\nYou are on the messaging overlay. Press enter to open the list of conversations.",
  "skills_text": "0 notifications total\nnew feed updates notifications\nHome\n1\n1 new network update notification\nMy Network\nJobs\nMessaging\nNotifications\nMe\nFor Business\nTry Premium for ₹0\nKabir M Joshi\nMPhil at Bayes Business School| Previously helping start-ups Scale at xto10x\nMore\nFollow\nMessage\nSkills\nAll\nIndustry Knowledge\nTools & Technologies\nInterpersonal Skills\nLanguages\nData Analysis\nData Analysis\nMPhil - Management and Organisations (September 2022) at Bayes Business School\nMPhil - Management and Organisations (September 2022) at Bayes Business School\n1 endorsement\n1 endorsement\nResearch Methods\nResearch Methods\nMPhil - Management and Organisations (September 2022) at Bayes Business School\nMPhil - Management and Organisations (September 2022) at Bayes Business School\n1 endorsement\n1 endorsement\nQuantitative Data\nQuantitative Data\nMPhil - Management and Organisations (September 2022) at Bayes Business School\nMPhil - Management and Organisations (September 2022) at Bayes Business School\n1 endorsement\n1 endorsement\nDiversity & Inclusion\nDiversity & Inclusion\nSummer Intern at Intel Corporation\nSummer Intern at Intel Corporation\n1 endorsement\n1 endorsement\nPsychometrics\nPsychometrics\nField Intern at YSC Consulting\nField Intern at YSC Consulting\n1 endorsement\n1 endorsement\nOrganizational Psychology\nOrganizational Psychology\nField Intern at YSC Consulting\nField Intern at YSC Consulting\n1 endorsement\n1 endorsement\nLeadership Development\nLeadership Development\n3 experiences across xto10x Technologies Pvt Ltd and 2 other companies\n3 experiences across xto10x Technologies Pvt Ltd and 2 other companies\nTata Institute of Social Sciences\nTata Institute of Social Sciences\nOrganizational Culture\nOrganizational Culture\n3 experiences across xto10x Technologies Pvt Ltd and 2 other companies\n3 experiences across xto10x Technologies Pvt Ltd and 2 other companies\nTata Institute of Social Sciences\nTata Institute of Social Sciences\nPerformance Management\nPerformance Management\nPeople and Culture at xto10x Technologies Pvt Ltd\nPeople and Culture at xto10x Technologies Pvt Ltd\nTata Institute of Social Sciences\nTata Institute of Social Sciences\nHuman Resource Development\nHuman Resource Development\n3 experiences across xto10x Technologies Pvt Ltd and 1 other company\n3 experiences across xto10x Technologies Pvt Ltd and 1 other company\n2 educational experiences at Tata Institute of Social Sciences and 1 other school\n2 educational experiences at Tata Institute of Social Sciences and 1 other school\nQualitative Research\nQualitative Research\nMPhil - Management and Organisations (September 2022) at Bayes Business School\nMPhil - Management and Organisations (September 2022) at Bayes Business School\nChange Management\nChange Management\n2 experiences across Bayes Business School and 1 other company\n2 experiences across Bayes Business School and 1 other company\nHuman Resources\nHuman Resources\n9 endorsements\n9 endorsements\nHospitality\nHospitality\n3 endorsements\n3 endorsements\nLeadership\nLeadership\n8 endorsements\n8 endorsements\nBusiness Management\nBusiness Management\n2 endorsements\n2 endorsements\nOrganizational Development\nOrganizational Development\n4 endorsements\n4 endorsements\nTeamwork\nTeamwork\n5 endorsements\n5 endorsements\nHospitality Management\nHospitality Management\n1 endorsement\n1 endorsement\nCustomer Service\nCustomer Service\n4 endorsements\n4 endorsements\nMicrosoft Office\nMicrosoft Office\n8 endorsements\n8 endorsements\nMicrosoft Word\nMicrosoft Word\n3 endorsements\n3 endorsements\nPowerPoint\nPowerPoint\n3 endorsements\n3 endorsements\nMicrosoft Excel\nMicrosoft Excel\n1 endorsement\n1 endorsement\nSocial Media\nSocial Media\n2 endorsements\n2 endorsements\nEnglish\nEnglish\n1 endorsement\n1 endorsement\nTalent Management\nTalent Management\n4 endorsements\n4 endorsements\nTeam Management\nTeam Management\n7 endorsements\n7 endorsements\nHospitality Industry\nHospitality Industry\nMore profiles for you\nMore profiles for you\nAndre Spicer\nAndre Spicer\n· 3rd+\n3rd+ degree connection\nExecutive Dean and Professor at Bayes Business School, City St George's, University of London.\nFollow\nDebjyoti Chakravorty\nDebjyoti Chakravorty\n· 3rd+\n3rd+ degree connection\nPhD Fellow in Management | Marginalized Workers, Poverty, Social Movements, Temporality (Imaginaries of Past & Future, Collective Memory), Narrative & History Reconstruction, Postcolonialism, Ethnography\nMessage\nDr Helen Tracey\nDr Helen Tracey\n· 3rd+\n3rd+ degree connection\nInterim Deputy Head of Leadership and HRM Department Assistant Professor in LHRM at Northumbria University\nMessage\nRose Mibu\nRose Mibu\n· 3rd+\n3rd+ degree connection\nMSc in Strategic Marketing Student - Imperial College Business School\nFollow\nAkane Vallery Uchida, CAIA®\nAkane Vallery Uchida, CAIA®\n· 3rd+\n3rd+ degree connection\nGerman/Japanese doctoral researcher in Management (Entrepreneurship) | Alternative investments and financial markets experience\nMessage\nShow more\nAbout\nAccessibility\nTalent Solutions\nProfessional Community Policies\nCareers\nMarketing Solutions\nPrivacy & Terms\nAd Choices\nAdvertising\nSales Solutions\nMobile\nSmall Business\nSafety Center\nQuestions?\nVisit our Help Center.\nManage your account and privacy\nGo to your Settings.\nRecommendation transparency\nLearn more about Recommended Content.\nSelect Language\n         العربية (Arabic)\n         বাংলা (Bangla)\n         Čeština (Czech)\n         Dansk (Danish)\n         Deutsch (German)\n         Ελληνικά (Greek)\n         English (English)\n         Español (Spanish)\n         فارسی (Persian)\n         Suomi (Finnish)\n         Français (French)\n         हिंदी (Hindi)\n         Magyar (Hungarian)\n         Bahasa Indonesia (Indonesian)\n         Italiano (Italian)\n         עברית (Hebrew)\n         日本語 (Japanese)\n         한국어 (Korean)\n         मराठी (Marathi)\n         Bahasa Malaysia (Malay)\n         Nederlands (Dutch)\n         Norsk (Norwegian)\n         ਪੰਜਾਬੀ (Punjabi)\n         Polski (Polish)\n         Português (Portuguese)\n         Română (Romanian)\n         Русский (Russian)\n         Svenska (Swedish)\n         తెలుగు (Telugu)\n         ภาษาไทย (Thai)\n         Tagalog (Tagalog)\n         Türkçe (Turkish)\n         Українська (Ukrainian)\n         Tiếng Việt (Vietnamese)\n         简体中文 (Chinese (Simplified))\n         正體中文 (Chinese (Traditional))\n     LinkedIn Corporation © 2025\nStatus is online\nMessaging\nYou are on the messaging overlay. Press enter to open the list of conversations.\nCompose message\nYou are on the messaging overlay. Press enter to open the list of conversations.",
  "scraped_at": "2025-07-23 01:48:35",
  "has_skills": true,
  "cleaned_profile": {
    "name": "Kabir M Joshi",
    "profile_url": "https://uk.linkedin.com/in/kabirmjoshi",
    "current_position": {
      "title": "MPhil - Management and Organisations",
      "company": "Bayes Business School",
      "location": "London, England, United Kingdom",
      "start_date": "Oct 2021",
      "end_date": "Present",
      "duration": "3 yrs 10 mos"
    },
    "previous_positions": [
      {
        "title": "Chief of Staff",
        "company": "Permia Sensing",
        "location": "On-site",
        "start_date": "Mar 2024",
        "end_date": "Sep 2024",
        "duration": "7 mos"
      },
      {
        "title": "People and Culture",
        "company": "xto10x Technologies Pvt Ltd",
        "location": "Bengaluru, Karnataka, India",
        "start_date": "Apr 2020",
        "end_date": "Feb 2021",
        "duration": "11 mos"
      },
      {
        "title": "Summer Intern",
        "company": "Intel Corporation",
        "location": "Bengaluru, Karnataka, India",
        "start_date": "Apr 2019",
        "end_date": "May 2019",
        "duration": "2 mos"
      },
      {
        "title": "Field Intern",
        "company": "YSC Consulting",
        "location": "Mumbai Metropolitan Region",
        "start_date": "Jan 2019",
        "end_date": "Feb 2019",
        "duration": "2 mos"
      }
    ],
    "education": [
      {
        "institution": "Bayes Business School",
        "degree": "MPhil - Management and Organisation",
        "field_of_study": "Organization behaviour",
        "years_attended": "Oct 2021 - Sep 2022"
      },
      {
        "institution": "Tata Institute of Social Sciences",
        "degree": "Master in Organisation Development, Change and Leadership",
        "field_of_study": "School of Management, TISS Mumbai",
        "years_attended": "2018 - 2020"
      }
    ],
    "connections": "500+",
    "followers": 3425,
    "skills": [
      "Data Analysis",
      "Research Methods",
      "Quantitative Data",
      "Diversity & Inclusion",
      "Psychometrics",
      "Organizational Psychology",
      "Leadership Development",
      "Organizational Culture",
      "Performance Management",
      "Human Resource Development",
      "Qualitative Research",
      "Change Management",
      "Human Resources",
      "Hospitality",
      "Leadership",
      "Business Management",
      "Organizational Development",
      "Teamwork",
      "Hospitality Management",
      "Customer Service",
      "Microsoft Office",
      "Microsoft Word",
      "PowerPoint",
      "Microsoft Excel",
      "Social Media",
      "English",
      "Talent Management",
      "Team Management",
      "Hospitality Industry"
    ],
    "interests": [
      "Permia Sensing",
      "British High Commission in India",
      "Raj Kunkolienkar",
      "Narendra Modi"
    ]
  },
  "tokens_used": {
    "prompt_tokens": 4689,
    "completion_tokens": 709,
    "total_tokens": 5398
  }
}