{
  "url": "https://in.linkedin.com/in/prateek-dasgupta-28a353124",
  "raw_text": "0 notifications total\nnew feed updates notifications\nHome\n1\n1 new network update notification\nMy Network\nJobs\nMessaging\nNotifications\nMe\nFor Business\nTry Premium for ₹0\nPrateek Dasgupta\nPartnerships, Content, 0-to-1 | xto10x . upGrad . BITS Pilani\nxto10x\nBirla Institute of Technology and Science, Pilani\nBengaluru, Karnataka, India Contact info\nxto10x.com\n500+ connections\nMessage\nFollow\nMore\nAbout\nAbout\nBuilding startup learning products has shown me what works—and what doesn't work—from launching new ideas to scaling them up. Working side by side with passionate operators, I’ve gained firsthand insight into solving problem creatively, crafting content that speaks to real needs, and designing partnerships that truly move ideas forward\nBuilding startup learning products has shown me what works—and what doesn't work—from launching new ideas to scaling them up. Working side by side with passionate operators, I’ve gained firsthand insight into solving problem creatively, crafting content that speaks to real needs, and designing partnerships that truly move ideas forward\nActivity\nActivity\n6,562 followers\n6,562 followers\nPosts\nComments\nLoaded 9 Posts posts\nPrateek Dasgupta\nPrateek Dasgupta\n   • 3rd+\nVerified • 3rd+\nPartnerships, Content, 0-to-1 | xto10x . upGrad . BITS Pilani\nPartnerships, Content, 0-to-1 | xto10x . upGrad . BITS Pilani\n1mo • \n 1 month ago • Visible to anyone on or off LinkedIn\nIt’s been a true privilege to contribute to the vision of transforming the entrepreneurial landscape of Saudi Arabia\n\nHonored to work alongside inspiring partners and bold founders to bring the very first cohort of the xto10x-Tomoh program to life.\n\nA heartfelt thank you tofor trusting us with this mission, and to,andfor being such dedicated partners throughout\n\nGrateful as always to, especiallyandfor the collaboration and belief.\n\nCan’t wait to see what the future holds! 🚀\n…more\nEng. Abdulrahman Alsmail\nEng. Abdulrahman Alsmail\nEng. Abdulrahman Alsmail\n   • 3rd+\nVerified • 3rd+\nGeneral Manager of Enterprises Growth at MonshaatSA\nGeneral Manager of Enterprises Growth at MonshaatSA\nضمن برنامج طموح لدعم الشركات متسارعة النمو، نفذنا مؤخرًا برنامجين مميزين بالشراكة مع Endeavor Saudi Arabia :\n\n🔹 Scaling Founders by\n\n🔹 Scaling Companies by\n\nواختتمنا البرنامجين بلقاء مشترك مع سعادة محافظ منشآت، حيث شاركت المنشآت المستفيدة تجاربها وإنجازاتها، وناقشنا أبرز التحديات والفرص التي تسهم في استدامة نموها.\n\nهذه اللقاءات تعكس إيماننا بأهمية التمكين المباشر، وخلق بيئة تفاعلية بين رواد الأعمال والجهات الداعمة لتسريع رحلة النمو والتوسع.\n\nكل الشكر لشركائنا، وللمنشآت الملهمة التي كانت جزءًا من هذه التجربة.\n\nكل الشكر لقيادات انديفورو\nوقيادات البرنامج\nشكر خاص لمدير المشروععلى كافة جهودها خلال فترة ست شهور وعلى قيادته للملف بنجاح وتحقيق الاثر.\nونتطلع إلى مواصلة دعم المزيد من قصص النجاح 💼🚀\n\n#\n…more\nShow translation\nActivate to view larger image,\n1/3\nActivate to view larger image,\n17\n2 comments\nPrateek Dasgupta reposted this\nHamza Al Swayyed, MSCs, CMP, CILT\nHamza Al Swayyed, MSCs, CMP, CILT\n   • 3rd+\nVerified • 3rd+\nBusiness Growth |Business Development |High Growth Enterprise | Market Expansion |Business Consultant | Business Investment |\nBusiness Growth |Business Development |High Growth Enterprise | Market Expansion |Business Consultant | Business Investment |\n1mo • Edited • \n 1 month ago • Edited • Visible to anyone on or off LinkedIn\nAs part of the Tomoh Program to support high-growth companies, we were proud to oversee the implementation of two impactful programs in collaboration with\nSaudi Arabia:\n\n🔹 Scaling Founders in partnership with the\nfor Creative Leadership\n🔹 Scaling Companies in collaboration with\n\n\nThe programs concluded with an inspiring session attended by H.E. the Governor of Monsha’at, where participating companies shared their growth journeys, achievements, and discussed key challenges and opportunities for sustainable scaling. These initiatives reflect our belief in the power of direct enablement and in creating interactive platforms that connect entrepreneurs with ecosystem partners to accelerate growth and expansion.\n\nGrateful for the inspiring companies that took part in this journey, and deeply appreciate all our partners who contributed to the success of these programs. A special thanks to everyone involved in the design and delivery of this impactful experience and heartfelt appreciation for the strategic guidance that helped shape the outcomes\n\nIt was a pleasure to oversee this effort as part of the Tomoh team, and we look forward to supporting more success stories in the future 🚀\n\nSpecial thanks tofor his invaluable strategic guidance.\n\n\n…more\nActivate to view larger image,\n1/4\nActivate to view larger image,\n81\n1 repost\nShow all posts\nExperience\nExperience\nxto10x\nxto10x\nFull-time · 3 yrs 5 mos\nFull-time · 3 yrs 5 mos\nInternationalisation\nInternationalisation\nFeb 2024 - Present · 1 yr 6 mos\nFeb 2024 to Present · 1 yr 6 mos\nBangalore Urban, Karnataka, India\nBangalore Urban, Karnataka, India\nBig wins:\n1. Renewed our contract for the Saudi Unicorns Program in 2024 after a successful 2023 run.\n2. Secured a contract with Monshaat, the Saudi govt agency that supports small businesses and entrepreneurship\nProgram Manager - Saudi Unicorns Program\nProgram Manager - Saudi Unicorns Program\nJul 2023 - Feb 2024 · 8 mos\nJul 2023 to Feb 2024 · 8 mos\nBengaluru, Karnataka, India\nBengaluru, Karnataka, India\nLed the end-to-end delivery of the Saudi Unicorns Program (>>$1Mn partnership)—an initiative by the Saudi govt to enable 35 of their top startups toward achieving unicorn status\n(More about the program - https://saudiunicorns.net/en)\n\n- Orchestrated the delivery of 14+ founder masterclasses, 65+ 1:1 mentoring sessions with startup operators, and 33 operating engagements. The outcome was an NPS of 92\n\n- Managed key relationships with Misk (non-profit government body) and Endeavor (Saudi partner); coordinated with cross-functional teams like OKRs, Customer Experience, Operations, Academy, and People Excellence to ensure seamless execution\nBuilding Learning Products (Founder's Academy, Leadership Quotient, IIMB Partnership, B2C products)\nBuilding Learning Products (Founder's Academy, Leadership Quotient, IIMB Partnership, B2C products)\nMar 2022 - Jul 2023 · 1 yr 5 mos\nMar 2022 to Jul 2023 · 1 yr 5 mos\nBangalore Urban, Karnataka, India\nBangalore Urban, Karnataka, India\nFounder's Academy\n- What: Founder-focused masterclasses on 10 scaling pillars (xto10x framework)\n- Impact: 100+ founders graduated; 1 in 3 became unicorns, portfolio growth of ~10-12x. Notable alumni include Razorpay, Groww, Licious, Wakefit, Rapido and more\n- My Role: Collaborated with startup operators (scaling 500+ startups) to develop playbooks and case studies\n\nLeadership Quotient\n- What: 360° feedback tool to improve leaders's effectiveness\n- Impact: The tools has helped 700+ leaders in India, SEA and MENA get a comprehensive overview of their strengths and improvement areas\n- My role: Coded the software that instantly generates personalized reports using survey data\n\nIIMB Partnership\n- Partnered with IIMB Bangalore to co-create a course for students. Featured speakers from Flipkart, Licious, PhonePe, and Curefoods\n- Impact: 4.79/5 session rating. NPS of 60+\n- My role: Program managed the initiative and later transformed it into a standalone learning product\n\nB2C Products\n-Designed a full-cycle process from planning to post-production (converting office space into studio, onboarded 3PL editors, etc). Produced videos at cost of ~20k per hour of video,industry benchmark is ~1L per hour\n- Repurposed IIMB recordings into a B2C product. Achieved 500+ course signups and a 4.79/5 rating\n- Launched \"The Startup Insiders\" brand, grew the followership to 1000+\n- Produced marketing videos to drive enrollment in our products (Sample: https://www.youtube.com/watch?v=ppdSX5dkOho)\nSenior Associate- Product Strategy - ML/AI products\nSenior Associate- Product Strategy - ML/AI products\nupGrad · Full-time\nupGrad · Full-time\nAug 2020 - Mar 2022 · 1 yr 8 mos\nAug 2020 to Mar 2022 · 1 yr 8 mos\nMumbai Area, India\nMumbai Area, India\nWorked with cross-functional teams of delivery, technology, and production to create AI & ML tracks for 1000+ learners with >4.75/5 ratings\nWorked with cross-functional teams of delivery, technology, and production to create AI & ML tracks for 1000+ learners with >4.75/5 ratings\nSummer Intern at Ethane Gas Cracking Complex, Dahej (500 ktpa Ethylene Plant)\nSummer Intern at Ethane Gas Cracking Complex, Dahej (500 ktpa Ethylene Plant)\nReliance Industries Limited\nReliance Industries Limited\nMay 2019 - Jul 2019 · 3 mos\nMay 2019 to Jul 2019 · 3 mos\nGujarat, India\nGujarat, India\nPerformed an assessment of the refractory losses in the furnaces and estimated the annual refractory loss in terms of fuel gas loss and presented my findings to a panel of technical heads for improving the thermal efficiency and reducing the losses.\nIndira Gandhi Centre for Atomic Research (IGCAR) logo\nSummer Research Intern\nSummer Research Intern\nIndira Gandhi Centre for Atomic Research (IGCAR)\nIndira Gandhi Centre for Atomic Research (IGCAR)\nMay 2018 - Jul 2018 · 3 mos\nMay 2018 to Jul 2018 · 3 mos\nIndia\nIndia\nInvestigated the mean drop size and hold-up in an Asymmetric Rotating Disc Column (ARDC) to study the effect of agitator speed, and phase velocities on the hydrodynamic parameters\nInvestigated the mean drop size and hold-up in an Asymmetric Rotating Disc Column (ARDC) to study the effect of agitator speed, and phase velocities on the hydrodynamic parameters\nEducation\nEducation\nBirla Institute of Technology and Science, Pilani\nBirla Institute of Technology and Science, Pilani\nBachelor’s Degree, Chemical Engineering\nBachelor’s Degree, Chemical Engineering\n2016 - 2020\n2016 - 2020\nGrade: 8.79/10\nGrade: 8.79/10\nBirla Institute of Technology and Science, Pilani\nBirla Institute of Technology and Science, Pilani\nMinor, Data Science\nMinor, Data Science\n2018 - 2019\n2018 - 2019\nGrade: 8.04/10\nGrade: 8.04/10\nActivities and societies: \nActivities and societies:\nShow all 4 educations\nLicenses & certifications\nLicenses & certifications\nDeep Learning A-Z™: Hands-On Artificial Neural Networks\nDeep Learning A-Z™: Hands-On Artificial Neural Networks\nUdemy\nUdemy\nIssued Aug 2019\nIssued Aug 2019\nCredential ID UC-YZ414N6W\nCredential ID UC-YZ414N6W\nShow credential\nProjects\nProjects\nCredit Card Fraud Detection\nCredit Card Fraud Detection\nNov 2018 - Dec 2019\nNov 2018 - Dec 2019\nAssociated with Birla Institute of Technology and Science, Pilani\nAssociated with Birla Institute of Technology and Science, Pilani\nSelf-Organizing Maps, DBSCAN\n------------------------\n✔Programmed a Self-Organizing Map (build on the idea of k-nearest neighbours) to filter potential credit card frauds using outlier detection\nImplemented the DBSCAN (Density-based spatial clustering of applications with noise) on the same dataset for outlier detection\nPower Prediction in a Combined Cycle Power Plant\nPower Prediction in a Combined Cycle Power Plant\nJul 2019 - Nov 2019\nJul 2019 - Nov 2019\nAssociated with Birla Institute of Technology and Science, Pilani\nAssociated with Birla Institute of Technology and Science, Pilani\n● Primary Objective:- Predicting the electric power in a CCPP using a model that can generate better accuracy compared to other traditional models results without being computationally expensive.\n● Solution: - Built an Extreme Learning Machine model (a novel fast learning algorithm) that was able to generate better results compared to traditional ML algorithms and MLPs. The model had an overall R2 of 0.925 and an RMSE of 4.121\n● Mentor:- Dr. Rajesh Kumar Tripathy, Assistant Professor, EEE Department, Birla Institute of Technology and Science (BITS) Pilani\nShow all 6 projects\nVolunteering\nVolunteering\nAssociation of Chemical Engineers logo\nPresident\nPresident\nAssociation of Chemical Engineers\nAssociation of Chemical Engineers\nMay 2018 - May 2019 · 1 yr 1 mo\nMay 2018 - May 2019 · 1 yr 1 mo\nEducation\nEducation\nMember\nMember\nMember\nATMOS'18 Fest Organising Body, techno-management fest of BITS Pilani Hyderabad Campus \nATMOS'18 Fest Organising Body, techno-management fest of BITS Pilani Hyderabad Campus\nMay 2018 - Oct 2018 · 6 mos\nMay 2018 - Oct 2018 · 6 mos\nEducation\nEducation\nSkills\nSkills\nMicrosoft Office\nMicrosoft Office\n4 endorsements\n4 endorsements\nManagement\nManagement\n4 endorsements\n4 endorsements\nShow all 26 skills\nRecommendations\nRecommendations\nReceived\nReceived\nGiven\nGiven\nNothing to see for now\nNothing to see for now\nRecommendations that Prateek receives will appear here.\nRecommendations thatPrateekreceives will appear here.\nCourses\nCourses\nApplied Statistical Methods\nApplied Statistical Methods\n9/10\n9/10\nAssociated with Birla Institute of Technology and Science, Pilani\nAssociated with Birla Institute of Technology and Science, Pilani\nCorrosion Engineering\nCorrosion Engineering\nOngoing\nOngoing\nAssociated with Birla Institute of Technology and Science, Pilani\nAssociated with Birla Institute of Technology and Science, Pilani\nShow all 11 courses\nLanguages\nLanguages\nBengali\nBengali\nNative or bilingual proficiency\nNative or bilingual proficiency\nEnglish\nEnglish\nProfessional working proficiency\nProfessional working proficiency\nShow all 3 languages\nInterests\nInterests\nTop Voices\nTop Voices\nCompanies\nCompanies\nGroups\nGroups\nNewsletters\nNewsletters\nSchools\nSchools\nRiya Gadhwal\nRiya Gadhwal\nAnalyst, American Express | Linkedin Top Voice | LinkedIn 190 K + | HPAIR Harvard'23,Asia'23 |100+ MUNs | Guest Speaker at IIT,IIM,DU | Taught 20,000+ Students | Head, Marketing Club'22 | SIU'23 |\nAnalyst, American Express | Linkedin Top Voice | LinkedIn 190 K + | HPAIR Harvard'23,Asia'23 |100+ MUNs | Guest Speaker at IIT,IIM,DU | Taught 20,000+ Students | Head, Marketing Club'22 | SIU'23 |\n190,110 followers\n190,110 followers\nFollow\nNishchal Jain\nNishchal Jain\nInvestor | Performance & Content Marketing | Educator\nInvestor | Performance & Content Marketing | Educator\n11,932 followers\n11,932 followers\nFollow\nShow all Top Voices\nMore profiles for you\nMore profiles for you\nPuneet Gupta\nPuneet Gupta\n· 3rd+\n3rd+ degree connection\nCertified Leadership Coach | Fractional CTO | Prod/Engg Advisor | Author | Storyteller | Comms Coach | Innovator | Strategy Consultant | Team Workshops\nFollow\nShantanu Jaiswal\nShantanu Jaiswal\n· 3rd+\n3rd+ degree connection\nHelping Startups Scale | Customer Success Manager | Ex- Pixis\nMessage\nRahul Jagannathan\nRahul Jagannathan\n· 3rd+\n3rd+ degree connection\nPeople Practice at xto10x | Leadership roles in startups | ICF Credentialed Coach | Hogan Certified | Music Hobbyist\nMessage\nTanmay A.\nTanmay A.\n· 3rd+\n3rd+ degree connection\nProduct @ xto10x | Helping startups scale smarter\nProduct @ xto10x | Helping startups scale smarter\nMessage\nGaurav Choudhary\nGaurav Choudhary\n· 3rd+\n3rd+ degree connection\nProduct Leader @ xto10x | Ex Myntra | Ex OLA | IIT Kanpur\nProduct Leader @ xto10x | Ex Myntra | Ex OLA | IIT Kanpur\nFollow\nShow all\nPeople you may know\nPeople you may know\nFrom Prateek's school\nFrom Prateek's school\nTumushime Yvette\nTumushime Yvette\nAfrican Leadership University\nAfrican Leadership University\nConnect\nbrian Kemboi\nbrian Kemboi\nStudent at University of Oxford\nStudent at University of Oxford\nConnect\nعبدالغفار عيد\nعبدالغفار عيد\nعبدالغفار عيد\n--\n--\nConnect\nMohamed Osman\nMohamed Osman\nطالب في جامعة آلملك سليمان الدوليه\nطالب في جامعة آلملك سليمان الدوليه\nConnect\nMonica Waithira\nMonica Waithira\nSoftware Programmer at Keeta\nSoftware Programmer at Keeta\nConnect\nShow all\nYou might like\nYou might like\nPages for you\nPages for you\nSciAstra\nSciAstra\nE-Learning Providers\nE-Learning Providers\n37,215 followers\n37,215 followers\nFollow\nAcademic Careers - Engineering Faculty jobs\nAcademic Careers - Engineering Faculty jobs\nEducation\nEducation\n11,593 followers\n11,593 followers\nFollow\nShow all\nAbout\nAccessibility\nTalent Solutions\nProfessional Community Policies\nCareers\nMarketing Solutions\nPrivacy & Terms\nAd Choices\nAdvertising\nSales Solutions\nMobile\nSmall Business\nSafety Center\nQuestions?\nVisit our Help Center.\nManage your account and privacy\nGo to your Settings.\nRecommendation transparency\nLearn more about Recommended Content.\nSelect Language\n         العربية (Arabic)\n         বাংলা (Bangla)\n         Čeština (Czech)\n         Dansk (Danish)\n         Deutsch (German)\n         Ελληνικά (Greek)\n         English (English)\n         Español (Spanish)\n         فارسی (Persian)\n         Suomi (Finnish)\n         Français (French)\n         हिंदी (Hindi)\n         Magyar (Hungarian)\n         Bahasa Indonesia (Indonesian)\n         Italiano (Italian)\n         עברית (Hebrew)\n         日本語 (Japanese)\n         한국어 (Korean)\n         मराठी (Marathi)\n         Bahasa Malaysia (Malay)\n         Nederlands (Dutch)\n         Norsk (Norwegian)\n         ਪੰਜਾਬੀ (Punjabi)\n         Polski (Polish)\n         Português (Portuguese)\n         Română (Romanian)\n         Русский (Russian)\n         Svenska (Swedish)\n         తెలుగు (Telugu)\n         ภาษาไทย (Thai)\n         Tagalog (Tagalog)\n         Türkçe (Turkish)\n         Українська (Ukrainian)\n         Tiếng Việt (Vietnamese)\n         简体中文 (Chinese (Simplified))\n         正體中文 (Chinese (Traditional))\n     LinkedIn Corporation © 2025\nStatus is online\nMessaging\nYou are on the messaging overlay. Press enter to open the list of conversations.\nCompose message\nYou are on the messaging overlay. Press enter to open the list of conversations.",
  "skills_text": "0 notifications total\nnew feed updates notifications\nHome\n1\n1 new network update notification\nMy Network\nJobs\nMessaging\nNotifications\nMe\nFor Business\nTry Premium for ₹0\nPrateek Dasgupta\nPartnerships, Content, 0-to-1 | xto10x . upGrad . BITS Pilani\nMore\nFollow\nMessage\nSkills\nAll\nIndustry Knowledge\nTools & Technologies\nInterpersonal Skills\nMicrosoft Office\nMicrosoft Office\n4 endorsements\n4 endorsements\nManagement\nManagement\n4 endorsements\n4 endorsements\nMicrosoft Excel\nMicrosoft Excel\n2 endorsements\n2 endorsements\nMicrosoft Word\nMicrosoft Word\n1 endorsement\n1 endorsement\nLeadership\nLeadership\n2 endorsements\n2 endorsements\nMicrosoft PowerPoint\nMicrosoft PowerPoint\n2 endorsements\n2 endorsements\nResearch\nResearch\n2 endorsements\n2 endorsements\nPublic Speaking\nPublic Speaking\n1 endorsement\n1 endorsement\nKeras\nKeras\nTensorFlow\nTensorFlow\nMachine Learning\nMachine Learning\nPassed LinkedIn Skill Assessment\nPassed LinkedIn Skill Assessment\n2 endorsements\n2 endorsements\nDeep Learning\nDeep Learning\nSPSS\nSPSS\nMatlab\nMatlab\n1 endorsement\n1 endorsement\nScikit-Learn\nScikit-Learn\nStatistical Data Analysis\nStatistical Data Analysis\nStatistics\nStatistics\nLogistic Regression\nLogistic Regression\nCluster Analysis\nCluster Analysis\nPython (Programming Language)\nPython (Programming Language)\nPassed LinkedIn Skill Assessment\nPassed LinkedIn Skill Assessment\nData Science\nData Science\nData Analysis\nData Analysis\nTeam Leadership\nTeam Leadership\nChemical Engineering\nChemical Engineering\nChemical Process Engineering\nChemical Process Engineering\nChemical Industry\nChemical Industry\nMore profiles for you\nMore profiles for you\nPuneet Gupta\nPuneet Gupta\n· 3rd+\n3rd+ degree connection\nCertified Leadership Coach | Fractional CTO | Prod/Engg Advisor | Author | Storyteller | Comms Coach | Innovator | Strategy Consultant | Team Workshops\nFollow\nShantanu Jaiswal\nShantanu Jaiswal\n· 3rd+\n3rd+ degree connection\nHelping Startups Scale | Customer Success Manager | Ex- Pixis\nMessage\nRahul Jagannathan\nRahul Jagannathan\n· 3rd+\n3rd+ degree connection\nPeople Practice at xto10x | Leadership roles in startups | ICF Credentialed Coach | Hogan Certified | Music Hobbyist\nMessage\nTanmay A.\nTanmay A.\n· 3rd+\n3rd+ degree connection\nProduct @ xto10x | Helping startups scale smarter\nProduct @ xto10x | Helping startups scale smarter\nMessage\nGaurav Choudhary\nGaurav Choudhary\n· 3rd+\n3rd+ degree connection\nProduct Leader @ xto10x | Ex Myntra | Ex OLA | IIT Kanpur\nProduct Leader @ xto10x | Ex Myntra | Ex OLA | IIT Kanpur\nFollow\nShow more\nAbout\nAccessibility\nTalent Solutions\nProfessional Community Policies\nCareers\nMarketing Solutions\nPrivacy & Terms\nAd Choices\nAdvertising\nSales Solutions\nMobile\nSmall Business\nSafety Center\nQuestions?\nVisit our Help Center.\nManage your account and privacy\nGo to your Settings.\nRecommendation transparency\nLearn more about Recommended Content.\nSelect Language\n         العربية (Arabic)\n         বাংলা (Bangla)\n         Čeština (Czech)\n         Dansk (Danish)\n         Deutsch (German)\n         Ελληνικά (Greek)\n         English (English)\n         Español (Spanish)\n         فارسی (Persian)\n         Suomi (Finnish)\n         Français (French)\n         हिंदी (Hindi)\n         Magyar (Hungarian)\n         Bahasa Indonesia (Indonesian)\n         Italiano (Italian)\n         עברית (Hebrew)\n         日本語 (Japanese)\n         한국어 (Korean)\n         मराठी (Marathi)\n         Bahasa Malaysia (Malay)\n         Nederlands (Dutch)\n         Norsk (Norwegian)\n         ਪੰਜਾਬੀ (Punjabi)\n         Polski (Polish)\n         Português (Portuguese)\n         Română (Romanian)\n         Русский (Russian)\n         Svenska (Swedish)\n         తెలుగు (Telugu)\n         ภาษาไทย (Thai)\n         Tagalog (Tagalog)\n         Türkçe (Turkish)\n         Українська (Ukrainian)\n         Tiếng Việt (Vietnamese)\n         简体中文 (Chinese (Simplified))\n         正體中文 (Chinese (Traditional))\n     LinkedIn Corporation © 2025\nStatus is online\nMessaging\nYou are on the messaging overlay. Press enter to open the list of conversations.\nCompose message\nYou are on the messaging overlay. Press enter to open the list of conversations.",
  "scraped_at": "2025-07-23 01:50:52",
  "has_skills": true,
  "cleaned_profile": {
    "name": "Prateek Dasgupta",
    "profile_url": "https://in.linkedin.com/in/prateek-dasgupta-28a353124",
    "current_position": {
      "title": "Internationalisation",
      "company": "xto10x",
      "location": "Bangalore Urban, Karnataka, India",
      "start_date": "Feb 2024",
      "end_date": "Present",
      "duration": "1 yr 6 mos"
    },
    "previous_positions": [
      {
        "title": "Program Manager - Saudi Unicorns Program",
        "company": "xto10x",
        "location": "Bengaluru, Karnataka, India",
        "start_date": "Jul 2023",
        "end_date": "Feb 2024",
        "duration": "8 mos"
      },
      {
        "title": "Building Learning Products (Founder's Academy, Leadership Quotient, IIMB Partnership, B2C products)",
        "company": "xto10x",
        "location": "Bangalore Urban, Karnataka, India",
        "start_date": "Mar 2022",
        "end_date": "Jul 2023",
        "duration": "1 yr 5 mos"
      },
      {
        "title": "Senior Associate- Product Strategy - ML/AI products",
        "company": "upGrad",
        "location": "Mumbai Area, India",
        "start_date": "Aug 2020",
        "end_date": "Mar 2022",
        "duration": "1 yr 8 mos"
      },
      {
        "title": "Summer Intern at Ethane Gas Cracking Complex, Dahej (500 ktpa Ethylene Plant)",
        "company": "Reliance Industries Limited",
        "location": "Gujarat, India",
        "start_date": "May 2019",
        "end_date": "Jul 2019",
        "duration": "3 mos"
      },
      {
        "title": "Summer Research Intern",
        "company": "Indira Gandhi Centre for Atomic Research (IGCAR)",
        "location": "India",
        "start_date": "May 2018",
        "end_date": "Jul 2018",
        "duration": "3 mos"
      }
    ],
    "education": [
      {
        "institution": "Birla Institute of Technology and Science, Pilani",
        "degree": "Bachelor’s Degree",
        "field_of_study": "Chemical Engineering",
        "years_attended": "2016 - 2020"
      },
      {
        "institution": "Birla Institute of Technology and Science, Pilani",
        "degree": "Minor",
        "field_of_study": "Data Science",
        "years_attended": "2018 - 2019"
      }
    ],
    "connections": "500+",
    "followers": "6562",
    "skills": [
      "Microsoft Office",
      "Management",
      "Microsoft Excel",
      "Microsoft Word",
      "Leadership",
      "Microsoft PowerPoint",
      "Research",
      "Public Speaking",
      "Keras",
      "TensorFlow",
      "Machine Learning",
      "Deep Learning",
      "SPSS",
      "Matlab",
      "Scikit-Learn",
      "Statistical Data Analysis",
      "Statistics",
      "Logistic Regression",
      "Cluster Analysis",
      "Python (Programming Language)",
      "Data Science",
      "Data Analysis",
      "Team Leadership",
      "Chemical Engineering",
      "Chemical Process Engineering",
      "Chemical Industry"
    ],
    "interests": [
      "Riya Gadhwal",
      "Nishchal Jain"
    ]
  },
  "tokens_used": {
    "prompt_tokens": 5450,
    "completion_tokens": 787,
    "total_tokens": 6237
  }
}