{
  "url": "https://in.linkedin.com/in/neeraj-aggarwal-b741131",
  "raw_text": "0 notifications total\nnew feed updates notifications\nHome\n1\n1 new network update notification\nMy Network\nJobs\nMessaging\nNotifications\nMe\nFor Business\nTry Premium for â‚¹0\nNeeraj Aggarwal\nCo-founder at xto10x | GM at Cure.fit | Vice President, Operations at Flipkart\nxto10x Technologies Pvt Ltd\nIndian Institute of Management, Lucknow\nBengaluru, Karnataka, India Contact info\n500+ connections\nMessage\nFollow\nMore\nAbout\nAbout\nPerformance-driven and results-oriented professional with more than 20 years experience in Leadership roles in e-Commerce, Health & Food, and Technology industries.\n\nBuilt and scaled an online Food Delivery business, managed Supply Chain Operations for an eCommerce leader and setup Operations for an assisted Internet company.\n\nDeep end to end experience in building a low cost, highly flexible supply chain for e-commerce across Warehousing, Transportation and Last Mile logistics.\n\nExpertise in rapidly scaling and managing a large supply chain in a high growth market. Scaled a Supply Chain team to employee strength of 25,000 people, 1.5 mil. sq. feet of warehousing space, geographical reach of 800 cities, and delivering 400,000 shipments every day.\n\nCapabilities include network design, developing breakthrough cost models, automation, new servicesâ€™ operationalization, 3rd party vendor development and handling high peak events.\n\nMulti-cultural and cross functional exposure in Technology gained in Asia Pacific, Europe and the U.S. with organizations like Capgemini, IBM, Satyam, Oracle & clients like GE, Santander and TSYS.\n\nM.B.A. from IIM, Lucknow and B.E. from Pune University.\n\nSpecialties: Operations and Supply Chain, eCommerce, Online Food Delivery, Health & Fitness, Last Mile Innovation, P/L Management, Leadership, Vendor Management, Customer Experience, Leveraging Technology for Transformation\nâ€¦see more\nActivity\nActivity\n24,635 followers\n24,635 followers\nPosts\nComments\nImages\nDocuments\nLoaded 9 Posts posts\nNeeraj Aggarwal\nNeeraj Aggarwal\n   â€¢ 3rd+\nVerified â€¢ 3rd+\nCo-founder at xto10x | GM at Cure.fit | Vice President, Operations at Flipkart\nCo-founder at xto10x | GM at Cure.fit | Vice President, Operations at Flipkart\n1w â€¢ \n 1 week ago â€¢ Visible to anyone on or off LinkedIn\nSuper proud of how PeopleCues has been able to transform key employee experience touch points.\nPeopleCues\nPeopleCues\n735 followers\n735 followers\n6-week review cycles were the norm. Until now.\n\nAt Angel One, performance reviews that once took 4â€“6 weeks now wrap up in just 2â€“4, and that shift means everything. Huge thanks to Angel One team for the kind words, and for recognizing what we truly care about:\nğŸ“ˆ â€œYouâ€™ve moved the needle on the metrics that matter in a performance review.â€ â€“\nğŸ¤– â€œThe AI-led SBI feedback engine has completely changed the quality of feedback.â€ â€“\n\nItâ€™s a reminder that meaningful change at work doesnâ€™t need to be loud, just well-designed.\nIf a better review experience helps employees feel heard and managers make sharper decisions, weâ€™re doing our job right.\n\nWhatâ€™s one underrated shift thatâ€™s made a big difference in your org? Comment below.\n\n\n\nâ€¦more\n15\n1 comment\nNeeraj Aggarwal reposted this\nEng. Abdulrahman Alsmail\nEng. Abdulrahman Alsmail\nEng. Abdulrahman Alsmail\n   â€¢ 3rd+\nVerified â€¢ 3rd+\nGeneral Manager of Enterprises Growth at MonshaatSA\nGeneral Manager of Enterprises Growth at MonshaatSA\n1mo â€¢ \n 1 month ago â€¢ Visible to anyone on or off LinkedIn\nØ¶Ù…Ù† Ø¨Ø±Ù†Ø§Ù…Ø¬ Ø·Ù…ÙˆØ­ Ù„Ø¯Ø¹Ù… Ø§Ù„Ø´Ø±ÙƒØ§Øª Ù…ØªØ³Ø§Ø±Ø¹Ø© Ø§Ù„Ù†Ù…ÙˆØŒ Ù†ÙØ°Ù†Ø§ Ù…Ø¤Ø®Ø±Ù‹Ø§ Ø¨Ø±Ù†Ø§Ù…Ø¬ÙŠÙ† Ù…Ù…ÙŠØ²ÙŠÙ† Ø¨Ø§Ù„Ø´Ø±Ø§ÙƒØ© Ù…Ø¹ Endeavor Saudi Arabia :\n\nğŸ”¹ Scaling Founders by\n\nğŸ”¹ Scaling Companies by\n\nÙˆØ§Ø®ØªØªÙ…Ù†Ø§ Ø§Ù„Ø¨Ø±Ù†Ø§Ù…Ø¬ÙŠÙ† Ø¨Ù„Ù‚Ø§Ø¡ Ù…Ø´ØªØ±Ùƒ Ù…Ø¹ Ø³Ø¹Ø§Ø¯Ø© Ù…Ø­Ø§ÙØ¸ Ù…Ù†Ø´Ø¢ØªØŒ Ø­ÙŠØ« Ø´Ø§Ø±ÙƒØª Ø§Ù„Ù…Ù†Ø´Ø¢Øª Ø§Ù„Ù…Ø³ØªÙÙŠØ¯Ø© ØªØ¬Ø§Ø±Ø¨Ù‡Ø§ ÙˆØ¥Ù†Ø¬Ø§Ø²Ø§ØªÙ‡Ø§ØŒ ÙˆÙ†Ø§Ù‚Ø´Ù†Ø§ Ø£Ø¨Ø±Ø² Ø§Ù„ØªØ­Ø¯ÙŠØ§Øª ÙˆØ§Ù„ÙØ±Øµ Ø§Ù„ØªÙŠ ØªØ³Ù‡Ù… ÙÙŠ Ø§Ø³ØªØ¯Ø§Ù…Ø© Ù†Ù…ÙˆÙ‡Ø§.\n\nÙ‡Ø°Ù‡ Ø§Ù„Ù„Ù‚Ø§Ø¡Ø§Øª ØªØ¹ÙƒØ³ Ø¥ÙŠÙ…Ø§Ù†Ù†Ø§ Ø¨Ø£Ù‡Ù…ÙŠØ© Ø§Ù„ØªÙ…ÙƒÙŠÙ† Ø§Ù„Ù…Ø¨Ø§Ø´Ø±ØŒ ÙˆØ®Ù„Ù‚ Ø¨ÙŠØ¦Ø© ØªÙØ§Ø¹Ù„ÙŠØ© Ø¨ÙŠÙ† Ø±ÙˆØ§Ø¯ Ø§Ù„Ø£Ø¹Ù…Ø§Ù„ ÙˆØ§Ù„Ø¬Ù‡Ø§Øª Ø§Ù„Ø¯Ø§Ø¹Ù…Ø© Ù„ØªØ³Ø±ÙŠØ¹ Ø±Ø­Ù„Ø© Ø§Ù„Ù†Ù…Ùˆ ÙˆØ§Ù„ØªÙˆØ³Ø¹.\n\nÙƒÙ„ Ø§Ù„Ø´ÙƒØ± Ù„Ø´Ø±ÙƒØ§Ø¦Ù†Ø§ØŒ ÙˆÙ„Ù„Ù…Ù†Ø´Ø¢Øª Ø§Ù„Ù…Ù„Ù‡Ù…Ø© Ø§Ù„ØªÙŠ ÙƒØ§Ù†Øª Ø¬Ø²Ø¡Ù‹Ø§ Ù…Ù† Ù‡Ø°Ù‡ Ø§Ù„ØªØ¬Ø±Ø¨Ø©.\n\nÙƒÙ„ Ø§Ù„Ø´ÙƒØ± Ù„Ù‚ÙŠØ§Ø¯Ø§Øª Ø§Ù†Ø¯ÙŠÙÙˆØ±Ùˆ\nÙˆÙ‚ÙŠØ§Ø¯Ø§Øª Ø§Ù„Ø¨Ø±Ù†Ø§Ù…Ø¬\nØ´ÙƒØ± Ø®Ø§Øµ Ù„Ù…Ø¯ÙŠØ± Ø§Ù„Ù…Ø´Ø±ÙˆØ¹Ø¹Ù„Ù‰ ÙƒØ§ÙØ© Ø¬Ù‡ÙˆØ¯Ù‡Ø§ Ø®Ù„Ø§Ù„ ÙØªØ±Ø© Ø³Øª Ø´Ù‡ÙˆØ± ÙˆØ¹Ù„Ù‰ Ù‚ÙŠØ§Ø¯ØªÙ‡ Ù„Ù„Ù…Ù„Ù Ø¨Ù†Ø¬Ø§Ø­ ÙˆØªØ­Ù‚ÙŠÙ‚ Ø§Ù„Ø§Ø«Ø±.\nÙˆÙ†ØªØ·Ù„Ø¹ Ø¥Ù„Ù‰ Ù…ÙˆØ§ØµÙ„Ø© Ø¯Ø¹Ù… Ø§Ù„Ù…Ø²ÙŠØ¯ Ù…Ù† Ù‚ØµØµ Ø§Ù„Ù†Ø¬Ø§Ø­ ğŸ’¼ğŸš€\n\n#\nâ€¦more\nActivate to view larger image,\n1/3\nActivate to view larger image,\n164\n13 comments\n5 reposts\nShow all posts\nExperience\nExperience\nCo-founder and COO\nCo-founder and COO\nxto10x Technologies Pvt Ltd\nxto10x Technologies Pvt Ltd\nMar 2019 - Present Â· 6 yrs 5 mos\nMar 2019 to Present Â· 6 yrs 5 mos\nBangalore\nBangalore\nGeneral Manager, Eat.Fit\nGeneral Manager, Eat.Fit\nCure.Fit\nCure.Fit\nJun 2017 - Feb 2019 Â· 1 yr 9 mos\nJun 2017 to Feb 2019 Â· 1 yr 9 mos\nBangalore\nBangalore\nGM and P&L owner for the Food Delivery vertical, Eat.fit \nGM and P&L owner for the Food Delivery vertical, Eat.fit\nFlipkart\nFlipkart\n4 yrs 4 mos\n4 yrs 4 mos\nVice President, Supply Chain Operations and Design\nVice President, Supply Chain Operations and Design\nJan 2016 - Apr 2017 Â· 1 yr 4 mos\nJan 2016 to Apr 2017 Â· 1 yr 4 mos\nSenior Director, Logistics Operations\nSenior Director, Logistics Operations\nJul 2014 - Dec 2015 Â· 1 yr 6 mos\nJul 2014 to Dec 2015 Â· 1 yr 6 mos\nDirector, Delivery (Last Mile) Operations\nDirector, Delivery (Last Mile) Operations\nJan 2013 - Jun 2014 Â· 1 yr 6 mos\nJan 2013 to Jun 2014 Â· 1 yr 6 mos\nHead Of Operations\nHead Of Operations\nHead Of Operations\nMaxrange Retail Pvt Ltd.\nMaxrange Retail Pvt Ltd.\nAug 2011 - Dec 2012 Â· 1 yr 5 mos\nAug 2011 to Dec 2012 Â· 1 yr 5 mos\nHyderabad\nHyderabad\nStarted by the founders of MedPlus, MaxRange Retail Pvt Ltd. is a start-up retail organization backed by a major Bahrain based PE fund. It aimed to capture the Tier 3 & Tier 4 market segment by using the centralized inventory & assisted internet model to provide a unique, kiosk-based shopping experience offering an extensive range at extremely competitive prices. Branded â€˜my SmartShopâ€™, it had over 80 shops in India.\n\n- Along with the CEO, was responsible for overall strategy formulation, performance management and reporting the key KPIs set for the organization to the Board every month.\nCapgemini\nCapgemini\n6 yrs 2 mos\n6 yrs 2 mos\nAccount Manager\nAccount Manager\nMay 2009 - Jul 2011 Â· 2 yrs 3 mos\nMay 2009 to Jul 2011 Â· 2 yrs 3 mos\nWas responsible for Account & P/L management, Delivery and Operations for a portfolio of financial services clients. Handling a team of close to 150, spread over different geographies, working on Cards platforms like PRIME and VisionPLUS, and retail banking systems.\nClient Engagement Manager\nClient Engagement Manager\nMar 2008 - Apr 2009 Â· 1 yr 2 mos\nMar 2008 to Apr 2009 Â· 1 yr 2 mos\nClient Enagagement Manager for a UK based Financial Institution with overall P/L ownership. Primary responsibilities include managing the overall client relationship, and new business development.\nClient Enagagement Manager for a UK based Financial Institution with overall P/L ownership. Primary responsibilities include managing the overall client relationship, and new business development.\nTest Program Manager\nTest Program Manager\nJun 2005 - Feb 2008 Â· 2 yrs 9 mos\nJun 2005 to Feb 2008 Â· 2 yrs 9 mos\nManaged a 40-member India based, VisionPLUS testing engagement. Oversaw estimations, project planning &amp; execution, liaising with client managers, resource selection &amp; staffing, knowledge management, training, metrics collection &amp; analysis, and reporting.\nShow all 12 experiences\nEducation\nEducation\nIndian Institute of Management, Lucknow\nIndian Institute of Management, Lucknow\nMBA, Finance and Systems\nMBA, Finance and Systems\n1999 - 2001\n1999 - 2001\nCollege of Engg. Pravara Nagar, Pune University\nCollege of Engg. Pravara Nagar, Pune University\nCollege of Engg. Pravara Nagar, Pune University\nB.E., Electronics and Telecommunications\nB.E., Electronics and Telecommunications\nJun 1994 - Apr 1998\nJun 1994 - Apr 1998\nSkills\nSkills\nTesting\nTesting\nEndorsed by 2 colleagues at Flipkart\nEndorsed by 2 colleagues at Flipkart\n43 endorsements\n43 endorsements\nAccount Management\nAccount Management\nEndorsed by 3 colleagues at Flipkart\nEndorsed by 3 colleagues at Flipkart\n26 endorsements\n26 endorsements\nShow all 45 skills\nRecommendations\nRecommendations\nReceived\nReceived\nGiven\nGiven\nVivekananda Hallekere\nVivekananda Hallekere\nVivekananda Hallekere\nCEO & Co-Founder, Bounce \nCEO & Co-Founder, Bounce\nOctober 5, 2020, Vivekananda was Neerajâ€™s client\nOctober 5, 2020,Vivekanandawas Neerajâ€™s client\nNeeraj is one of the best ops experts I have met. He has been extremely helpful in our journey at Bounce. He is always approachable, understands the details, down to earth, very effective in communicating and also a great leader. We are lucky to have met him and get his time for Bounce. I would highly recommend anyone starting up in an op heavy business to talk to Neeraj. \nNeeraj is one of the best ops experts I have met. He has been extremely helpful in our journey at Bounce. He is always approachable, understands the details, down to earth, very effective in communicating and also a great leader. We are lucky to have met him and get his time for Bounce. I would highly recommend anyone starting up in an op heavy business to talk to Neeraj.\nArnab Chakraborty\nArnab Chakraborty\nSpecialist in Building E-commerce Supply Chain. Founding Team Member, Karvy Next- Qykxpress, Ex Flipkart\nSpecialist in Building E-commerce Supply Chain. Founding Team Member, Karvy Next- Qykxpress, Ex Flipkart\nSeptember 29, 2020, Arnab reported directly to Neeraj\nSeptember 29, 2020,Arnabreported directly toNeeraj\nYou get the opportunity to work in Flipkart kind of organization, very rarely, the icing on the cake was to have Neeraj as the Boss. With his ability to go deep into the subject, amazing analytical skill, trust in the team, and above all humility, made him our friend, philosopher, and guide more than a Boss. I fondly recall those days of working together on new implementations like BYOD (Mobile for Delivery Executives), Hub Layout, Van Delivery, Early Morning Deliveries, and many others, which were new experiments at that time in eCommerce, but became standard practice for the industry. Proud to have him as a friend and mentor to this day. All the very best for your role at Xto10X. I am sure this will be another feather in your cap.\nYou get the opportunity to work in Flipkart kind of organization, very rarely, the icing on the cake was to have Neeraj as the Boss. With his ability to go deep into the subject, amazing analytical skill, trust in the team, and above all humility, made him our friend, philosopher, and guide more than a Boss. I fondly recall those days of working together on new implementations like BYOD (Mobile for Delivery Executives), Hub Layout, Van Delivery, Early Morning Deliveries, and many others, which were new experiments at that time in eCommerce, but became standard practice for the industry. Proud to have him as a friend and mentor to this day. All the very best for your role at Xto10X. I am sure this will be another feather in your cap.\nShow all 10 received\n\n\n\n\n\n\nInterests\nInterests\nTop Voices\nTop Voices\nCompanies\nCompanies\nGroups\nGroups\nNewsletters\nNewsletters\nSchools\nSchools\nRajan Singh\nRajan Singh\nFounder, HabitStrong | Ex-IPS | Wharton | IITK | McKinsey | Private Equity\nFounder, HabitStrong | Ex-IPS | Wharton | IITK | McKinsey | Private Equity\n325,000 followers\n325,000 followers\nFollow\nSahil Bloom\nSahil Bloom\nNYT Bestselling Author of The 5 Types of Wealth\nNYT Bestselling Author of The 5 Types of Wealth\n649,327 followers\n649,327 followers\nFollow\nShow all Top Voices\nMore profiles for you\nMore profiles for you\nShreyans Daga\nShreyans Daga\nShreyans Daga\nÂ· 3rd+\n3rd+ degree connection\nCo-Founder at MyGate\nCo-Founder at MyGate\nMessage\nSachin Bansal\nSachin Bansal\nÂ· 3rd+\n3rd+ degree connection\nBuilding Navi\nBuilding Navi\nFollow\nKalyan Krishnamurthy\nKalyan Krishnamurthy\nKalyan Krishnamurthy\nÂ· 3rd+\n3rd+ degree connection\nCEO at Flipkart\nCEO at Flipkart\nMessage\nGaurav Choudhary\nGaurav Choudhary\nÂ· 3rd+\n3rd+ degree connection\nProduct Leader @ xto10x | Ex Myntra | Ex OLA | IIT Kanpur\nProduct Leader @ xto10x | Ex Myntra | Ex OLA | IIT Kanpur\nFollow\nRishhi Mehra\nRishhi Mehra\nÂ· 3rd+\n3rd+ degree connection\nConnecting Talent with Opportunity\nConnecting Talent with Opportunity\nFollow\nShow all\nPeople you may know\nPeople you may know\nFrom Neeraj's school\nFrom Neeraj's school\nRiya Singh\nRiya Singh\nStudent at Indian Institute of Management, Lucknow\nStudent at Indian Institute of Management, Lucknow\nConnect\nPranjali Goel\nPranjali Goel\nManager Designate, Godrej Properties- Gallop'25 | Samsung Intern | IIM Lucknow PGP'25 | Placement Systems | Hansraj College\nConnect\nVISHNU S U\nVISHNU S U\nResearch Scholar in Agribusiness Managementâ— PhD'29 IIM Lucknowâ— MBA'24 @ IABMI AAU Anand\nConnect\nParas Bhatt\nParas Bhatt\nIIM Lucknow'27 l B.Sc.(Hons.) Agriculture |GBPUA&T'24, Pantnagar\nConnect\nGautam Singh\nGautam Singh\nSTUDENT AT CHANDRA BHANU KRISHI MAHAVIDYALAY || UNIVERSITY OF LUCKNOW||\nConnect\nShow all\nYou might like\nYou might like\nPages for you\nPages for you\nIndian Aviation Career\nIndian Aviation Career\nAirlines and Aviation\nAirlines and Aviation\n57,409 followers\n57,409 followers\nFollow\nEntrepreneurial Mindset\nEntrepreneurial Mindset\nThink Tanks\nThink Tanks\n1,220,182 followers\n1,220,182 followers\nFollow\nShow all\nAbout\nAccessibility\nTalent Solutions\nProfessional Community Policies\nCareers\nMarketing Solutions\nPrivacy & Terms\nAd Choices\nAdvertising\nSales Solutions\nMobile\nSmall Business\nSafety Center\nQuestions?\nVisit our Help Center.\nManage your account and privacy\nGo to your Settings.\nRecommendation transparency\nLearn more about Recommended Content.\nSelect Language\n         Ø§Ù„Ø¹Ø±Ø¨ÙŠØ© (Arabic)\n         à¦¬à¦¾à¦‚à¦²à¦¾ (Bangla)\n         ÄŒeÅ¡tina (Czech)\n         Dansk (Danish)\n         Deutsch (German)\n         Î•Î»Î»Î·Î½Î¹ÎºÎ¬ (Greek)\n         English (English)\n         EspaÃ±ol (Spanish)\n         ÙØ§Ø±Ø³ÛŒ (Persian)\n         Suomi (Finnish)\n         FranÃ§ais (French)\n         à¤¹à¤¿à¤‚à¤¦à¥€ (Hindi)\n         Magyar (Hungarian)\n         Bahasa Indonesia (Indonesian)\n         Italiano (Italian)\n         ×¢×‘×¨×™×ª (Hebrew)\n         æ—¥æœ¬èª (Japanese)\n         í•œêµ­ì–´ (Korean)\n         à¤®à¤°à¤¾à¤ à¥€ (Marathi)\n         Bahasa Malaysia (Malay)\n         Nederlands (Dutch)\n         Norsk (Norwegian)\n         à¨ªà©°à¨œà¨¾à¨¬à©€ (Punjabi)\n         Polski (Polish)\n         PortuguÃªs (Portuguese)\n         RomÃ¢nÄƒ (Romanian)\n         Ğ ÑƒÑÑĞºĞ¸Ğ¹ (Russian)\n         Svenska (Swedish)\n         à°¤à±†à°²à±à°—à± (Telugu)\n         à¸ à¸²à¸©à¸²à¹„à¸—à¸¢ (Thai)\n         Tagalog (Tagalog)\n         TÃ¼rkÃ§e (Turkish)\n         Ğ£ĞºÑ€Ğ°Ñ—Ğ½ÑÑŒĞºĞ° (Ukrainian)\n         Tiáº¿ng Viá»‡t (Vietnamese)\n         ç®€ä½“ä¸­æ–‡ (Chinese (Simplified))\n         æ­£é«”ä¸­æ–‡ (Chinese (Traditional))\n     LinkedIn Corporation Â© 2025\nStatus is online\nMessaging\nYou are on the messaging overlay. Press enter to open the list of conversations.\nCompose message\nYou are on the messaging overlay. Press enter to open the list of conversations.",
  "skills_text": "0 notifications total\nnew feed updates notifications\nHome\n1\n1 new network update notification\nMy Network\nJobs\nMessaging\nNotifications\nMe\nFor Business\nTry Premium for â‚¹0\nNeeraj Aggarwal\nCo-founder at xto10x | GM at Cure.fit | Vice President, Operations at Flipkart\nMore\nFollow\nMessage\nSkills\nAll\nIndustry Knowledge\nInterpersonal Skills\nOther Skills\nTesting\nTesting\nEndorsed by 2 colleagues at Flipkart\nEndorsed by 2 colleagues at Flipkart\n43 endorsements\n43 endorsements\nAccount Management\nAccount Management\nEndorsed by 3 colleagues at Flipkart\nEndorsed by 3 colleagues at Flipkart\n26 endorsements\n26 endorsements\nVisionPLUS\nVisionPLUS\nEndorsed by 3 colleagues at Capgemini\nEndorsed by 3 colleagues at Capgemini\n10 endorsements\n10 endorsements\nPrime\nPrime\n3 endorsements\n3 endorsements\nCards\nCards\n8 endorsements\n8 endorsements\nCRM\nCRM\n99+ endorsements\n99+ endorsements\nTeam Building\nTeam Building\n6 endorsements\n6 endorsements\nLeadership\nLeadership\n75 endorsements\n75 endorsements\nFinancial Services\nFinancial Services\n15 endorsements\n15 endorsements\nBusiness Analysis\nBusiness Analysis\n99+ endorsements\n99+ endorsements\nTeam Management\nTeam Management\n99+ endorsements\n99+ endorsements\nNew Business Development\nNew Business Development\n21 endorsements\n21 endorsements\nProcess Consulting\nProcess Consulting\n9 endorsements\n9 endorsements\nGlobal Delivery\nGlobal Delivery\n20 endorsements\n20 endorsements\nTest Management\nTest Management\n9 endorsements\n9 endorsements\nBusiness Transformation\nBusiness Transformation\n8 endorsements\n8 endorsements\nProduct Development\nProduct Development\n8 endorsements\n8 endorsements\nRequirements Gathering\nRequirements Gathering\n16 endorsements\n16 endorsements\nRequirements Analysis\nRequirements Analysis\n40 endorsements\n40 endorsements\nManage Client Relationships\nManage Client Relationships\n4 endorsements\n4 endorsements\nProject Management\nProject Management\n59 endorsements\n59 endorsements\nBusiness Development\nBusiness Development\n48 endorsements\n48 endorsements\nPerformance Management\nPerformance Management\n21 endorsements\n21 endorsements\nSolution Architecture\nSolution Architecture\n9 endorsements\n9 endorsements\nOffshoring\nOffshoring\n5 endorsements\n5 endorsements\nRelationship Management\nRelationship Management\n4 endorsements\n4 endorsements\nPre-sales\nPre-sales\n36 endorsements\n36 endorsements\nProgram Management\nProgram Management\n53 endorsements\n53 endorsements\nVendor Management\nVendor Management\n98 endorsements\n98 endorsements\nProject Planning\nProject Planning\n27 endorsements\n27 endorsements\nOutsourcing\nOutsourcing\n26 endorsements\n26 endorsements\nCross-functional Team Leadership\nCross-functional Team Leadership\n7 endorsements\n7 endorsements\nSoftware Project Management\nSoftware Project Management\n25 endorsements\n25 endorsements\nSDLC\nSDLC\n15 endorsements\n15 endorsements\nAnalysis\nAnalysis\n19 endorsements\n19 endorsements\nStart-ups\nStart-ups\n12 endorsements\n12 endorsements\nManagement\nManagement\n99+ endorsements\n99+ endorsements\nSix Sigma\nSix Sigma\n18 endorsements\n18 endorsements\nBusiness Intelligence\nBusiness Intelligence\n22 endorsements\n22 endorsements\nIT Strategy\nIT Strategy\n28 endorsements\n28 endorsements\nTraining\nTraining\n16 endorsements\n16 endorsements\nE-commerce\nE-commerce\n27 endorsements\n27 endorsements\nSupply Chain Management\nSupply Chain Management\n50 endorsements\n50 endorsements\nCustomer Relationship Management (CRM)\nCustomer Relationship Management (CRM)\n45 endorsements\n45 endorsements\nSoftware Development Life Cycle (SDLC)\nSoftware Development Life Cycle (SDLC)\n7 endorsements\n7 endorsements\nMore profiles for you\nMore profiles for you\nShreyans Daga\nShreyans Daga\nShreyans Daga\nÂ· 3rd+\n3rd+ degree connection\nCo-Founder at MyGate\nCo-Founder at MyGate\nMessage\nSachin Bansal\nSachin Bansal\nÂ· 3rd+\n3rd+ degree connection\nBuilding Navi\nBuilding Navi\nFollow\nKalyan Krishnamurthy\nKalyan Krishnamurthy\nKalyan Krishnamurthy\nÂ· 3rd+\n3rd+ degree connection\nCEO at Flipkart\nCEO at Flipkart\nMessage\nGaurav Choudhary\nGaurav Choudhary\nÂ· 3rd+\n3rd+ degree connection\nProduct Leader @ xto10x | Ex Myntra | Ex OLA | IIT Kanpur\nProduct Leader @ xto10x | Ex Myntra | Ex OLA | IIT Kanpur\nFollow\nRishhi Mehra\nRishhi Mehra\nÂ· 3rd+\n3rd+ degree connection\nConnecting Talent with Opportunity\nConnecting Talent with Opportunity\nFollow\nShow more\nAbout\nAccessibility\nTalent Solutions\nProfessional Community Policies\nCareers\nMarketing Solutions\nPrivacy & Terms\nAd Choices\nAdvertising\nSales Solutions\nMobile\nSmall Business\nSafety Center\nQuestions?\nVisit our Help Center.\nManage your account and privacy\nGo to your Settings.\nRecommendation transparency\nLearn more about Recommended Content.\nSelect Language\n         Ø§Ù„Ø¹Ø±Ø¨ÙŠØ© (Arabic)\n         à¦¬à¦¾à¦‚à¦²à¦¾ (Bangla)\n         ÄŒeÅ¡tina (Czech)\n         Dansk (Danish)\n         Deutsch (German)\n         Î•Î»Î»Î·Î½Î¹ÎºÎ¬ (Greek)\n         English (English)\n         EspaÃ±ol (Spanish)\n         ÙØ§Ø±Ø³ÛŒ (Persian)\n         Suomi (Finnish)\n         FranÃ§ais (French)\n         à¤¹à¤¿à¤‚à¤¦à¥€ (Hindi)\n         Magyar (Hungarian)\n         Bahasa Indonesia (Indonesian)\n         Italiano (Italian)\n         ×¢×‘×¨×™×ª (Hebrew)\n         æ—¥æœ¬èª (Japanese)\n         í•œêµ­ì–´ (Korean)\n         à¤®à¤°à¤¾à¤ à¥€ (Marathi)\n         Bahasa Malaysia (Malay)\n         Nederlands (Dutch)\n         Norsk (Norwegian)\n         à¨ªà©°à¨œà¨¾à¨¬à©€ (Punjabi)\n         Polski (Polish)\n         PortuguÃªs (Portuguese)\n         RomÃ¢nÄƒ (Romanian)\n         Ğ ÑƒÑÑĞºĞ¸Ğ¹ (Russian)\n         Svenska (Swedish)\n         à°¤à±†à°²à±à°—à± (Telugu)\n         à¸ à¸²à¸©à¸²à¹„à¸—à¸¢ (Thai)\n         Tagalog (Tagalog)\n         TÃ¼rkÃ§e (Turkish)\n         Ğ£ĞºÑ€Ğ°Ñ—Ğ½ÑÑŒĞºĞ° (Ukrainian)\n         Tiáº¿ng Viá»‡t (Vietnamese)\n         ç®€ä½“ä¸­æ–‡ (Chinese (Simplified))\n         æ­£é«”ä¸­æ–‡ (Chinese (Traditional))\n     LinkedIn Corporation Â© 2025\nStatus is online\nMessaging\nYou are on the messaging overlay. Press enter to open the list of conversations.\nCompose message\nYou are on the messaging overlay. Press enter to open the list of conversations.",
  "scraped_at": "2025-07-23 03:09:52",
  "has_skills": true,
  "cleaned_profile": {
    "name": "Neeraj Aggarwal",
    "profile_url": "https://in.linkedin.com/in/neeraj-aggarwal-b741131",
    "current_position": {
      "title": "Co-founder and COO",
      "company": "xto10x Technologies Pvt Ltd",
      "location": "Bangalore",
      "start_date": "Mar 2019",
      "end_date": "Present",
      "duration": "6 yrs 5 mos"
    },
    "previous_positions": [
      {
        "title": "General Manager, Eat.Fit",
        "company": "Cure.Fit",
        "location": "Bangalore",
        "start_date": "Jun 2017",
        "end_date": "Feb 2019",
        "duration": "1 yr 9 mos"
      },
      {
        "title": "Vice President, Supply Chain Operations and Design",
        "company": "Flipkart",
        "start_date": "Jan 2016",
        "end_date": "Apr 2017",
        "duration": "1 yr 4 mos"
      },
      {
        "title": "Senior Director, Logistics Operations",
        "company": "Flipkart",
        "start_date": "Jul 2014",
        "end_date": "Dec 2015",
        "duration": "1 yr 6 mos"
      },
      {
        "title": "Director, Delivery (Last Mile) Operations",
        "company": "Flipkart",
        "start_date": "Jan 2013",
        "end_date": "Jun 2014",
        "duration": "1 yr 6 mos"
      },
      {
        "title": "Head Of Operations",
        "company": "Maxrange Retail Pvt Ltd.",
        "location": "Hyderabad",
        "start_date": "Aug 2011",
        "end_date": "Dec 2012",
        "duration": "1 yr 5 mos"
      },
      {
        "title": "Account Manager",
        "company": "Capgemini",
        "start_date": "May 2009",
        "end_date": "Jul 2011",
        "duration": "2 yrs 3 mos"
      },
      {
        "title": "Client Engagement Manager",
        "company": "Capgemini",
        "start_date": "Mar 2008",
        "end_date": "Apr 2009",
        "duration": "1 yr 2 mos"
      },
      {
        "title": "Test Program Manager",
        "company": "Capgemini",
        "start_date": "Jun 2005",
        "end_date": "Feb 2008",
        "duration": "2 yrs 9 mos"
      }
    ],
    "education": [
      {
        "institution": "Indian Institute of Management, Lucknow",
        "degree": "MBA",
        "field_of_study": "Finance and Systems",
        "years_attended": "1999 - 2001"
      },
      {
        "institution": "College of Engg. Pravara Nagar, Pune University",
        "degree": "B.E.",
        "field_of_study": "Electronics and Telecommunications",
        "years_attended": "Jun 1994 - Apr 1998"
      }
    ],
    "connections": "500+",
    "followers": 24635,
    "skills": [
      "Testing",
      "Account Management",
      "VisionPLUS",
      "Prime",
      "Cards",
      "CRM",
      "Team Building",
      "Leadership",
      "Financial Services",
      "Business Analysis",
      "Team Management",
      "New Business Development",
      "Process Consulting",
      "Global Delivery",
      "Test Management",
      "Business Transformation",
      "Product Development",
      "Requirements Gathering",
      "Requirements Analysis",
      "Manage Client Relationships",
      "Project Management",
      "Business Development",
      "Performance Management",
      "Solution Architecture",
      "Offshoring",
      "Relationship Management",
      "Pre-sales",
      "Program Management",
      "Vendor Management",
      "Project Planning",
      "Outsourcing",
      "Cross-functional Team Leadership",
      "Software Project Management",
      "SDLC",
      "Analysis",
      "Start-ups",
      "Management",
      "Six Sigma",
      "Business Intelligence",
      "IT Strategy",
      "Training",
      "E-commerce",
      "Supply Chain Management",
      "Customer Relationship Management (CRM)",
      "Software Development Life Cycle (SDLC)"
    ],
    "interests": [
      "Rajan Singh",
      "Sahil Bloom"
    ]
  },
  "tokens_used": {
    "prompt_tokens": 5246,
    "completion_tokens": 979,
    "total_tokens": 6225
  }
}