{
  "url": "https://www.linkedin.com/in/sushanthhegde",
  "raw_text": "0 notifications total\nnew feed updates notifications\nHome\n1\n1 new network update notification\nMy Network\nJobs\nMessaging\nNotifications\nMe\nFor Business\nTry Premium for ₹0\nSushanth Hegde\nProduct Designer 2 @Microsoft | Ex - xto10x, Nuclei | MS HCI @UMD\nMicrosoft\nUniversity of Maryland\nSan Francisco Bay Area Contact info\n500+ connections\nMessage\nFollow\nMore\nAbout\nAbout\nI studied Computer Science & Engg., but found my calling in design. Currently working as a product designer at Microsoft. Prior to this I have helped design and ship products among numerous award winning startups like xto10x and Nuclei.\n\nOutside of work, I spend my time working on conceptual illustrations, exploring wilderness, listening to podcasts and reading books. My personal goals this year are to learn a musical instrument and swim more than 2k without being sick.\n…see more\nFeatured\nFeatured\nLink\nLink\nProduct Designer - Sushanth Hegde\nProduct Designer - Sushanth Hegde\nsushanthhegde.com\nsushanthhegde.com\nCurrently pursuing masters in HCI at the University of Maryland. Previously architected & lead product experiences @xto10x and @Nuclei for 4 years\nCurrently pursuing masters in HCI at the University of Maryland. Previously architected & lead product experiences @xto10x and @Nuclei for 4 years\nActivity\nActivity\n1,366 followers\n1,366 followers\nSushanth hasn’t posted yet\nRecent posts Sushanth shares will be displayed here.\nShow all activity\nExperience\nExperience\nProduct Designer 2\nProduct Designer 2\nMicrosoft · Full-time\nMicrosoft · Full-time\nJun 2023 - Present · 2 yrs 2 mos\nJun 2023 to Present · 2 yrs 2 mos\nSan Francisco Bay Area · On-site\nSan Francisco Bay Area · On-site\nProduct Design Intern\nProduct Design Intern\nMicrosoft · Full-time\nMicrosoft · Full-time\nJun 2022 - Aug 2022 · 3 mos\nJun 2022 to Aug 2022 · 3 mos\nSan Francisco Bay Area\nSan Francisco Bay Area\nSenior Product Designer\nSenior Product Designer\nxto10x · Full-time\nxto10x · Full-time\nMar 2020 - Jul 2021 · 1 yr 5 mos\nMar 2020 to Jul 2021 · 1 yr 5 mos\nBengaluru, Karnataka, India\nBengaluru, Karnataka, India\n- User research, Information Architecture, Interaction design, Visual design, User testing \n & Design Systems\n- B2B SAAS\nProduct Designer\nProduct Designer\nNuclei · Full-time\nNuclei · Full-time\nSep 2018 - Dec 2019 · 1 yr 4 mos\nSep 2018 to Dec 2019 · 1 yr 4 mos\nBengaluru, Karnataka, India\nBengaluru, Karnataka, India\n- User research, Information Architecture, Interaction design, Visual design, User testing \n & Design Systems\n- Mobile, Fin-Tech\nUser Experience Designer\nUser Experience Designer\nTipstat · Full-time\nTipstat · Full-time\nJan 2017 - Sep 2018 · 1 yr 9 mos\nJan 2017 to Sep 2018 · 1 yr 9 mos\nBengaluru, Karnataka, India\nBengaluru, Karnataka, India\n- User research, Information Architecture, Interaction design, Visual design\n- Mobile & Web, Fin-Tech, Social Networking\n- User research, Information Architecture, Interaction design, Visual design - Mobile & Web, Fin-Tech, Social Networking\nShow all 8 experiences\nEducation\nEducation\nUniversity of Maryland\nUniversity of Maryland\nMaster's degree, Human Computer Interaction\nMaster's degree, Human Computer Interaction\nAug 2021 - Jun 2023\nAug 2021 - Jun 2023\nPES University\nPES University\nBachelor of Technology - BTech, Computer Science\nBachelor of Technology - BTech, Computer Science\n2013 - 2017\n2013 - 2017\nActivities and societies: Aatmatrisha 15, Prakalpa 16, Ayana 16, Endeavour 16, Endeavour 14, Quriosa 14, \nEntrepreneurship Cell (E-Cell), Papyrus\nActivities and societies: Aatmatrisha 15, Prakalpa 16, Ayana 16, Endeavour 16, Endeavour 14, Quriosa 14, Entrepreneurship Cell (E-Cell), Papyrus\nLicenses & certifications\nLicenses & certifications\nStartup School - Founders Track\nStartup School - Founders Track\nY Combinator\nY Combinator\nIssued Jun 2017\nIssued Jun 2017\nCredential ID 10740242\nCredential ID 10740242\nShow credential\nProjects\nProjects\nPothole Ranking System\nPothole Ranking System\nFeb 2016 - Present\nFeb 2016 - Present\nUses Location Services and Sensor Manager on the client side android app to get GPS and accelerometer readings. On the server side the machine learns based on SVM with a sliding window approach to classify between potholes, accidents and smooth riding. Maps API is used for visualization. A crowd sourced android app stores and sends the log file [GPS and accelerometer readings] collected by the biker, into the server where the data is segregated and along with the previous history of that location, is used to generate a score for the pothole. These values are plotted on a heat map of the city.\nOther contributors\nOther contributors\nSmart Provisioning of MariaDB/MongoDB\nSmart Provisioning of MariaDB/MongoDB\nOct 2015 - Present\nOct 2015 - Present\nAssociated with PES University\nAssociated with PES University\nA secure package manager whose main objective was to install and maintain MongoDB and MariaDB using local repositories by which cyber attacks were prevented on large connected enterprise systems. We targeted this package manager solely on RHEL 7.\nOther contributors\nOther contributors\nShow all 5 projects\nVolunteering\nVolunteering\nVolunteer\nVolunteer\nVolunteer\nIgniting Young Minds\nIgniting Young Minds\nOct 2015 - Nov 2015 · 2 mos\nOct 2015 - Nov 2015 · 2 mos\nChildren\nChildren\nImparting soft skills lessons (such as moral values, spoken English, etiquettes and manners, personal hygiene) for underprivileged children. \nImparting soft skills lessons (such as moral values, spoken English, etiquettes and manners, personal hygiene) for underprivileged children.\nSkills\nSkills\nUser Interface Design\nUser Interface Design\nEndorsed by 2 colleagues at Microsoft\nEndorsed by 2 colleagues at Microsoft\nEndorsed by 1 person in the last 6 months\nEndorsed by 1 person in the last 6 months\n11 endorsements\n11 endorsements\nUser Experience Design\nUser Experience Design\nEndorsed by 2 colleagues at Microsoft\nEndorsed by 2 colleagues at Microsoft\nEndorsed by 1 person in the last 6 months\nEndorsed by 1 person in the last 6 months\n11 endorsements\n11 endorsements\nShow all 31 skills\nRecommendations\nRecommendations\nReceived\nReceived\nGiven\nGiven\nNothing to see for now\nNothing to see for now\nRecommendations that Sushanth receives will appear here.\nRecommendations thatSushanthreceives will appear here.\nHonors & awards\nHonors & awards\nWinner of TechnoBiz track at 8th IEEE international conference on Cloud Computing in Emerging Markets (CCEM)\nWinner of TechnoBiz track at 8th IEEE international conference on Cloud Computing in Emerging Markets (CCEM)\nIssued by IEEE · Sep 2019\nIssued by IEEE · Sep 2019\n1st Runner up Wired Open Hackathon\n1st Runner up Wired Open Hackathon\nIssued by Cowrks · Nov 2016\nIssued by Cowrks · Nov 2016\nAssociated with PES University\nAssociated with PES University\nShow all 4 honors & awards\nLanguages\nLanguages\nEnglish\nEnglish\nFull professional proficiency\nFull professional proficiency\nHindi\nHindi\nProfessional working proficiency\nProfessional working proficiency\nShow all 3 languages\nOrganizations\nOrganizations\nE Cell PES University\nE Cell PES University\nHead of Design\nHead of Design\nPapyrus\nPapyrus\nHead of Design\nHead of Design\nShow all 4 organizations\nInterests\nInterests\nTop Voices\nTop Voices\nCompanies\nCompanies\nGroups\nGroups\nSchools\nSchools\nSatya Nadella\nSatya Nadella\nChairman and CEO at Microsoft\nChairman and CEO at Microsoft\n11,462,503 followers\n11,462,503 followers\nFollow\nJohn Maeda\nJohn Maeda\nAI @ MSFT / Laws of Simplicity + How To Speak Machine / LinkedIn Top US Influencer\nAI @ MSFT / Laws of Simplicity + How To Speak Machine / LinkedIn Top US Influencer\n468,156 followers\n468,156 followers\nFollow\nCauses\nCauses\nAnimal Welfare • Arts and Culture • Children • Environment • Science and Technology • Social Services\nAnimal Welfare • Arts and Culture • Children • Environment • Science and Technology • Social Services\nMore profiles for you\nMore profiles for you\nRuchica Sinha\nRuchica Sinha\n· 3rd+\n3rd+ degree connection\nM.S. HCI @University of Maryland | Previously Design Intern @PepsiCo and Product Designer @Pine Labs\nMessage\nAnshika Srivastava\nAnshika Srivastava\n· 3rd+\n3rd+ degree connection\nProduct Designer | Health-tech\nProduct Designer | Health-tech\nFollow\nPallavi Kothapalli\nPallavi Kothapalli\n· 3rd+\n3rd+ degree connection\nProduct Designer | Architect | MS HCI @ UMD\nProduct Designer | Architect | MS HCI @ UMD\nMessage\nMeghana Alla\nMeghana Alla\n· 3rd+\n3rd+ degree connection\nDesign @ Deloitte \nDesign @ Deloitte\nMessage\nMital Kamani\nMital Kamani\n· 3rd+\n3rd+ degree connection\nProduct Designer at Rilla\nProduct Designer at Rilla\nFollow\nShow all\nPeople you may know\nPeople you may know\nFrom Sushanth's school\nFrom Sushanth's school\nMariaassumpta Onyeiwu\nMariaassumpta Onyeiwu\nCustomer Support Rep, Fiction/Non-Fiction writer, editor, skilled communicator with a background in journalism and mass communication, Comptia a+ certified, cybersecurity-in-view.\nConnect\nGeofrey Mwathi\nGeofrey Mwathi\nInformation Technology Support Specialist at BITSN\nInformation Technology Support Specialist at BITSN\nConnect\nYvonne Addo\nYvonne Addo\nPatient Support Associate | CPhT | Customer Satisfaction Excellence | CRM Technology | Pharma | Medical Data Transcription Specialist| Spanish as a Second Language\nConnect\nIana Grabch\nIana Grabch\nChannel Account Manager at Hydra Business Solutions\nChannel Account Manager at Hydra Business Solutions\nConnect\nEitan Nahon\nEitan Nahon\nIncoming Finance Student at University of Maryland | NYSE NextGen Bootcamp Alumni | Passionate About Markets & Investing\nConnect\nShow all\nYou might like\nYou might like\nPages for you\nPages for you\nGAL AeroStaff Ltd\nGAL AeroStaff Ltd\nStaffing and Recruiting\nStaffing and Recruiting\n8,824 followers\n8,824 followers\nFollow\nFinshots\nFinshots\nFinancial Services\nFinancial Services\n481,966 followers\n481,966 followers\nFollow\nShow all\nAbout\nAccessibility\nTalent Solutions\nProfessional Community Policies\nCareers\nMarketing Solutions\nPrivacy & Terms\nAd Choices\nAdvertising\nSales Solutions\nMobile\nSmall Business\nSafety Center\nQuestions?\nVisit our Help Center.\nManage your account and privacy\nGo to your Settings.\nRecommendation transparency\nLearn more about Recommended Content.\nSelect Language\n         العربية (Arabic)\n         বাংলা (Bangla)\n         Čeština (Czech)\n         Dansk (Danish)\n         Deutsch (German)\n         Ελληνικά (Greek)\n         English (English)\n         Español (Spanish)\n         فارسی (Persian)\n         Suomi (Finnish)\n         Français (French)\n         हिंदी (Hindi)\n         Magyar (Hungarian)\n         Bahasa Indonesia (Indonesian)\n         Italiano (Italian)\n         עברית (Hebrew)\n         日本語 (Japanese)\n         한국어 (Korean)\n         मराठी (Marathi)\n         Bahasa Malaysia (Malay)\n         Nederlands (Dutch)\n         Norsk (Norwegian)\n         ਪੰਜਾਬੀ (Punjabi)\n         Polski (Polish)\n         Português (Portuguese)\n         Română (Romanian)\n         Русский (Russian)\n         Svenska (Swedish)\n         తెలుగు (Telugu)\n         ภาษาไทย (Thai)\n         Tagalog (Tagalog)\n         Türkçe (Turkish)\n         Українська (Ukrainian)\n         Tiếng Việt (Vietnamese)\n         简体中文 (Chinese (Simplified))\n         正體中文 (Chinese (Traditional))\n     LinkedIn Corporation © 2025\nStatus is online\nMessaging\nYou are on the messaging overlay. Press enter to open the list of conversations.\nCompose message\nYou are on the messaging overlay. Press enter to open the list of conversations.",
  "skills_text": "0 notifications total\nnew feed updates notifications\nHome\n1\n1 new network update notification\nMy Network\nJobs\nMessaging\nNotifications\nMe\nFor Business\nTry Premium for ₹0\nSushanth Hegde\nProduct Designer 2 @Microsoft | Ex - xto10x, Nuclei | MS HCI @UMD\nMore\nFollow\nMessage\nSkills\nAll\nIndustry Knowledge\nTools & Technologies\nInterpersonal Skills\nUser Interface Design\nUser Interface Design\nEndorsed by 2 colleagues at Microsoft\nEndorsed by 2 colleagues at Microsoft\nEndorsed by 1 person in the last 6 months\nEndorsed by 1 person in the last 6 months\n11 endorsements\n11 endorsements\nUser Experience Design\nUser Experience Design\nEndorsed by 2 colleagues at Microsoft\nEndorsed by 2 colleagues at Microsoft\nEndorsed by 1 person in the last 6 months\nEndorsed by 1 person in the last 6 months\n11 endorsements\n11 endorsements\nDesign Thinking\nDesign Thinking\nEndorsed by 1 person in the last 6 months\nEndorsed by 1 person in the last 6 months\n7 endorsements\n7 endorsements\nPhotoshop\nPhotoshop\n13 endorsements\n13 endorsements\nIllustrator\nIllustrator\n6 endorsements\n6 endorsements\nWeb Design\nWeb Design\n7 endorsements\n7 endorsements\nGraphic Design\nGraphic Design\n5 endorsements\n5 endorsements\nHTML5\nHTML5\n3 endorsements\n3 endorsements\nCSS\nCSS\n8 endorsements\n8 endorsements\nJavaScript\nJavaScript\n2 endorsements\n2 endorsements\nPython\nPython\n2 endorsements\n2 endorsements\nCorel Draw\nCorel Draw\n5 endorsements\n5 endorsements\nUnity3D\nUnity3D\n4 endorsements\n4 endorsements\nGame Design\nGame Design\n5 endorsements\n5 endorsements\nJava\nJava\n4 endorsements\n4 endorsements\nSketchbook Pro\nSketchbook Pro\n5 endorsements\n5 endorsements\nDigital Sketching\nDigital Sketching\n6 endorsements\n6 endorsements\nAfter Effects\nAfter Effects\n4 endorsements\n4 endorsements\nSketch\nSketch\n2 endorsements\n2 endorsements\nMobile Design\nMobile Design\n4 endorsements\n4 endorsements\nInteraction Design\nInteraction Design\n2 endorsements\n2 endorsements\nUser Experience (UX)\nUser Experience (UX)\n3 endorsements\n3 endorsements\nWireframing\nWireframing\n3 endorsements\n3 endorsements\nUX Research\nUX Research\nUser-centered Design\nUser-centered Design\n2 endorsements\n2 endorsements\nInformation Architecture\nInformation Architecture\nDesign Systems\nDesign Systems\nUser Flows\nUser Flows\n1 endorsement\n1 endorsement\nVisual Design\nVisual Design\nMobile Interaction Design\nMobile Interaction Design\n1 endorsement\n1 endorsement\nCascading Style Sheets (CSS)\nCascading Style Sheets (CSS)\n1 endorsement\n1 endorsement\nMore profiles for you\nMore profiles for you\nRuchica Sinha\nRuchica Sinha\n· 3rd+\n3rd+ degree connection\nM.S. HCI @University of Maryland | Previously Design Intern @PepsiCo and Product Designer @Pine Labs\nMessage\nAnshika Srivastava\nAnshika Srivastava\n· 3rd+\n3rd+ degree connection\nProduct Designer | Health-tech\nProduct Designer | Health-tech\nFollow\nPallavi Kothapalli\nPallavi Kothapalli\n· 3rd+\n3rd+ degree connection\nProduct Designer | Architect | MS HCI @ UMD\nProduct Designer | Architect | MS HCI @ UMD\nMessage\nMeghana Alla\nMeghana Alla\n· 3rd+\n3rd+ degree connection\nDesign @ Deloitte \nDesign @ Deloitte\nMessage\nMital Kamani\nMital Kamani\n· 3rd+\n3rd+ degree connection\nProduct Designer at Rilla\nProduct Designer at Rilla\nFollow\nShow more\nAbout\nAccessibility\nTalent Solutions\nProfessional Community Policies\nCareers\nMarketing Solutions\nPrivacy & Terms\nAd Choices\nAdvertising\nSales Solutions\nMobile\nSmall Business\nSafety Center\nQuestions?\nVisit our Help Center.\nManage your account and privacy\nGo to your Settings.\nRecommendation transparency\nLearn more about Recommended Content.\nSelect Language\n         العربية (Arabic)\n         বাংলা (Bangla)\n         Čeština (Czech)\n         Dansk (Danish)\n         Deutsch (German)\n         Ελληνικά (Greek)\n         English (English)\n         Español (Spanish)\n         فارسی (Persian)\n         Suomi (Finnish)\n         Français (French)\n         हिंदी (Hindi)\n         Magyar (Hungarian)\n         Bahasa Indonesia (Indonesian)\n         Italiano (Italian)\n         עברית (Hebrew)\n         日本語 (Japanese)\n         한국어 (Korean)\n         मराठी (Marathi)\n         Bahasa Malaysia (Malay)\n         Nederlands (Dutch)\n         Norsk (Norwegian)\n         ਪੰਜਾਬੀ (Punjabi)\n         Polski (Polish)\n         Português (Portuguese)\n         Română (Romanian)\n         Русский (Russian)\n         Svenska (Swedish)\n         తెలుగు (Telugu)\n         ภาษาไทย (Thai)\n         Tagalog (Tagalog)\n         Türkçe (Turkish)\n         Українська (Ukrainian)\n         Tiếng Việt (Vietnamese)\n         简体中文 (Chinese (Simplified))\n         正體中文 (Chinese (Traditional))\n     LinkedIn Corporation © 2025\nStatus is online\nMessaging\nYou are on the messaging overlay. Press enter to open the list of conversations.\nCompose message\nYou are on the messaging overlay. Press enter to open the list of conversations.",
  "scraped_at": "2025-07-23 03:10:18",
  "has_skills": true,
  "cleaned_profile": {
    "name": "Sushanth Hegde",
    "profile_url": "https://www.linkedin.com/in/sushanthhegde",
    "current_position": {
      "title": "Product Designer 2",
      "company": "Microsoft",
      "location": "San Francisco Bay Area",
      "start_date": "Jun 2023",
      "end_date": "Present",
      "duration": "2 yrs 2 mos"
    },
    "previous_positions": [
      {
        "title": "Product Design Intern",
        "company": "Microsoft",
        "location": "San Francisco Bay Area",
        "start_date": "Jun 2022",
        "end_date": "Aug 2022",
        "duration": "3 mos"
      },
      {
        "title": "Senior Product Designer",
        "company": "xto10x",
        "location": "Bengaluru, Karnataka, India",
        "start_date": "Mar 2020",
        "end_date": "Jul 2021",
        "duration": "1 yr 5 mos"
      },
      {
        "title": "Product Designer",
        "company": "Nuclei",
        "location": "Bengaluru, Karnataka, India",
        "start_date": "Sep 2018",
        "end_date": "Dec 2019",
        "duration": "1 yr 4 mos"
      },
      {
        "title": "User Experience Designer",
        "company": "Tipstat",
        "location": "Bengaluru, Karnataka, India",
        "start_date": "Jan 2017",
        "end_date": "Sep 2018",
        "duration": "1 yr 9 mos"
      }
    ],
    "education": [
      {
        "institution": "University of Maryland",
        "degree": "Master's degree",
        "field_of_study": "Human Computer Interaction",
        "years_attended": "Aug 2021 - Jun 2023"
      },
      {
        "institution": "PES University",
        "degree": "Bachelor of Technology - BTech",
        "field_of_study": "Computer Science",
        "years_attended": "2013 - 2017"
      }
    ],
    "connections": "500+",
    "followers": 1366,
    "skills": [
      "User Interface Design",
      "User Experience Design",
      "Design Thinking",
      "Photoshop",
      "Illustrator",
      "Web Design",
      "Graphic Design",
      "HTML5",
      "CSS",
      "JavaScript",
      "Python",
      "Corel Draw",
      "Unity3D",
      "Game Design",
      "Java",
      "Sketchbook Pro",
      "Digital Sketching",
      "After Effects",
      "Sketch",
      "Mobile Design",
      "Interaction Design",
      "User Experience (UX)",
      "Wireframing",
      "UX Research",
      "User-centered Design",
      "Information Architecture",
      "Design Systems",
      "User Flows",
      "Visual Design",
      "Mobile Interaction Design",
      "Cascading Style Sheets (CSS)"
    ],
    "interests": [
      "Satya Nadella",
      "John Maeda",
      "Animal Welfare",
      "Arts and Culture",
      "Children",
      "Environment",
      "Science and Technology",
      "Social Services"
    ]
  },
  "tokens_used": {
    "prompt_tokens": 4141,
    "completion_tokens": 724,
    "total_tokens": 4865
  }
}